Workbook
Name BingSearchKey: Config!$B$4
Name SegmentId: Dashboard!$E$2
Name SerpApiKey: Config!$B$5

Sheet Brand_Kit
A1: Certify Intel v1 — Excel-Only (Brand Kit)
A3: PLACEHOLDER BRANDING: Replace with official Certify Health assets (logo + hex colors).
A5: Logo (placeholder):
A12: Colors
A13: Name | B13: Hex | D13: Swatch
A14: Primary | B14: #0B2E4A
A15: Secondary | B15: #1E9FB3
A16: Accent | B16: #F2A900
A17: Background | B17: #F5F7FA
A18: Border | B18: #D0D7DE
A20: Typography
A21: Header Font | B21: Aptos Display
A22: Body Font | B22: Aptos

Sheet Config
A1: Config (Inputs in BLUE)
A3: API Keys (optional; for autonomous competitor discovery via web search APIs)
A4: Bing Search API Key | B4: ENTER_KEY
A5: SerpAPI Key | B5: ENTER_KEY
A6: Max Competitors to Import | B6: 50
A8: Refresh Settings
A9: Evidence freshness threshold (days) | B9: 30
A10: Minimum allowed known-coverage (fail closed below) | B10: 0.6
A12: Scoring Weights (editable)
A13: Weight | B13: Value
A14: Threat_FeatureOverlap | B14: 0.35
A15: Threat_PricingAggressive | B15: 0.25
A16: Threat_FundingVelocity | B16: 0.2
A17: Threat_SegmentFit | B17: 0.2
A18: Opp_FeatureGap | B18: 0.5
A19: Opp_WeakSegmentFit | B19: 0.25
A20: Opp_LowCoverage | B20: 0.25

Sheet Sources_Allowlist
A1: Sources Allowlist (Fail-Closed)
A3: Only allowlisted domains/paths can be ingested. Non-allowlisted URLs must be BLOCKED and reviewed.
A4: source_key | B4: tier | C4: domain | D4: allow_path_prefix | E4: deny_path_prefix | F4: enabled | G4: license_notes | H4: owner
A5: DEMO | B5: TIER1 | C5: file | D5: / | F5: TRUE | G5: Local demo evidence (offline) | H5: system
A6: SEC_EDGAR | B6: TIER1 | C6: www.sec.gov | D6: /Archives | E6: /cgi-bin | F6: FALSE | G6: Public filings; respect ToS/rate limits | H6: system
A7: Company_PR | B7: TIER2 | F7: FALSE | G7: Per-entity allowlist required | H7: user
A8: G2 | B8: SIGNAL | C8: www.g2.com | D8: /products | E8: / | F8: FALSE | G8: Requires license / ToS review | H8: user
A9: Capterra | B9: SIGNAL | C9: www.capterra.com | D9: / | E9: / | F9: FALSE | G9: Requires license / ToS review | H9: user

Sheet Segment_Rules
A1: Middle Market Segmentation Rules (Always Applied)
A3: Edit thresholds in BLUE. All metrics and dashboards must filter to this segment.
A4: segment_id | B4: segment_name | C4: revenue_min_usd | D4: revenue_max_usd | E4: practice_size_min | F4: practice_size_max | G4: region_includes | H4: notes
A5: SEG_MM | B5: Middle Market | C5: 5000000 | D5: 200000000 | E5: 5 | F5: 200 | G5: US (all) | H5: Placeholder thresholds; replace with Certify definition

Sheet Field_Dictionary
A1: Field Dictionary (Claim Keys + Quality Gates)
A3: Fail-closed: missing/ambiguous evidence must output UNKNOWN and create review tasks.
A4: field_key | B4: category | C4: value_type | D4: units | E4: min_confidence | F4: requires_tier1 | G4: promotion_rule | H4: example_source | I4: notes
A5: pricing_acv_mid_market | B5: Pricing | C5: number | D5: USD/year | E5: 0.8 | F5: TRUE | G5: PROMOTE_IF>=MINCONF_AND_TIER | H5: pricing page | I5: Explicit annual price or ACV
A6: arr_estimate | B6: Financial | C6: number | D6: USD/year | E6: 0.85 | F6: TRUE | G6: PROMOTE_IF_TIER1_ONLY | H6: 10-K/press | I6: Only explicit ARR mention
A7: contract_terms | B7: Pricing | C7: text | E7: 0.7 | F7: FALSE | G7: PROMOTE_IF>=MINCONF | H7: pricing/terms | I7: Explicit contract duration/cancellation
A8: features | B8: Product | C8: text | E8: 0.65 | F8: FALSE | G8: PROMOTE_IF>=MINCONF | H8: product page | I8: Semicolon-separated feature tags
A9: funding_round | B9: Funding | C9: text | E9: 0.8 | F9: TRUE | G9: PROMOTE_IF_TIER1_ONLY | H9: filings/press | I9: Explicit round amount and date
A10: geo_coverage | B10: Market | C10: text | E10: 0.7 | F10: FALSE | G10: PROMOTE_IF>=MINCONF | H10: about page | I10: Regions served
A11: practice_size_target | B11: Market | C11: text | E11: 0.7 | F11: FALSE | G11: PROMOTE_IF>=MINCONF | H11: case studies | I11: Explicit ICP statements

Sheet Feature_Taxonomy
A1: Feature Taxonomy (canonical features + synonyms)
A4: feature_id | B4: feature_name | C4: category | D4: synonyms_csv | E4: notes
A5: F001 | B5: Eligibility Verification | C5: Revenue Cycle | D5: eligibility check;insurance eligibility
A6: F002 | B6: Prior Authorization | C6: Revenue Cycle | D6: prior auth;pre-authorization
A7: F003 | B7: Patient Payments | C7: Billing | D7: payment portal;online payments
A8: F004 | B8: Scheduling | C8: Front Office | D8: appointment scheduling;calendar

Sheet Input
A1: Input (Normalized; Evidence-Led)
A2: Green = imported/linked; Blue = editable inputs; Yellow/Red = review required.
A4: Entities
A6: entity_id | B6: canonical_name | C6: domain | D6: vertical | E6: region | F6: segment_id | G6: discovered_via | H6: discovered_at | I6: status | J6: hq_city | K6: hq_state | L6: notes
A7: E001 | B7: AcmeRival | C7: acmerival.com | D7: Provider Credentialing | E7: US | F7: SEG_MM | G7: DEMO | H7: 2026-01-12 | I7: ACTIVE | J7: New York | K7: NY | L7: DEMO ROW
A8: E002 | B8: EnrollPro | C8: enrollpro.io | D8: Provider Enrollment | E8: US | F8: SEG_MM | G8: DEMO | H8: 2026-01-12 | I8: ACTIVE | J8: Austin | K8: TX | L8: DEMO ROW
A9: E003 | B9: ComplianceFlow | C9: complianceflow.health | D9: Compliance Automation | E9: US | F9: SEG_MM | G9: DEMO | H9: 2026-01-12 | I9: ACTIVE | J9: Chicago | K9: IL | L9: DEMO ROW
A10: E004 | B10: CredentiSure | C10: credentisure.com | D10: Credentialing | E10: US | F10: SEG_MM | G10: DEMO | H10: 2026-01-12 | I10: ACTIVE | J10: Boston | K10: MA | L10: DEMO ROW
A11: E005 | B11: PracticeOps | C11: practiceops.com | D11: Practice Ops Suite | E11: US | F11: SEG_MM | G11: DEMO | H11: 2026-01-12 | I11: ACTIVE | J11: Miami | K11: FL | L11: DEMO ROW
A12: E006 | B12: MidMarketMedTech | C12: mmmedtech.com | D12: Healthcare IT | E12: US | F12: SEG_MM | G12: DEMO | H12: 2026-01-12 | I12: ACTIVE | J12: Seattle | K12: WA | L12: DEMO ROW
A15: Evidence (Claims must link here)
A17: evidence_id | B17: entity_id | C17: source_key | D17: tier | E17: url | F17: fetched_at | G17: snippet | H17: content_hash | I17: text_hash | J17: domain_calc | K17: allowlist_ok
A18: EV001 | B18: E001 | C18: DEMO | D18: TIER1 | E18: file://docs/demo_sources/E001_pricing.html | F18: 2026-01-12 | G18: DEMO evidence placeholder. Replace with allowlisted URL + snippet. | H18: 0217e879a9ae84b4 | I18: 46aae5c96408e7ec | J18: =IF(LEFT(#REF!,7)="file://","file",LOWER(_xludf.TEXTBEFORE(_xludf.TEXTAFTER(#REF!,"//"),"/"))) -> #REF!
A19: EV002 | B19: E002 | C19: DEMO | D19: TIER1 | E19: file://docs/demo_sources/E002_pricing.html | F19: 2026-01-12 | G19: DEMO evidence placeholder. Replace with allowlisted URL + snippet. | H19: 3deb1e85e3854868 | I19: 46aae5c96408e7ec | J19: =IF(LEFT(#REF!,7)="file://","file",LOWER(_xludf.TEXTBEFORE(_xludf.TEXTAFTER(#REF!,"//"),"/"))) -> #REF!
A20: EV003 | B20: E003 | C20: DEMO | D20: TIER1 | E20: file://docs/demo_sources/E003_pricing.html | F20: 2026-01-12 | G20: DEMO evidence placeholder. Replace with allowlisted URL + snippet. | H20: d42285f8d1a9736f | I20: 46aae5c96408e7ec | J20: =IF(LEFT(#REF!,7)="file://","file",LOWER(_xludf.TEXTBEFORE(_xludf.TEXTAFTER(#REF!,"//"),"/"))) -> #REF!
A21: EV004 | B21: E004 | C21: DEMO | D21: TIER1 | E21: file://docs/demo_sources/E004_pricing.html | F21: 2026-01-12 | G21: DEMO evidence placeholder. Replace with allowlisted URL + snippet. | H21: b1e3c58050111249 | I21: 46aae5c96408e7ec | J21: =IF(LEFT(#REF!,7)="file://","file",LOWER(_xludf.TEXTBEFORE(_xludf.TEXTAFTER(#REF!,"//"),"/"))) -> #REF!
A22: EV005 | B22: E001 | C22: DEMO | D22: SIGNAL | E22: file://docs/demo_sources/E001_pr.html | F22: 2026-01-12 | G22: DEMO PR mention (signal only). | H22: 0510eddd78110203 | I22: 41bfa2f2111d7821 | J22: =IF(LEFT(#REF!,7)="file://","file",LOWER(_xludf.TEXTBEFORE(_xludf.TEXTAFTER(#REF!,"//"),"/"))) -> #REF!
A25: Claim Candidates (Fail-Closed; UNKNOWN → Review)
A27: candidate_id | B27: entity_id | C27: segment_id | D27: field_key | E27: value_text | F27: value_num | G27: units | H27: confidence | I27: evidence_id | J27: span_start | K27: span_end | L27: tier | M27: status_final | N27: status_manual | O27: status_auto | P27: auto_reason | Q27: reviewer_notes
A28: C001 | B28: E001 | C28: SEG_MM | D28: pricing_acv_mid_market | F28: 12000 | G28: USD/year | H28: 0.9 | I28: EV001 | J28: 0 | K28: 200 | L28: TIER1 | M28: =_xludf.LET(man,#REF!,auto,#REF!,IF(man="REJECTED","REJECTED",IF(man="IN_REVIEW","IN_REVIEW",IF(man="PROMOTED",IF(auto="PROMOTABLE","PROMOTED","REVIEW_REQUIRED"),IF(auto="PROMOTABLE","PROMOTED","REVIEW_REQUIRED"))))) -> #NAME? | N28: PROMOTED | O28: =_xludf.LET(minc,IFERROR(_xludf.XLOOKUP(#REF!,tblFieldDictionary[field_key],tblFieldDictionary[min_confidence]),1),REQ1,IFERROR(_xludf.XLOOKUP(#REF!,tblFieldDictionary[field_key],tblFieldDictionary[requires_tier1]),"FALSE"),hasEvid,ISNUMBER(MATCH(#REF!,tblEvidence[evidence_id],0)),hasVal,OR(AND(#REF!<>"",#REF!<>"UNKNOWN"),#REF!<>""),confOK,#REF!>=minc,tierOK,IF(REQ1="TRUE",#REF!="TIER1",TRUE),IF(NOT(hasEvid),"REVIEW_REQUIRED",IF(NOT(hasVal),"REVIEW_REQUIRED",IF(NOT(confOK),"REVIEW_REQUIRED",IF(NOT(tierOK),"REVIEW_REQUIRED","PROMOTABLE"))))) -> #NAME? | P28: =_xludf.LET(minc,IFERROR(_xludf.XLOOKUP(#REF!,tblFieldDictionary[field_key],tblFieldDictionary[min_confidence]),1),REQ1,IFERROR(_xludf.XLOOKUP(#REF!,tblFieldDictionary[field_key],tblFieldDictionary[requires_tier1]),"FALSE"),hasEvid,ISNUMBER(MATCH(#REF!,tblEvidence[evidence_id],0)),hasVal,OR(AND(#REF!<>"",#REF!<>"UNKNOWN"),#REF!<>""),confOK,#REF!>=minc,tierOK,IF(REQ1="TRUE",#REF!="TIER1",TRUE),IF(NOT(hasEvid),"MISSING_EVIDENCE",IF(NOT(hasVal),"MISSING_VALUE",IF(NOT(confOK),"LOW_CONFIDENCE",IF(NOT(tierOK),"TIER1_REQUIRED","OK"))))) -> #NAME?
A29: C002 | B29: E001 | C29: SEG_MM | D29: contract_terms | E29: Annual contract, cancel with 30 days notice | H29: 0.75 | I29: EV001 | J29: 201 | K29: 320 | L29: TIER1 | M29: =_xludf.LET(man,#REF!,auto,#REF!,IF(man="REJECTED","REJECTED",IF(man="IN_REVIEW","IN_REVIEW",IF(man="PROMOTED",IF(auto="PROMOTABLE","PROMOTED","REVIEW_REQUIRED"),IF(auto="PROMOTABLE","PROMOTED","REVIEW_REQUIRED"))))) -> #NAME? | N29: PROMOTED | O29: =_xludf.LET(minc,IFERROR(_xludf.XLOOKUP(#REF!,tblFieldDictionary[field_key],tblFieldDictionary[min_confidence]),1),REQ1,IFERROR(_xludf.XLOOKUP(#REF!,tblFieldDictionary[field_key],tblFieldDictionary[requires_tier1]),"FALSE"),hasEvid,ISNUMBER(MATCH(#REF!,tblEvidence[evidence_id],0)),hasVal,OR(AND(#REF!<>"",#REF!<>"UNKNOWN"),#REF!<>""),confOK,#REF!>=minc,tierOK,IF(REQ1="TRUE",#REF!="TIER1",TRUE),IF(NOT(hasEvid),"REVIEW_REQUIRED",IF(NOT(hasVal),"REVIEW_REQUIRED",IF(NOT(confOK),"REVIEW_REQUIRED",IF(NOT(tierOK),"REVIEW_REQUIRED","PROMOTABLE"))))) -> #NAME? | P29: =_xludf.LET(minc,IFERROR(_xludf.XLOOKUP(#REF!,tblFieldDictionary[field_key],tblFieldDictionary[min_confidence]),1),REQ1,IFERROR(_xludf.XLOOKUP(#REF!,tblFieldDictionary[field_key],tblFieldDictionary[requires_tier1]),"FALSE"),hasEvid,ISNUMBER(MATCH(#REF!,tblEvidence[evidence_id],0)),hasVal,OR(AND(#REF!<>"",#REF!<>"UNKNOWN"),#REF!<>""),confOK,#REF!>=minc,tierOK,IF(REQ1="TRUE",#REF!="TIER1",TRUE),IF(NOT(hasEvid),"MISSING_EVIDENCE",IF(NOT(hasVal),"MISSING_VALUE",IF(NOT(confOK),"LOW_CONFIDENCE",IF(NOT(tierOK),"TIER1_REQUIRED","OK"))))) -> #NAME?
A30: C003 | B30: E001 | C30: SEG_MM | D30: features | E30: Credentialing; Enrollment; Payer Roster | H30: 0.7 | I30: EV001 | J30: 321 | K30: 520 | L30: TIER1 | M30: =_xludf.LET(man,#REF!,auto,#REF!,IF(man="REJECTED","REJECTED",IF(man="IN_REVIEW","IN_REVIEW",IF(man="PROMOTED",IF(auto="PROMOTABLE","PROMOTED","REVIEW_REQUIRED"),IF(auto="PROMOTABLE","PROMOTED","REVIEW_REQUIRED"))))) -> #NAME? | N30: PROMOTED | O30: =_xludf.LET(minc,IFERROR(_xludf.XLOOKUP(#REF!,tblFieldDictionary[field_key],tblFieldDictionary[min_confidence]),1),REQ1,IFERROR(_xludf.XLOOKUP(#REF!,tblFieldDictionary[field_key],tblFieldDictionary[requires_tier1]),"FALSE"),hasEvid,ISNUMBER(MATCH(#REF!,tblEvidence[evidence_id],0)),hasVal,OR(AND(#REF!<>"",#REF!<>"UNKNOWN"),#REF!<>""),confOK,#REF!>=minc,tierOK,IF(REQ1="TRUE",#REF!="TIER1",TRUE),IF(NOT(hasEvid),"REVIEW_REQUIRED",IF(NOT(hasVal),"REVIEW_REQUIRED",IF(NOT(confOK),"REVIEW_REQUIRED",IF(NOT(tierOK),"REVIEW_REQUIRED","PROMOTABLE"))))) -> #NAME? | P30: =_xludf.LET(minc,IFERROR(_xludf.XLOOKUP(#REF!,tblFieldDictionary[field_key],tblFieldDictionary[min_confidence]),1),REQ1,IFERROR(_xludf.XLOOKUP(#REF!,tblFieldDictionary[field_key],tblFieldDictionary[requires_tier1]),"FALSE"),hasEvid,ISNUMBER(MATCH(#REF!,tblEvidence[evidence_id],0)),hasVal,OR(AND(#REF!<>"",#REF!<>"UNKNOWN"),#REF!<>""),confOK,#REF!>=minc,tierOK,IF(REQ1="TRUE",#REF!="TIER1",TRUE),IF(NOT(hasEvid),"MISSING_EVIDENCE",IF(NOT(hasVal),"MISSING_VALUE",IF(NOT(confOK),"LOW_CONFIDENCE",IF(NOT(tierOK),"TIER1_REQUIRED","OK"))))) -> #NAME?
A31: C004 | B31: E002 | C31: SEG_MM | D31: pricing_acv_mid_market | E31: UNKNOWN | G31: USD/year | H31: 0.2 | I31: EV002 | J31: 0 | K31: 180 | L31: TIER1 | M31: =_xludf.LET(man,#REF!,auto,#REF!,IF(man="REJECTED","REJECTED",IF(man="IN_REVIEW","IN_REVIEW",IF(man="PROMOTED",IF(auto="PROMOTABLE","PROMOTED","REVIEW_REQUIRED"),IF(auto="PROMOTABLE","PROMOTED","REVIEW_REQUIRED"))))) -> #NAME? | N31: REVIEW_REQUIRED | O31: =_xludf.LET(minc,IFERROR(_xludf.XLOOKUP(#REF!,tblFieldDictionary[field_key],tblFieldDictionary[min_confidence]),1),REQ1,IFERROR(_xludf.XLOOKUP(#REF!,tblFieldDictionary[field_key],tblFieldDictionary[requires_tier1]),"FALSE"),hasEvid,ISNUMBER(MATCH(#REF!,tblEvidence[evidence_id],0)),hasVal,OR(AND(#REF!<>"",#REF!<>"UNKNOWN"),#REF!<>""),confOK,#REF!>=minc,tierOK,IF(REQ1="TRUE",#REF!="TIER1",TRUE),IF(NOT(hasEvid),"REVIEW_REQUIRED",IF(NOT(hasVal),"REVIEW_REQUIRED",IF(NOT(confOK),"REVIEW_REQUIRED",IF(NOT(tierOK),"REVIEW_REQUIRED","PROMOTABLE"))))) -> #NAME? | P31: =_xludf.LET(minc,IFERROR(_xludf.XLOOKUP(#REF!,tblFieldDictionary[field_key],tblFieldDictionary[min_confidence]),1),REQ1,IFERROR(_xludf.XLOOKUP(#REF!,tblFieldDictionary[field_key],tblFieldDictionary[requires_tier1]),"FALSE"),hasEvid,ISNUMBER(MATCH(#REF!,tblEvidence[evidence_id],0)),hasVal,OR(AND(#REF!<>"",#REF!<>"UNKNOWN"),#REF!<>""),confOK,#REF!>=minc,tierOK,IF(REQ1="TRUE",#REF!="TIER1",TRUE),IF(NOT(hasEvid),"MISSING_EVIDENCE",IF(NOT(hasVal),"MISSING_VALUE",IF(NOT(confOK),"LOW_CONFIDENCE",IF(NOT(tierOK),"TIER1_REQUIRED","OK"))))) -> #NAME? | Q31: No explicit ACV on page
A32: C005 | B32: E002 | C32: SEG_MM | D32: features | E32: Enrollment; Automated forms; Integrations | H32: 0.7 | I32: EV002 | J32: 181 | K32: 420 | L32: TIER1 | M32: =_xludf.LET(man,#REF!,auto,#REF!,IF(man="REJECTED","REJECTED",IF(man="IN_REVIEW","IN_REVIEW",IF(man="PROMOTED",IF(auto="PROMOTABLE","PROMOTED","REVIEW_REQUIRED"),IF(auto="PROMOTABLE","PROMOTED","REVIEW_REQUIRED"))))) -> #NAME? | N32: PROMOTED | O32: =_xludf.LET(minc,IFERROR(_xludf.XLOOKUP(#REF!,tblFieldDictionary[field_key],tblFieldDictionary[min_confidence]),1),REQ1,IFERROR(_xludf.XLOOKUP(#REF!,tblFieldDictionary[field_key],tblFieldDictionary[requires_tier1]),"FALSE"),hasEvid,ISNUMBER(MATCH(#REF!,tblEvidence[evidence_id],0)),hasVal,OR(AND(#REF!<>"",#REF!<>"UNKNOWN"),#REF!<>""),confOK,#REF!>=minc,tierOK,IF(REQ1="TRUE",#REF!="TIER1",TRUE),IF(NOT(hasEvid),"REVIEW_REQUIRED",IF(NOT(hasVal),"REVIEW_REQUIRED",IF(NOT(confOK),"REVIEW_REQUIRED",IF(NOT(tierOK),"REVIEW_REQUIRED","PROMOTABLE"))))) -> #NAME? | P32: =_xludf.LET(minc,IFERROR(_xludf.XLOOKUP(#REF!,tblFieldDictionary[field_key],tblFieldDictionary[min_confidence]),1),REQ1,IFERROR(_xludf.XLOOKUP(#REF!,tblFieldDictionary[field_key],tblFieldDictionary[requires_tier1]),"FALSE"),hasEvid,ISNUMBER(MATCH(#REF!,tblEvidence[evidence_id],0)),hasVal,OR(AND(#REF!<>"",#REF!<>"UNKNOWN"),#REF!<>""),confOK,#REF!>=minc,tierOK,IF(REQ1="TRUE",#REF!="TIER1",TRUE),IF(NOT(hasEvid),"MISSING_EVIDENCE",IF(NOT(hasVal),"MISSING_VALUE",IF(NOT(confOK),"LOW_CONFIDENCE",IF(NOT(tierOK),"TIER1_REQUIRED","OK"))))) -> #NAME?
A33: C006 | B33: E003 | C33: SEG_MM | D33: funding_round | E33: UNKNOWN | H33: 0.1 | I33: EV003 | J33: 0 | K33: 250 | L33: SIGNAL | M33: =_xludf.LET(man,#REF!,auto,#REF!,IF(man="REJECTED","REJECTED",IF(man="IN_REVIEW","IN_REVIEW",IF(man="PROMOTED",IF(auto="PROMOTABLE","PROMOTED","REVIEW_REQUIRED"),IF(auto="PROMOTABLE","PROMOTED","REVIEW_REQUIRED"))))) -> #NAME? | N33: REVIEW_REQUIRED | O33: =_xludf.LET(minc,IFERROR(_xludf.XLOOKUP(#REF!,tblFieldDictionary[field_key],tblFieldDictionary[min_confidence]),1),REQ1,IFERROR(_xludf.XLOOKUP(#REF!,tblFieldDictionary[field_key],tblFieldDictionary[requires_tier1]),"FALSE"),hasEvid,ISNUMBER(MATCH(#REF!,tblEvidence[evidence_id],0)),hasVal,OR(AND(#REF!<>"",#REF!<>"UNKNOWN"),#REF!<>""),confOK,#REF!>=minc,tierOK,IF(REQ1="TRUE",#REF!="TIER1",TRUE),IF(NOT(hasEvid),"REVIEW_REQUIRED",IF(NOT(hasVal),"REVIEW_REQUIRED",IF(NOT(confOK),"REVIEW_REQUIRED",IF(NOT(tierOK),"REVIEW_REQUIRED","PROMOTABLE"))))) -> #NAME? | P33: =_xludf.LET(minc,IFERROR(_xludf.XLOOKUP(#REF!,tblFieldDictionary[field_key],tblFieldDictionary[min_confidence]),1),REQ1,IFERROR(_xludf.XLOOKUP(#REF!,tblFieldDictionary[field_key],tblFieldDictionary[requires_tier1]),"FALSE"),hasEvid,ISNUMBER(MATCH(#REF!,tblEvidence[evidence_id],0)),hasVal,OR(AND(#REF!<>"",#REF!<>"UNKNOWN"),#REF!<>""),confOK,#REF!>=minc,tierOK,IF(REQ1="TRUE",#REF!="TIER1",TRUE),IF(NOT(hasEvid),"MISSING_EVIDENCE",IF(NOT(hasVal),"MISSING_VALUE",IF(NOT(confOK),"LOW_CONFIDENCE",IF(NOT(tierOK),"TIER1_REQUIRED","OK"))))) -> #NAME? | Q33: Signal only; needs tier-1 corroboration
A34: C007 | B34: E004 | C34: SEG_MM | D34: pricing_acv_mid_market | F34: 18000 | G34: USD/year | H34: 0.82 | I34: EV004 | J34: 0 | K34: 210 | L34: TIER1 | M34: =_xludf.LET(man,#REF!,auto,#REF!,IF(man="REJECTED","REJECTED",IF(man="IN_REVIEW","IN_REVIEW",IF(man="PROMOTED",IF(auto="PROMOTABLE","PROMOTED","REVIEW_REQUIRED"),IF(auto="PROMOTABLE","PROMOTED","REVIEW_REQUIRED"))))) -> #NAME? | N34: PROMOTED | O34: =_xludf.LET(minc,IFERROR(_xludf.XLOOKUP(#REF!,tblFieldDictionary[field_key],tblFieldDictionary[min_confidence]),1),REQ1,IFERROR(_xludf.XLOOKUP(#REF!,tblFieldDictionary[field_key],tblFieldDictionary[requires_tier1]),"FALSE"),hasEvid,ISNUMBER(MATCH(#REF!,tblEvidence[evidence_id],0)),hasVal,OR(AND(#REF!<>"",#REF!<>"UNKNOWN"),#REF!<>""),confOK,#REF!>=minc,tierOK,IF(REQ1="TRUE",#REF!="TIER1",TRUE),IF(NOT(hasEvid),"REVIEW_REQUIRED",IF(NOT(hasVal),"REVIEW_REQUIRED",IF(NOT(confOK),"REVIEW_REQUIRED",IF(NOT(tierOK),"REVIEW_REQUIRED","PROMOTABLE"))))) -> #NAME? | P34: =_xludf.LET(minc,IFERROR(_xludf.XLOOKUP(#REF!,tblFieldDictionary[field_key],tblFieldDictionary[min_confidence]),1),REQ1,IFERROR(_xludf.XLOOKUP(#REF!,tblFieldDictionary[field_key],tblFieldDictionary[requires_tier1]),"FALSE"),hasEvid,ISNUMBER(MATCH(#REF!,tblEvidence[evidence_id],0)),hasVal,OR(AND(#REF!<>"",#REF!<>"UNKNOWN"),#REF!<>""),confOK,#REF!>=minc,tierOK,IF(REQ1="TRUE",#REF!="TIER1",TRUE),IF(NOT(hasEvid),"MISSING_EVIDENCE",IF(NOT(hasVal),"MISSING_VALUE",IF(NOT(confOK),"LOW_CONFIDENCE",IF(NOT(tierOK),"TIER1_REQUIRED","OK"))))) -> #NAME?
A35: C008 | B35: E004 | C35: SEG_MM | D35: features | E35: Credentialing; Compliance; Analytics | H35: 0.68 | I35: EV004 | J35: 211 | K35: 400 | L35: TIER1 | M35: =_xludf.LET(man,#REF!,auto,#REF!,IF(man="REJECTED","REJECTED",IF(man="IN_REVIEW","IN_REVIEW",IF(man="PROMOTED",IF(auto="PROMOTABLE","PROMOTED","REVIEW_REQUIRED"),IF(auto="PROMOTABLE","PROMOTED","REVIEW_REQUIRED"))))) -> #NAME? | N35: PROMOTED | O35: =_xludf.LET(minc,IFERROR(_xludf.XLOOKUP(#REF!,tblFieldDictionary[field_key],tblFieldDictionary[min_confidence]),1),REQ1,IFERROR(_xludf.XLOOKUP(#REF!,tblFieldDictionary[field_key],tblFieldDictionary[requires_tier1]),"FALSE"),hasEvid,ISNUMBER(MATCH(#REF!,tblEvidence[evidence_id],0)),hasVal,OR(AND(#REF!<>"",#REF!<>"UNKNOWN"),#REF!<>""),confOK,#REF!>=minc,tierOK,IF(REQ1="TRUE",#REF!="TIER1",TRUE),IF(NOT(hasEvid),"REVIEW_REQUIRED",IF(NOT(hasVal),"REVIEW_REQUIRED",IF(NOT(confOK),"REVIEW_REQUIRED",IF(NOT(tierOK),"REVIEW_REQUIRED","PROMOTABLE"))))) -> #NAME? | P35: =_xludf.LET(minc,IFERROR(_xludf.XLOOKUP(#REF!,tblFieldDictionary[field_key],tblFieldDictionary[min_confidence]),1),REQ1,IFERROR(_xludf.XLOOKUP(#REF!,tblFieldDictionary[field_key],tblFieldDictionary[requires_tier1]),"FALSE"),hasEvid,ISNUMBER(MATCH(#REF!,tblEvidence[evidence_id],0)),hasVal,OR(AND(#REF!<>"",#REF!<>"UNKNOWN"),#REF!<>""),confOK,#REF!>=minc,tierOK,IF(REQ1="TRUE",#REF!="TIER1",TRUE),IF(NOT(hasEvid),"MISSING_EVIDENCE",IF(NOT(hasVal),"MISSING_VALUE",IF(NOT(confOK),"LOW_CONFIDENCE",IF(NOT(tierOK),"TIER1_REQUIRED","OK"))))) -> #NAME?
A36: C009 | B36: E005 | C36: SEG_MM | D36: pricing_acv_mid_market | F36: 9000 | G36: USD/year | H36: 0.8 | I36: EV005 | J36: 0 | K36: 200 | L36: SIGNAL | M36: =_xludf.LET(man,#REF!,auto,#REF!,IF(man="REJECTED","REJECTED",IF(man="IN_REVIEW","IN_REVIEW",IF(man="PROMOTED",IF(auto="PROMOTABLE","PROMOTED","REVIEW_REQUIRED"),IF(auto="PROMOTABLE","PROMOTED","REVIEW_REQUIRED"))))) -> #NAME? | N36: REVIEW_REQUIRED | O36: =_xludf.LET(minc,IFERROR(_xludf.XLOOKUP(#REF!,tblFieldDictionary[field_key],tblFieldDictionary[min_confidence]),1),REQ1,IFERROR(_xludf.XLOOKUP(#REF!,tblFieldDictionary[field_key],tblFieldDictionary[requires_tier1]),"FALSE"),hasEvid,ISNUMBER(MATCH(#REF!,tblEvidence[evidence_id],0)),hasVal,OR(AND(#REF!<>"",#REF!<>"UNKNOWN"),#REF!<>""),confOK,#REF!>=minc,tierOK,IF(REQ1="TRUE",#REF!="TIER1",TRUE),IF(NOT(hasEvid),"REVIEW_REQUIRED",IF(NOT(hasVal),"REVIEW_REQUIRED",IF(NOT(confOK),"REVIEW_REQUIRED",IF(NOT(tierOK),"REVIEW_REQUIRED","PROMOTABLE"))))) -> #NAME? | P36: =_xludf.LET(minc,IFERROR(_xludf.XLOOKUP(#REF!,tblFieldDictionary[field_key],tblFieldDictionary[min_confidence]),1),REQ1,IFERROR(_xludf.XLOOKUP(#REF!,tblFieldDictionary[field_key],tblFieldDictionary[requires_tier1]),"FALSE"),hasEvid,ISNUMBER(MATCH(#REF!,tblEvidence[evidence_id],0)),hasVal,OR(AND(#REF!<>"",#REF!<>"UNKNOWN"),#REF!<>""),confOK,#REF!>=minc,tierOK,IF(REQ1="TRUE",#REF!="TIER1",TRUE),IF(NOT(hasEvid),"MISSING_EVIDENCE",IF(NOT(hasVal),"MISSING_VALUE",IF(NOT(confOK),"LOW_CONFIDENCE",IF(NOT(tierOK),"TIER1_REQUIRED","OK"))))) -> #NAME? | Q36: Pricing from signal source; needs tier-1

Sheet Claims_Current
A1: Claims_Current (Normalized Claims; Versioned via Review Workflow)
A2: This sheet is the contract consumed by Metrics and Dashboards. Values must be evidence-backed; missing/uncertain → UNKNOWN.
A4: entity_id | B4: canonical_name | C4: segment_id | D4: field_key | E4: value_text | F4: value_num | G4: units | H4: confidence | I4: evidence_id | J4: evidence_url | K4: tier | L4: status | M4: last_updated | N4: explain
A5: E001 | B5: AcmeRival | C5: SEG_MM | D5: pricing_acv_mid_market | E5: =_xludf.LET(v,IFERROR(LOOKUP(2,1/((tblClaimCandidates[entity_id]=#REF!)*(tblClaimCandidates[field_key]=#REF!)*(tblClaimCandidates[status_final]="PROMOTED")),tblClaimCandidates[value_text]),""),IF(v="","UNKNOWN",v)) -> #NAME? | F5: =_xludf.LET(cnt,COUNTIFS(tblClaimCandidates[entity_id],#REF!,tblClaimCandidates[field_key],#REF!,tblClaimCandidates[status_final],"PROMOTED"),IF(cnt=0,NA(),SUMIFS(tblClaimCandidates[value_num],tblClaimCandidates[entity_id],#REF!,tblClaimCandidates[field_key],#REF!,tblClaimCandidates[status_final],"PROMOTED"))) -> #NAME? | G5: =IFERROR(_xludf.XLOOKUP(#REF!,tblFieldDictionary[field_key],tblFieldDictionary[units]),"") | H5: =_xludf.LET(cnt,COUNTIFS(tblClaimCandidates[entity_id],#REF!,tblClaimCandidates[field_key],#REF!,tblClaimCandidates[status_final],"PROMOTED"),IF(cnt=0,NA(),AVERAGEIFS(tblClaimCandidates[confidence],tblClaimCandidates[entity_id],#REF!,tblClaimCandidates[field_key],#REF!,tblClaimCandidates[status_final],"PROMOTED"))) -> #NAME? | I5: =IFERROR(LOOKUP(2,1/((tblClaimCandidates[entity_id]=#REF!)*(tblClaimCandidates[field_key]=#REF!)*(tblClaimCandidates[status_final]="PROMOTED")),tblClaimCandidates[evidence_id]),"") | J5: =IF(#REF!="","",IFERROR(_xludf.XLOOKUP(#REF!,tblEvidence[evidence_id],tblEvidence[url],""),"")) -> #REF! | K5: =IFERROR(LOOKUP(2,1/((tblClaimCandidates[entity_id]=#REF!)*(tblClaimCandidates[field_key]=#REF!)*(tblClaimCandidates[status_final]="PROMOTED")),tblClaimCandidates[tier]),"") | L5: =IF(#REF!="UNKNOWN","UNKNOWN","PROMOTED") -> #REF! | M5: =IF(#REF!="PROMOTED",TODAY(),"") -> #REF! | N5: =IF(#REF!="PROMOTED","evidence_linked","UNKNOWN_or_unverified") -> #REF!
A6: E001 | B6: AcmeRival | C6: SEG_MM | D6: arr_estimate | E6: =_xludf.LET(v,IFERROR(LOOKUP(2,1/((tblClaimCandidates[entity_id]=#REF!)*(tblClaimCandidates[field_key]=#REF!)*(tblClaimCandidates[status_final]="PROMOTED")),tblClaimCandidates[value_text]),""),IF(v="","UNKNOWN",v)) -> #NAME? | F6: =_xludf.LET(cnt,COUNTIFS(tblClaimCandidates[entity_id],#REF!,tblClaimCandidates[field_key],#REF!,tblClaimCandidates[status_final],"PROMOTED"),IF(cnt=0,NA(),SUMIFS(tblClaimCandidates[value_num],tblClaimCandidates[entity_id],#REF!,tblClaimCandidates[field_key],#REF!,tblClaimCandidates[status_final],"PROMOTED"))) -> #NAME? | G6: =IFERROR(_xludf.XLOOKUP(#REF!,tblFieldDictionary[field_key],tblFieldDictionary[units]),"") | H6: =_xludf.LET(cnt,COUNTIFS(tblClaimCandidates[entity_id],#REF!,tblClaimCandidates[field_key],#REF!,tblClaimCandidates[status_final],"PROMOTED"),IF(cnt=0,NA(),AVERAGEIFS(tblClaimCandidates[confidence],tblClaimCandidates[entity_id],#REF!,tblClaimCandidates[field_key],#REF!,tblClaimCandidates[status_final],"PROMOTED"))) -> #NAME? | I6: =IFERROR(LOOKUP(2,1/((tblClaimCandidates[entity_id]=#REF!)*(tblClaimCandidates[field_key]=#REF!)*(tblClaimCandidates[status_final]="PROMOTED")),tblClaimCandidates[evidence_id]),"") | J6: =IF(#REF!="","",IFERROR(_xludf.XLOOKUP(#REF!,tblEvidence[evidence_id],tblEvidence[url],""),"")) -> #REF! | K6: =IFERROR(LOOKUP(2,1/((tblClaimCandidates[entity_id]=#REF!)*(tblClaimCandidates[field_key]=#REF!)*(tblClaimCandidates[status_final]="PROMOTED")),tblClaimCandidates[tier]),"") | L6: =IF(#REF!="UNKNOWN","UNKNOWN","PROMOTED") -> #REF! | M6: =IF(#REF!="PROMOTED",TODAY(),"") -> #REF! | N6: =IF(#REF!="PROMOTED","evidence_linked","UNKNOWN_or_unverified") -> #REF!
A7: E001 | B7: AcmeRival | C7: SEG_MM | D7: contract_terms | E7: =_xludf.LET(v,IFERROR(LOOKUP(2,1/((tblClaimCandidates[entity_id]=#REF!)*(tblClaimCandidates[field_key]=#REF!)*(tblClaimCandidates[status_final]="PROMOTED")),tblClaimCandidates[value_text]),""),IF(v="","UNKNOWN",v)) -> #NAME? | F7: =_xludf.LET(cnt,COUNTIFS(tblClaimCandidates[entity_id],#REF!,tblClaimCandidates[field_key],#REF!,tblClaimCandidates[status_final],"PROMOTED"),IF(cnt=0,NA(),SUMIFS(tblClaimCandidates[value_num],tblClaimCandidates[entity_id],#REF!,tblClaimCandidates[field_key],#REF!,tblClaimCandidates[status_final],"PROMOTED"))) -> #NAME? | G7: =IFERROR(_xludf.XLOOKUP(#REF!,tblFieldDictionary[field_key],tblFieldDictionary[units]),"") | H7: =_xludf.LET(cnt,COUNTIFS(tblClaimCandidates[entity_id],#REF!,tblClaimCandidates[field_key],#REF!,tblClaimCandidates[status_final],"PROMOTED"),IF(cnt=0,NA(),AVERAGEIFS(tblClaimCandidates[confidence],tblClaimCandidates[entity_id],#REF!,tblClaimCandidates[field_key],#REF!,tblClaimCandidates[status_final],"PROMOTED"))) -> #NAME? | I7: =IFERROR(LOOKUP(2,1/((tblClaimCandidates[entity_id]=#REF!)*(tblClaimCandidates[field_key]=#REF!)*(tblClaimCandidates[status_final]="PROMOTED")),tblClaimCandidates[evidence_id]),"") | J7: =IF(#REF!="","",IFERROR(_xludf.XLOOKUP(#REF!,tblEvidence[evidence_id],tblEvidence[url],""),"")) -> #REF! | K7: =IFERROR(LOOKUP(2,1/((tblClaimCandidates[entity_id]=#REF!)*(tblClaimCandidates[field_key]=#REF!)*(tblClaimCandidates[status_final]="PROMOTED")),tblClaimCandidates[tier]),"") | L7: =IF(#REF!="UNKNOWN","UNKNOWN","PROMOTED") -> #REF! | M7: =IF(#REF!="PROMOTED",TODAY(),"") -> #REF! | N7: =IF(#REF!="PROMOTED","evidence_linked","UNKNOWN_or_unverified") -> #REF!
A8: E001 | B8: AcmeRival | C8: SEG_MM | D8: features | E8: =_xludf.LET(v,IFERROR(LOOKUP(2,1/((tblClaimCandidates[entity_id]=#REF!)*(tblClaimCandidates[field_key]=#REF!)*(tblClaimCandidates[status_final]="PROMOTED")),tblClaimCandidates[value_text]),""),IF(v="","UNKNOWN",v)) -> #NAME? | F8: =_xludf.LET(cnt,COUNTIFS(tblClaimCandidates[entity_id],#REF!,tblClaimCandidates[field_key],#REF!,tblClaimCandidates[status_final],"PROMOTED"),IF(cnt=0,NA(),SUMIFS(tblClaimCandidates[value_num],tblClaimCandidates[entity_id],#REF!,tblClaimCandidates[field_key],#REF!,tblClaimCandidates[status_final],"PROMOTED"))) -> #NAME? | G8: =IFERROR(_xludf.XLOOKUP(#REF!,tblFieldDictionary[field_key],tblFieldDictionary[units]),"") | H8: =_xludf.LET(cnt,COUNTIFS(tblClaimCandidates[entity_id],#REF!,tblClaimCandidates[field_key],#REF!,tblClaimCandidates[status_final],"PROMOTED"),IF(cnt=0,NA(),AVERAGEIFS(tblClaimCandidates[confidence],tblClaimCandidates[entity_id],#REF!,tblClaimCandidates[field_key],#REF!,tblClaimCandidates[status_final],"PROMOTED"))) -> #NAME? | I8: =IFERROR(LOOKUP(2,1/((tblClaimCandidates[entity_id]=#REF!)*(tblClaimCandidates[field_key]=#REF!)*(tblClaimCandidates[status_final]="PROMOTED")),tblClaimCandidates[evidence_id]),"") | J8: =IF(#REF!="","",IFERROR(_xludf.XLOOKUP(#REF!,tblEvidence[evidence_id],tblEvidence[url],""),"")) -> #REF! | K8: =IFERROR(LOOKUP(2,1/((tblClaimCandidates[entity_id]=#REF!)*(tblClaimCandidates[field_key]=#REF!)*(tblClaimCandidates[status_final]="PROMOTED")),tblClaimCandidates[tier]),"") | L8: =IF(#REF!="UNKNOWN","UNKNOWN","PROMOTED") -> #REF! | M8: =IF(#REF!="PROMOTED",TODAY(),"") -> #REF! | N8: =IF(#REF!="PROMOTED","evidence_linked","UNKNOWN_or_unverified") -> #REF!
A9: E001 | B9: AcmeRival | C9: SEG_MM | D9: funding_round | E9: =_xludf.LET(v,IFERROR(LOOKUP(2,1/((tblClaimCandidates[entity_id]=#REF!)*(tblClaimCandidates[field_key]=#REF!)*(tblClaimCandidates[status_final]="PROMOTED")),tblClaimCandidates[value_text]),""),IF(v="","UNKNOWN",v)) -> #NAME? | F9: =_xludf.LET(cnt,COUNTIFS(tblClaimCandidates[entity_id],#REF!,tblClaimCandidates[field_key],#REF!,tblClaimCandidates[status_final],"PROMOTED"),IF(cnt=0,NA(),SUMIFS(tblClaimCandidates[value_num],tblClaimCandidates[entity_id],#REF!,tblClaimCandidates[field_key],#REF!,tblClaimCandidates[status_final],"PROMOTED"))) -> #NAME? | G9: =IFERROR(_xludf.XLOOKUP(#REF!,tblFieldDictionary[field_key],tblFieldDictionary[units]),"") | H9: =_xludf.LET(cnt,COUNTIFS(tblClaimCandidates[entity_id],#REF!,tblClaimCandidates[field_key],#REF!,tblClaimCandidates[status_final],"PROMOTED"),IF(cnt=0,NA(),AVERAGEIFS(tblClaimCandidates[confidence],tblClaimCandidates[entity_id],#REF!,tblClaimCandidates[field_key],#REF!,tblClaimCandidates[status_final],"PROMOTED"))) -> #NAME? | I9: =IFERROR(LOOKUP(2,1/((tblClaimCandidates[entity_id]=#REF!)*(tblClaimCandidates[field_key]=#REF!)*(tblClaimCandidates[status_final]="PROMOTED")),tblClaimCandidates[evidence_id]),"") | J9: =IF(#REF!="","",IFERROR(_xludf.XLOOKUP(#REF!,tblEvidence[evidence_id],tblEvidence[url],""),"")) -> #REF! | K9: =IFERROR(LOOKUP(2,1/((tblClaimCandidates[entity_id]=#REF!)*(tblClaimCandidates[field_key]=#REF!)*(tblClaimCandidates[status_final]="PROMOTED")),tblClaimCandidates[tier]),"") | L9: =IF(#REF!="UNKNOWN","UNKNOWN","PROMOTED") -> #REF! | M9: =IF(#REF!="PROMOTED",TODAY(),"") -> #REF! | N9: =IF(#REF!="PROMOTED","evidence_linked","UNKNOWN_or_unverified") -> #REF!
A10: E001 | B10: AcmeRival | C10: SEG_MM | D10: geo_coverage | E10: =_xludf.LET(v,IFERROR(LOOKUP(2,1/((tblClaimCandidates[entity_id]=#REF!)*(tblClaimCandidates[field_key]=#REF!)*(tblClaimCandidates[status_final]="PROMOTED")),tblClaimCandidates[value_text]),""),IF(v="","UNKNOWN",v)) -> #NAME? | F10: =_xludf.LET(cnt,COUNTIFS(tblClaimCandidates[entity_id],#REF!,tblClaimCandidates[field_key],#REF!,tblClaimCandidates[status_final],"PROMOTED"),IF(cnt=0,NA(),SUMIFS(tblClaimCandidates[value_num],tblClaimCandidates[entity_id],#REF!,tblClaimCandidates[field_key],#REF!,tblClaimCandidates[status_final],"PROMOTED"))) -> #NAME? | G10: =IFERROR(_xludf.XLOOKUP(#REF!,tblFieldDictionary[field_key],tblFieldDictionary[units]),"") | H10: =_xludf.LET(cnt,COUNTIFS(tblClaimCandidates[entity_id],#REF!,tblClaimCandidates[field_key],#REF!,tblClaimCandidates[status_final],"PROMOTED"),IF(cnt=0,NA(),AVERAGEIFS(tblClaimCandidates[confidence],tblClaimCandidates[entity_id],#REF!,tblClaimCandidates[field_key],#REF!,tblClaimCandidates[status_final],"PROMOTED"))) -> #NAME? | I10: =IFERROR(LOOKUP(2,1/((tblClaimCandidates[entity_id]=#REF!)*(tblClaimCandidates[field_key]=#REF!)*(tblClaimCandidates[status_final]="PROMOTED")),tblClaimCandidates[evidence_id]),"") | J10: =IF(#REF!="","",IFERROR(_xludf.XLOOKUP(#REF!,tblEvidence[evidence_id],tblEvidence[url],""),"")) -> #REF! | K10: =IFERROR(LOOKUP(2,1/((tblClaimCandidates[entity_id]=#REF!)*(tblClaimCandidates[field_key]=#REF!)*(tblClaimCandidates[status_final]="PROMOTED")),tblClaimCandidates[tier]),"") | L10: =IF(#REF!="UNKNOWN","UNKNOWN","PROMOTED") -> #REF! | M10: =IF(#REF!="PROMOTED",TODAY(),"") -> #REF! | N10: =IF(#REF!="PROMOTED","evidence_linked","UNKNOWN_or_unverified") -> #REF!
A11: E001 | B11: AcmeRival | C11: SEG_MM | D11: practice_size_target | E11: =_xludf.LET(v,IFERROR(LOOKUP(2,1/((tblClaimCandidates[entity_id]=#REF!)*(tblClaimCandidates[field_key]=#REF!)*(tblClaimCandidates[status_final]="PROMOTED")),tblClaimCandidates[value_text]),""),IF(v="","UNKNOWN",v)) -> #NAME? | F11: =_xludf.LET(cnt,COUNTIFS(tblClaimCandidates[entity_id],#REF!,tblClaimCandidates[field_key],#REF!,tblClaimCandidates[status_final],"PROMOTED"),IF(cnt=0,NA(),SUMIFS(tblClaimCandidates[value_num],tblClaimCandidates[entity_id],#REF!,tblClaimCandidates[field_key],#REF!,tblClaimCandidates[status_final],"PROMOTED"))) -> #NAME? | G11: =IFERROR(_xludf.XLOOKUP(#REF!,tblFieldDictionary[field_key],tblFieldDictionary[units]),"") | H11: =_xludf.LET(cnt,COUNTIFS(tblClaimCandidates[entity_id],#REF!,tblClaimCandidates[field_key],#REF!,tblClaimCandidates[status_final],"PROMOTED"),IF(cnt=0,NA(),AVERAGEIFS(tblClaimCandidates[confidence],tblClaimCandidates[entity_id],#REF!,tblClaimCandidates[field_key],#REF!,tblClaimCandidates[status_final],"PROMOTED"))) -> #NAME? | I11: =IFERROR(LOOKUP(2,1/((tblClaimCandidates[entity_id]=#REF!)*(tblClaimCandidates[field_key]=#REF!)*(tblClaimCandidates[status_final]="PROMOTED")),tblClaimCandidates[evidence_id]),"") | J11: =IF(#REF!="","",IFERROR(_xludf.XLOOKUP(#REF!,tblEvidence[evidence_id],tblEvidence[url],""),"")) -> #REF! | K11: =IFERROR(LOOKUP(2,1/((tblClaimCandidates[entity_id]=#REF!)*(tblClaimCandidates[field_key]=#REF!)*(tblClaimCandidates[status_final]="PROMOTED")),tblClaimCandidates[tier]),"") | L11: =IF(#REF!="UNKNOWN","UNKNOWN","PROMOTED") -> #REF! | M11: =IF(#REF!="PROMOTED",TODAY(),"") -> #REF! | N11: =IF(#REF!="PROMOTED","evidence_linked","UNKNOWN_or_unverified") -> #REF!
A12: E002 | B12: EnrollPro | C12: SEG_MM | D12: pricing_acv_mid_market | E12: =_xludf.LET(v,IFERROR(LOOKUP(2,1/((tblClaimCandidates[entity_id]=#REF!)*(tblClaimCandidates[field_key]=#REF!)*(tblClaimCandidates[status_final]="PROMOTED")),tblClaimCandidates[value_text]),""),IF(v="","UNKNOWN",v)) -> #NAME? | F12: =_xludf.LET(cnt,COUNTIFS(tblClaimCandidates[entity_id],#REF!,tblClaimCandidates[field_key],#REF!,tblClaimCandidates[status_final],"PROMOTED"),IF(cnt=0,NA(),SUMIFS(tblClaimCandidates[value_num],tblClaimCandidates[entity_id],#REF!,tblClaimCandidates[field_key],#REF!,tblClaimCandidates[status_final],"PROMOTED"))) -> #NAME? | G12: =IFERROR(_xludf.XLOOKUP(#REF!,tblFieldDictionary[field_key],tblFieldDictionary[units]),"") | H12: =_xludf.LET(cnt,COUNTIFS(tblClaimCandidates[entity_id],#REF!,tblClaimCandidates[field_key],#REF!,tblClaimCandidates[status_final],"PROMOTED"),IF(cnt=0,NA(),AVERAGEIFS(tblClaimCandidates[confidence],tblClaimCandidates[entity_id],#REF!,tblClaimCandidates[field_key],#REF!,tblClaimCandidates[status_final],"PROMOTED"))) -> #NAME? | I12: =IFERROR(LOOKUP(2,1/((tblClaimCandidates[entity_id]=#REF!)*(tblClaimCandidates[field_key]=#REF!)*(tblClaimCandidates[status_final]="PROMOTED")),tblClaimCandidates[evidence_id]),"") | J12: =IF(#REF!="","",IFERROR(_xludf.XLOOKUP(#REF!,tblEvidence[evidence_id],tblEvidence[url],""),"")) -> #REF! | K12: =IFERROR(LOOKUP(2,1/((tblClaimCandidates[entity_id]=#REF!)*(tblClaimCandidates[field_key]=#REF!)*(tblClaimCandidates[status_final]="PROMOTED")),tblClaimCandidates[tier]),"") | L12: =IF(#REF!="UNKNOWN","UNKNOWN","PROMOTED") -> #REF! | M12: =IF(#REF!="PROMOTED",TODAY(),"") -> #REF! | N12: =IF(#REF!="PROMOTED","evidence_linked","UNKNOWN_or_unverified") -> #REF!
A13: E002 | B13: EnrollPro | C13: SEG_MM | D13: arr_estimate | E13: =_xludf.LET(v,IFERROR(LOOKUP(2,1/((tblClaimCandidates[entity_id]=#REF!)*(tblClaimCandidates[field_key]=#REF!)*(tblClaimCandidates[status_final]="PROMOTED")),tblClaimCandidates[value_text]),""),IF(v="","UNKNOWN",v)) -> #NAME? | F13: =_xludf.LET(cnt,COUNTIFS(tblClaimCandidates[entity_id],#REF!,tblClaimCandidates[field_key],#REF!,tblClaimCandidates[status_final],"PROMOTED"),IF(cnt=0,NA(),SUMIFS(tblClaimCandidates[value_num],tblClaimCandidates[entity_id],#REF!,tblClaimCandidates[field_key],#REF!,tblClaimCandidates[status_final],"PROMOTED"))) -> #NAME? | G13: =IFERROR(_xludf.XLOOKUP(#REF!,tblFieldDictionary[field_key],tblFieldDictionary[units]),"") | H13: =_xludf.LET(cnt,COUNTIFS(tblClaimCandidates[entity_id],#REF!,tblClaimCandidates[field_key],#REF!,tblClaimCandidates[status_final],"PROMOTED"),IF(cnt=0,NA(),AVERAGEIFS(tblClaimCandidates[confidence],tblClaimCandidates[entity_id],#REF!,tblClaimCandidates[field_key],#REF!,tblClaimCandidates[status_final],"PROMOTED"))) -> #NAME? | I13: =IFERROR(LOOKUP(2,1/((tblClaimCandidates[entity_id]=#REF!)*(tblClaimCandidates[field_key]=#REF!)*(tblClaimCandidates[status_final]="PROMOTED")),tblClaimCandidates[evidence_id]),"") | J13: =IF(#REF!="","",IFERROR(_xludf.XLOOKUP(#REF!,tblEvidence[evidence_id],tblEvidence[url],""),"")) -> #REF! | K13: =IFERROR(LOOKUP(2,1/((tblClaimCandidates[entity_id]=#REF!)*(tblClaimCandidates[field_key]=#REF!)*(tblClaimCandidates[status_final]="PROMOTED")),tblClaimCandidates[tier]),"") | L13: =IF(#REF!="UNKNOWN","UNKNOWN","PROMOTED") -> #REF! | M13: =IF(#REF!="PROMOTED",TODAY(),"") -> #REF! | N13: =IF(#REF!="PROMOTED","evidence_linked","UNKNOWN_or_unverified") -> #REF!
A14: E002 | B14: EnrollPro | C14: SEG_MM | D14: contract_terms | E14: =_xludf.LET(v,IFERROR(LOOKUP(2,1/((tblClaimCandidates[entity_id]=#REF!)*(tblClaimCandidates[field_key]=#REF!)*(tblClaimCandidates[status_final]="PROMOTED")),tblClaimCandidates[value_text]),""),IF(v="","UNKNOWN",v)) -> #NAME? | F14: =_xludf.LET(cnt,COUNTIFS(tblClaimCandidates[entity_id],#REF!,tblClaimCandidates[field_key],#REF!,tblClaimCandidates[status_final],"PROMOTED"),IF(cnt=0,NA(),SUMIFS(tblClaimCandidates[value_num],tblClaimCandidates[entity_id],#REF!,tblClaimCandidates[field_key],#REF!,tblClaimCandidates[status_final],"PROMOTED"))) -> #NAME? | G14: =IFERROR(_xludf.XLOOKUP(#REF!,tblFieldDictionary[field_key],tblFieldDictionary[units]),"") | H14: =_xludf.LET(cnt,COUNTIFS(tblClaimCandidates[entity_id],#REF!,tblClaimCandidates[field_key],#REF!,tblClaimCandidates[status_final],"PROMOTED"),IF(cnt=0,NA(),AVERAGEIFS(tblClaimCandidates[confidence],tblClaimCandidates[entity_id],#REF!,tblClaimCandidates[field_key],#REF!,tblClaimCandidates[status_final],"PROMOTED"))) -> #NAME? | I14: =IFERROR(LOOKUP(2,1/((tblClaimCandidates[entity_id]=#REF!)*(tblClaimCandidates[field_key]=#REF!)*(tblClaimCandidates[status_final]="PROMOTED")),tblClaimCandidates[evidence_id]),"") | J14: =IF(#REF!="","",IFERROR(_xludf.XLOOKUP(#REF!,tblEvidence[evidence_id],tblEvidence[url],""),"")) -> #REF! | K14: =IFERROR(LOOKUP(2,1/((tblClaimCandidates[entity_id]=#REF!)*(tblClaimCandidates[field_key]=#REF!)*(tblClaimCandidates[status_final]="PROMOTED")),tblClaimCandidates[tier]),"") | L14: =IF(#REF!="UNKNOWN","UNKNOWN","PROMOTED") -> #REF! | M14: =IF(#REF!="PROMOTED",TODAY(),"") -> #REF! | N14: =IF(#REF!="PROMOTED","evidence_linked","UNKNOWN_or_unverified") -> #REF!
A15: E002 | B15: EnrollPro | C15: SEG_MM | D15: features | E15: =_xludf.LET(v,IFERROR(LOOKUP(2,1/((tblClaimCandidates[entity_id]=#REF!)*(tblClaimCandidates[field_key]=#REF!)*(tblClaimCandidates[status_final]="PROMOTED")),tblClaimCandidates[value_text]),""),IF(v="","UNKNOWN",v)) -> #NAME? | F15: =_xludf.LET(cnt,COUNTIFS(tblClaimCandidates[entity_id],#REF!,tblClaimCandidates[field_key],#REF!,tblClaimCandidates[status_final],"PROMOTED"),IF(cnt=0,NA(),SUMIFS(tblClaimCandidates[value_num],tblClaimCandidates[entity_id],#REF!,tblClaimCandidates[field_key],#REF!,tblClaimCandidates[status_final],"PROMOTED"))) -> #NAME? | G15: =IFERROR(_xludf.XLOOKUP(#REF!,tblFieldDictionary[field_key],tblFieldDictionary[units]),"") | H15: =_xludf.LET(cnt,COUNTIFS(tblClaimCandidates[entity_id],#REF!,tblClaimCandidates[field_key],#REF!,tblClaimCandidates[status_final],"PROMOTED"),IF(cnt=0,NA(),AVERAGEIFS(tblClaimCandidates[confidence],tblClaimCandidates[entity_id],#REF!,tblClaimCandidates[field_key],#REF!,tblClaimCandidates[status_final],"PROMOTED"))) -> #NAME? | I15: =IFERROR(LOOKUP(2,1/((tblClaimCandidates[entity_id]=#REF!)*(tblClaimCandidates[field_key]=#REF!)*(tblClaimCandidates[status_final]="PROMOTED")),tblClaimCandidates[evidence_id]),"") | J15: =IF(#REF!="","",IFERROR(_xludf.XLOOKUP(#REF!,tblEvidence[evidence_id],tblEvidence[url],""),"")) -> #REF! | K15: =IFERROR(LOOKUP(2,1/((tblClaimCandidates[entity_id]=#REF!)*(tblClaimCandidates[field_key]=#REF!)*(tblClaimCandidates[status_final]="PROMOTED")),tblClaimCandidates[tier]),"") | L15: =IF(#REF!="UNKNOWN","UNKNOWN","PROMOTED") -> #REF! | M15: =IF(#REF!="PROMOTED",TODAY(),"") -> #REF! | N15: =IF(#REF!="PROMOTED","evidence_linked","UNKNOWN_or_unverified") -> #REF!
A16: E002 | B16: EnrollPro | C16: SEG_MM | D16: funding_round | E16: =_xludf.LET(v,IFERROR(LOOKUP(2,1/((tblClaimCandidates[entity_id]=#REF!)*(tblClaimCandidates[field_key]=#REF!)*(tblClaimCandidates[status_final]="PROMOTED")),tblClaimCandidates[value_text]),""),IF(v="","UNKNOWN",v)) -> #NAME? | F16: =_xludf.LET(cnt,COUNTIFS(tblClaimCandidates[entity_id],#REF!,tblClaimCandidates[field_key],#REF!,tblClaimCandidates[status_final],"PROMOTED"),IF(cnt=0,NA(),SUMIFS(tblClaimCandidates[value_num],tblClaimCandidates[entity_id],#REF!,tblClaimCandidates[field_key],#REF!,tblClaimCandidates[status_final],"PROMOTED"))) -> #NAME? | G16: =IFERROR(_xludf.XLOOKUP(#REF!,tblFieldDictionary[field_key],tblFieldDictionary[units]),"") | H16: =_xludf.LET(cnt,COUNTIFS(tblClaimCandidates[entity_id],#REF!,tblClaimCandidates[field_key],#REF!,tblClaimCandidates[status_final],"PROMOTED"),IF(cnt=0,NA(),AVERAGEIFS(tblClaimCandidates[confidence],tblClaimCandidates[entity_id],#REF!,tblClaimCandidates[field_key],#REF!,tblClaimCandidates[status_final],"PROMOTED"))) -> #NAME? | I16: =IFERROR(LOOKUP(2,1/((tblClaimCandidates[entity_id]=#REF!)*(tblClaimCandidates[field_key]=#REF!)*(tblClaimCandidates[status_final]="PROMOTED")),tblClaimCandidates[evidence_id]),"") | J16: =IF(#REF!="","",IFERROR(_xludf.XLOOKUP(#REF!,tblEvidence[evidence_id],tblEvidence[url],""),"")) -> #REF! | K16: =IFERROR(LOOKUP(2,1/((tblClaimCandidates[entity_id]=#REF!)*(tblClaimCandidates[field_key]=#REF!)*(tblClaimCandidates[status_final]="PROMOTED")),tblClaimCandidates[tier]),"") | L16: =IF(#REF!="UNKNOWN","UNKNOWN","PROMOTED") -> #REF! | M16: =IF(#REF!="PROMOTED",TODAY(),"") -> #REF! | N16: =IF(#REF!="PROMOTED","evidence_linked","UNKNOWN_or_unverified") -> #REF!
... A46: E006 | B46: MidMarketMedTech | C46: SEG_MM | D46: practice_size_target | E46: =_xludf.LET(v,IFERROR(LOOKUP(2,1/((tblClaimCandidates[entity_id]=#REF!)*(tblClaimCandidates[field_key]=#REF!)*(tblClaimCandidates[status_final]="PROMOTED")),tblClaimCandidates[value_text]),""),IF(v="","UNKNOWN",v)) -> #NAME? | F46: =_xludf.LET(cnt,COUNTIFS(tblClaimCandidates[entity_id],#REF!,tblClaimCandidates[field_key],#REF!,tblClaimCandidates[status_final],"PROMOTED"),IF(cnt=0,NA(),SUMIFS(tblClaimCandidates[value_num],tblClaimCandidates[entity_id],#REF!,tblClaimCandidates[field_key],#REF!,tblClaimCandidates[status_final],"PROMOTED"))) -> #NAME? | G46: =IFERROR(_xludf.XLOOKUP(#REF!,tblFieldDictionary[field_key],tblFieldDictionary[units]),"") | H46: =_xludf.LET(cnt,COUNTIFS(tblClaimCandidates[entity_id],#REF!,tblClaimCandidates[field_key],#REF!,tblClaimCandidates[status_final],"PROMOTED"),IF(cnt=0,NA(),AVERAGEIFS(tblClaimCandidates[confidence],tblClaimCandidates[entity_id],#REF!,tblClaimCandidates[field_key],#REF!,tblClaimCandidates[status_final],"PROMOTED"))) -> #NAME? | I46: =IFERROR(LOOKUP(2,1/((tblClaimCandidates[entity_id]=#REF!)*(tblClaimCandidates[field_key]=#REF!)*(tblClaimCandidates[status_final]="PROMOTED")),tblClaimCandidates[evidence_id]),"") | J46: =IF(#REF!="","",IFERROR(_xludf.XLOOKUP(#REF!,tblEvidence[evidence_id],tblEvidence[url],""),"")) -> #REF! | K46: =IFERROR(LOOKUP(2,1/((tblClaimCandidates[entity_id]=#REF!)*(tblClaimCandidates[field_key]=#REF!)*(tblClaimCandidates[status_final]="PROMOTED")),tblClaimCandidates[tier]),"") | L46: =IF(#REF!="UNKNOWN","UNKNOWN","PROMOTED") -> #REF! | M46: =IF(#REF!="PROMOTED",TODAY(),"") -> #REF! | N46: =IF(#REF!="PROMOTED","evidence_linked","UNKNOWN_or_unverified") -> #REF!

Sheet Metrics
A1: Metrics (Derived; Formula-Driven)
A2: All figures are derived from Claims_Current (which must be evidence-backed). UNKNOWN propagates to Review Queue and fail-closed flags.
A4: Global Drivers
A5: Median ACV (USD/year) | D5: Evidence Freshness Threshold (days) | E5: =Config!$B$9 -> 30 | G5: Min Coverage (fail-closed) | H5: =Config!$B$10 -> 0.6
A7: entity_id | B7: canonical_name | C7: known_claims | D7: unknown_claims | E7: coverage_pct | F7: avg_conf | G7: acv_usd | H7: acv_band | I7: features_text | J7: feature_count | K7: segment_fit | L7: funding_present | M7: threat_score | N7: opportunity_score | O7: flags | P7: segment_id | Q7: vertical | R7: in_scope | AA7: competitors_in_scope
A8: =IF(Input!$A$7="","",Input!$A$7) -> E001 | B8: =IFERROR(_xludf.XLOOKUP(#REF!,tblEntities[entity_id],tblEntities[canonical_name]),"") | C8: =IF(#REF!="","",COUNTIFS(tblClaimsCurrent[entity_id],#REF!,tblClaimsCurrent[status],"PROMOTED")) -> #REF! | D8: =IF(#REF!="","",COUNTIFS(tblClaimsCurrent[entity_id],#REF!,tblClaimsCurrent[status],"UNKNOWN")) -> #REF! | E8: =_xludf.LET(t,#REF!+#REF!,IF(t=0,NA(),#REF!/t)) -> #NAME? | F8: =_xludf.LET(cnt,COUNTIFS(tblClaimsCurrent[entity_id],#REF!,tblClaimsCurrent[status],"PROMOTED"),IF(cnt=0,NA(),AVERAGEIFS(tblClaimsCurrent[confidence],tblClaimsCurrent[entity_id],#REF!,tblClaimsCurrent[status],"PROMOTED"))) -> #NAME? | G8: =_xludf.LET(cnt,COUNTIFS(tblClaimsCurrent[entity_id],#REF!,tblClaimsCurrent[field_key],"pricing_acv_mid_market",tblClaimsCurrent[status],"PROMOTED"),IF(cnt=0,NA(),SUMIFS(tblClaimsCurrent[value_num],tblClaimsCurrent[entity_id],#REF!,tblClaimsCurrent[field_key],"pricing_acv_mid_market",tblClaimsCurrent[status],"PROMOTED"))) -> #NAME? | H8: =IF(OR(NOT(ISNUMBER(#REF!)),$B$5=""),"UNKNOWN",IF(#REF!<=($B$5*0.85),"Low",IF(#REF!>=($B$5*1.15),"High","Mid"))) -> UNKNOWN | I8: =_xludf.LET(v,IFERROR(LOOKUP(2,1/((tblClaimsCurrent[entity_id]=#REF!)*(tblClaimsCurrent[field_key]="features")*(tblClaimsCurrent[status]="PROMOTED")),tblClaimsCurrent[value_text]),"UNKNOWN"),IF(v="","UNKNOWN",v)) -> #NAME? | J8: =IF(OR(#REF!="UNKNOWN",#REF!=""),NA(),1+LEN(#REF!)-LEN(SUBSTITUTE(#REF!,";",""))) -> #REF! | K8: =IF(#REF!="",NA(),IF(#REF!="SEG_MM",1,0)) -> #REF! | L8: =IF(#REF!="","",IF(COUNTIFS(tblClaimsCurrent[entity_id],#REF!,tblClaimsCurrent[field_key],"funding_round",tblClaimsCurrent[status],"PROMOTED")>0,1,0)) -> #REF! | M8: =IF(OR(#REF!=FALSE,ISNA(#REF!),ISNA(#REF!),ISNA(#REF!),#REF!="UNKNOWN"),NA(),MIN(1,Config!$B$14*MIN(1,#REF!/10)+Config!$B$15*IF(#REF!="Low",1,IF(#REF!="Mid",0.5,0))+Config!$B$16*#REF!+Config!$B$17*#REF!)) -> #REF! | N8: =IF(OR(#REF!=FALSE,ISNA(#REF!),ISNA(#REF!),ISNA(#REF!)),NA(),MIN(1,Config!$B$18*(1-MIN(1,#REF!/10))+Config!$B$19*(1-#REF!)+Config!$B$20*(1-#REF!))) -> #REF! | O8: =IF(#REF!=FALSE,"OUT_OF_SCOPE",IF(ISNA(#REF!),"UNKNOWN",IF(#REF!<Config!$B$10,"FAIL_CLOSED_LOW_COVERAGE","OK"))) -> #REF! | P8: =IFERROR(_xludf.XLOOKUP(#REF!,tblEntities[entity_id],tblEntities[segment_id]),"") | Q8: =IFERROR(_xludf.XLOOKUP(#REF!,tblEntities[entity_id],tblEntities[vertical]),"") | R8: =AND(#REF!=Dashboard!$E$2,IF(Dashboard!$E$3="All",TRUE,#REF!=Dashboard!$E$3)) -> #REF!
A9: =IF(Input!$A$8="","",Input!$A$8) -> E002 | B9: =IFERROR(_xludf.XLOOKUP(#REF!,tblEntities[entity_id],tblEntities[canonical_name]),"") | C9: =IF(#REF!="","",COUNTIFS(tblClaimsCurrent[entity_id],#REF!,tblClaimsCurrent[status],"PROMOTED")) -> #REF! | D9: =IF(#REF!="","",COUNTIFS(tblClaimsCurrent[entity_id],#REF!,tblClaimsCurrent[status],"UNKNOWN")) -> #REF! | E9: =_xludf.LET(t,#REF!+#REF!,IF(t=0,NA(),#REF!/t)) -> #NAME? | F9: =_xludf.LET(cnt,COUNTIFS(tblClaimsCurrent[entity_id],#REF!,tblClaimsCurrent[status],"PROMOTED"),IF(cnt=0,NA(),AVERAGEIFS(tblClaimsCurrent[confidence],tblClaimsCurrent[entity_id],#REF!,tblClaimsCurrent[status],"PROMOTED"))) -> #NAME? | G9: =_xludf.LET(cnt,COUNTIFS(tblClaimsCurrent[entity_id],#REF!,tblClaimsCurrent[field_key],"pricing_acv_mid_market",tblClaimsCurrent[status],"PROMOTED"),IF(cnt=0,NA(),SUMIFS(tblClaimsCurrent[value_num],tblClaimsCurrent[entity_id],#REF!,tblClaimsCurrent[field_key],"pricing_acv_mid_market",tblClaimsCurrent[status],"PROMOTED"))) -> #NAME? | H9: =IF(OR(NOT(ISNUMBER(#REF!)),$B$5=""),"UNKNOWN",IF(#REF!<=($B$5*0.85),"Low",IF(#REF!>=($B$5*1.15),"High","Mid"))) -> UNKNOWN | I9: =_xludf.LET(v,IFERROR(LOOKUP(2,1/((tblClaimsCurrent[entity_id]=#REF!)*(tblClaimsCurrent[field_key]="features")*(tblClaimsCurrent[status]="PROMOTED")),tblClaimsCurrent[value_text]),"UNKNOWN"),IF(v="","UNKNOWN",v)) -> #NAME? | J9: =IF(OR(#REF!="UNKNOWN",#REF!=""),NA(),1+LEN(#REF!)-LEN(SUBSTITUTE(#REF!,";",""))) -> #REF! | K9: =IF(#REF!="",NA(),IF(#REF!="SEG_MM",1,0)) -> #REF! | L9: =IF(#REF!="","",IF(COUNTIFS(tblClaimsCurrent[entity_id],#REF!,tblClaimsCurrent[field_key],"funding_round",tblClaimsCurrent[status],"PROMOTED")>0,1,0)) -> #REF! | M9: =IF(OR(#REF!=FALSE,ISNA(#REF!),ISNA(#REF!),ISNA(#REF!),#REF!="UNKNOWN"),NA(),MIN(1,Config!$B$14*MIN(1,#REF!/10)+Config!$B$15*IF(#REF!="Low",1,IF(#REF!="Mid",0.5,0))+Config!$B$16*#REF!+Config!$B$17*#REF!)) -> #REF! | N9: =IF(OR(#REF!=FALSE,ISNA(#REF!),ISNA(#REF!),ISNA(#REF!)),NA(),MIN(1,Config!$B$18*(1-MIN(1,#REF!/10))+Config!$B$19*(1-#REF!)+Config!$B$20*(1-#REF!))) -> #REF! | O9: =IF(#REF!=FALSE,"OUT_OF_SCOPE",IF(ISNA(#REF!),"UNKNOWN",IF(#REF!<Config!$B$10,"FAIL_CLOSED_LOW_COVERAGE","OK"))) -> #REF! | P9: =IFERROR(_xludf.XLOOKUP(#REF!,tblEntities[entity_id],tblEntities[segment_id]),"") | Q9: =IFERROR(_xludf.XLOOKUP(#REF!,tblEntities[entity_id],tblEntities[vertical]),"") | R9: =AND(#REF!=Dashboard!$E$2,IF(Dashboard!$E$3="All",TRUE,#REF!=Dashboard!$E$3)) -> #REF!
A10: =IF(Input!$A$9="","",Input!$A$9) -> E003 | B10: =IFERROR(_xludf.XLOOKUP(#REF!,tblEntities[entity_id],tblEntities[canonical_name]),"") | C10: =IF(#REF!="","",COUNTIFS(tblClaimsCurrent[entity_id],#REF!,tblClaimsCurrent[status],"PROMOTED")) -> #REF! | D10: =IF(#REF!="","",COUNTIFS(tblClaimsCurrent[entity_id],#REF!,tblClaimsCurrent[status],"UNKNOWN")) -> #REF! | E10: =_xludf.LET(t,#REF!+#REF!,IF(t=0,NA(),#REF!/t)) -> #NAME? | F10: =_xludf.LET(cnt,COUNTIFS(tblClaimsCurrent[entity_id],#REF!,tblClaimsCurrent[status],"PROMOTED"),IF(cnt=0,NA(),AVERAGEIFS(tblClaimsCurrent[confidence],tblClaimsCurrent[entity_id],#REF!,tblClaimsCurrent[status],"PROMOTED"))) -> #NAME? | G10: =_xludf.LET(cnt,COUNTIFS(tblClaimsCurrent[entity_id],#REF!,tblClaimsCurrent[field_key],"pricing_acv_mid_market",tblClaimsCurrent[status],"PROMOTED"),IF(cnt=0,NA(),SUMIFS(tblClaimsCurrent[value_num],tblClaimsCurrent[entity_id],#REF!,tblClaimsCurrent[field_key],"pricing_acv_mid_market",tblClaimsCurrent[status],"PROMOTED"))) -> #NAME? | H10: =IF(OR(NOT(ISNUMBER(#REF!)),$B$5=""),"UNKNOWN",IF(#REF!<=($B$5*0.85),"Low",IF(#REF!>=($B$5*1.15),"High","Mid"))) -> UNKNOWN | I10: =_xludf.LET(v,IFERROR(LOOKUP(2,1/((tblClaimsCurrent[entity_id]=#REF!)*(tblClaimsCurrent[field_key]="features")*(tblClaimsCurrent[status]="PROMOTED")),tblClaimsCurrent[value_text]),"UNKNOWN"),IF(v="","UNKNOWN",v)) -> #NAME? | J10: =IF(OR(#REF!="UNKNOWN",#REF!=""),NA(),1+LEN(#REF!)-LEN(SUBSTITUTE(#REF!,";",""))) -> #REF! | K10: =IF(#REF!="",NA(),IF(#REF!="SEG_MM",1,0)) -> #REF! | L10: =IF(#REF!="","",IF(COUNTIFS(tblClaimsCurrent[entity_id],#REF!,tblClaimsCurrent[field_key],"funding_round",tblClaimsCurrent[status],"PROMOTED")>0,1,0)) -> #REF! | M10: =IF(OR(#REF!=FALSE,ISNA(#REF!),ISNA(#REF!),ISNA(#REF!),#REF!="UNKNOWN"),NA(),MIN(1,Config!$B$14*MIN(1,#REF!/10)+Config!$B$15*IF(#REF!="Low",1,IF(#REF!="Mid",0.5,0))+Config!$B$16*#REF!+Config!$B$17*#REF!)) -> #REF! | N10: =IF(OR(#REF!=FALSE,ISNA(#REF!),ISNA(#REF!),ISNA(#REF!)),NA(),MIN(1,Config!$B$18*(1-MIN(1,#REF!/10))+Config!$B$19*(1-#REF!)+Config!$B$20*(1-#REF!))) -> #REF! | O10: =IF(#REF!=FALSE,"OUT_OF_SCOPE",IF(ISNA(#REF!),"UNKNOWN",IF(#REF!<Config!$B$10,"FAIL_CLOSED_LOW_COVERAGE","OK"))) -> #REF! | P10: =IFERROR(_xludf.XLOOKUP(#REF!,tblEntities[entity_id],tblEntities[segment_id]),"") | Q10: =IFERROR(_xludf.XLOOKUP(#REF!,tblEntities[entity_id],tblEntities[vertical]),"") | R10: =AND(#REF!=Dashboard!$E$2,IF(Dashboard!$E$3="All",TRUE,#REF!=Dashboard!$E$3)) -> #REF!
A11: =IF(Input!$A$10="","",Input!$A$10) -> E004 | B11: =IFERROR(_xludf.XLOOKUP(#REF!,tblEntities[entity_id],tblEntities[canonical_name]),"") | C11: =IF(#REF!="","",COUNTIFS(tblClaimsCurrent[entity_id],#REF!,tblClaimsCurrent[status],"PROMOTED")) -> #REF! | D11: =IF(#REF!="","",COUNTIFS(tblClaimsCurrent[entity_id],#REF!,tblClaimsCurrent[status],"UNKNOWN")) -> #REF! | E11: =_xludf.LET(t,#REF!+#REF!,IF(t=0,NA(),#REF!/t)) -> #NAME? | F11: =_xludf.LET(cnt,COUNTIFS(tblClaimsCurrent[entity_id],#REF!,tblClaimsCurrent[status],"PROMOTED"),IF(cnt=0,NA(),AVERAGEIFS(tblClaimsCurrent[confidence],tblClaimsCurrent[entity_id],#REF!,tblClaimsCurrent[status],"PROMOTED"))) -> #NAME? | G11: =_xludf.LET(cnt,COUNTIFS(tblClaimsCurrent[entity_id],#REF!,tblClaimsCurrent[field_key],"pricing_acv_mid_market",tblClaimsCurrent[status],"PROMOTED"),IF(cnt=0,NA(),SUMIFS(tblClaimsCurrent[value_num],tblClaimsCurrent[entity_id],#REF!,tblClaimsCurrent[field_key],"pricing_acv_mid_market",tblClaimsCurrent[status],"PROMOTED"))) -> #NAME? | H11: =IF(OR(NOT(ISNUMBER(#REF!)),$B$5=""),"UNKNOWN",IF(#REF!<=($B$5*0.85),"Low",IF(#REF!>=($B$5*1.15),"High","Mid"))) -> UNKNOWN | I11: =_xludf.LET(v,IFERROR(LOOKUP(2,1/((tblClaimsCurrent[entity_id]=#REF!)*(tblClaimsCurrent[field_key]="features")*(tblClaimsCurrent[status]="PROMOTED")),tblClaimsCurrent[value_text]),"UNKNOWN"),IF(v="","UNKNOWN",v)) -> #NAME? | J11: =IF(OR(#REF!="UNKNOWN",#REF!=""),NA(),1+LEN(#REF!)-LEN(SUBSTITUTE(#REF!,";",""))) -> #REF! | K11: =IF(#REF!="",NA(),IF(#REF!="SEG_MM",1,0)) -> #REF! | L11: =IF(#REF!="","",IF(COUNTIFS(tblClaimsCurrent[entity_id],#REF!,tblClaimsCurrent[field_key],"funding_round",tblClaimsCurrent[status],"PROMOTED")>0,1,0)) -> #REF! | M11: =IF(OR(#REF!=FALSE,ISNA(#REF!),ISNA(#REF!),ISNA(#REF!),#REF!="UNKNOWN"),NA(),MIN(1,Config!$B$14*MIN(1,#REF!/10)+Config!$B$15*IF(#REF!="Low",1,IF(#REF!="Mid",0.5,0))+Config!$B$16*#REF!+Config!$B$17*#REF!)) -> #REF! | N11: =IF(OR(#REF!=FALSE,ISNA(#REF!),ISNA(#REF!),ISNA(#REF!)),NA(),MIN(1,Config!$B$18*(1-MIN(1,#REF!/10))+Config!$B$19*(1-#REF!)+Config!$B$20*(1-#REF!))) -> #REF! | O11: =IF(#REF!=FALSE,"OUT_OF_SCOPE",IF(ISNA(#REF!),"UNKNOWN",IF(#REF!<Config!$B$10,"FAIL_CLOSED_LOW_COVERAGE","OK"))) -> #REF! | P11: =IFERROR(_xludf.XLOOKUP(#REF!,tblEntities[entity_id],tblEntities[segment_id]),"") | Q11: =IFERROR(_xludf.XLOOKUP(#REF!,tblEntities[entity_id],tblEntities[vertical]),"") | R11: =AND(#REF!=Dashboard!$E$2,IF(Dashboard!$E$3="All",TRUE,#REF!=Dashboard!$E$3)) -> #REF!
A12: =IF(Input!$A$11="","",Input!$A$11) -> E005 | B12: =IFERROR(_xludf.XLOOKUP(#REF!,tblEntities[entity_id],tblEntities[canonical_name]),"") | C12: =IF(#REF!="","",COUNTIFS(tblClaimsCurrent[entity_id],#REF!,tblClaimsCurrent[status],"PROMOTED")) -> #REF! | D12: =IF(#REF!="","",COUNTIFS(tblClaimsCurrent[entity_id],#REF!,tblClaimsCurrent[status],"UNKNOWN")) -> #REF! | E12: =_xludf.LET(t,#REF!+#REF!,IF(t=0,NA(),#REF!/t)) -> #NAME? | F12: =_xludf.LET(cnt,COUNTIFS(tblClaimsCurrent[entity_id],#REF!,tblClaimsCurrent[status],"PROMOTED"),IF(cnt=0,NA(),AVERAGEIFS(tblClaimsCurrent[confidence],tblClaimsCurrent[entity_id],#REF!,tblClaimsCurrent[status],"PROMOTED"))) -> #NAME? | G12: =_xludf.LET(cnt,COUNTIFS(tblClaimsCurrent[entity_id],#REF!,tblClaimsCurrent[field_key],"pricing_acv_mid_market",tblClaimsCurrent[status],"PROMOTED"),IF(cnt=0,NA(),SUMIFS(tblClaimsCurrent[value_num],tblClaimsCurrent[entity_id],#REF!,tblClaimsCurrent[field_key],"pricing_acv_mid_market",tblClaimsCurrent[status],"PROMOTED"))) -> #NAME? | H12: =IF(OR(NOT(ISNUMBER(#REF!)),$B$5=""),"UNKNOWN",IF(#REF!<=($B$5*0.85),"Low",IF(#REF!>=($B$5*1.15),"High","Mid"))) -> UNKNOWN | I12: =_xludf.LET(v,IFERROR(LOOKUP(2,1/((tblClaimsCurrent[entity_id]=#REF!)*(tblClaimsCurrent[field_key]="features")*(tblClaimsCurrent[status]="PROMOTED")),tblClaimsCurrent[value_text]),"UNKNOWN"),IF(v="","UNKNOWN",v)) -> #NAME? | J12: =IF(OR(#REF!="UNKNOWN",#REF!=""),NA(),1+LEN(#REF!)-LEN(SUBSTITUTE(#REF!,";",""))) -> #REF! | K12: =IF(#REF!="",NA(),IF(#REF!="SEG_MM",1,0)) -> #REF! | L12: =IF(#REF!="","",IF(COUNTIFS(tblClaimsCurrent[entity_id],#REF!,tblClaimsCurrent[field_key],"funding_round",tblClaimsCurrent[status],"PROMOTED")>0,1,0)) -> #REF! | M12: =IF(OR(#REF!=FALSE,ISNA(#REF!),ISNA(#REF!),ISNA(#REF!),#REF!="UNKNOWN"),NA(),MIN(1,Config!$B$14*MIN(1,#REF!/10)+Config!$B$15*IF(#REF!="Low",1,IF(#REF!="Mid",0.5,0))+Config!$B$16*#REF!+Config!$B$17*#REF!)) -> #REF! | N12: =IF(OR(#REF!=FALSE,ISNA(#REF!),ISNA(#REF!),ISNA(#REF!)),NA(),MIN(1,Config!$B$18*(1-MIN(1,#REF!/10))+Config!$B$19*(1-#REF!)+Config!$B$20*(1-#REF!))) -> #REF! | O12: =IF(#REF!=FALSE,"OUT_OF_SCOPE",IF(ISNA(#REF!),"UNKNOWN",IF(#REF!<Config!$B$10,"FAIL_CLOSED_LOW_COVERAGE","OK"))) -> #REF! | P12: =IFERROR(_xludf.XLOOKUP(#REF!,tblEntities[entity_id],tblEntities[segment_id]),"") | Q12: =IFERROR(_xludf.XLOOKUP(#REF!,tblEntities[entity_id],tblEntities[vertical]),"") | R12: =AND(#REF!=Dashboard!$E$2,IF(Dashboard!$E$3="All",TRUE,#REF!=Dashboard!$E$3)) -> #REF!
A13: =IF(Input!$A$12="","",Input!$A$12) -> E006 | B13: =IFERROR(_xludf.XLOOKUP(#REF!,tblEntities[entity_id],tblEntities[canonical_name]),"") | C13: =IF(#REF!="","",COUNTIFS(tblClaimsCurrent[entity_id],#REF!,tblClaimsCurrent[status],"PROMOTED")) -> #REF! | D13: =IF(#REF!="","",COUNTIFS(tblClaimsCurrent[entity_id],#REF!,tblClaimsCurrent[status],"UNKNOWN")) -> #REF! | E13: =_xludf.LET(t,#REF!+#REF!,IF(t=0,NA(),#REF!/t)) -> #NAME? | F13: =_xludf.LET(cnt,COUNTIFS(tblClaimsCurrent[entity_id],#REF!,tblClaimsCurrent[status],"PROMOTED"),IF(cnt=0,NA(),AVERAGEIFS(tblClaimsCurrent[confidence],tblClaimsCurrent[entity_id],#REF!,tblClaimsCurrent[status],"PROMOTED"))) -> #NAME? | G13: =_xludf.LET(cnt,COUNTIFS(tblClaimsCurrent[entity_id],#REF!,tblClaimsCurrent[field_key],"pricing_acv_mid_market",tblClaimsCurrent[status],"PROMOTED"),IF(cnt=0,NA(),SUMIFS(tblClaimsCurrent[value_num],tblClaimsCurrent[entity_id],#REF!,tblClaimsCurrent[field_key],"pricing_acv_mid_market",tblClaimsCurrent[status],"PROMOTED"))) -> #NAME? | H13: =IF(OR(NOT(ISNUMBER(#REF!)),$B$5=""),"UNKNOWN",IF(#REF!<=($B$5*0.85),"Low",IF(#REF!>=($B$5*1.15),"High","Mid"))) -> UNKNOWN | I13: =_xludf.LET(v,IFERROR(LOOKUP(2,1/((tblClaimsCurrent[entity_id]=#REF!)*(tblClaimsCurrent[field_key]="features")*(tblClaimsCurrent[status]="PROMOTED")),tblClaimsCurrent[value_text]),"UNKNOWN"),IF(v="","UNKNOWN",v)) -> #NAME? | J13: =IF(OR(#REF!="UNKNOWN",#REF!=""),NA(),1+LEN(#REF!)-LEN(SUBSTITUTE(#REF!,";",""))) -> #REF! | K13: =IF(#REF!="",NA(),IF(#REF!="SEG_MM",1,0)) -> #REF! | L13: =IF(#REF!="","",IF(COUNTIFS(tblClaimsCurrent[entity_id],#REF!,tblClaimsCurrent[field_key],"funding_round",tblClaimsCurrent[status],"PROMOTED")>0,1,0)) -> #REF! | M13: =IF(OR(#REF!=FALSE,ISNA(#REF!),ISNA(#REF!),ISNA(#REF!),#REF!="UNKNOWN"),NA(),MIN(1,Config!$B$14*MIN(1,#REF!/10)+Config!$B$15*IF(#REF!="Low",1,IF(#REF!="Mid",0.5,0))+Config!$B$16*#REF!+Config!$B$17*#REF!)) -> #REF! | N13: =IF(OR(#REF!=FALSE,ISNA(#REF!),ISNA(#REF!),ISNA(#REF!)),NA(),MIN(1,Config!$B$18*(1-MIN(1,#REF!/10))+Config!$B$19*(1-#REF!)+Config!$B$20*(1-#REF!))) -> #REF! | O13: =IF(#REF!=FALSE,"OUT_OF_SCOPE",IF(ISNA(#REF!),"UNKNOWN",IF(#REF!<Config!$B$10,"FAIL_CLOSED_LOW_COVERAGE","OK"))) -> #REF! | P13: =IFERROR(_xludf.XLOOKUP(#REF!,tblEntities[entity_id],tblEntities[segment_id]),"") | Q13: =IFERROR(_xludf.XLOOKUP(#REF!,tblEntities[entity_id],tblEntities[vertical]),"") | R13: =AND(#REF!=Dashboard!$E$2,IF(Dashboard!$E$3="All",TRUE,#REF!=Dashboard!$E$3)) -> #REF!
A14: =IF(Input!$A$13="","",Input!$A$13) | B14: =IFERROR(_xludf.XLOOKUP(#REF!,tblEntities[entity_id],tblEntities[canonical_name]),"") | C14: =IF(#REF!="","",COUNTIFS(tblClaimsCurrent[entity_id],#REF!,tblClaimsCurrent[status],"PROMOTED")) -> #REF! | D14: =IF(#REF!="","",COUNTIFS(tblClaimsCurrent[entity_id],#REF!,tblClaimsCurrent[status],"UNKNOWN")) -> #REF! | E14: =_xludf.LET(t,#REF!+#REF!,IF(t=0,NA(),#REF!/t)) -> #NAME? | F14: =_xludf.LET(cnt,COUNTIFS(tblClaimsCurrent[entity_id],#REF!,tblClaimsCurrent[status],"PROMOTED"),IF(cnt=0,NA(),AVERAGEIFS(tblClaimsCurrent[confidence],tblClaimsCurrent[entity_id],#REF!,tblClaimsCurrent[status],"PROMOTED"))) -> #NAME? | G14: =_xludf.LET(cnt,COUNTIFS(tblClaimsCurrent[entity_id],#REF!,tblClaimsCurrent[field_key],"pricing_acv_mid_market",tblClaimsCurrent[status],"PROMOTED"),IF(cnt=0,NA(),SUMIFS(tblClaimsCurrent[value_num],tblClaimsCurrent[entity_id],#REF!,tblClaimsCurrent[field_key],"pricing_acv_mid_market",tblClaimsCurrent[status],"PROMOTED"))) -> #NAME? | H14: =IF(OR(NOT(ISNUMBER(#REF!)),$B$5=""),"UNKNOWN",IF(#REF!<=($B$5*0.85),"Low",IF(#REF!>=($B$5*1.15),"High","Mid"))) -> UNKNOWN | I14: =_xludf.LET(v,IFERROR(LOOKUP(2,1/((tblClaimsCurrent[entity_id]=#REF!)*(tblClaimsCurrent[field_key]="features")*(tblClaimsCurrent[status]="PROMOTED")),tblClaimsCurrent[value_text]),"UNKNOWN"),IF(v="","UNKNOWN",v)) -> #NAME? | J14: =IF(OR(#REF!="UNKNOWN",#REF!=""),NA(),1+LEN(#REF!)-LEN(SUBSTITUTE(#REF!,";",""))) -> #REF! | K14: =IF(#REF!="",NA(),IF(#REF!="SEG_MM",1,0)) -> #REF! | L14: =IF(#REF!="","",IF(COUNTIFS(tblClaimsCurrent[entity_id],#REF!,tblClaimsCurrent[field_key],"funding_round",tblClaimsCurrent[status],"PROMOTED")>0,1,0)) -> #REF! | M14: =IF(OR(#REF!=FALSE,ISNA(#REF!),ISNA(#REF!),ISNA(#REF!),#REF!="UNKNOWN"),NA(),MIN(1,Config!$B$14*MIN(1,#REF!/10)+Config!$B$15*IF(#REF!="Low",1,IF(#REF!="Mid",0.5,0))+Config!$B$16*#REF!+Config!$B$17*#REF!)) -> #REF! | N14: =IF(OR(#REF!=FALSE,ISNA(#REF!),ISNA(#REF!),ISNA(#REF!)),NA(),MIN(1,Config!$B$18*(1-MIN(1,#REF!/10))+Config!$B$19*(1-#REF!)+Config!$B$20*(1-#REF!))) -> #REF! | O14: =IF(#REF!=FALSE,"OUT_OF_SCOPE",IF(ISNA(#REF!),"UNKNOWN",IF(#REF!<Config!$B$10,"FAIL_CLOSED_LOW_COVERAGE","OK"))) -> #REF! | P14: =IFERROR(_xludf.XLOOKUP(#REF!,tblEntities[entity_id],tblEntities[segment_id]),"") | Q14: =IFERROR(_xludf.XLOOKUP(#REF!,tblEntities[entity_id],tblEntities[vertical]),"") | R14: =AND(#REF!=Dashboard!$E$2,IF(Dashboard!$E$3="All",TRUE,#REF!=Dashboard!$E$3)) -> #REF!
A15: =IF(Input!$A$14="","",Input!$A$14) | B15: =IFERROR(_xludf.XLOOKUP(#REF!,tblEntities[entity_id],tblEntities[canonical_name]),"") | C15: =IF(#REF!="","",COUNTIFS(tblClaimsCurrent[entity_id],#REF!,tblClaimsCurrent[status],"PROMOTED")) -> #REF! | D15: =IF(#REF!="","",COUNTIFS(tblClaimsCurrent[entity_id],#REF!,tblClaimsCurrent[status],"UNKNOWN")) -> #REF! | E15: =_xludf.LET(t,#REF!+#REF!,IF(t=0,NA(),#REF!/t)) -> #NAME? | F15: =_xludf.LET(cnt,COUNTIFS(tblClaimsCurrent[entity_id],#REF!,tblClaimsCurrent[status],"PROMOTED"),IF(cnt=0,NA(),AVERAGEIFS(tblClaimsCurrent[confidence],tblClaimsCurrent[entity_id],#REF!,tblClaimsCurrent[status],"PROMOTED"))) -> #NAME? | G15: =_xludf.LET(cnt,COUNTIFS(tblClaimsCurrent[entity_id],#REF!,tblClaimsCurrent[field_key],"pricing_acv_mid_market",tblClaimsCurrent[status],"PROMOTED"),IF(cnt=0,NA(),SUMIFS(tblClaimsCurrent[value_num],tblClaimsCurrent[entity_id],#REF!,tblClaimsCurrent[field_key],"pricing_acv_mid_market",tblClaimsCurrent[status],"PROMOTED"))) -> #NAME? | H15: =IF(OR(NOT(ISNUMBER(#REF!)),$B$5=""),"UNKNOWN",IF(#REF!<=($B$5*0.85),"Low",IF(#REF!>=($B$5*1.15),"High","Mid"))) -> UNKNOWN | I15: =_xludf.LET(v,IFERROR(LOOKUP(2,1/((tblClaimsCurrent[entity_id]=#REF!)*(tblClaimsCurrent[field_key]="features")*(tblClaimsCurrent[status]="PROMOTED")),tblClaimsCurrent[value_text]),"UNKNOWN"),IF(v="","UNKNOWN",v)) -> #NAME? | J15: =IF(OR(#REF!="UNKNOWN",#REF!=""),NA(),1+LEN(#REF!)-LEN(SUBSTITUTE(#REF!,";",""))) -> #REF! | K15: =IF(#REF!="",NA(),IF(#REF!="SEG_MM",1,0)) -> #REF! | L15: =IF(#REF!="","",IF(COUNTIFS(tblClaimsCurrent[entity_id],#REF!,tblClaimsCurrent[field_key],"funding_round",tblClaimsCurrent[status],"PROMOTED")>0,1,0)) -> #REF! | M15: =IF(OR(#REF!=FALSE,ISNA(#REF!),ISNA(#REF!),ISNA(#REF!),#REF!="UNKNOWN"),NA(),MIN(1,Config!$B$14*MIN(1,#REF!/10)+Config!$B$15*IF(#REF!="Low",1,IF(#REF!="Mid",0.5,0))+Config!$B$16*#REF!+Config!$B$17*#REF!)) -> #REF! | N15: =IF(OR(#REF!=FALSE,ISNA(#REF!),ISNA(#REF!),ISNA(#REF!)),NA(),MIN(1,Config!$B$18*(1-MIN(1,#REF!/10))+Config!$B$19*(1-#REF!)+Config!$B$20*(1-#REF!))) -> #REF! | O15: =IF(#REF!=FALSE,"OUT_OF_SCOPE",IF(ISNA(#REF!),"UNKNOWN",IF(#REF!<Config!$B$10,"FAIL_CLOSED_LOW_COVERAGE","OK"))) -> #REF! | P15: =IFERROR(_xludf.XLOOKUP(#REF!,tblEntities[entity_id],tblEntities[segment_id]),"") | Q15: =IFERROR(_xludf.XLOOKUP(#REF!,tblEntities[entity_id],tblEntities[vertical]),"") | R15: =AND(#REF!=Dashboard!$E$2,IF(Dashboard!$E$3="All",TRUE,#REF!=Dashboard!$E$3)) -> #REF!
A16: =IF(Input!$A$15="","",Input!$A$15) -> Evidence (Claims must link here) | B16: =IFERROR(_xludf.XLOOKUP(#REF!,tblEntities[entity_id],tblEntities[canonical_name]),"") | C16: =IF(#REF!="","",COUNTIFS(tblClaimsCurrent[entity_id],#REF!,tblClaimsCurrent[status],"PROMOTED")) -> #REF! | D16: =IF(#REF!="","",COUNTIFS(tblClaimsCurrent[entity_id],#REF!,tblClaimsCurrent[status],"UNKNOWN")) -> #REF! | E16: =_xludf.LET(t,#REF!+#REF!,IF(t=0,NA(),#REF!/t)) -> #NAME? | F16: =_xludf.LET(cnt,COUNTIFS(tblClaimsCurrent[entity_id],#REF!,tblClaimsCurrent[status],"PROMOTED"),IF(cnt=0,NA(),AVERAGEIFS(tblClaimsCurrent[confidence],tblClaimsCurrent[entity_id],#REF!,tblClaimsCurrent[status],"PROMOTED"))) -> #NAME? | G16: =_xludf.LET(cnt,COUNTIFS(tblClaimsCurrent[entity_id],#REF!,tblClaimsCurrent[field_key],"pricing_acv_mid_market",tblClaimsCurrent[status],"PROMOTED"),IF(cnt=0,NA(),SUMIFS(tblClaimsCurrent[value_num],tblClaimsCurrent[entity_id],#REF!,tblClaimsCurrent[field_key],"pricing_acv_mid_market",tblClaimsCurrent[status],"PROMOTED"))) -> #NAME? | H16: =IF(OR(NOT(ISNUMBER(#REF!)),$B$5=""),"UNKNOWN",IF(#REF!<=($B$5*0.85),"Low",IF(#REF!>=($B$5*1.15),"High","Mid"))) -> UNKNOWN | I16: =_xludf.LET(v,IFERROR(LOOKUP(2,1/((tblClaimsCurrent[entity_id]=#REF!)*(tblClaimsCurrent[field_key]="features")*(tblClaimsCurrent[status]="PROMOTED")),tblClaimsCurrent[value_text]),"UNKNOWN"),IF(v="","UNKNOWN",v)) -> #NAME? | J16: =IF(OR(#REF!="UNKNOWN",#REF!=""),NA(),1+LEN(#REF!)-LEN(SUBSTITUTE(#REF!,";",""))) -> #REF! | K16: =IF(#REF!="",NA(),IF(#REF!="SEG_MM",1,0)) -> #REF! | L16: =IF(#REF!="","",IF(COUNTIFS(tblClaimsCurrent[entity_id],#REF!,tblClaimsCurrent[field_key],"funding_round",tblClaimsCurrent[status],"PROMOTED")>0,1,0)) -> #REF! | M16: =IF(OR(#REF!=FALSE,ISNA(#REF!),ISNA(#REF!),ISNA(#REF!),#REF!="UNKNOWN"),NA(),MIN(1,Config!$B$14*MIN(1,#REF!/10)+Config!$B$15*IF(#REF!="Low",1,IF(#REF!="Mid",0.5,0))+Config!$B$16*#REF!+Config!$B$17*#REF!)) -> #REF! | N16: =IF(OR(#REF!=FALSE,ISNA(#REF!),ISNA(#REF!),ISNA(#REF!)),NA(),MIN(1,Config!$B$18*(1-MIN(1,#REF!/10))+Config!$B$19*(1-#REF!)+Config!$B$20*(1-#REF!))) -> #REF! | O16: =IF(#REF!=FALSE,"OUT_OF_SCOPE",IF(ISNA(#REF!),"UNKNOWN",IF(#REF!<Config!$B$10,"FAIL_CLOSED_LOW_COVERAGE","OK"))) -> #REF! | P16: =IFERROR(_xludf.XLOOKUP(#REF!,tblEntities[entity_id],tblEntities[segment_id]),"") | Q16: =IFERROR(_xludf.XLOOKUP(#REF!,tblEntities[entity_id],tblEntities[vertical]),"") | R16: =AND(#REF!=Dashboard!$E$2,IF(Dashboard!$E$3="All",TRUE,#REF!=Dashboard!$E$3)) -> #REF!
A17: =IF(Input!$A$16="","",Input!$A$16) | B17: =IFERROR(_xludf.XLOOKUP(#REF!,tblEntities[entity_id],tblEntities[canonical_name]),"") | C17: =IF(#REF!="","",COUNTIFS(tblClaimsCurrent[entity_id],#REF!,tblClaimsCurrent[status],"PROMOTED")) -> #REF! | D17: =IF(#REF!="","",COUNTIFS(tblClaimsCurrent[entity_id],#REF!,tblClaimsCurrent[status],"UNKNOWN")) -> #REF! | E17: =_xludf.LET(t,#REF!+#REF!,IF(t=0,NA(),#REF!/t)) -> #NAME? | F17: =_xludf.LET(cnt,COUNTIFS(tblClaimsCurrent[entity_id],#REF!,tblClaimsCurrent[status],"PROMOTED"),IF(cnt=0,NA(),AVERAGEIFS(tblClaimsCurrent[confidence],tblClaimsCurrent[entity_id],#REF!,tblClaimsCurrent[status],"PROMOTED"))) -> #NAME? | G17: =_xludf.LET(cnt,COUNTIFS(tblClaimsCurrent[entity_id],#REF!,tblClaimsCurrent[field_key],"pricing_acv_mid_market",tblClaimsCurrent[status],"PROMOTED"),IF(cnt=0,NA(),SUMIFS(tblClaimsCurrent[value_num],tblClaimsCurrent[entity_id],#REF!,tblClaimsCurrent[field_key],"pricing_acv_mid_market",tblClaimsCurrent[status],"PROMOTED"))) -> #NAME? | H17: =IF(OR(NOT(ISNUMBER(#REF!)),$B$5=""),"UNKNOWN",IF(#REF!<=($B$5*0.85),"Low",IF(#REF!>=($B$5*1.15),"High","Mid"))) -> UNKNOWN | I17: =_xludf.LET(v,IFERROR(LOOKUP(2,1/((tblClaimsCurrent[entity_id]=#REF!)*(tblClaimsCurrent[field_key]="features")*(tblClaimsCurrent[status]="PROMOTED")),tblClaimsCurrent[value_text]),"UNKNOWN"),IF(v="","UNKNOWN",v)) -> #NAME? | J17: =IF(OR(#REF!="UNKNOWN",#REF!=""),NA(),1+LEN(#REF!)-LEN(SUBSTITUTE(#REF!,";",""))) -> #REF! | K17: =IF(#REF!="",NA(),IF(#REF!="SEG_MM",1,0)) -> #REF! | L17: =IF(#REF!="","",IF(COUNTIFS(tblClaimsCurrent[entity_id],#REF!,tblClaimsCurrent[field_key],"funding_round",tblClaimsCurrent[status],"PROMOTED")>0,1,0)) -> #REF! | M17: =IF(OR(#REF!=FALSE,ISNA(#REF!),ISNA(#REF!),ISNA(#REF!),#REF!="UNKNOWN"),NA(),MIN(1,Config!$B$14*MIN(1,#REF!/10)+Config!$B$15*IF(#REF!="Low",1,IF(#REF!="Mid",0.5,0))+Config!$B$16*#REF!+Config!$B$17*#REF!)) -> #REF! | N17: =IF(OR(#REF!=FALSE,ISNA(#REF!),ISNA(#REF!),ISNA(#REF!)),NA(),MIN(1,Config!$B$18*(1-MIN(1,#REF!/10))+Config!$B$19*(1-#REF!)+Config!$B$20*(1-#REF!))) -> #REF! | O17: =IF(#REF!=FALSE,"OUT_OF_SCOPE",IF(ISNA(#REF!),"UNKNOWN",IF(#REF!<Config!$B$10,"FAIL_CLOSED_LOW_COVERAGE","OK"))) -> #REF! | P17: =IFERROR(_xludf.XLOOKUP(#REF!,tblEntities[entity_id],tblEntities[segment_id]),"") | Q17: =IFERROR(_xludf.XLOOKUP(#REF!,tblEntities[entity_id],tblEntities[vertical]),"") | R17: =AND(#REF!=Dashboard!$E$2,IF(Dashboard!$E$3="All",TRUE,#REF!=Dashboard!$E$3)) -> #REF!
A18: =IF(Input!$A$17="","",Input!$A$17) -> evidence_id | B18: =IFERROR(_xludf.XLOOKUP(#REF!,tblEntities[entity_id],tblEntities[canonical_name]),"") | C18: =IF(#REF!="","",COUNTIFS(tblClaimsCurrent[entity_id],#REF!,tblClaimsCurrent[status],"PROMOTED")) -> #REF! | D18: =IF(#REF!="","",COUNTIFS(tblClaimsCurrent[entity_id],#REF!,tblClaimsCurrent[status],"UNKNOWN")) -> #REF! | E18: =_xludf.LET(t,#REF!+#REF!,IF(t=0,NA(),#REF!/t)) -> #NAME? | F18: =_xludf.LET(cnt,COUNTIFS(tblClaimsCurrent[entity_id],#REF!,tblClaimsCurrent[status],"PROMOTED"),IF(cnt=0,NA(),AVERAGEIFS(tblClaimsCurrent[confidence],tblClaimsCurrent[entity_id],#REF!,tblClaimsCurrent[status],"PROMOTED"))) -> #NAME? | G18: =_xludf.LET(cnt,COUNTIFS(tblClaimsCurrent[entity_id],#REF!,tblClaimsCurrent[field_key],"pricing_acv_mid_market",tblClaimsCurrent[status],"PROMOTED"),IF(cnt=0,NA(),SUMIFS(tblClaimsCurrent[value_num],tblClaimsCurrent[entity_id],#REF!,tblClaimsCurrent[field_key],"pricing_acv_mid_market",tblClaimsCurrent[status],"PROMOTED"))) -> #NAME? | H18: =IF(OR(NOT(ISNUMBER(#REF!)),$B$5=""),"UNKNOWN",IF(#REF!<=($B$5*0.85),"Low",IF(#REF!>=($B$5*1.15),"High","Mid"))) -> UNKNOWN | I18: =_xludf.LET(v,IFERROR(LOOKUP(2,1/((tblClaimsCurrent[entity_id]=#REF!)*(tblClaimsCurrent[field_key]="features")*(tblClaimsCurrent[status]="PROMOTED")),tblClaimsCurrent[value_text]),"UNKNOWN"),IF(v="","UNKNOWN",v)) -> #NAME? | J18: =IF(OR(#REF!="UNKNOWN",#REF!=""),NA(),1+LEN(#REF!)-LEN(SUBSTITUTE(#REF!,";",""))) -> #REF! | K18: =IF(#REF!="",NA(),IF(#REF!="SEG_MM",1,0)) -> #REF! | L18: =IF(#REF!="","",IF(COUNTIFS(tblClaimsCurrent[entity_id],#REF!,tblClaimsCurrent[field_key],"funding_round",tblClaimsCurrent[status],"PROMOTED")>0,1,0)) -> #REF! | M18: =IF(OR(#REF!=FALSE,ISNA(#REF!),ISNA(#REF!),ISNA(#REF!),#REF!="UNKNOWN"),NA(),MIN(1,Config!$B$14*MIN(1,#REF!/10)+Config!$B$15*IF(#REF!="Low",1,IF(#REF!="Mid",0.5,0))+Config!$B$16*#REF!+Config!$B$17*#REF!)) -> #REF! | N18: =IF(OR(#REF!=FALSE,ISNA(#REF!),ISNA(#REF!),ISNA(#REF!)),NA(),MIN(1,Config!$B$18*(1-MIN(1,#REF!/10))+Config!$B$19*(1-#REF!)+Config!$B$20*(1-#REF!))) -> #REF! | O18: =IF(#REF!=FALSE,"OUT_OF_SCOPE",IF(ISNA(#REF!),"UNKNOWN",IF(#REF!<Config!$B$10,"FAIL_CLOSED_LOW_COVERAGE","OK"))) -> #REF! | P18: =IFERROR(_xludf.XLOOKUP(#REF!,tblEntities[entity_id],tblEntities[segment_id]),"") | Q18: =IFERROR(_xludf.XLOOKUP(#REF!,tblEntities[entity_id],tblEntities[vertical]),"") | R18: =AND(#REF!=Dashboard!$E$2,IF(Dashboard!$E$3="All",TRUE,#REF!=Dashboard!$E$3)) -> #REF!
A19: =IF(Input!$A$18="","",Input!$A$18) -> EV001 | B19: =IFERROR(_xludf.XLOOKUP(#REF!,tblEntities[entity_id],tblEntities[canonical_name]),"") | C19: =IF(#REF!="","",COUNTIFS(tblClaimsCurrent[entity_id],#REF!,tblClaimsCurrent[status],"PROMOTED")) -> #REF! | D19: =IF(#REF!="","",COUNTIFS(tblClaimsCurrent[entity_id],#REF!,tblClaimsCurrent[status],"UNKNOWN")) -> #REF! | E19: =_xludf.LET(t,#REF!+#REF!,IF(t=0,NA(),#REF!/t)) -> #NAME? | F19: =_xludf.LET(cnt,COUNTIFS(tblClaimsCurrent[entity_id],#REF!,tblClaimsCurrent[status],"PROMOTED"),IF(cnt=0,NA(),AVERAGEIFS(tblClaimsCurrent[confidence],tblClaimsCurrent[entity_id],#REF!,tblClaimsCurrent[status],"PROMOTED"))) -> #NAME? | G19: =_xludf.LET(cnt,COUNTIFS(tblClaimsCurrent[entity_id],#REF!,tblClaimsCurrent[field_key],"pricing_acv_mid_market",tblClaimsCurrent[status],"PROMOTED"),IF(cnt=0,NA(),SUMIFS(tblClaimsCurrent[value_num],tblClaimsCurrent[entity_id],#REF!,tblClaimsCurrent[field_key],"pricing_acv_mid_market",tblClaimsCurrent[status],"PROMOTED"))) -> #NAME? | H19: =IF(OR(NOT(ISNUMBER(#REF!)),$B$5=""),"UNKNOWN",IF(#REF!<=($B$5*0.85),"Low",IF(#REF!>=($B$5*1.15),"High","Mid"))) -> UNKNOWN | I19: =_xludf.LET(v,IFERROR(LOOKUP(2,1/((tblClaimsCurrent[entity_id]=#REF!)*(tblClaimsCurrent[field_key]="features")*(tblClaimsCurrent[status]="PROMOTED")),tblClaimsCurrent[value_text]),"UNKNOWN"),IF(v="","UNKNOWN",v)) -> #NAME? | J19: =IF(OR(#REF!="UNKNOWN",#REF!=""),NA(),1+LEN(#REF!)-LEN(SUBSTITUTE(#REF!,";",""))) -> #REF! | K19: =IF(#REF!="",NA(),IF(#REF!="SEG_MM",1,0)) -> #REF! | L19: =IF(#REF!="","",IF(COUNTIFS(tblClaimsCurrent[entity_id],#REF!,tblClaimsCurrent[field_key],"funding_round",tblClaimsCurrent[status],"PROMOTED")>0,1,0)) -> #REF! | M19: =IF(OR(#REF!=FALSE,ISNA(#REF!),ISNA(#REF!),ISNA(#REF!),#REF!="UNKNOWN"),NA(),MIN(1,Config!$B$14*MIN(1,#REF!/10)+Config!$B$15*IF(#REF!="Low",1,IF(#REF!="Mid",0.5,0))+Config!$B$16*#REF!+Config!$B$17*#REF!)) -> #REF! | N19: =IF(OR(#REF!=FALSE,ISNA(#REF!),ISNA(#REF!),ISNA(#REF!)),NA(),MIN(1,Config!$B$18*(1-MIN(1,#REF!/10))+Config!$B$19*(1-#REF!)+Config!$B$20*(1-#REF!))) -> #REF! | O19: =IF(#REF!=FALSE,"OUT_OF_SCOPE",IF(ISNA(#REF!),"UNKNOWN",IF(#REF!<Config!$B$10,"FAIL_CLOSED_LOW_COVERAGE","OK"))) -> #REF! | P19: =IFERROR(_xludf.XLOOKUP(#REF!,tblEntities[entity_id],tblEntities[segment_id]),"") | Q19: =IFERROR(_xludf.XLOOKUP(#REF!,tblEntities[entity_id],tblEntities[vertical]),"") | R19: =AND(#REF!=Dashboard!$E$2,IF(Dashboard!$E$3="All",TRUE,#REF!=Dashboard!$E$3)) -> #REF!
A20: =IF(Input!$A$19="","",Input!$A$19) -> EV002 | B20: =IFERROR(_xludf.XLOOKUP(#REF!,tblEntities[entity_id],tblEntities[canonical_name]),"") | C20: =IF(#REF!="","",COUNTIFS(tblClaimsCurrent[entity_id],#REF!,tblClaimsCurrent[status],"PROMOTED")) -> #REF! | D20: =IF(#REF!="","",COUNTIFS(tblClaimsCurrent[entity_id],#REF!,tblClaimsCurrent[status],"UNKNOWN")) -> #REF! | E20: =_xludf.LET(t,#REF!+#REF!,IF(t=0,NA(),#REF!/t)) -> #NAME? | F20: =_xludf.LET(cnt,COUNTIFS(tblClaimsCurrent[entity_id],#REF!,tblClaimsCurrent[status],"PROMOTED"),IF(cnt=0,NA(),AVERAGEIFS(tblClaimsCurrent[confidence],tblClaimsCurrent[entity_id],#REF!,tblClaimsCurrent[status],"PROMOTED"))) -> #NAME? | G20: =_xludf.LET(cnt,COUNTIFS(tblClaimsCurrent[entity_id],#REF!,tblClaimsCurrent[field_key],"pricing_acv_mid_market",tblClaimsCurrent[status],"PROMOTED"),IF(cnt=0,NA(),SUMIFS(tblClaimsCurrent[value_num],tblClaimsCurrent[entity_id],#REF!,tblClaimsCurrent[field_key],"pricing_acv_mid_market",tblClaimsCurrent[status],"PROMOTED"))) -> #NAME? | H20: =IF(OR(NOT(ISNUMBER(#REF!)),$B$5=""),"UNKNOWN",IF(#REF!<=($B$5*0.85),"Low",IF(#REF!>=($B$5*1.15),"High","Mid"))) -> UNKNOWN | I20: =_xludf.LET(v,IFERROR(LOOKUP(2,1/((tblClaimsCurrent[entity_id]=#REF!)*(tblClaimsCurrent[field_key]="features")*(tblClaimsCurrent[status]="PROMOTED")),tblClaimsCurrent[value_text]),"UNKNOWN"),IF(v="","UNKNOWN",v)) -> #NAME? | J20: =IF(OR(#REF!="UNKNOWN",#REF!=""),NA(),1+LEN(#REF!)-LEN(SUBSTITUTE(#REF!,";",""))) -> #REF! | K20: =IF(#REF!="",NA(),IF(#REF!="SEG_MM",1,0)) -> #REF! | L20: =IF(#REF!="","",IF(COUNTIFS(tblClaimsCurrent[entity_id],#REF!,tblClaimsCurrent[field_key],"funding_round",tblClaimsCurrent[status],"PROMOTED")>0,1,0)) -> #REF! | M20: =IF(OR(#REF!=FALSE,ISNA(#REF!),ISNA(#REF!),ISNA(#REF!),#REF!="UNKNOWN"),NA(),MIN(1,Config!$B$14*MIN(1,#REF!/10)+Config!$B$15*IF(#REF!="Low",1,IF(#REF!="Mid",0.5,0))+Config!$B$16*#REF!+Config!$B$17*#REF!)) -> #REF! | N20: =IF(OR(#REF!=FALSE,ISNA(#REF!),ISNA(#REF!),ISNA(#REF!)),NA(),MIN(1,Config!$B$18*(1-MIN(1,#REF!/10))+Config!$B$19*(1-#REF!)+Config!$B$20*(1-#REF!))) -> #REF! | O20: =IF(#REF!=FALSE,"OUT_OF_SCOPE",IF(ISNA(#REF!),"UNKNOWN",IF(#REF!<Config!$B$10,"FAIL_CLOSED_LOW_COVERAGE","OK"))) -> #REF! | P20: =IFERROR(_xludf.XLOOKUP(#REF!,tblEntities[entity_id],tblEntities[segment_id]),"") | Q20: =IFERROR(_xludf.XLOOKUP(#REF!,tblEntities[entity_id],tblEntities[vertical]),"") | R20: =AND(#REF!=Dashboard!$E$2,IF(Dashboard!$E$3="All",TRUE,#REF!=Dashboard!$E$3)) -> #REF!
A21: =IF(Input!$A$20="","",Input!$A$20) -> EV003 | B21: =IFERROR(_xludf.XLOOKUP(#REF!,tblEntities[entity_id],tblEntities[canonical_name]),"") | C21: =IF(#REF!="","",COUNTIFS(tblClaimsCurrent[entity_id],#REF!,tblClaimsCurrent[status],"PROMOTED")) -> #REF! | D21: =IF(#REF!="","",COUNTIFS(tblClaimsCurrent[entity_id],#REF!,tblClaimsCurrent[status],"UNKNOWN")) -> #REF! | E21: =_xludf.LET(t,#REF!+#REF!,IF(t=0,NA(),#REF!/t)) -> #NAME? | F21: =_xludf.LET(cnt,COUNTIFS(tblClaimsCurrent[entity_id],#REF!,tblClaimsCurrent[status],"PROMOTED"),IF(cnt=0,NA(),AVERAGEIFS(tblClaimsCurrent[confidence],tblClaimsCurrent[entity_id],#REF!,tblClaimsCurrent[status],"PROMOTED"))) -> #NAME? | G21: =_xludf.LET(cnt,COUNTIFS(tblClaimsCurrent[entity_id],#REF!,tblClaimsCurrent[field_key],"pricing_acv_mid_market",tblClaimsCurrent[status],"PROMOTED"),IF(cnt=0,NA(),SUMIFS(tblClaimsCurrent[value_num],tblClaimsCurrent[entity_id],#REF!,tblClaimsCurrent[field_key],"pricing_acv_mid_market",tblClaimsCurrent[status],"PROMOTED"))) -> #NAME? | H21: =IF(OR(NOT(ISNUMBER(#REF!)),$B$5=""),"UNKNOWN",IF(#REF!<=($B$5*0.85),"Low",IF(#REF!>=($B$5*1.15),"High","Mid"))) -> UNKNOWN | I21: =_xludf.LET(v,IFERROR(LOOKUP(2,1/((tblClaimsCurrent[entity_id]=#REF!)*(tblClaimsCurrent[field_key]="features")*(tblClaimsCurrent[status]="PROMOTED")),tblClaimsCurrent[value_text]),"UNKNOWN"),IF(v="","UNKNOWN",v)) -> #NAME? | J21: =IF(OR(#REF!="UNKNOWN",#REF!=""),NA(),1+LEN(#REF!)-LEN(SUBSTITUTE(#REF!,";",""))) -> #REF! | K21: =IF(#REF!="",NA(),IF(#REF!="SEG_MM",1,0)) -> #REF! | L21: =IF(#REF!="","",IF(COUNTIFS(tblClaimsCurrent[entity_id],#REF!,tblClaimsCurrent[field_key],"funding_round",tblClaimsCurrent[status],"PROMOTED")>0,1,0)) -> #REF! | M21: =IF(OR(#REF!=FALSE,ISNA(#REF!),ISNA(#REF!),ISNA(#REF!),#REF!="UNKNOWN"),NA(),MIN(1,Config!$B$14*MIN(1,#REF!/10)+Config!$B$15*IF(#REF!="Low",1,IF(#REF!="Mid",0.5,0))+Config!$B$16*#REF!+Config!$B$17*#REF!)) -> #REF! | N21: =IF(OR(#REF!=FALSE,ISNA(#REF!),ISNA(#REF!),ISNA(#REF!)),NA(),MIN(1,Config!$B$18*(1-MIN(1,#REF!/10))+Config!$B$19*(1-#REF!)+Config!$B$20*(1-#REF!))) -> #REF! | O21: =IF(#REF!=FALSE,"OUT_OF_SCOPE",IF(ISNA(#REF!),"UNKNOWN",IF(#REF!<Config!$B$10,"FAIL_CLOSED_LOW_COVERAGE","OK"))) -> #REF! | P21: =IFERROR(_xludf.XLOOKUP(#REF!,tblEntities[entity_id],tblEntities[segment_id]),"") | Q21: =IFERROR(_xludf.XLOOKUP(#REF!,tblEntities[entity_id],tblEntities[vertical]),"") | R21: =AND(#REF!=Dashboard!$E$2,IF(Dashboard!$E$3="All",TRUE,#REF!=Dashboard!$E$3)) -> #REF!
A22: =IF(Input!$A$21="","",Input!$A$21) -> EV004 | B22: =IFERROR(_xludf.XLOOKUP(#REF!,tblEntities[entity_id],tblEntities[canonical_name]),"") | C22: =IF(#REF!="","",COUNTIFS(tblClaimsCurrent[entity_id],#REF!,tblClaimsCurrent[status],"PROMOTED")) -> #REF! | D22: =IF(#REF!="","",COUNTIFS(tblClaimsCurrent[entity_id],#REF!,tblClaimsCurrent[status],"UNKNOWN")) -> #REF! | E22: =_xludf.LET(t,#REF!+#REF!,IF(t=0,NA(),#REF!/t)) -> #NAME? | F22: =_xludf.LET(cnt,COUNTIFS(tblClaimsCurrent[entity_id],#REF!,tblClaimsCurrent[status],"PROMOTED"),IF(cnt=0,NA(),AVERAGEIFS(tblClaimsCurrent[confidence],tblClaimsCurrent[entity_id],#REF!,tblClaimsCurrent[status],"PROMOTED"))) -> #NAME? | G22: =_xludf.LET(cnt,COUNTIFS(tblClaimsCurrent[entity_id],#REF!,tblClaimsCurrent[field_key],"pricing_acv_mid_market",tblClaimsCurrent[status],"PROMOTED"),IF(cnt=0,NA(),SUMIFS(tblClaimsCurrent[value_num],tblClaimsCurrent[entity_id],#REF!,tblClaimsCurrent[field_key],"pricing_acv_mid_market",tblClaimsCurrent[status],"PROMOTED"))) -> #NAME? | H22: =IF(OR(NOT(ISNUMBER(#REF!)),$B$5=""),"UNKNOWN",IF(#REF!<=($B$5*0.85),"Low",IF(#REF!>=($B$5*1.15),"High","Mid"))) -> UNKNOWN | I22: =_xludf.LET(v,IFERROR(LOOKUP(2,1/((tblClaimsCurrent[entity_id]=#REF!)*(tblClaimsCurrent[field_key]="features")*(tblClaimsCurrent[status]="PROMOTED")),tblClaimsCurrent[value_text]),"UNKNOWN"),IF(v="","UNKNOWN",v)) -> #NAME? | J22: =IF(OR(#REF!="UNKNOWN",#REF!=""),NA(),1+LEN(#REF!)-LEN(SUBSTITUTE(#REF!,";",""))) -> #REF! | K22: =IF(#REF!="",NA(),IF(#REF!="SEG_MM",1,0)) -> #REF! | L22: =IF(#REF!="","",IF(COUNTIFS(tblClaimsCurrent[entity_id],#REF!,tblClaimsCurrent[field_key],"funding_round",tblClaimsCurrent[status],"PROMOTED")>0,1,0)) -> #REF! | M22: =IF(OR(#REF!=FALSE,ISNA(#REF!),ISNA(#REF!),ISNA(#REF!),#REF!="UNKNOWN"),NA(),MIN(1,Config!$B$14*MIN(1,#REF!/10)+Config!$B$15*IF(#REF!="Low",1,IF(#REF!="Mid",0.5,0))+Config!$B$16*#REF!+Config!$B$17*#REF!)) -> #REF! | N22: =IF(OR(#REF!=FALSE,ISNA(#REF!),ISNA(#REF!),ISNA(#REF!)),NA(),MIN(1,Config!$B$18*(1-MIN(1,#REF!/10))+Config!$B$19*(1-#REF!)+Config!$B$20*(1-#REF!))) -> #REF! | O22: =IF(#REF!=FALSE,"OUT_OF_SCOPE",IF(ISNA(#REF!),"UNKNOWN",IF(#REF!<Config!$B$10,"FAIL_CLOSED_LOW_COVERAGE","OK"))) -> #REF! | P22: =IFERROR(_xludf.XLOOKUP(#REF!,tblEntities[entity_id],tblEntities[segment_id]),"") | Q22: =IFERROR(_xludf.XLOOKUP(#REF!,tblEntities[entity_id],tblEntities[vertical]),"") | R22: =AND(#REF!=Dashboard!$E$2,IF(Dashboard!$E$3="All",TRUE,#REF!=Dashboard!$E$3)) -> #REF!
A23: =IF(Input!$A$22="","",Input!$A$22) -> EV005 | B23: =IFERROR(_xludf.XLOOKUP(#REF!,tblEntities[entity_id],tblEntities[canonical_name]),"") | C23: =IF(#REF!="","",COUNTIFS(tblClaimsCurrent[entity_id],#REF!,tblClaimsCurrent[status],"PROMOTED")) -> #REF! | D23: =IF(#REF!="","",COUNTIFS(tblClaimsCurrent[entity_id],#REF!,tblClaimsCurrent[status],"UNKNOWN")) -> #REF! | E23: =_xludf.LET(t,#REF!+#REF!,IF(t=0,NA(),#REF!/t)) -> #NAME? | F23: =_xludf.LET(cnt,COUNTIFS(tblClaimsCurrent[entity_id],#REF!,tblClaimsCurrent[status],"PROMOTED"),IF(cnt=0,NA(),AVERAGEIFS(tblClaimsCurrent[confidence],tblClaimsCurrent[entity_id],#REF!,tblClaimsCurrent[status],"PROMOTED"))) -> #NAME? | G23: =_xludf.LET(cnt,COUNTIFS(tblClaimsCurrent[entity_id],#REF!,tblClaimsCurrent[field_key],"pricing_acv_mid_market",tblClaimsCurrent[status],"PROMOTED"),IF(cnt=0,NA(),SUMIFS(tblClaimsCurrent[value_num],tblClaimsCurrent[entity_id],#REF!,tblClaimsCurrent[field_key],"pricing_acv_mid_market",tblClaimsCurrent[status],"PROMOTED"))) -> #NAME? | H23: =IF(OR(NOT(ISNUMBER(#REF!)),$B$5=""),"UNKNOWN",IF(#REF!<=($B$5*0.85),"Low",IF(#REF!>=($B$5*1.15),"High","Mid"))) -> UNKNOWN | I23: =_xludf.LET(v,IFERROR(LOOKUP(2,1/((tblClaimsCurrent[entity_id]=#REF!)*(tblClaimsCurrent[field_key]="features")*(tblClaimsCurrent[status]="PROMOTED")),tblClaimsCurrent[value_text]),"UNKNOWN"),IF(v="","UNKNOWN",v)) -> #NAME? | J23: =IF(OR(#REF!="UNKNOWN",#REF!=""),NA(),1+LEN(#REF!)-LEN(SUBSTITUTE(#REF!,";",""))) -> #REF! | K23: =IF(#REF!="",NA(),IF(#REF!="SEG_MM",1,0)) -> #REF! | L23: =IF(#REF!="","",IF(COUNTIFS(tblClaimsCurrent[entity_id],#REF!,tblClaimsCurrent[field_key],"funding_round",tblClaimsCurrent[status],"PROMOTED")>0,1,0)) -> #REF! | M23: =IF(OR(#REF!=FALSE,ISNA(#REF!),ISNA(#REF!),ISNA(#REF!),#REF!="UNKNOWN"),NA(),MIN(1,Config!$B$14*MIN(1,#REF!/10)+Config!$B$15*IF(#REF!="Low",1,IF(#REF!="Mid",0.5,0))+Config!$B$16*#REF!+Config!$B$17*#REF!)) -> #REF! | N23: =IF(OR(#REF!=FALSE,ISNA(#REF!),ISNA(#REF!),ISNA(#REF!)),NA(),MIN(1,Config!$B$18*(1-MIN(1,#REF!/10))+Config!$B$19*(1-#REF!)+Config!$B$20*(1-#REF!))) -> #REF! | O23: =IF(#REF!=FALSE,"OUT_OF_SCOPE",IF(ISNA(#REF!),"UNKNOWN",IF(#REF!<Config!$B$10,"FAIL_CLOSED_LOW_COVERAGE","OK"))) -> #REF! | P23: =IFERROR(_xludf.XLOOKUP(#REF!,tblEntities[entity_id],tblEntities[segment_id]),"") | Q23: =IFERROR(_xludf.XLOOKUP(#REF!,tblEntities[entity_id],tblEntities[vertical]),"") | R23: =AND(#REF!=Dashboard!$E$2,IF(Dashboard!$E$3="All",TRUE,#REF!=Dashboard!$E$3)) -> #REF!
A24: =IF(Input!$A$23="","",Input!$A$23) | B24: =IFERROR(_xludf.XLOOKUP(#REF!,tblEntities[entity_id],tblEntities[canonical_name]),"") | C24: =IF(#REF!="","",COUNTIFS(tblClaimsCurrent[entity_id],#REF!,tblClaimsCurrent[status],"PROMOTED")) -> #REF! | D24: =IF(#REF!="","",COUNTIFS(tblClaimsCurrent[entity_id],#REF!,tblClaimsCurrent[status],"UNKNOWN")) -> #REF! | E24: =_xludf.LET(t,#REF!+#REF!,IF(t=0,NA(),#REF!/t)) -> #NAME? | F24: =_xludf.LET(cnt,COUNTIFS(tblClaimsCurrent[entity_id],#REF!,tblClaimsCurrent[status],"PROMOTED"),IF(cnt=0,NA(),AVERAGEIFS(tblClaimsCurrent[confidence],tblClaimsCurrent[entity_id],#REF!,tblClaimsCurrent[status],"PROMOTED"))) -> #NAME? | G24: =_xludf.LET(cnt,COUNTIFS(tblClaimsCurrent[entity_id],#REF!,tblClaimsCurrent[field_key],"pricing_acv_mid_market",tblClaimsCurrent[status],"PROMOTED"),IF(cnt=0,NA(),SUMIFS(tblClaimsCurrent[value_num],tblClaimsCurrent[entity_id],#REF!,tblClaimsCurrent[field_key],"pricing_acv_mid_market",tblClaimsCurrent[status],"PROMOTED"))) -> #NAME? | H24: =IF(OR(NOT(ISNUMBER(#REF!)),$B$5=""),"UNKNOWN",IF(#REF!<=($B$5*0.85),"Low",IF(#REF!>=($B$5*1.15),"High","Mid"))) -> UNKNOWN | I24: =_xludf.LET(v,IFERROR(LOOKUP(2,1/((tblClaimsCurrent[entity_id]=#REF!)*(tblClaimsCurrent[field_key]="features")*(tblClaimsCurrent[status]="PROMOTED")),tblClaimsCurrent[value_text]),"UNKNOWN"),IF(v="","UNKNOWN",v)) -> #NAME? | J24: =IF(OR(#REF!="UNKNOWN",#REF!=""),NA(),1+LEN(#REF!)-LEN(SUBSTITUTE(#REF!,";",""))) -> #REF! | K24: =IF(#REF!="",NA(),IF(#REF!="SEG_MM",1,0)) -> #REF! | L24: =IF(#REF!="","",IF(COUNTIFS(tblClaimsCurrent[entity_id],#REF!,tblClaimsCurrent[field_key],"funding_round",tblClaimsCurrent[status],"PROMOTED")>0,1,0)) -> #REF! | M24: =IF(OR(#REF!=FALSE,ISNA(#REF!),ISNA(#REF!),ISNA(#REF!),#REF!="UNKNOWN"),NA(),MIN(1,Config!$B$14*MIN(1,#REF!/10)+Config!$B$15*IF(#REF!="Low",1,IF(#REF!="Mid",0.5,0))+Config!$B$16*#REF!+Config!$B$17*#REF!)) -> #REF! | N24: =IF(OR(#REF!=FALSE,ISNA(#REF!),ISNA(#REF!),ISNA(#REF!)),NA(),MIN(1,Config!$B$18*(1-MIN(1,#REF!/10))+Config!$B$19*(1-#REF!)+Config!$B$20*(1-#REF!))) -> #REF! | O24: =IF(#REF!=FALSE,"OUT_OF_SCOPE",IF(ISNA(#REF!),"UNKNOWN",IF(#REF!<Config!$B$10,"FAIL_CLOSED_LOW_COVERAGE","OK"))) -> #REF! | P24: =IFERROR(_xludf.XLOOKUP(#REF!,tblEntities[entity_id],tblEntities[segment_id]),"") | Q24: =IFERROR(_xludf.XLOOKUP(#REF!,tblEntities[entity_id],tblEntities[vertical]),"") | R24: =AND(#REF!=Dashboard!$E$2,IF(Dashboard!$E$3="All",TRUE,#REF!=Dashboard!$E$3)) -> #REF!
A25: =IF(Input!$A$24="","",Input!$A$24) | B25: =IFERROR(_xludf.XLOOKUP(#REF!,tblEntities[entity_id],tblEntities[canonical_name]),"") | C25: =IF(#REF!="","",COUNTIFS(tblClaimsCurrent[entity_id],#REF!,tblClaimsCurrent[status],"PROMOTED")) -> #REF! | D25: =IF(#REF!="","",COUNTIFS(tblClaimsCurrent[entity_id],#REF!,tblClaimsCurrent[status],"UNKNOWN")) -> #REF! | E25: =_xludf.LET(t,#REF!+#REF!,IF(t=0,NA(),#REF!/t)) -> #NAME? | F25: =_xludf.LET(cnt,COUNTIFS(tblClaimsCurrent[entity_id],#REF!,tblClaimsCurrent[status],"PROMOTED"),IF(cnt=0,NA(),AVERAGEIFS(tblClaimsCurrent[confidence],tblClaimsCurrent[entity_id],#REF!,tblClaimsCurrent[status],"PROMOTED"))) -> #NAME? | G25: =_xludf.LET(cnt,COUNTIFS(tblClaimsCurrent[entity_id],#REF!,tblClaimsCurrent[field_key],"pricing_acv_mid_market",tblClaimsCurrent[status],"PROMOTED"),IF(cnt=0,NA(),SUMIFS(tblClaimsCurrent[value_num],tblClaimsCurrent[entity_id],#REF!,tblClaimsCurrent[field_key],"pricing_acv_mid_market",tblClaimsCurrent[status],"PROMOTED"))) -> #NAME? | H25: =IF(OR(NOT(ISNUMBER(#REF!)),$B$5=""),"UNKNOWN",IF(#REF!<=($B$5*0.85),"Low",IF(#REF!>=($B$5*1.15),"High","Mid"))) -> UNKNOWN | I25: =_xludf.LET(v,IFERROR(LOOKUP(2,1/((tblClaimsCurrent[entity_id]=#REF!)*(tblClaimsCurrent[field_key]="features")*(tblClaimsCurrent[status]="PROMOTED")),tblClaimsCurrent[value_text]),"UNKNOWN"),IF(v="","UNKNOWN",v)) -> #NAME? | J25: =IF(OR(#REF!="UNKNOWN",#REF!=""),NA(),1+LEN(#REF!)-LEN(SUBSTITUTE(#REF!,";",""))) -> #REF! | K25: =IF(#REF!="",NA(),IF(#REF!="SEG_MM",1,0)) -> #REF! | L25: =IF(#REF!="","",IF(COUNTIFS(tblClaimsCurrent[entity_id],#REF!,tblClaimsCurrent[field_key],"funding_round",tblClaimsCurrent[status],"PROMOTED")>0,1,0)) -> #REF! | M25: =IF(OR(#REF!=FALSE,ISNA(#REF!),ISNA(#REF!),ISNA(#REF!),#REF!="UNKNOWN"),NA(),MIN(1,Config!$B$14*MIN(1,#REF!/10)+Config!$B$15*IF(#REF!="Low",1,IF(#REF!="Mid",0.5,0))+Config!$B$16*#REF!+Config!$B$17*#REF!)) -> #REF! | N25: =IF(OR(#REF!=FALSE,ISNA(#REF!),ISNA(#REF!),ISNA(#REF!)),NA(),MIN(1,Config!$B$18*(1-MIN(1,#REF!/10))+Config!$B$19*(1-#REF!)+Config!$B$20*(1-#REF!))) -> #REF! | O25: =IF(#REF!=FALSE,"OUT_OF_SCOPE",IF(ISNA(#REF!),"UNKNOWN",IF(#REF!<Config!$B$10,"FAIL_CLOSED_LOW_COVERAGE","OK"))) -> #REF! | P25: =IFERROR(_xludf.XLOOKUP(#REF!,tblEntities[entity_id],tblEntities[segment_id]),"") | Q25: =IFERROR(_xludf.XLOOKUP(#REF!,tblEntities[entity_id],tblEntities[vertical]),"") | R25: =AND(#REF!=Dashboard!$E$2,IF(Dashboard!$E$3="All",TRUE,#REF!=Dashboard!$E$3)) -> #REF!
A26: =IF(Input!$A$25="","",Input!$A$25) -> Claim Candidates (Fail-Closed; UNKNOWN → Review) | B26: =IFERROR(_xludf.XLOOKUP(#REF!,tblEntities[entity_id],tblEntities[canonical_name]),"") | C26: =IF(#REF!="","",COUNTIFS(tblClaimsCurrent[entity_id],#REF!,tblClaimsCurrent[status],"PROMOTED")) -> #REF! | D26: =IF(#REF!="","",COUNTIFS(tblClaimsCurrent[entity_id],#REF!,tblClaimsCurrent[status],"UNKNOWN")) -> #REF! | E26: =_xludf.LET(t,#REF!+#REF!,IF(t=0,NA(),#REF!/t)) -> #NAME? | F26: =_xludf.LET(cnt,COUNTIFS(tblClaimsCurrent[entity_id],#REF!,tblClaimsCurrent[status],"PROMOTED"),IF(cnt=0,NA(),AVERAGEIFS(tblClaimsCurrent[confidence],tblClaimsCurrent[entity_id],#REF!,tblClaimsCurrent[status],"PROMOTED"))) -> #NAME? | G26: =_xludf.LET(cnt,COUNTIFS(tblClaimsCurrent[entity_id],#REF!,tblClaimsCurrent[field_key],"pricing_acv_mid_market",tblClaimsCurrent[status],"PROMOTED"),IF(cnt=0,NA(),SUMIFS(tblClaimsCurrent[value_num],tblClaimsCurrent[entity_id],#REF!,tblClaimsCurrent[field_key],"pricing_acv_mid_market",tblClaimsCurrent[status],"PROMOTED"))) -> #NAME? | H26: =IF(OR(NOT(ISNUMBER(#REF!)),$B$5=""),"UNKNOWN",IF(#REF!<=($B$5*0.85),"Low",IF(#REF!>=($B$5*1.15),"High","Mid"))) -> UNKNOWN | I26: =_xludf.LET(v,IFERROR(LOOKUP(2,1/((tblClaimsCurrent[entity_id]=#REF!)*(tblClaimsCurrent[field_key]="features")*(tblClaimsCurrent[status]="PROMOTED")),tblClaimsCurrent[value_text]),"UNKNOWN"),IF(v="","UNKNOWN",v)) -> #NAME? | J26: =IF(OR(#REF!="UNKNOWN",#REF!=""),NA(),1+LEN(#REF!)-LEN(SUBSTITUTE(#REF!,";",""))) -> #REF! | K26: =IF(#REF!="",NA(),IF(#REF!="SEG_MM",1,0)) -> #REF! | L26: =IF(#REF!="","",IF(COUNTIFS(tblClaimsCurrent[entity_id],#REF!,tblClaimsCurrent[field_key],"funding_round",tblClaimsCurrent[status],"PROMOTED")>0,1,0)) -> #REF! | M26: =IF(OR(#REF!=FALSE,ISNA(#REF!),ISNA(#REF!),ISNA(#REF!),#REF!="UNKNOWN"),NA(),MIN(1,Config!$B$14*MIN(1,#REF!/10)+Config!$B$15*IF(#REF!="Low",1,IF(#REF!="Mid",0.5,0))+Config!$B$16*#REF!+Config!$B$17*#REF!)) -> #REF! | N26: =IF(OR(#REF!=FALSE,ISNA(#REF!),ISNA(#REF!),ISNA(#REF!)),NA(),MIN(1,Config!$B$18*(1-MIN(1,#REF!/10))+Config!$B$19*(1-#REF!)+Config!$B$20*(1-#REF!))) -> #REF! | O26: =IF(#REF!=FALSE,"OUT_OF_SCOPE",IF(ISNA(#REF!),"UNKNOWN",IF(#REF!<Config!$B$10,"FAIL_CLOSED_LOW_COVERAGE","OK"))) -> #REF! | P26: =IFERROR(_xludf.XLOOKUP(#REF!,tblEntities[entity_id],tblEntities[segment_id]),"") | Q26: =IFERROR(_xludf.XLOOKUP(#REF!,tblEntities[entity_id],tblEntities[vertical]),"") | R26: =AND(#REF!=Dashboard!$E$2,IF(Dashboard!$E$3="All",TRUE,#REF!=Dashboard!$E$3)) -> #REF!
A27: =IF(Input!$A$26="","",Input!$A$26) | B27: =IFERROR(_xludf.XLOOKUP(#REF!,tblEntities[entity_id],tblEntities[canonical_name]),"") | C27: =IF(#REF!="","",COUNTIFS(tblClaimsCurrent[entity_id],#REF!,tblClaimsCurrent[status],"PROMOTED")) -> #REF! | D27: =IF(#REF!="","",COUNTIFS(tblClaimsCurrent[entity_id],#REF!,tblClaimsCurrent[status],"UNKNOWN")) -> #REF! | E27: =_xludf.LET(t,#REF!+#REF!,IF(t=0,NA(),#REF!/t)) -> #NAME? | F27: =_xludf.LET(cnt,COUNTIFS(tblClaimsCurrent[entity_id],#REF!,tblClaimsCurrent[status],"PROMOTED"),IF(cnt=0,NA(),AVERAGEIFS(tblClaimsCurrent[confidence],tblClaimsCurrent[entity_id],#REF!,tblClaimsCurrent[status],"PROMOTED"))) -> #NAME? | G27: =_xludf.LET(cnt,COUNTIFS(tblClaimsCurrent[entity_id],#REF!,tblClaimsCurrent[field_key],"pricing_acv_mid_market",tblClaimsCurrent[status],"PROMOTED"),IF(cnt=0,NA(),SUMIFS(tblClaimsCurrent[value_num],tblClaimsCurrent[entity_id],#REF!,tblClaimsCurrent[field_key],"pricing_acv_mid_market",tblClaimsCurrent[status],"PROMOTED"))) -> #NAME? | H27: =IF(OR(NOT(ISNUMBER(#REF!)),$B$5=""),"UNKNOWN",IF(#REF!<=($B$5*0.85),"Low",IF(#REF!>=($B$5*1.15),"High","Mid"))) -> UNKNOWN | I27: =_xludf.LET(v,IFERROR(LOOKUP(2,1/((tblClaimsCurrent[entity_id]=#REF!)*(tblClaimsCurrent[field_key]="features")*(tblClaimsCurrent[status]="PROMOTED")),tblClaimsCurrent[value_text]),"UNKNOWN"),IF(v="","UNKNOWN",v)) -> #NAME? | J27: =IF(OR(#REF!="UNKNOWN",#REF!=""),NA(),1+LEN(#REF!)-LEN(SUBSTITUTE(#REF!,";",""))) -> #REF! | K27: =IF(#REF!="",NA(),IF(#REF!="SEG_MM",1,0)) -> #REF! | L27: =IF(#REF!="","",IF(COUNTIFS(tblClaimsCurrent[entity_id],#REF!,tblClaimsCurrent[field_key],"funding_round",tblClaimsCurrent[status],"PROMOTED")>0,1,0)) -> #REF! | M27: =IF(OR(#REF!=FALSE,ISNA(#REF!),ISNA(#REF!),ISNA(#REF!),#REF!="UNKNOWN"),NA(),MIN(1,Config!$B$14*MIN(1,#REF!/10)+Config!$B$15*IF(#REF!="Low",1,IF(#REF!="Mid",0.5,0))+Config!$B$16*#REF!+Config!$B$17*#REF!)) -> #REF! | N27: =IF(OR(#REF!=FALSE,ISNA(#REF!),ISNA(#REF!),ISNA(#REF!)),NA(),MIN(1,Config!$B$18*(1-MIN(1,#REF!/10))+Config!$B$19*(1-#REF!)+Config!$B$20*(1-#REF!))) -> #REF! | O27: =IF(#REF!=FALSE,"OUT_OF_SCOPE",IF(ISNA(#REF!),"UNKNOWN",IF(#REF!<Config!$B$10,"FAIL_CLOSED_LOW_COVERAGE","OK"))) -> #REF! | P27: =IFERROR(_xludf.XLOOKUP(#REF!,tblEntities[entity_id],tblEntities[segment_id]),"") | Q27: =IFERROR(_xludf.XLOOKUP(#REF!,tblEntities[entity_id],tblEntities[vertical]),"") | R27: =AND(#REF!=Dashboard!$E$2,IF(Dashboard!$E$3="All",TRUE,#REF!=Dashboard!$E$3)) -> #REF!
A28: =IF(Input!$A$27="","",Input!$A$27) -> candidate_id | B28: =IFERROR(_xludf.XLOOKUP(#REF!,tblEntities[entity_id],tblEntities[canonical_name]),"") | C28: =IF(#REF!="","",COUNTIFS(tblClaimsCurrent[entity_id],#REF!,tblClaimsCurrent[status],"PROMOTED")) -> #REF! | D28: =IF(#REF!="","",COUNTIFS(tblClaimsCurrent[entity_id],#REF!,tblClaimsCurrent[status],"UNKNOWN")) -> #REF! | E28: =_xludf.LET(t,#REF!+#REF!,IF(t=0,NA(),#REF!/t)) -> #NAME? | F28: =_xludf.LET(cnt,COUNTIFS(tblClaimsCurrent[entity_id],#REF!,tblClaimsCurrent[status],"PROMOTED"),IF(cnt=0,NA(),AVERAGEIFS(tblClaimsCurrent[confidence],tblClaimsCurrent[entity_id],#REF!,tblClaimsCurrent[status],"PROMOTED"))) -> #NAME? | G28: =_xludf.LET(cnt,COUNTIFS(tblClaimsCurrent[entity_id],#REF!,tblClaimsCurrent[field_key],"pricing_acv_mid_market",tblClaimsCurrent[status],"PROMOTED"),IF(cnt=0,NA(),SUMIFS(tblClaimsCurrent[value_num],tblClaimsCurrent[entity_id],#REF!,tblClaimsCurrent[field_key],"pricing_acv_mid_market",tblClaimsCurrent[status],"PROMOTED"))) -> #NAME? | H28: =IF(OR(NOT(ISNUMBER(#REF!)),$B$5=""),"UNKNOWN",IF(#REF!<=($B$5*0.85),"Low",IF(#REF!>=($B$5*1.15),"High","Mid"))) -> UNKNOWN | I28: =_xludf.LET(v,IFERROR(LOOKUP(2,1/((tblClaimsCurrent[entity_id]=#REF!)*(tblClaimsCurrent[field_key]="features")*(tblClaimsCurrent[status]="PROMOTED")),tblClaimsCurrent[value_text]),"UNKNOWN"),IF(v="","UNKNOWN",v)) -> #NAME? | J28: =IF(OR(#REF!="UNKNOWN",#REF!=""),NA(),1+LEN(#REF!)-LEN(SUBSTITUTE(#REF!,";",""))) -> #REF! | K28: =IF(#REF!="",NA(),IF(#REF!="SEG_MM",1,0)) -> #REF! | L28: =IF(#REF!="","",IF(COUNTIFS(tblClaimsCurrent[entity_id],#REF!,tblClaimsCurrent[field_key],"funding_round",tblClaimsCurrent[status],"PROMOTED")>0,1,0)) -> #REF! | M28: =IF(OR(#REF!=FALSE,ISNA(#REF!),ISNA(#REF!),ISNA(#REF!),#REF!="UNKNOWN"),NA(),MIN(1,Config!$B$14*MIN(1,#REF!/10)+Config!$B$15*IF(#REF!="Low",1,IF(#REF!="Mid",0.5,0))+Config!$B$16*#REF!+Config!$B$17*#REF!)) -> #REF! | N28: =IF(OR(#REF!=FALSE,ISNA(#REF!),ISNA(#REF!),ISNA(#REF!)),NA(),MIN(1,Config!$B$18*(1-MIN(1,#REF!/10))+Config!$B$19*(1-#REF!)+Config!$B$20*(1-#REF!))) -> #REF! | O28: =IF(#REF!=FALSE,"OUT_OF_SCOPE",IF(ISNA(#REF!),"UNKNOWN",IF(#REF!<Config!$B$10,"FAIL_CLOSED_LOW_COVERAGE","OK"))) -> #REF! | P28: =IFERROR(_xludf.XLOOKUP(#REF!,tblEntities[entity_id],tblEntities[segment_id]),"") | Q28: =IFERROR(_xludf.XLOOKUP(#REF!,tblEntities[entity_id],tblEntities[vertical]),"") | R28: =AND(#REF!=Dashboard!$E$2,IF(Dashboard!$E$3="All",TRUE,#REF!=Dashboard!$E$3)) -> #REF!
A29: =IF(Input!$A$28="","",Input!$A$28) -> C001 | B29: =IFERROR(_xludf.XLOOKUP(#REF!,tblEntities[entity_id],tblEntities[canonical_name]),"") | C29: =IF(#REF!="","",COUNTIFS(tblClaimsCurrent[entity_id],#REF!,tblClaimsCurrent[status],"PROMOTED")) -> #REF! | D29: =IF(#REF!="","",COUNTIFS(tblClaimsCurrent[entity_id],#REF!,tblClaimsCurrent[status],"UNKNOWN")) -> #REF! | E29: =_xludf.LET(t,#REF!+#REF!,IF(t=0,NA(),#REF!/t)) -> #NAME? | F29: =_xludf.LET(cnt,COUNTIFS(tblClaimsCurrent[entity_id],#REF!,tblClaimsCurrent[status],"PROMOTED"),IF(cnt=0,NA(),AVERAGEIFS(tblClaimsCurrent[confidence],tblClaimsCurrent[entity_id],#REF!,tblClaimsCurrent[status],"PROMOTED"))) -> #NAME? | G29: =_xludf.LET(cnt,COUNTIFS(tblClaimsCurrent[entity_id],#REF!,tblClaimsCurrent[field_key],"pricing_acv_mid_market",tblClaimsCurrent[status],"PROMOTED"),IF(cnt=0,NA(),SUMIFS(tblClaimsCurrent[value_num],tblClaimsCurrent[entity_id],#REF!,tblClaimsCurrent[field_key],"pricing_acv_mid_market",tblClaimsCurrent[status],"PROMOTED"))) -> #NAME? | H29: =IF(OR(NOT(ISNUMBER(#REF!)),$B$5=""),"UNKNOWN",IF(#REF!<=($B$5*0.85),"Low",IF(#REF!>=($B$5*1.15),"High","Mid"))) -> UNKNOWN | I29: =_xludf.LET(v,IFERROR(LOOKUP(2,1/((tblClaimsCurrent[entity_id]=#REF!)*(tblClaimsCurrent[field_key]="features")*(tblClaimsCurrent[status]="PROMOTED")),tblClaimsCurrent[value_text]),"UNKNOWN"),IF(v="","UNKNOWN",v)) -> #NAME? | J29: =IF(OR(#REF!="UNKNOWN",#REF!=""),NA(),1+LEN(#REF!)-LEN(SUBSTITUTE(#REF!,";",""))) -> #REF! | K29: =IF(#REF!="",NA(),IF(#REF!="SEG_MM",1,0)) -> #REF! | L29: =IF(#REF!="","",IF(COUNTIFS(tblClaimsCurrent[entity_id],#REF!,tblClaimsCurrent[field_key],"funding_round",tblClaimsCurrent[status],"PROMOTED")>0,1,0)) -> #REF! | M29: =IF(OR(#REF!=FALSE,ISNA(#REF!),ISNA(#REF!),ISNA(#REF!),#REF!="UNKNOWN"),NA(),MIN(1,Config!$B$14*MIN(1,#REF!/10)+Config!$B$15*IF(#REF!="Low",1,IF(#REF!="Mid",0.5,0))+Config!$B$16*#REF!+Config!$B$17*#REF!)) -> #REF! | N29: =IF(OR(#REF!=FALSE,ISNA(#REF!),ISNA(#REF!),ISNA(#REF!)),NA(),MIN(1,Config!$B$18*(1-MIN(1,#REF!/10))+Config!$B$19*(1-#REF!)+Config!$B$20*(1-#REF!))) -> #REF! | O29: =IF(#REF!=FALSE,"OUT_OF_SCOPE",IF(ISNA(#REF!),"UNKNOWN",IF(#REF!<Config!$B$10,"FAIL_CLOSED_LOW_COVERAGE","OK"))) -> #REF! | P29: =IFERROR(_xludf.XLOOKUP(#REF!,tblEntities[entity_id],tblEntities[segment_id]),"") | Q29: =IFERROR(_xludf.XLOOKUP(#REF!,tblEntities[entity_id],tblEntities[vertical]),"") | R29: =AND(#REF!=Dashboard!$E$2,IF(Dashboard!$E$3="All",TRUE,#REF!=Dashboard!$E$3)) -> #REF!
A30: =IF(Input!$A$29="","",Input!$A$29) -> C002 | B30: =IFERROR(_xludf.XLOOKUP(#REF!,tblEntities[entity_id],tblEntities[canonical_name]),"") | C30: =IF(#REF!="","",COUNTIFS(tblClaimsCurrent[entity_id],#REF!,tblClaimsCurrent[status],"PROMOTED")) -> #REF! | D30: =IF(#REF!="","",COUNTIFS(tblClaimsCurrent[entity_id],#REF!,tblClaimsCurrent[status],"UNKNOWN")) -> #REF! | E30: =_xludf.LET(t,#REF!+#REF!,IF(t=0,NA(),#REF!/t)) -> #NAME? | F30: =_xludf.LET(cnt,COUNTIFS(tblClaimsCurrent[entity_id],#REF!,tblClaimsCurrent[status],"PROMOTED"),IF(cnt=0,NA(),AVERAGEIFS(tblClaimsCurrent[confidence],tblClaimsCurrent[entity_id],#REF!,tblClaimsCurrent[status],"PROMOTED"))) -> #NAME? | G30: =_xludf.LET(cnt,COUNTIFS(tblClaimsCurrent[entity_id],#REF!,tblClaimsCurrent[field_key],"pricing_acv_mid_market",tblClaimsCurrent[status],"PROMOTED"),IF(cnt=0,NA(),SUMIFS(tblClaimsCurrent[value_num],tblClaimsCurrent[entity_id],#REF!,tblClaimsCurrent[field_key],"pricing_acv_mid_market",tblClaimsCurrent[status],"PROMOTED"))) -> #NAME? | H30: =IF(OR(NOT(ISNUMBER(#REF!)),$B$5=""),"UNKNOWN",IF(#REF!<=($B$5*0.85),"Low",IF(#REF!>=($B$5*1.15),"High","Mid"))) -> UNKNOWN | I30: =_xludf.LET(v,IFERROR(LOOKUP(2,1/((tblClaimsCurrent[entity_id]=#REF!)*(tblClaimsCurrent[field_key]="features")*(tblClaimsCurrent[status]="PROMOTED")),tblClaimsCurrent[value_text]),"UNKNOWN"),IF(v="","UNKNOWN",v)) -> #NAME? | J30: =IF(OR(#REF!="UNKNOWN",#REF!=""),NA(),1+LEN(#REF!)-LEN(SUBSTITUTE(#REF!,";",""))) -> #REF! | K30: =IF(#REF!="",NA(),IF(#REF!="SEG_MM",1,0)) -> #REF! | L30: =IF(#REF!="","",IF(COUNTIFS(tblClaimsCurrent[entity_id],#REF!,tblClaimsCurrent[field_key],"funding_round",tblClaimsCurrent[status],"PROMOTED")>0,1,0)) -> #REF! | M30: =IF(OR(#REF!=FALSE,ISNA(#REF!),ISNA(#REF!),ISNA(#REF!),#REF!="UNKNOWN"),NA(),MIN(1,Config!$B$14*MIN(1,#REF!/10)+Config!$B$15*IF(#REF!="Low",1,IF(#REF!="Mid",0.5,0))+Config!$B$16*#REF!+Config!$B$17*#REF!)) -> #REF! | N30: =IF(OR(#REF!=FALSE,ISNA(#REF!),ISNA(#REF!),ISNA(#REF!)),NA(),MIN(1,Config!$B$18*(1-MIN(1,#REF!/10))+Config!$B$19*(1-#REF!)+Config!$B$20*(1-#REF!))) -> #REF! | O30: =IF(#REF!=FALSE,"OUT_OF_SCOPE",IF(ISNA(#REF!),"UNKNOWN",IF(#REF!<Config!$B$10,"FAIL_CLOSED_LOW_COVERAGE","OK"))) -> #REF! | P30: =IFERROR(_xludf.XLOOKUP(#REF!,tblEntities[entity_id],tblEntities[segment_id]),"") | Q30: =IFERROR(_xludf.XLOOKUP(#REF!,tblEntities[entity_id],tblEntities[vertical]),"") | R30: =AND(#REF!=Dashboard!$E$2,IF(Dashboard!$E$3="All",TRUE,#REF!=Dashboard!$E$3)) -> #REF!
A31: =IF(Input!$A$30="","",Input!$A$30) -> C003 | B31: =IFERROR(_xludf.XLOOKUP(#REF!,tblEntities[entity_id],tblEntities[canonical_name]),"") | C31: =IF(#REF!="","",COUNTIFS(tblClaimsCurrent[entity_id],#REF!,tblClaimsCurrent[status],"PROMOTED")) -> #REF! | D31: =IF(#REF!="","",COUNTIFS(tblClaimsCurrent[entity_id],#REF!,tblClaimsCurrent[status],"UNKNOWN")) -> #REF! | E31: =_xludf.LET(t,#REF!+#REF!,IF(t=0,NA(),#REF!/t)) -> #NAME? | F31: =_xludf.LET(cnt,COUNTIFS(tblClaimsCurrent[entity_id],#REF!,tblClaimsCurrent[status],"PROMOTED"),IF(cnt=0,NA(),AVERAGEIFS(tblClaimsCurrent[confidence],tblClaimsCurrent[entity_id],#REF!,tblClaimsCurrent[status],"PROMOTED"))) -> #NAME? | G31: =_xludf.LET(cnt,COUNTIFS(tblClaimsCurrent[entity_id],#REF!,tblClaimsCurrent[field_key],"pricing_acv_mid_market",tblClaimsCurrent[status],"PROMOTED"),IF(cnt=0,NA(),SUMIFS(tblClaimsCurrent[value_num],tblClaimsCurrent[entity_id],#REF!,tblClaimsCurrent[field_key],"pricing_acv_mid_market",tblClaimsCurrent[status],"PROMOTED"))) -> #NAME? | H31: =IF(OR(NOT(ISNUMBER(#REF!)),$B$5=""),"UNKNOWN",IF(#REF!<=($B$5*0.85),"Low",IF(#REF!>=($B$5*1.15),"High","Mid"))) -> UNKNOWN | I31: =_xludf.LET(v,IFERROR(LOOKUP(2,1/((tblClaimsCurrent[entity_id]=#REF!)*(tblClaimsCurrent[field_key]="features")*(tblClaimsCurrent[status]="PROMOTED")),tblClaimsCurrent[value_text]),"UNKNOWN"),IF(v="","UNKNOWN",v)) -> #NAME? | J31: =IF(OR(#REF!="UNKNOWN",#REF!=""),NA(),1+LEN(#REF!)-LEN(SUBSTITUTE(#REF!,";",""))) -> #REF! | K31: =IF(#REF!="",NA(),IF(#REF!="SEG_MM",1,0)) -> #REF! | L31: =IF(#REF!="","",IF(COUNTIFS(tblClaimsCurrent[entity_id],#REF!,tblClaimsCurrent[field_key],"funding_round",tblClaimsCurrent[status],"PROMOTED")>0,1,0)) -> #REF! | M31: =IF(OR(#REF!=FALSE,ISNA(#REF!),ISNA(#REF!),ISNA(#REF!),#REF!="UNKNOWN"),NA(),MIN(1,Config!$B$14*MIN(1,#REF!/10)+Config!$B$15*IF(#REF!="Low",1,IF(#REF!="Mid",0.5,0))+Config!$B$16*#REF!+Config!$B$17*#REF!)) -> #REF! | N31: =IF(OR(#REF!=FALSE,ISNA(#REF!),ISNA(#REF!),ISNA(#REF!)),NA(),MIN(1,Config!$B$18*(1-MIN(1,#REF!/10))+Config!$B$19*(1-#REF!)+Config!$B$20*(1-#REF!))) -> #REF! | O31: =IF(#REF!=FALSE,"OUT_OF_SCOPE",IF(ISNA(#REF!),"UNKNOWN",IF(#REF!<Config!$B$10,"FAIL_CLOSED_LOW_COVERAGE","OK"))) -> #REF! | P31: =IFERROR(_xludf.XLOOKUP(#REF!,tblEntities[entity_id],tblEntities[segment_id]),"") | Q31: =IFERROR(_xludf.XLOOKUP(#REF!,tblEntities[entity_id],tblEntities[vertical]),"") | R31: =AND(#REF!=Dashboard!$E$2,IF(Dashboard!$E$3="All",TRUE,#REF!=Dashboard!$E$3)) -> #REF!
A32: =IF(Input!$A$31="","",Input!$A$31) -> C004 | B32: =IFERROR(_xludf.XLOOKUP(#REF!,tblEntities[entity_id],tblEntities[canonical_name]),"") | C32: =IF(#REF!="","",COUNTIFS(tblClaimsCurrent[entity_id],#REF!,tblClaimsCurrent[status],"PROMOTED")) -> #REF! | D32: =IF(#REF!="","",COUNTIFS(tblClaimsCurrent[entity_id],#REF!,tblClaimsCurrent[status],"UNKNOWN")) -> #REF! | E32: =_xludf.LET(t,#REF!+#REF!,IF(t=0,NA(),#REF!/t)) -> #NAME? | F32: =_xludf.LET(cnt,COUNTIFS(tblClaimsCurrent[entity_id],#REF!,tblClaimsCurrent[status],"PROMOTED"),IF(cnt=0,NA(),AVERAGEIFS(tblClaimsCurrent[confidence],tblClaimsCurrent[entity_id],#REF!,tblClaimsCurrent[status],"PROMOTED"))) -> #NAME? | G32: =_xludf.LET(cnt,COUNTIFS(tblClaimsCurrent[entity_id],#REF!,tblClaimsCurrent[field_key],"pricing_acv_mid_market",tblClaimsCurrent[status],"PROMOTED"),IF(cnt=0,NA(),SUMIFS(tblClaimsCurrent[value_num],tblClaimsCurrent[entity_id],#REF!,tblClaimsCurrent[field_key],"pricing_acv_mid_market",tblClaimsCurrent[status],"PROMOTED"))) -> #NAME? | H32: =IF(OR(NOT(ISNUMBER(#REF!)),$B$5=""),"UNKNOWN",IF(#REF!<=($B$5*0.85),"Low",IF(#REF!>=($B$5*1.15),"High","Mid"))) -> UNKNOWN | I32: =_xludf.LET(v,IFERROR(LOOKUP(2,1/((tblClaimsCurrent[entity_id]=#REF!)*(tblClaimsCurrent[field_key]="features")*(tblClaimsCurrent[status]="PROMOTED")),tblClaimsCurrent[value_text]),"UNKNOWN"),IF(v="","UNKNOWN",v)) -> #NAME? | J32: =IF(OR(#REF!="UNKNOWN",#REF!=""),NA(),1+LEN(#REF!)-LEN(SUBSTITUTE(#REF!,";",""))) -> #REF! | K32: =IF(#REF!="",NA(),IF(#REF!="SEG_MM",1,0)) -> #REF! | L32: =IF(#REF!="","",IF(COUNTIFS(tblClaimsCurrent[entity_id],#REF!,tblClaimsCurrent[field_key],"funding_round",tblClaimsCurrent[status],"PROMOTED")>0,1,0)) -> #REF! | M32: =IF(OR(#REF!=FALSE,ISNA(#REF!),ISNA(#REF!),ISNA(#REF!),#REF!="UNKNOWN"),NA(),MIN(1,Config!$B$14*MIN(1,#REF!/10)+Config!$B$15*IF(#REF!="Low",1,IF(#REF!="Mid",0.5,0))+Config!$B$16*#REF!+Config!$B$17*#REF!)) -> #REF! | N32: =IF(OR(#REF!=FALSE,ISNA(#REF!),ISNA(#REF!),ISNA(#REF!)),NA(),MIN(1,Config!$B$18*(1-MIN(1,#REF!/10))+Config!$B$19*(1-#REF!)+Config!$B$20*(1-#REF!))) -> #REF! | O32: =IF(#REF!=FALSE,"OUT_OF_SCOPE",IF(ISNA(#REF!),"UNKNOWN",IF(#REF!<Config!$B$10,"FAIL_CLOSED_LOW_COVERAGE","OK"))) -> #REF! | P32: =IFERROR(_xludf.XLOOKUP(#REF!,tblEntities[entity_id],tblEntities[segment_id]),"") | Q32: =IFERROR(_xludf.XLOOKUP(#REF!,tblEntities[entity_id],tblEntities[vertical]),"") | R32: =AND(#REF!=Dashboard!$E$2,IF(Dashboard!$E$3="All",TRUE,#REF!=Dashboard!$E$3)) -> #REF!
A33: =IF(Input!$A$32="","",Input!$A$32) -> C005 | B33: =IFERROR(_xludf.XLOOKUP(#REF!,tblEntities[entity_id],tblEntities[canonical_name]),"") | C33: =IF(#REF!="","",COUNTIFS(tblClaimsCurrent[entity_id],#REF!,tblClaimsCurrent[status],"PROMOTED")) -> #REF! | D33: =IF(#REF!="","",COUNTIFS(tblClaimsCurrent[entity_id],#REF!,tblClaimsCurrent[status],"UNKNOWN")) -> #REF! | E33: =_xludf.LET(t,#REF!+#REF!,IF(t=0,NA(),#REF!/t)) -> #NAME? | F33: =_xludf.LET(cnt,COUNTIFS(tblClaimsCurrent[entity_id],#REF!,tblClaimsCurrent[status],"PROMOTED"),IF(cnt=0,NA(),AVERAGEIFS(tblClaimsCurrent[confidence],tblClaimsCurrent[entity_id],#REF!,tblClaimsCurrent[status],"PROMOTED"))) -> #NAME? | G33: =_xludf.LET(cnt,COUNTIFS(tblClaimsCurrent[entity_id],#REF!,tblClaimsCurrent[field_key],"pricing_acv_mid_market",tblClaimsCurrent[status],"PROMOTED"),IF(cnt=0,NA(),SUMIFS(tblClaimsCurrent[value_num],tblClaimsCurrent[entity_id],#REF!,tblClaimsCurrent[field_key],"pricing_acv_mid_market",tblClaimsCurrent[status],"PROMOTED"))) -> #NAME? | H33: =IF(OR(NOT(ISNUMBER(#REF!)),$B$5=""),"UNKNOWN",IF(#REF!<=($B$5*0.85),"Low",IF(#REF!>=($B$5*1.15),"High","Mid"))) -> UNKNOWN | I33: =_xludf.LET(v,IFERROR(LOOKUP(2,1/((tblClaimsCurrent[entity_id]=#REF!)*(tblClaimsCurrent[field_key]="features")*(tblClaimsCurrent[status]="PROMOTED")),tblClaimsCurrent[value_text]),"UNKNOWN"),IF(v="","UNKNOWN",v)) -> #NAME? | J33: =IF(OR(#REF!="UNKNOWN",#REF!=""),NA(),1+LEN(#REF!)-LEN(SUBSTITUTE(#REF!,";",""))) -> #REF! | K33: =IF(#REF!="",NA(),IF(#REF!="SEG_MM",1,0)) -> #REF! | L33: =IF(#REF!="","",IF(COUNTIFS(tblClaimsCurrent[entity_id],#REF!,tblClaimsCurrent[field_key],"funding_round",tblClaimsCurrent[status],"PROMOTED")>0,1,0)) -> #REF! | M33: =IF(OR(#REF!=FALSE,ISNA(#REF!),ISNA(#REF!),ISNA(#REF!),#REF!="UNKNOWN"),NA(),MIN(1,Config!$B$14*MIN(1,#REF!/10)+Config!$B$15*IF(#REF!="Low",1,IF(#REF!="Mid",0.5,0))+Config!$B$16*#REF!+Config!$B$17*#REF!)) -> #REF! | N33: =IF(OR(#REF!=FALSE,ISNA(#REF!),ISNA(#REF!),ISNA(#REF!)),NA(),MIN(1,Config!$B$18*(1-MIN(1,#REF!/10))+Config!$B$19*(1-#REF!)+Config!$B$20*(1-#REF!))) -> #REF! | O33: =IF(#REF!=FALSE,"OUT_OF_SCOPE",IF(ISNA(#REF!),"UNKNOWN",IF(#REF!<Config!$B$10,"FAIL_CLOSED_LOW_COVERAGE","OK"))) -> #REF! | P33: =IFERROR(_xludf.XLOOKUP(#REF!,tblEntities[entity_id],tblEntities[segment_id]),"") | Q33: =IFERROR(_xludf.XLOOKUP(#REF!,tblEntities[entity_id],tblEntities[vertical]),"") | R33: =AND(#REF!=Dashboard!$E$2,IF(Dashboard!$E$3="All",TRUE,#REF!=Dashboard!$E$3)) -> #REF!
A34: =IF(Input!$A$33="","",Input!$A$33) -> C006 | B34: =IFERROR(_xludf.XLOOKUP(#REF!,tblEntities[entity_id],tblEntities[canonical_name]),"") | C34: =IF(#REF!="","",COUNTIFS(tblClaimsCurrent[entity_id],#REF!,tblClaimsCurrent[status],"PROMOTED")) -> #REF! | D34: =IF(#REF!="","",COUNTIFS(tblClaimsCurrent[entity_id],#REF!,tblClaimsCurrent[status],"UNKNOWN")) -> #REF! | E34: =_xludf.LET(t,#REF!+#REF!,IF(t=0,NA(),#REF!/t)) -> #NAME? | F34: =_xludf.LET(cnt,COUNTIFS(tblClaimsCurrent[entity_id],#REF!,tblClaimsCurrent[status],"PROMOTED"),IF(cnt=0,NA(),AVERAGEIFS(tblClaimsCurrent[confidence],tblClaimsCurrent[entity_id],#REF!,tblClaimsCurrent[status],"PROMOTED"))) -> #NAME? | G34: =_xludf.LET(cnt,COUNTIFS(tblClaimsCurrent[entity_id],#REF!,tblClaimsCurrent[field_key],"pricing_acv_mid_market",tblClaimsCurrent[status],"PROMOTED"),IF(cnt=0,NA(),SUMIFS(tblClaimsCurrent[value_num],tblClaimsCurrent[entity_id],#REF!,tblClaimsCurrent[field_key],"pricing_acv_mid_market",tblClaimsCurrent[status],"PROMOTED"))) -> #NAME? | H34: =IF(OR(NOT(ISNUMBER(#REF!)),$B$5=""),"UNKNOWN",IF(#REF!<=($B$5*0.85),"Low",IF(#REF!>=($B$5*1.15),"High","Mid"))) -> UNKNOWN | I34: =_xludf.LET(v,IFERROR(LOOKUP(2,1/((tblClaimsCurrent[entity_id]=#REF!)*(tblClaimsCurrent[field_key]="features")*(tblClaimsCurrent[status]="PROMOTED")),tblClaimsCurrent[value_text]),"UNKNOWN"),IF(v="","UNKNOWN",v)) -> #NAME? | J34: =IF(OR(#REF!="UNKNOWN",#REF!=""),NA(),1+LEN(#REF!)-LEN(SUBSTITUTE(#REF!,";",""))) -> #REF! | K34: =IF(#REF!="",NA(),IF(#REF!="SEG_MM",1,0)) -> #REF! | L34: =IF(#REF!="","",IF(COUNTIFS(tblClaimsCurrent[entity_id],#REF!,tblClaimsCurrent[field_key],"funding_round",tblClaimsCurrent[status],"PROMOTED")>0,1,0)) -> #REF! | M34: =IF(OR(#REF!=FALSE,ISNA(#REF!),ISNA(#REF!),ISNA(#REF!),#REF!="UNKNOWN"),NA(),MIN(1,Config!$B$14*MIN(1,#REF!/10)+Config!$B$15*IF(#REF!="Low",1,IF(#REF!="Mid",0.5,0))+Config!$B$16*#REF!+Config!$B$17*#REF!)) -> #REF! | N34: =IF(OR(#REF!=FALSE,ISNA(#REF!),ISNA(#REF!),ISNA(#REF!)),NA(),MIN(1,Config!$B$18*(1-MIN(1,#REF!/10))+Config!$B$19*(1-#REF!)+Config!$B$20*(1-#REF!))) -> #REF! | O34: =IF(#REF!=FALSE,"OUT_OF_SCOPE",IF(ISNA(#REF!),"UNKNOWN",IF(#REF!<Config!$B$10,"FAIL_CLOSED_LOW_COVERAGE","OK"))) -> #REF! | P34: =IFERROR(_xludf.XLOOKUP(#REF!,tblEntities[entity_id],tblEntities[segment_id]),"") | Q34: =IFERROR(_xludf.XLOOKUP(#REF!,tblEntities[entity_id],tblEntities[vertical]),"") | R34: =AND(#REF!=Dashboard!$E$2,IF(Dashboard!$E$3="All",TRUE,#REF!=Dashboard!$E$3)) -> #REF!
A35: =IF(Input!$A$34="","",Input!$A$34) -> C007 | B35: =IFERROR(_xludf.XLOOKUP(#REF!,tblEntities[entity_id],tblEntities[canonical_name]),"") | C35: =IF(#REF!="","",COUNTIFS(tblClaimsCurrent[entity_id],#REF!,tblClaimsCurrent[status],"PROMOTED")) -> #REF! | D35: =IF(#REF!="","",COUNTIFS(tblClaimsCurrent[entity_id],#REF!,tblClaimsCurrent[status],"UNKNOWN")) -> #REF! | E35: =_xludf.LET(t,#REF!+#REF!,IF(t=0,NA(),#REF!/t)) -> #NAME? | F35: =_xludf.LET(cnt,COUNTIFS(tblClaimsCurrent[entity_id],#REF!,tblClaimsCurrent[status],"PROMOTED"),IF(cnt=0,NA(),AVERAGEIFS(tblClaimsCurrent[confidence],tblClaimsCurrent[entity_id],#REF!,tblClaimsCurrent[status],"PROMOTED"))) -> #NAME? | G35: =_xludf.LET(cnt,COUNTIFS(tblClaimsCurrent[entity_id],#REF!,tblClaimsCurrent[field_key],"pricing_acv_mid_market",tblClaimsCurrent[status],"PROMOTED"),IF(cnt=0,NA(),SUMIFS(tblClaimsCurrent[value_num],tblClaimsCurrent[entity_id],#REF!,tblClaimsCurrent[field_key],"pricing_acv_mid_market",tblClaimsCurrent[status],"PROMOTED"))) -> #NAME? | H35: =IF(OR(NOT(ISNUMBER(#REF!)),$B$5=""),"UNKNOWN",IF(#REF!<=($B$5*0.85),"Low",IF(#REF!>=($B$5*1.15),"High","Mid"))) -> UNKNOWN | I35: =_xludf.LET(v,IFERROR(LOOKUP(2,1/((tblClaimsCurrent[entity_id]=#REF!)*(tblClaimsCurrent[field_key]="features")*(tblClaimsCurrent[status]="PROMOTED")),tblClaimsCurrent[value_text]),"UNKNOWN"),IF(v="","UNKNOWN",v)) -> #NAME? | J35: =IF(OR(#REF!="UNKNOWN",#REF!=""),NA(),1+LEN(#REF!)-LEN(SUBSTITUTE(#REF!,";",""))) -> #REF! | K35: =IF(#REF!="",NA(),IF(#REF!="SEG_MM",1,0)) -> #REF! | L35: =IF(#REF!="","",IF(COUNTIFS(tblClaimsCurrent[entity_id],#REF!,tblClaimsCurrent[field_key],"funding_round",tblClaimsCurrent[status],"PROMOTED")>0,1,0)) -> #REF! | M35: =IF(OR(#REF!=FALSE,ISNA(#REF!),ISNA(#REF!),ISNA(#REF!),#REF!="UNKNOWN"),NA(),MIN(1,Config!$B$14*MIN(1,#REF!/10)+Config!$B$15*IF(#REF!="Low",1,IF(#REF!="Mid",0.5,0))+Config!$B$16*#REF!+Config!$B$17*#REF!)) -> #REF! | N35: =IF(OR(#REF!=FALSE,ISNA(#REF!),ISNA(#REF!),ISNA(#REF!)),NA(),MIN(1,Config!$B$18*(1-MIN(1,#REF!/10))+Config!$B$19*(1-#REF!)+Config!$B$20*(1-#REF!))) -> #REF! | O35: =IF(#REF!=FALSE,"OUT_OF_SCOPE",IF(ISNA(#REF!),"UNKNOWN",IF(#REF!<Config!$B$10,"FAIL_CLOSED_LOW_COVERAGE","OK"))) -> #REF! | P35: =IFERROR(_xludf.XLOOKUP(#REF!,tblEntities[entity_id],tblEntities[segment_id]),"") | Q35: =IFERROR(_xludf.XLOOKUP(#REF!,tblEntities[entity_id],tblEntities[vertical]),"") | R35: =AND(#REF!=Dashboard!$E$2,IF(Dashboard!$E$3="All",TRUE,#REF!=Dashboard!$E$3)) -> #REF!
A36: =IF(Input!$A$35="","",Input!$A$35) -> C008 | B36: =IFERROR(_xludf.XLOOKUP(#REF!,tblEntities[entity_id],tblEntities[canonical_name]),"") | C36: =IF(#REF!="","",COUNTIFS(tblClaimsCurrent[entity_id],#REF!,tblClaimsCurrent[status],"PROMOTED")) -> #REF! | D36: =IF(#REF!="","",COUNTIFS(tblClaimsCurrent[entity_id],#REF!,tblClaimsCurrent[status],"UNKNOWN")) -> #REF! | E36: =_xludf.LET(t,#REF!+#REF!,IF(t=0,NA(),#REF!/t)) -> #NAME? | F36: =_xludf.LET(cnt,COUNTIFS(tblClaimsCurrent[entity_id],#REF!,tblClaimsCurrent[status],"PROMOTED"),IF(cnt=0,NA(),AVERAGEIFS(tblClaimsCurrent[confidence],tblClaimsCurrent[entity_id],#REF!,tblClaimsCurrent[status],"PROMOTED"))) -> #NAME? | G36: =_xludf.LET(cnt,COUNTIFS(tblClaimsCurrent[entity_id],#REF!,tblClaimsCurrent[field_key],"pricing_acv_mid_market",tblClaimsCurrent[status],"PROMOTED"),IF(cnt=0,NA(),SUMIFS(tblClaimsCurrent[value_num],tblClaimsCurrent[entity_id],#REF!,tblClaimsCurrent[field_key],"pricing_acv_mid_market",tblClaimsCurrent[status],"PROMOTED"))) -> #NAME? | H36: =IF(OR(NOT(ISNUMBER(#REF!)),$B$5=""),"UNKNOWN",IF(#REF!<=($B$5*0.85),"Low",IF(#REF!>=($B$5*1.15),"High","Mid"))) -> UNKNOWN | I36: =_xludf.LET(v,IFERROR(LOOKUP(2,1/((tblClaimsCurrent[entity_id]=#REF!)*(tblClaimsCurrent[field_key]="features")*(tblClaimsCurrent[status]="PROMOTED")),tblClaimsCurrent[value_text]),"UNKNOWN"),IF(v="","UNKNOWN",v)) -> #NAME? | J36: =IF(OR(#REF!="UNKNOWN",#REF!=""),NA(),1+LEN(#REF!)-LEN(SUBSTITUTE(#REF!,";",""))) -> #REF! | K36: =IF(#REF!="",NA(),IF(#REF!="SEG_MM",1,0)) -> #REF! | L36: =IF(#REF!="","",IF(COUNTIFS(tblClaimsCurrent[entity_id],#REF!,tblClaimsCurrent[field_key],"funding_round",tblClaimsCurrent[status],"PROMOTED")>0,1,0)) -> #REF! | M36: =IF(OR(#REF!=FALSE,ISNA(#REF!),ISNA(#REF!),ISNA(#REF!),#REF!="UNKNOWN"),NA(),MIN(1,Config!$B$14*MIN(1,#REF!/10)+Config!$B$15*IF(#REF!="Low",1,IF(#REF!="Mid",0.5,0))+Config!$B$16*#REF!+Config!$B$17*#REF!)) -> #REF! | N36: =IF(OR(#REF!=FALSE,ISNA(#REF!),ISNA(#REF!),ISNA(#REF!)),NA(),MIN(1,Config!$B$18*(1-MIN(1,#REF!/10))+Config!$B$19*(1-#REF!)+Config!$B$20*(1-#REF!))) -> #REF! | O36: =IF(#REF!=FALSE,"OUT_OF_SCOPE",IF(ISNA(#REF!),"UNKNOWN",IF(#REF!<Config!$B$10,"FAIL_CLOSED_LOW_COVERAGE","OK"))) -> #REF! | P36: =IFERROR(_xludf.XLOOKUP(#REF!,tblEntities[entity_id],tblEntities[segment_id]),"") | Q36: =IFERROR(_xludf.XLOOKUP(#REF!,tblEntities[entity_id],tblEntities[vertical]),"") | R36: =AND(#REF!=Dashboard!$E$2,IF(Dashboard!$E$3="All",TRUE,#REF!=Dashboard!$E$3)) -> #REF!
A37: =IF(Input!$A$36="","",Input!$A$36) -> C009 | B37: =IFERROR(_xludf.XLOOKUP(#REF!,tblEntities[entity_id],tblEntities[canonical_name]),"") | C37: =IF(#REF!="","",COUNTIFS(tblClaimsCurrent[entity_id],#REF!,tblClaimsCurrent[status],"PROMOTED")) -> #REF! | D37: =IF(#REF!="","",COUNTIFS(tblClaimsCurrent[entity_id],#REF!,tblClaimsCurrent[status],"UNKNOWN")) -> #REF! | E37: =_xludf.LET(t,#REF!+#REF!,IF(t=0,NA(),#REF!/t)) -> #NAME? | F37: =_xludf.LET(cnt,COUNTIFS(tblClaimsCurrent[entity_id],#REF!,tblClaimsCurrent[status],"PROMOTED"),IF(cnt=0,NA(),AVERAGEIFS(tblClaimsCurrent[confidence],tblClaimsCurrent[entity_id],#REF!,tblClaimsCurrent[status],"PROMOTED"))) -> #NAME? | G37: =_xludf.LET(cnt,COUNTIFS(tblClaimsCurrent[entity_id],#REF!,tblClaimsCurrent[field_key],"pricing_acv_mid_market",tblClaimsCurrent[status],"PROMOTED"),IF(cnt=0,NA(),SUMIFS(tblClaimsCurrent[value_num],tblClaimsCurrent[entity_id],#REF!,tblClaimsCurrent[field_key],"pricing_acv_mid_market",tblClaimsCurrent[status],"PROMOTED"))) -> #NAME? | H37: =IF(OR(NOT(ISNUMBER(#REF!)),$B$5=""),"UNKNOWN",IF(#REF!<=($B$5*0.85),"Low",IF(#REF!>=($B$5*1.15),"High","Mid"))) -> UNKNOWN | I37: =_xludf.LET(v,IFERROR(LOOKUP(2,1/((tblClaimsCurrent[entity_id]=#REF!)*(tblClaimsCurrent[field_key]="features")*(tblClaimsCurrent[status]="PROMOTED")),tblClaimsCurrent[value_text]),"UNKNOWN"),IF(v="","UNKNOWN",v)) -> #NAME? | J37: =IF(OR(#REF!="UNKNOWN",#REF!=""),NA(),1+LEN(#REF!)-LEN(SUBSTITUTE(#REF!,";",""))) -> #REF! | K37: =IF(#REF!="",NA(),IF(#REF!="SEG_MM",1,0)) -> #REF! | L37: =IF(#REF!="","",IF(COUNTIFS(tblClaimsCurrent[entity_id],#REF!,tblClaimsCurrent[field_key],"funding_round",tblClaimsCurrent[status],"PROMOTED")>0,1,0)) -> #REF! | M37: =IF(OR(#REF!=FALSE,ISNA(#REF!),ISNA(#REF!),ISNA(#REF!),#REF!="UNKNOWN"),NA(),MIN(1,Config!$B$14*MIN(1,#REF!/10)+Config!$B$15*IF(#REF!="Low",1,IF(#REF!="Mid",0.5,0))+Config!$B$16*#REF!+Config!$B$17*#REF!)) -> #REF! | N37: =IF(OR(#REF!=FALSE,ISNA(#REF!),ISNA(#REF!),ISNA(#REF!)),NA(),MIN(1,Config!$B$18*(1-MIN(1,#REF!/10))+Config!$B$19*(1-#REF!)+Config!$B$20*(1-#REF!))) -> #REF! | O37: =IF(#REF!=FALSE,"OUT_OF_SCOPE",IF(ISNA(#REF!),"UNKNOWN",IF(#REF!<Config!$B$10,"FAIL_CLOSED_LOW_COVERAGE","OK"))) -> #REF! | P37: =IFERROR(_xludf.XLOOKUP(#REF!,tblEntities[entity_id],tblEntities[segment_id]),"") | Q37: =IFERROR(_xludf.XLOOKUP(#REF!,tblEntities[entity_id],tblEntities[vertical]),"") | R37: =AND(#REF!=Dashboard!$E$2,IF(Dashboard!$E$3="All",TRUE,#REF!=Dashboard!$E$3)) -> #REF!
A38: =IF(Input!$A$37="","",Input!$A$37) | B38: =IFERROR(_xludf.XLOOKUP(#REF!,tblEntities[entity_id],tblEntities[canonical_name]),"") | C38: =IF(#REF!="","",COUNTIFS(tblClaimsCurrent[entity_id],#REF!,tblClaimsCurrent[status],"PROMOTED")) -> #REF! | D38: =IF(#REF!="","",COUNTIFS(tblClaimsCurrent[entity_id],#REF!,tblClaimsCurrent[status],"UNKNOWN")) -> #REF! | E38: =_xludf.LET(t,#REF!+#REF!,IF(t=0,NA(),#REF!/t)) -> #NAME? | F38: =_xludf.LET(cnt,COUNTIFS(tblClaimsCurrent[entity_id],#REF!,tblClaimsCurrent[status],"PROMOTED"),IF(cnt=0,NA(),AVERAGEIFS(tblClaimsCurrent[confidence],tblClaimsCurrent[entity_id],#REF!,tblClaimsCurrent[status],"PROMOTED"))) -> #NAME? | G38: =_xludf.LET(cnt,COUNTIFS(tblClaimsCurrent[entity_id],#REF!,tblClaimsCurrent[field_key],"pricing_acv_mid_market",tblClaimsCurrent[status],"PROMOTED"),IF(cnt=0,NA(),SUMIFS(tblClaimsCurrent[value_num],tblClaimsCurrent[entity_id],#REF!,tblClaimsCurrent[field_key],"pricing_acv_mid_market",tblClaimsCurrent[status],"PROMOTED"))) -> #NAME? | H38: =IF(OR(NOT(ISNUMBER(#REF!)),$B$5=""),"UNKNOWN",IF(#REF!<=($B$5*0.85),"Low",IF(#REF!>=($B$5*1.15),"High","Mid"))) -> UNKNOWN | I38: =_xludf.LET(v,IFERROR(LOOKUP(2,1/((tblClaimsCurrent[entity_id]=#REF!)*(tblClaimsCurrent[field_key]="features")*(tblClaimsCurrent[status]="PROMOTED")),tblClaimsCurrent[value_text]),"UNKNOWN"),IF(v="","UNKNOWN",v)) -> #NAME? | J38: =IF(OR(#REF!="UNKNOWN",#REF!=""),NA(),1+LEN(#REF!)-LEN(SUBSTITUTE(#REF!,";",""))) -> #REF! | K38: =IF(#REF!="",NA(),IF(#REF!="SEG_MM",1,0)) -> #REF! | L38: =IF(#REF!="","",IF(COUNTIFS(tblClaimsCurrent[entity_id],#REF!,tblClaimsCurrent[field_key],"funding_round",tblClaimsCurrent[status],"PROMOTED")>0,1,0)) -> #REF! | M38: =IF(OR(#REF!=FALSE,ISNA(#REF!),ISNA(#REF!),ISNA(#REF!),#REF!="UNKNOWN"),NA(),MIN(1,Config!$B$14*MIN(1,#REF!/10)+Config!$B$15*IF(#REF!="Low",1,IF(#REF!="Mid",0.5,0))+Config!$B$16*#REF!+Config!$B$17*#REF!)) -> #REF! | N38: =IF(OR(#REF!=FALSE,ISNA(#REF!),ISNA(#REF!),ISNA(#REF!)),NA(),MIN(1,Config!$B$18*(1-MIN(1,#REF!/10))+Config!$B$19*(1-#REF!)+Config!$B$20*(1-#REF!))) -> #REF! | O38: =IF(#REF!=FALSE,"OUT_OF_SCOPE",IF(ISNA(#REF!),"UNKNOWN",IF(#REF!<Config!$B$10,"FAIL_CLOSED_LOW_COVERAGE","OK"))) -> #REF! | P38: =IFERROR(_xludf.XLOOKUP(#REF!,tblEntities[entity_id],tblEntities[segment_id]),"") | Q38: =IFERROR(_xludf.XLOOKUP(#REF!,tblEntities[entity_id],tblEntities[vertical]),"") | R38: =AND(#REF!=Dashboard!$E$2,IF(Dashboard!$E$3="All",TRUE,#REF!=Dashboard!$E$3)) -> #REF!
A39: =IF(Input!$A$38="","",Input!$A$38) | B39: =IFERROR(_xludf.XLOOKUP(#REF!,tblEntities[entity_id],tblEntities[canonical_name]),"") | C39: =IF(#REF!="","",COUNTIFS(tblClaimsCurrent[entity_id],#REF!,tblClaimsCurrent[status],"PROMOTED")) -> #REF! | D39: =IF(#REF!="","",COUNTIFS(tblClaimsCurrent[entity_id],#REF!,tblClaimsCurrent[status],"UNKNOWN")) -> #REF! | E39: =_xludf.LET(t,#REF!+#REF!,IF(t=0,NA(),#REF!/t)) -> #NAME? | F39: =_xludf.LET(cnt,COUNTIFS(tblClaimsCurrent[entity_id],#REF!,tblClaimsCurrent[status],"PROMOTED"),IF(cnt=0,NA(),AVERAGEIFS(tblClaimsCurrent[confidence],tblClaimsCurrent[entity_id],#REF!,tblClaimsCurrent[status],"PROMOTED"))) -> #NAME? | G39: =_xludf.LET(cnt,COUNTIFS(tblClaimsCurrent[entity_id],#REF!,tblClaimsCurrent[field_key],"pricing_acv_mid_market",tblClaimsCurrent[status],"PROMOTED"),IF(cnt=0,NA(),SUMIFS(tblClaimsCurrent[value_num],tblClaimsCurrent[entity_id],#REF!,tblClaimsCurrent[field_key],"pricing_acv_mid_market",tblClaimsCurrent[status],"PROMOTED"))) -> #NAME? | H39: =IF(OR(NOT(ISNUMBER(#REF!)),$B$5=""),"UNKNOWN",IF(#REF!<=($B$5*0.85),"Low",IF(#REF!>=($B$5*1.15),"High","Mid"))) -> UNKNOWN | I39: =_xludf.LET(v,IFERROR(LOOKUP(2,1/((tblClaimsCurrent[entity_id]=#REF!)*(tblClaimsCurrent[field_key]="features")*(tblClaimsCurrent[status]="PROMOTED")),tblClaimsCurrent[value_text]),"UNKNOWN"),IF(v="","UNKNOWN",v)) -> #NAME? | J39: =IF(OR(#REF!="UNKNOWN",#REF!=""),NA(),1+LEN(#REF!)-LEN(SUBSTITUTE(#REF!,";",""))) -> #REF! | K39: =IF(#REF!="",NA(),IF(#REF!="SEG_MM",1,0)) -> #REF! | L39: =IF(#REF!="","",IF(COUNTIFS(tblClaimsCurrent[entity_id],#REF!,tblClaimsCurrent[field_key],"funding_round",tblClaimsCurrent[status],"PROMOTED")>0,1,0)) -> #REF! | M39: =IF(OR(#REF!=FALSE,ISNA(#REF!),ISNA(#REF!),ISNA(#REF!),#REF!="UNKNOWN"),NA(),MIN(1,Config!$B$14*MIN(1,#REF!/10)+Config!$B$15*IF(#REF!="Low",1,IF(#REF!="Mid",0.5,0))+Config!$B$16*#REF!+Config!$B$17*#REF!)) -> #REF! | N39: =IF(OR(#REF!=FALSE,ISNA(#REF!),ISNA(#REF!),ISNA(#REF!)),NA(),MIN(1,Config!$B$18*(1-MIN(1,#REF!/10))+Config!$B$19*(1-#REF!)+Config!$B$20*(1-#REF!))) -> #REF! | O39: =IF(#REF!=FALSE,"OUT_OF_SCOPE",IF(ISNA(#REF!),"UNKNOWN",IF(#REF!<Config!$B$10,"FAIL_CLOSED_LOW_COVERAGE","OK"))) -> #REF! | P39: =IFERROR(_xludf.XLOOKUP(#REF!,tblEntities[entity_id],tblEntities[segment_id]),"") | Q39: =IFERROR(_xludf.XLOOKUP(#REF!,tblEntities[entity_id],tblEntities[vertical]),"") | R39: =AND(#REF!=Dashboard!$E$2,IF(Dashboard!$E$3="All",TRUE,#REF!=Dashboard!$E$3)) -> #REF!
A40: =IF(Input!$A$39="","",Input!$A$39) | B40: =IFERROR(_xludf.XLOOKUP(#REF!,tblEntities[entity_id],tblEntities[canonical_name]),"") | C40: =IF(#REF!="","",COUNTIFS(tblClaimsCurrent[entity_id],#REF!,tblClaimsCurrent[status],"PROMOTED")) -> #REF! | D40: =IF(#REF!="","",COUNTIFS(tblClaimsCurrent[entity_id],#REF!,tblClaimsCurrent[status],"UNKNOWN")) -> #REF! | E40: =_xludf.LET(t,#REF!+#REF!,IF(t=0,NA(),#REF!/t)) -> #NAME? | F40: =_xludf.LET(cnt,COUNTIFS(tblClaimsCurrent[entity_id],#REF!,tblClaimsCurrent[status],"PROMOTED"),IF(cnt=0,NA(),AVERAGEIFS(tblClaimsCurrent[confidence],tblClaimsCurrent[entity_id],#REF!,tblClaimsCurrent[status],"PROMOTED"))) -> #NAME? | G40: =_xludf.LET(cnt,COUNTIFS(tblClaimsCurrent[entity_id],#REF!,tblClaimsCurrent[field_key],"pricing_acv_mid_market",tblClaimsCurrent[status],"PROMOTED"),IF(cnt=0,NA(),SUMIFS(tblClaimsCurrent[value_num],tblClaimsCurrent[entity_id],#REF!,tblClaimsCurrent[field_key],"pricing_acv_mid_market",tblClaimsCurrent[status],"PROMOTED"))) -> #NAME? | H40: =IF(OR(NOT(ISNUMBER(#REF!)),$B$5=""),"UNKNOWN",IF(#REF!<=($B$5*0.85),"Low",IF(#REF!>=($B$5*1.15),"High","Mid"))) -> UNKNOWN | I40: =_xludf.LET(v,IFERROR(LOOKUP(2,1/((tblClaimsCurrent[entity_id]=#REF!)*(tblClaimsCurrent[field_key]="features")*(tblClaimsCurrent[status]="PROMOTED")),tblClaimsCurrent[value_text]),"UNKNOWN"),IF(v="","UNKNOWN",v)) -> #NAME? | J40: =IF(OR(#REF!="UNKNOWN",#REF!=""),NA(),1+LEN(#REF!)-LEN(SUBSTITUTE(#REF!,";",""))) -> #REF! | K40: =IF(#REF!="",NA(),IF(#REF!="SEG_MM",1,0)) -> #REF! | L40: =IF(#REF!="","",IF(COUNTIFS(tblClaimsCurrent[entity_id],#REF!,tblClaimsCurrent[field_key],"funding_round",tblClaimsCurrent[status],"PROMOTED")>0,1,0)) -> #REF! | M40: =IF(OR(#REF!=FALSE,ISNA(#REF!),ISNA(#REF!),ISNA(#REF!),#REF!="UNKNOWN"),NA(),MIN(1,Config!$B$14*MIN(1,#REF!/10)+Config!$B$15*IF(#REF!="Low",1,IF(#REF!="Mid",0.5,0))+Config!$B$16*#REF!+Config!$B$17*#REF!)) -> #REF! | N40: =IF(OR(#REF!=FALSE,ISNA(#REF!),ISNA(#REF!),ISNA(#REF!)),NA(),MIN(1,Config!$B$18*(1-MIN(1,#REF!/10))+Config!$B$19*(1-#REF!)+Config!$B$20*(1-#REF!))) -> #REF! | O40: =IF(#REF!=FALSE,"OUT_OF_SCOPE",IF(ISNA(#REF!),"UNKNOWN",IF(#REF!<Config!$B$10,"FAIL_CLOSED_LOW_COVERAGE","OK"))) -> #REF! | P40: =IFERROR(_xludf.XLOOKUP(#REF!,tblEntities[entity_id],tblEntities[segment_id]),"") | Q40: =IFERROR(_xludf.XLOOKUP(#REF!,tblEntities[entity_id],tblEntities[vertical]),"") | R40: =AND(#REF!=Dashboard!$E$2,IF(Dashboard!$E$3="All",TRUE,#REF!=Dashboard!$E$3)) -> #REF!
A41: =IF(Input!$A$40="","",Input!$A$40) | B41: =IFERROR(_xludf.XLOOKUP(#REF!,tblEntities[entity_id],tblEntities[canonical_name]),"") | C41: =IF(#REF!="","",COUNTIFS(tblClaimsCurrent[entity_id],#REF!,tblClaimsCurrent[status],"PROMOTED")) -> #REF! | D41: =IF(#REF!="","",COUNTIFS(tblClaimsCurrent[entity_id],#REF!,tblClaimsCurrent[status],"UNKNOWN")) -> #REF! | E41: =_xludf.LET(t,#REF!+#REF!,IF(t=0,NA(),#REF!/t)) -> #NAME? | F41: =_xludf.LET(cnt,COUNTIFS(tblClaimsCurrent[entity_id],#REF!,tblClaimsCurrent[status],"PROMOTED"),IF(cnt=0,NA(),AVERAGEIFS(tblClaimsCurrent[confidence],tblClaimsCurrent[entity_id],#REF!,tblClaimsCurrent[status],"PROMOTED"))) -> #NAME? | G41: =_xludf.LET(cnt,COUNTIFS(tblClaimsCurrent[entity_id],#REF!,tblClaimsCurrent[field_key],"pricing_acv_mid_market",tblClaimsCurrent[status],"PROMOTED"),IF(cnt=0,NA(),SUMIFS(tblClaimsCurrent[value_num],tblClaimsCurrent[entity_id],#REF!,tblClaimsCurrent[field_key],"pricing_acv_mid_market",tblClaimsCurrent[status],"PROMOTED"))) -> #NAME? | H41: =IF(OR(NOT(ISNUMBER(#REF!)),$B$5=""),"UNKNOWN",IF(#REF!<=($B$5*0.85),"Low",IF(#REF!>=($B$5*1.15),"High","Mid"))) -> UNKNOWN | I41: =_xludf.LET(v,IFERROR(LOOKUP(2,1/((tblClaimsCurrent[entity_id]=#REF!)*(tblClaimsCurrent[field_key]="features")*(tblClaimsCurrent[status]="PROMOTED")),tblClaimsCurrent[value_text]),"UNKNOWN"),IF(v="","UNKNOWN",v)) -> #NAME? | J41: =IF(OR(#REF!="UNKNOWN",#REF!=""),NA(),1+LEN(#REF!)-LEN(SUBSTITUTE(#REF!,";",""))) -> #REF! | K41: =IF(#REF!="",NA(),IF(#REF!="SEG_MM",1,0)) -> #REF! | L41: =IF(#REF!="","",IF(COUNTIFS(tblClaimsCurrent[entity_id],#REF!,tblClaimsCurrent[field_key],"funding_round",tblClaimsCurrent[status],"PROMOTED")>0,1,0)) -> #REF! | M41: =IF(OR(#REF!=FALSE,ISNA(#REF!),ISNA(#REF!),ISNA(#REF!),#REF!="UNKNOWN"),NA(),MIN(1,Config!$B$14*MIN(1,#REF!/10)+Config!$B$15*IF(#REF!="Low",1,IF(#REF!="Mid",0.5,0))+Config!$B$16*#REF!+Config!$B$17*#REF!)) -> #REF! | N41: =IF(OR(#REF!=FALSE,ISNA(#REF!),ISNA(#REF!),ISNA(#REF!)),NA(),MIN(1,Config!$B$18*(1-MIN(1,#REF!/10))+Config!$B$19*(1-#REF!)+Config!$B$20*(1-#REF!))) -> #REF! | O41: =IF(#REF!=FALSE,"OUT_OF_SCOPE",IF(ISNA(#REF!),"UNKNOWN",IF(#REF!<Config!$B$10,"FAIL_CLOSED_LOW_COVERAGE","OK"))) -> #REF! | P41: =IFERROR(_xludf.XLOOKUP(#REF!,tblEntities[entity_id],tblEntities[segment_id]),"") | Q41: =IFERROR(_xludf.XLOOKUP(#REF!,tblEntities[entity_id],tblEntities[vertical]),"") | R41: =AND(#REF!=Dashboard!$E$2,IF(Dashboard!$E$3="All",TRUE,#REF!=Dashboard!$E$3)) -> #REF!
A42: =IF(Input!$A$41="","",Input!$A$41) | B42: =IFERROR(_xludf.XLOOKUP(#REF!,tblEntities[entity_id],tblEntities[canonical_name]),"") | C42: =IF(#REF!="","",COUNTIFS(tblClaimsCurrent[entity_id],#REF!,tblClaimsCurrent[status],"PROMOTED")) -> #REF! | D42: =IF(#REF!="","",COUNTIFS(tblClaimsCurrent[entity_id],#REF!,tblClaimsCurrent[status],"UNKNOWN")) -> #REF! | E42: =_xludf.LET(t,#REF!+#REF!,IF(t=0,NA(),#REF!/t)) -> #NAME? | F42: =_xludf.LET(cnt,COUNTIFS(tblClaimsCurrent[entity_id],#REF!,tblClaimsCurrent[status],"PROMOTED"),IF(cnt=0,NA(),AVERAGEIFS(tblClaimsCurrent[confidence],tblClaimsCurrent[entity_id],#REF!,tblClaimsCurrent[status],"PROMOTED"))) -> #NAME? | G42: =_xludf.LET(cnt,COUNTIFS(tblClaimsCurrent[entity_id],#REF!,tblClaimsCurrent[field_key],"pricing_acv_mid_market",tblClaimsCurrent[status],"PROMOTED"),IF(cnt=0,NA(),SUMIFS(tblClaimsCurrent[value_num],tblClaimsCurrent[entity_id],#REF!,tblClaimsCurrent[field_key],"pricing_acv_mid_market",tblClaimsCurrent[status],"PROMOTED"))) -> #NAME? | H42: =IF(OR(NOT(ISNUMBER(#REF!)),$B$5=""),"UNKNOWN",IF(#REF!<=($B$5*0.85),"Low",IF(#REF!>=($B$5*1.15),"High","Mid"))) -> UNKNOWN | I42: =_xludf.LET(v,IFERROR(LOOKUP(2,1/((tblClaimsCurrent[entity_id]=#REF!)*(tblClaimsCurrent[field_key]="features")*(tblClaimsCurrent[status]="PROMOTED")),tblClaimsCurrent[value_text]),"UNKNOWN"),IF(v="","UNKNOWN",v)) -> #NAME? | J42: =IF(OR(#REF!="UNKNOWN",#REF!=""),NA(),1+LEN(#REF!)-LEN(SUBSTITUTE(#REF!,";",""))) -> #REF! | K42: =IF(#REF!="",NA(),IF(#REF!="SEG_MM",1,0)) -> #REF! | L42: =IF(#REF!="","",IF(COUNTIFS(tblClaimsCurrent[entity_id],#REF!,tblClaimsCurrent[field_key],"funding_round",tblClaimsCurrent[status],"PROMOTED")>0,1,0)) -> #REF! | M42: =IF(OR(#REF!=FALSE,ISNA(#REF!),ISNA(#REF!),ISNA(#REF!),#REF!="UNKNOWN"),NA(),MIN(1,Config!$B$14*MIN(1,#REF!/10)+Config!$B$15*IF(#REF!="Low",1,IF(#REF!="Mid",0.5,0))+Config!$B$16*#REF!+Config!$B$17*#REF!)) -> #REF! | N42: =IF(OR(#REF!=FALSE,ISNA(#REF!),ISNA(#REF!),ISNA(#REF!)),NA(),MIN(1,Config!$B$18*(1-MIN(1,#REF!/10))+Config!$B$19*(1-#REF!)+Config!$B$20*(1-#REF!))) -> #REF! | O42: =IF(#REF!=FALSE,"OUT_OF_SCOPE",IF(ISNA(#REF!),"UNKNOWN",IF(#REF!<Config!$B$10,"FAIL_CLOSED_LOW_COVERAGE","OK"))) -> #REF! | P42: =IFERROR(_xludf.XLOOKUP(#REF!,tblEntities[entity_id],tblEntities[segment_id]),"") | Q42: =IFERROR(_xludf.XLOOKUP(#REF!,tblEntities[entity_id],tblEntities[vertical]),"") | R42: =AND(#REF!=Dashboard!$E$2,IF(Dashboard!$E$3="All",TRUE,#REF!=Dashboard!$E$3)) -> #REF!
A43: =IF(Input!$A$42="","",Input!$A$42) | B43: =IFERROR(_xludf.XLOOKUP(#REF!,tblEntities[entity_id],tblEntities[canonical_name]),"") | C43: =IF(#REF!="","",COUNTIFS(tblClaimsCurrent[entity_id],#REF!,tblClaimsCurrent[status],"PROMOTED")) -> #REF! | D43: =IF(#REF!="","",COUNTIFS(tblClaimsCurrent[entity_id],#REF!,tblClaimsCurrent[status],"UNKNOWN")) -> #REF! | E43: =_xludf.LET(t,#REF!+#REF!,IF(t=0,NA(),#REF!/t)) -> #NAME? | F43: =_xludf.LET(cnt,COUNTIFS(tblClaimsCurrent[entity_id],#REF!,tblClaimsCurrent[status],"PROMOTED"),IF(cnt=0,NA(),AVERAGEIFS(tblClaimsCurrent[confidence],tblClaimsCurrent[entity_id],#REF!,tblClaimsCurrent[status],"PROMOTED"))) -> #NAME? | G43: =_xludf.LET(cnt,COUNTIFS(tblClaimsCurrent[entity_id],#REF!,tblClaimsCurrent[field_key],"pricing_acv_mid_market",tblClaimsCurrent[status],"PROMOTED"),IF(cnt=0,NA(),SUMIFS(tblClaimsCurrent[value_num],tblClaimsCurrent[entity_id],#REF!,tblClaimsCurrent[field_key],"pricing_acv_mid_market",tblClaimsCurrent[status],"PROMOTED"))) -> #NAME? | H43: =IF(OR(NOT(ISNUMBER(#REF!)),$B$5=""),"UNKNOWN",IF(#REF!<=($B$5*0.85),"Low",IF(#REF!>=($B$5*1.15),"High","Mid"))) -> UNKNOWN | I43: =_xludf.LET(v,IFERROR(LOOKUP(2,1/((tblClaimsCurrent[entity_id]=#REF!)*(tblClaimsCurrent[field_key]="features")*(tblClaimsCurrent[status]="PROMOTED")),tblClaimsCurrent[value_text]),"UNKNOWN"),IF(v="","UNKNOWN",v)) -> #NAME? | J43: =IF(OR(#REF!="UNKNOWN",#REF!=""),NA(),1+LEN(#REF!)-LEN(SUBSTITUTE(#REF!,";",""))) -> #REF! | K43: =IF(#REF!="",NA(),IF(#REF!="SEG_MM",1,0)) -> #REF! | L43: =IF(#REF!="","",IF(COUNTIFS(tblClaimsCurrent[entity_id],#REF!,tblClaimsCurrent[field_key],"funding_round",tblClaimsCurrent[status],"PROMOTED")>0,1,0)) -> #REF! | M43: =IF(OR(#REF!=FALSE,ISNA(#REF!),ISNA(#REF!),ISNA(#REF!),#REF!="UNKNOWN"),NA(),MIN(1,Config!$B$14*MIN(1,#REF!/10)+Config!$B$15*IF(#REF!="Low",1,IF(#REF!="Mid",0.5,0))+Config!$B$16*#REF!+Config!$B$17*#REF!)) -> #REF! | N43: =IF(OR(#REF!=FALSE,ISNA(#REF!),ISNA(#REF!),ISNA(#REF!)),NA(),MIN(1,Config!$B$18*(1-MIN(1,#REF!/10))+Config!$B$19*(1-#REF!)+Config!$B$20*(1-#REF!))) -> #REF! | O43: =IF(#REF!=FALSE,"OUT_OF_SCOPE",IF(ISNA(#REF!),"UNKNOWN",IF(#REF!<Config!$B$10,"FAIL_CLOSED_LOW_COVERAGE","OK"))) -> #REF! | P43: =IFERROR(_xludf.XLOOKUP(#REF!,tblEntities[entity_id],tblEntities[segment_id]),"") | Q43: =IFERROR(_xludf.XLOOKUP(#REF!,tblEntities[entity_id],tblEntities[vertical]),"") | R43: =AND(#REF!=Dashboard!$E$2,IF(Dashboard!$E$3="All",TRUE,#REF!=Dashboard!$E$3)) -> #REF!
A44: =IF(Input!$A$43="","",Input!$A$43) | B44: =IFERROR(_xludf.XLOOKUP(#REF!,tblEntities[entity_id],tblEntities[canonical_name]),"") | C44: =IF(#REF!="","",COUNTIFS(tblClaimsCurrent[entity_id],#REF!,tblClaimsCurrent[status],"PROMOTED")) -> #REF! | D44: =IF(#REF!="","",COUNTIFS(tblClaimsCurrent[entity_id],#REF!,tblClaimsCurrent[status],"UNKNOWN")) -> #REF! | E44: =_xludf.LET(t,#REF!+#REF!,IF(t=0,NA(),#REF!/t)) -> #NAME? | F44: =_xludf.LET(cnt,COUNTIFS(tblClaimsCurrent[entity_id],#REF!,tblClaimsCurrent[status],"PROMOTED"),IF(cnt=0,NA(),AVERAGEIFS(tblClaimsCurrent[confidence],tblClaimsCurrent[entity_id],#REF!,tblClaimsCurrent[status],"PROMOTED"))) -> #NAME? | G44: =_xludf.LET(cnt,COUNTIFS(tblClaimsCurrent[entity_id],#REF!,tblClaimsCurrent[field_key],"pricing_acv_mid_market",tblClaimsCurrent[status],"PROMOTED"),IF(cnt=0,NA(),SUMIFS(tblClaimsCurrent[value_num],tblClaimsCurrent[entity_id],#REF!,tblClaimsCurrent[field_key],"pricing_acv_mid_market",tblClaimsCurrent[status],"PROMOTED"))) -> #NAME? | H44: =IF(OR(NOT(ISNUMBER(#REF!)),$B$5=""),"UNKNOWN",IF(#REF!<=($B$5*0.85),"Low",IF(#REF!>=($B$5*1.15),"High","Mid"))) -> UNKNOWN | I44: =_xludf.LET(v,IFERROR(LOOKUP(2,1/((tblClaimsCurrent[entity_id]=#REF!)*(tblClaimsCurrent[field_key]="features")*(tblClaimsCurrent[status]="PROMOTED")),tblClaimsCurrent[value_text]),"UNKNOWN"),IF(v="","UNKNOWN",v)) -> #NAME? | J44: =IF(OR(#REF!="UNKNOWN",#REF!=""),NA(),1+LEN(#REF!)-LEN(SUBSTITUTE(#REF!,";",""))) -> #REF! | K44: =IF(#REF!="",NA(),IF(#REF!="SEG_MM",1,0)) -> #REF! | L44: =IF(#REF!="","",IF(COUNTIFS(tblClaimsCurrent[entity_id],#REF!,tblClaimsCurrent[field_key],"funding_round",tblClaimsCurrent[status],"PROMOTED")>0,1,0)) -> #REF! | M44: =IF(OR(#REF!=FALSE,ISNA(#REF!),ISNA(#REF!),ISNA(#REF!),#REF!="UNKNOWN"),NA(),MIN(1,Config!$B$14*MIN(1,#REF!/10)+Config!$B$15*IF(#REF!="Low",1,IF(#REF!="Mid",0.5,0))+Config!$B$16*#REF!+Config!$B$17*#REF!)) -> #REF! | N44: =IF(OR(#REF!=FALSE,ISNA(#REF!),ISNA(#REF!),ISNA(#REF!)),NA(),MIN(1,Config!$B$18*(1-MIN(1,#REF!/10))+Config!$B$19*(1-#REF!)+Config!$B$20*(1-#REF!))) -> #REF! | O44: =IF(#REF!=FALSE,"OUT_OF_SCOPE",IF(ISNA(#REF!),"UNKNOWN",IF(#REF!<Config!$B$10,"FAIL_CLOSED_LOW_COVERAGE","OK"))) -> #REF! | P44: =IFERROR(_xludf.XLOOKUP(#REF!,tblEntities[entity_id],tblEntities[segment_id]),"") | Q44: =IFERROR(_xludf.XLOOKUP(#REF!,tblEntities[entity_id],tblEntities[vertical]),"") | R44: =AND(#REF!=Dashboard!$E$2,IF(Dashboard!$E$3="All",TRUE,#REF!=Dashboard!$E$3)) -> #REF!
A45: =IF(Input!$A$44="","",Input!$A$44) | B45: =IFERROR(_xludf.XLOOKUP(#REF!,tblEntities[entity_id],tblEntities[canonical_name]),"") | C45: =IF(#REF!="","",COUNTIFS(tblClaimsCurrent[entity_id],#REF!,tblClaimsCurrent[status],"PROMOTED")) -> #REF! | D45: =IF(#REF!="","",COUNTIFS(tblClaimsCurrent[entity_id],#REF!,tblClaimsCurrent[status],"UNKNOWN")) -> #REF! | E45: =_xludf.LET(t,#REF!+#REF!,IF(t=0,NA(),#REF!/t)) -> #NAME? | F45: =_xludf.LET(cnt,COUNTIFS(tblClaimsCurrent[entity_id],#REF!,tblClaimsCurrent[status],"PROMOTED"),IF(cnt=0,NA(),AVERAGEIFS(tblClaimsCurrent[confidence],tblClaimsCurrent[entity_id],#REF!,tblClaimsCurrent[status],"PROMOTED"))) -> #NAME? | G45: =_xludf.LET(cnt,COUNTIFS(tblClaimsCurrent[entity_id],#REF!,tblClaimsCurrent[field_key],"pricing_acv_mid_market",tblClaimsCurrent[status],"PROMOTED"),IF(cnt=0,NA(),SUMIFS(tblClaimsCurrent[value_num],tblClaimsCurrent[entity_id],#REF!,tblClaimsCurrent[field_key],"pricing_acv_mid_market",tblClaimsCurrent[status],"PROMOTED"))) -> #NAME? | H45: =IF(OR(NOT(ISNUMBER(#REF!)),$B$5=""),"UNKNOWN",IF(#REF!<=($B$5*0.85),"Low",IF(#REF!>=($B$5*1.15),"High","Mid"))) -> UNKNOWN | I45: =_xludf.LET(v,IFERROR(LOOKUP(2,1/((tblClaimsCurrent[entity_id]=#REF!)*(tblClaimsCurrent[field_key]="features")*(tblClaimsCurrent[status]="PROMOTED")),tblClaimsCurrent[value_text]),"UNKNOWN"),IF(v="","UNKNOWN",v)) -> #NAME? | J45: =IF(OR(#REF!="UNKNOWN",#REF!=""),NA(),1+LEN(#REF!)-LEN(SUBSTITUTE(#REF!,";",""))) -> #REF! | K45: =IF(#REF!="",NA(),IF(#REF!="SEG_MM",1,0)) -> #REF! | L45: =IF(#REF!="","",IF(COUNTIFS(tblClaimsCurrent[entity_id],#REF!,tblClaimsCurrent[field_key],"funding_round",tblClaimsCurrent[status],"PROMOTED")>0,1,0)) -> #REF! | M45: =IF(OR(#REF!=FALSE,ISNA(#REF!),ISNA(#REF!),ISNA(#REF!),#REF!="UNKNOWN"),NA(),MIN(1,Config!$B$14*MIN(1,#REF!/10)+Config!$B$15*IF(#REF!="Low",1,IF(#REF!="Mid",0.5,0))+Config!$B$16*#REF!+Config!$B$17*#REF!)) -> #REF! | N45: =IF(OR(#REF!=FALSE,ISNA(#REF!),ISNA(#REF!),ISNA(#REF!)),NA(),MIN(1,Config!$B$18*(1-MIN(1,#REF!/10))+Config!$B$19*(1-#REF!)+Config!$B$20*(1-#REF!))) -> #REF! | O45: =IF(#REF!=FALSE,"OUT_OF_SCOPE",IF(ISNA(#REF!),"UNKNOWN",IF(#REF!<Config!$B$10,"FAIL_CLOSED_LOW_COVERAGE","OK"))) -> #REF! | P45: =IFERROR(_xludf.XLOOKUP(#REF!,tblEntities[entity_id],tblEntities[segment_id]),"") | Q45: =IFERROR(_xludf.XLOOKUP(#REF!,tblEntities[entity_id],tblEntities[vertical]),"") | R45: =AND(#REF!=Dashboard!$E$2,IF(Dashboard!$E$3="All",TRUE,#REF!=Dashboard!$E$3)) -> #REF!
A46: =IF(Input!$A$45="","",Input!$A$45) | B46: =IFERROR(_xludf.XLOOKUP(#REF!,tblEntities[entity_id],tblEntities[canonical_name]),"") | C46: =IF(#REF!="","",COUNTIFS(tblClaimsCurrent[entity_id],#REF!,tblClaimsCurrent[status],"PROMOTED")) -> #REF! | D46: =IF(#REF!="","",COUNTIFS(tblClaimsCurrent[entity_id],#REF!,tblClaimsCurrent[status],"UNKNOWN")) -> #REF! | E46: =_xludf.LET(t,#REF!+#REF!,IF(t=0,NA(),#REF!/t)) -> #NAME? | F46: =_xludf.LET(cnt,COUNTIFS(tblClaimsCurrent[entity_id],#REF!,tblClaimsCurrent[status],"PROMOTED"),IF(cnt=0,NA(),AVERAGEIFS(tblClaimsCurrent[confidence],tblClaimsCurrent[entity_id],#REF!,tblClaimsCurrent[status],"PROMOTED"))) -> #NAME? | G46: =_xludf.LET(cnt,COUNTIFS(tblClaimsCurrent[entity_id],#REF!,tblClaimsCurrent[field_key],"pricing_acv_mid_market",tblClaimsCurrent[status],"PROMOTED"),IF(cnt=0,NA(),SUMIFS(tblClaimsCurrent[value_num],tblClaimsCurrent[entity_id],#REF!,tblClaimsCurrent[field_key],"pricing_acv_mid_market",tblClaimsCurrent[status],"PROMOTED"))) -> #NAME? | H46: =IF(OR(NOT(ISNUMBER(#REF!)),$B$5=""),"UNKNOWN",IF(#REF!<=($B$5*0.85),"Low",IF(#REF!>=($B$5*1.15),"High","Mid"))) -> UNKNOWN | I46: =_xludf.LET(v,IFERROR(LOOKUP(2,1/((tblClaimsCurrent[entity_id]=#REF!)*(tblClaimsCurrent[field_key]="features")*(tblClaimsCurrent[status]="PROMOTED")),tblClaimsCurrent[value_text]),"UNKNOWN"),IF(v="","UNKNOWN",v)) -> #NAME? | J46: =IF(OR(#REF!="UNKNOWN",#REF!=""),NA(),1+LEN(#REF!)-LEN(SUBSTITUTE(#REF!,";",""))) -> #REF! | K46: =IF(#REF!="",NA(),IF(#REF!="SEG_MM",1,0)) -> #REF! | L46: =IF(#REF!="","",IF(COUNTIFS(tblClaimsCurrent[entity_id],#REF!,tblClaimsCurrent[field_key],"funding_round",tblClaimsCurrent[status],"PROMOTED")>0,1,0)) -> #REF! | M46: =IF(OR(#REF!=FALSE,ISNA(#REF!),ISNA(#REF!),ISNA(#REF!),#REF!="UNKNOWN"),NA(),MIN(1,Config!$B$14*MIN(1,#REF!/10)+Config!$B$15*IF(#REF!="Low",1,IF(#REF!="Mid",0.5,0))+Config!$B$16*#REF!+Config!$B$17*#REF!)) -> #REF! | N46: =IF(OR(#REF!=FALSE,ISNA(#REF!),ISNA(#REF!),ISNA(#REF!)),NA(),MIN(1,Config!$B$18*(1-MIN(1,#REF!/10))+Config!$B$19*(1-#REF!)+Config!$B$20*(1-#REF!))) -> #REF! | O46: =IF(#REF!=FALSE,"OUT_OF_SCOPE",IF(ISNA(#REF!),"UNKNOWN",IF(#REF!<Config!$B$10,"FAIL_CLOSED_LOW_COVERAGE","OK"))) -> #REF! | P46: =IFERROR(_xludf.XLOOKUP(#REF!,tblEntities[entity_id],tblEntities[segment_id]),"") | Q46: =IFERROR(_xludf.XLOOKUP(#REF!,tblEntities[entity_id],tblEntities[vertical]),"") | R46: =AND(#REF!=Dashboard!$E$2,IF(Dashboard!$E$3="All",TRUE,#REF!=Dashboard!$E$3)) -> #REF!
A47: =IF(Input!$A$46="","",Input!$A$46) | B47: =IFERROR(_xludf.XLOOKUP(#REF!,tblEntities[entity_id],tblEntities[canonical_name]),"") | C47: =IF(#REF!="","",COUNTIFS(tblClaimsCurrent[entity_id],#REF!,tblClaimsCurrent[status],"PROMOTED")) -> #REF! | D47: =IF(#REF!="","",COUNTIFS(tblClaimsCurrent[entity_id],#REF!,tblClaimsCurrent[status],"UNKNOWN")) -> #REF! | E47: =_xludf.LET(t,#REF!+#REF!,IF(t=0,NA(),#REF!/t)) -> #NAME? | F47: =_xludf.LET(cnt,COUNTIFS(tblClaimsCurrent[entity_id],#REF!,tblClaimsCurrent[status],"PROMOTED"),IF(cnt=0,NA(),AVERAGEIFS(tblClaimsCurrent[confidence],tblClaimsCurrent[entity_id],#REF!,tblClaimsCurrent[status],"PROMOTED"))) -> #NAME? | G47: =_xludf.LET(cnt,COUNTIFS(tblClaimsCurrent[entity_id],#REF!,tblClaimsCurrent[field_key],"pricing_acv_mid_market",tblClaimsCurrent[status],"PROMOTED"),IF(cnt=0,NA(),SUMIFS(tblClaimsCurrent[value_num],tblClaimsCurrent[entity_id],#REF!,tblClaimsCurrent[field_key],"pricing_acv_mid_market",tblClaimsCurrent[status],"PROMOTED"))) -> #NAME? | H47: =IF(OR(NOT(ISNUMBER(#REF!)),$B$5=""),"UNKNOWN",IF(#REF!<=($B$5*0.85),"Low",IF(#REF!>=($B$5*1.15),"High","Mid"))) -> UNKNOWN | I47: =_xludf.LET(v,IFERROR(LOOKUP(2,1/((tblClaimsCurrent[entity_id]=#REF!)*(tblClaimsCurrent[field_key]="features")*(tblClaimsCurrent[status]="PROMOTED")),tblClaimsCurrent[value_text]),"UNKNOWN"),IF(v="","UNKNOWN",v)) -> #NAME? | J47: =IF(OR(#REF!="UNKNOWN",#REF!=""),NA(),1+LEN(#REF!)-LEN(SUBSTITUTE(#REF!,";",""))) -> #REF! | K47: =IF(#REF!="",NA(),IF(#REF!="SEG_MM",1,0)) -> #REF! | L47: =IF(#REF!="","",IF(COUNTIFS(tblClaimsCurrent[entity_id],#REF!,tblClaimsCurrent[field_key],"funding_round",tblClaimsCurrent[status],"PROMOTED")>0,1,0)) -> #REF! | M47: =IF(OR(#REF!=FALSE,ISNA(#REF!),ISNA(#REF!),ISNA(#REF!),#REF!="UNKNOWN"),NA(),MIN(1,Config!$B$14*MIN(1,#REF!/10)+Config!$B$15*IF(#REF!="Low",1,IF(#REF!="Mid",0.5,0))+Config!$B$16*#REF!+Config!$B$17*#REF!)) -> #REF! | N47: =IF(OR(#REF!=FALSE,ISNA(#REF!),ISNA(#REF!),ISNA(#REF!)),NA(),MIN(1,Config!$B$18*(1-MIN(1,#REF!/10))+Config!$B$19*(1-#REF!)+Config!$B$20*(1-#REF!))) -> #REF! | O47: =IF(#REF!=FALSE,"OUT_OF_SCOPE",IF(ISNA(#REF!),"UNKNOWN",IF(#REF!<Config!$B$10,"FAIL_CLOSED_LOW_COVERAGE","OK"))) -> #REF! | P47: =IFERROR(_xludf.XLOOKUP(#REF!,tblEntities[entity_id],tblEntities[segment_id]),"") | Q47: =IFERROR(_xludf.XLOOKUP(#REF!,tblEntities[entity_id],tblEntities[vertical]),"") | R47: =AND(#REF!=Dashboard!$E$2,IF(Dashboard!$E$3="All",TRUE,#REF!=Dashboard!$E$3)) -> #REF!
A48: =IF(Input!$A$47="","",Input!$A$47) | B48: =IFERROR(_xludf.XLOOKUP(#REF!,tblEntities[entity_id],tblEntities[canonical_name]),"") | C48: =IF(#REF!="","",COUNTIFS(tblClaimsCurrent[entity_id],#REF!,tblClaimsCurrent[status],"PROMOTED")) -> #REF! | D48: =IF(#REF!="","",COUNTIFS(tblClaimsCurrent[entity_id],#REF!,tblClaimsCurrent[status],"UNKNOWN")) -> #REF! | E48: =_xludf.LET(t,#REF!+#REF!,IF(t=0,NA(),#REF!/t)) -> #NAME? | F48: =_xludf.LET(cnt,COUNTIFS(tblClaimsCurrent[entity_id],#REF!,tblClaimsCurrent[status],"PROMOTED"),IF(cnt=0,NA(),AVERAGEIFS(tblClaimsCurrent[confidence],tblClaimsCurrent[entity_id],#REF!,tblClaimsCurrent[status],"PROMOTED"))) -> #NAME? | G48: =_xludf.LET(cnt,COUNTIFS(tblClaimsCurrent[entity_id],#REF!,tblClaimsCurrent[field_key],"pricing_acv_mid_market",tblClaimsCurrent[status],"PROMOTED"),IF(cnt=0,NA(),SUMIFS(tblClaimsCurrent[value_num],tblClaimsCurrent[entity_id],#REF!,tblClaimsCurrent[field_key],"pricing_acv_mid_market",tblClaimsCurrent[status],"PROMOTED"))) -> #NAME? | H48: =IF(OR(NOT(ISNUMBER(#REF!)),$B$5=""),"UNKNOWN",IF(#REF!<=($B$5*0.85),"Low",IF(#REF!>=($B$5*1.15),"High","Mid"))) -> UNKNOWN | I48: =_xludf.LET(v,IFERROR(LOOKUP(2,1/((tblClaimsCurrent[entity_id]=#REF!)*(tblClaimsCurrent[field_key]="features")*(tblClaimsCurrent[status]="PROMOTED")),tblClaimsCurrent[value_text]),"UNKNOWN"),IF(v="","UNKNOWN",v)) -> #NAME? | J48: =IF(OR(#REF!="UNKNOWN",#REF!=""),NA(),1+LEN(#REF!)-LEN(SUBSTITUTE(#REF!,";",""))) -> #REF! | K48: =IF(#REF!="",NA(),IF(#REF!="SEG_MM",1,0)) -> #REF! | L48: =IF(#REF!="","",IF(COUNTIFS(tblClaimsCurrent[entity_id],#REF!,tblClaimsCurrent[field_key],"funding_round",tblClaimsCurrent[status],"PROMOTED")>0,1,0)) -> #REF! | M48: =IF(OR(#REF!=FALSE,ISNA(#REF!),ISNA(#REF!),ISNA(#REF!),#REF!="UNKNOWN"),NA(),MIN(1,Config!$B$14*MIN(1,#REF!/10)+Config!$B$15*IF(#REF!="Low",1,IF(#REF!="Mid",0.5,0))+Config!$B$16*#REF!+Config!$B$17*#REF!)) -> #REF! | N48: =IF(OR(#REF!=FALSE,ISNA(#REF!),ISNA(#REF!),ISNA(#REF!)),NA(),MIN(1,Config!$B$18*(1-MIN(1,#REF!/10))+Config!$B$19*(1-#REF!)+Config!$B$20*(1-#REF!))) -> #REF! | O48: =IF(#REF!=FALSE,"OUT_OF_SCOPE",IF(ISNA(#REF!),"UNKNOWN",IF(#REF!<Config!$B$10,"FAIL_CLOSED_LOW_COVERAGE","OK"))) -> #REF! | P48: =IFERROR(_xludf.XLOOKUP(#REF!,tblEntities[entity_id],tblEntities[segment_id]),"") | Q48: =IFERROR(_xludf.XLOOKUP(#REF!,tblEntities[entity_id],tblEntities[vertical]),"") | R48: =AND(#REF!=Dashboard!$E$2,IF(Dashboard!$E$3="All",TRUE,#REF!=Dashboard!$E$3)) -> #REF!
A49: =IF(Input!$A$48="","",Input!$A$48) | B49: =IFERROR(_xludf.XLOOKUP(#REF!,tblEntities[entity_id],tblEntities[canonical_name]),"") | C49: =IF(#REF!="","",COUNTIFS(tblClaimsCurrent[entity_id],#REF!,tblClaimsCurrent[status],"PROMOTED")) -> #REF! | D49: =IF(#REF!="","",COUNTIFS(tblClaimsCurrent[entity_id],#REF!,tblClaimsCurrent[status],"UNKNOWN")) -> #REF! | E49: =_xludf.LET(t,#REF!+#REF!,IF(t=0,NA(),#REF!/t)) -> #NAME? | F49: =_xludf.LET(cnt,COUNTIFS(tblClaimsCurrent[entity_id],#REF!,tblClaimsCurrent[status],"PROMOTED"),IF(cnt=0,NA(),AVERAGEIFS(tblClaimsCurrent[confidence],tblClaimsCurrent[entity_id],#REF!,tblClaimsCurrent[status],"PROMOTED"))) -> #NAME? | G49: =_xludf.LET(cnt,COUNTIFS(tblClaimsCurrent[entity_id],#REF!,tblClaimsCurrent[field_key],"pricing_acv_mid_market",tblClaimsCurrent[status],"PROMOTED"),IF(cnt=0,NA(),SUMIFS(tblClaimsCurrent[value_num],tblClaimsCurrent[entity_id],#REF!,tblClaimsCurrent[field_key],"pricing_acv_mid_market",tblClaimsCurrent[status],"PROMOTED"))) -> #NAME? | H49: =IF(OR(NOT(ISNUMBER(#REF!)),$B$5=""),"UNKNOWN",IF(#REF!<=($B$5*0.85),"Low",IF(#REF!>=($B$5*1.15),"High","Mid"))) -> UNKNOWN | I49: =_xludf.LET(v,IFERROR(LOOKUP(2,1/((tblClaimsCurrent[entity_id]=#REF!)*(tblClaimsCurrent[field_key]="features")*(tblClaimsCurrent[status]="PROMOTED")),tblClaimsCurrent[value_text]),"UNKNOWN"),IF(v="","UNKNOWN",v)) -> #NAME? | J49: =IF(OR(#REF!="UNKNOWN",#REF!=""),NA(),1+LEN(#REF!)-LEN(SUBSTITUTE(#REF!,";",""))) -> #REF! | K49: =IF(#REF!="",NA(),IF(#REF!="SEG_MM",1,0)) -> #REF! | L49: =IF(#REF!="","",IF(COUNTIFS(tblClaimsCurrent[entity_id],#REF!,tblClaimsCurrent[field_key],"funding_round",tblClaimsCurrent[status],"PROMOTED")>0,1,0)) -> #REF! | M49: =IF(OR(#REF!=FALSE,ISNA(#REF!),ISNA(#REF!),ISNA(#REF!),#REF!="UNKNOWN"),NA(),MIN(1,Config!$B$14*MIN(1,#REF!/10)+Config!$B$15*IF(#REF!="Low",1,IF(#REF!="Mid",0.5,0))+Config!$B$16*#REF!+Config!$B$17*#REF!)) -> #REF! | N49: =IF(OR(#REF!=FALSE,ISNA(#REF!),ISNA(#REF!),ISNA(#REF!)),NA(),MIN(1,Config!$B$18*(1-MIN(1,#REF!/10))+Config!$B$19*(1-#REF!)+Config!$B$20*(1-#REF!))) -> #REF! | O49: =IF(#REF!=FALSE,"OUT_OF_SCOPE",IF(ISNA(#REF!),"UNKNOWN",IF(#REF!<Config!$B$10,"FAIL_CLOSED_LOW_COVERAGE","OK"))) -> #REF! | P49: =IFERROR(_xludf.XLOOKUP(#REF!,tblEntities[entity_id],tblEntities[segment_id]),"") | Q49: =IFERROR(_xludf.XLOOKUP(#REF!,tblEntities[entity_id],tblEntities[vertical]),"") | R49: =AND(#REF!=Dashboard!$E$2,IF(Dashboard!$E$3="All",TRUE,#REF!=Dashboard!$E$3)) -> #REF!
A50: =IF(Input!$A$49="","",Input!$A$49) | B50: =IFERROR(_xludf.XLOOKUP(#REF!,tblEntities[entity_id],tblEntities[canonical_name]),"") | C50: =IF(#REF!="","",COUNTIFS(tblClaimsCurrent[entity_id],#REF!,tblClaimsCurrent[status],"PROMOTED")) -> #REF! | D50: =IF(#REF!="","",COUNTIFS(tblClaimsCurrent[entity_id],#REF!,tblClaimsCurrent[status],"UNKNOWN")) -> #REF! | E50: =_xludf.LET(t,#REF!+#REF!,IF(t=0,NA(),#REF!/t)) -> #NAME? | F50: =_xludf.LET(cnt,COUNTIFS(tblClaimsCurrent[entity_id],#REF!,tblClaimsCurrent[status],"PROMOTED"),IF(cnt=0,NA(),AVERAGEIFS(tblClaimsCurrent[confidence],tblClaimsCurrent[entity_id],#REF!,tblClaimsCurrent[status],"PROMOTED"))) -> #NAME? | G50: =_xludf.LET(cnt,COUNTIFS(tblClaimsCurrent[entity_id],#REF!,tblClaimsCurrent[field_key],"pricing_acv_mid_market",tblClaimsCurrent[status],"PROMOTED"),IF(cnt=0,NA(),SUMIFS(tblClaimsCurrent[value_num],tblClaimsCurrent[entity_id],#REF!,tblClaimsCurrent[field_key],"pricing_acv_mid_market",tblClaimsCurrent[status],"PROMOTED"))) -> #NAME? | H50: =IF(OR(NOT(ISNUMBER(#REF!)),$B$5=""),"UNKNOWN",IF(#REF!<=($B$5*0.85),"Low",IF(#REF!>=($B$5*1.15),"High","Mid"))) -> UNKNOWN | I50: =_xludf.LET(v,IFERROR(LOOKUP(2,1/((tblClaimsCurrent[entity_id]=#REF!)*(tblClaimsCurrent[field_key]="features")*(tblClaimsCurrent[status]="PROMOTED")),tblClaimsCurrent[value_text]),"UNKNOWN"),IF(v="","UNKNOWN",v)) -> #NAME? | J50: =IF(OR(#REF!="UNKNOWN",#REF!=""),NA(),1+LEN(#REF!)-LEN(SUBSTITUTE(#REF!,";",""))) -> #REF! | K50: =IF(#REF!="",NA(),IF(#REF!="SEG_MM",1,0)) -> #REF! | L50: =IF(#REF!="","",IF(COUNTIFS(tblClaimsCurrent[entity_id],#REF!,tblClaimsCurrent[field_key],"funding_round",tblClaimsCurrent[status],"PROMOTED")>0,1,0)) -> #REF! | M50: =IF(OR(#REF!=FALSE,ISNA(#REF!),ISNA(#REF!),ISNA(#REF!),#REF!="UNKNOWN"),NA(),MIN(1,Config!$B$14*MIN(1,#REF!/10)+Config!$B$15*IF(#REF!="Low",1,IF(#REF!="Mid",0.5,0))+Config!$B$16*#REF!+Config!$B$17*#REF!)) -> #REF! | N50: =IF(OR(#REF!=FALSE,ISNA(#REF!),ISNA(#REF!),ISNA(#REF!)),NA(),MIN(1,Config!$B$18*(1-MIN(1,#REF!/10))+Config!$B$19*(1-#REF!)+Config!$B$20*(1-#REF!))) -> #REF! | O50: =IF(#REF!=FALSE,"OUT_OF_SCOPE",IF(ISNA(#REF!),"UNKNOWN",IF(#REF!<Config!$B$10,"FAIL_CLOSED_LOW_COVERAGE","OK"))) -> #REF! | P50: =IFERROR(_xludf.XLOOKUP(#REF!,tblEntities[entity_id],tblEntities[segment_id]),"") | Q50: =IFERROR(_xludf.XLOOKUP(#REF!,tblEntities[entity_id],tblEntities[vertical]),"") | R50: =AND(#REF!=Dashboard!$E$2,IF(Dashboard!$E$3="All",TRUE,#REF!=Dashboard!$E$3)) -> #REF!
A51: =IF(Input!$A$50="","",Input!$A$50) | B51: =IFERROR(_xludf.XLOOKUP(#REF!,tblEntities[entity_id],tblEntities[canonical_name]),"") | C51: =IF(#REF!="","",COUNTIFS(tblClaimsCurrent[entity_id],#REF!,tblClaimsCurrent[status],"PROMOTED")) -> #REF! | D51: =IF(#REF!="","",COUNTIFS(tblClaimsCurrent[entity_id],#REF!,tblClaimsCurrent[status],"UNKNOWN")) -> #REF! | E51: =_xludf.LET(t,#REF!+#REF!,IF(t=0,NA(),#REF!/t)) -> #NAME? | F51: =_xludf.LET(cnt,COUNTIFS(tblClaimsCurrent[entity_id],#REF!,tblClaimsCurrent[status],"PROMOTED"),IF(cnt=0,NA(),AVERAGEIFS(tblClaimsCurrent[confidence],tblClaimsCurrent[entity_id],#REF!,tblClaimsCurrent[status],"PROMOTED"))) -> #NAME? | G51: =_xludf.LET(cnt,COUNTIFS(tblClaimsCurrent[entity_id],#REF!,tblClaimsCurrent[field_key],"pricing_acv_mid_market",tblClaimsCurrent[status],"PROMOTED"),IF(cnt=0,NA(),SUMIFS(tblClaimsCurrent[value_num],tblClaimsCurrent[entity_id],#REF!,tblClaimsCurrent[field_key],"pricing_acv_mid_market",tblClaimsCurrent[status],"PROMOTED"))) -> #NAME? | H51: =IF(OR(NOT(ISNUMBER(#REF!)),$B$5=""),"UNKNOWN",IF(#REF!<=($B$5*0.85),"Low",IF(#REF!>=($B$5*1.15),"High","Mid"))) -> UNKNOWN | I51: =_xludf.LET(v,IFERROR(LOOKUP(2,1/((tblClaimsCurrent[entity_id]=#REF!)*(tblClaimsCurrent[field_key]="features")*(tblClaimsCurrent[status]="PROMOTED")),tblClaimsCurrent[value_text]),"UNKNOWN"),IF(v="","UNKNOWN",v)) -> #NAME? | J51: =IF(OR(#REF!="UNKNOWN",#REF!=""),NA(),1+LEN(#REF!)-LEN(SUBSTITUTE(#REF!,";",""))) -> #REF! | K51: =IF(#REF!="",NA(),IF(#REF!="SEG_MM",1,0)) -> #REF! | L51: =IF(#REF!="","",IF(COUNTIFS(tblClaimsCurrent[entity_id],#REF!,tblClaimsCurrent[field_key],"funding_round",tblClaimsCurrent[status],"PROMOTED")>0,1,0)) -> #REF! | M51: =IF(OR(#REF!=FALSE,ISNA(#REF!),ISNA(#REF!),ISNA(#REF!),#REF!="UNKNOWN"),NA(),MIN(1,Config!$B$14*MIN(1,#REF!/10)+Config!$B$15*IF(#REF!="Low",1,IF(#REF!="Mid",0.5,0))+Config!$B$16*#REF!+Config!$B$17*#REF!)) -> #REF! | N51: =IF(OR(#REF!=FALSE,ISNA(#REF!),ISNA(#REF!),ISNA(#REF!)),NA(),MIN(1,Config!$B$18*(1-MIN(1,#REF!/10))+Config!$B$19*(1-#REF!)+Config!$B$20*(1-#REF!))) -> #REF! | O51: =IF(#REF!=FALSE,"OUT_OF_SCOPE",IF(ISNA(#REF!),"UNKNOWN",IF(#REF!<Config!$B$10,"FAIL_CLOSED_LOW_COVERAGE","OK"))) -> #REF! | P51: =IFERROR(_xludf.XLOOKUP(#REF!,tblEntities[entity_id],tblEntities[segment_id]),"") | Q51: =IFERROR(_xludf.XLOOKUP(#REF!,tblEntities[entity_id],tblEntities[vertical]),"") | R51: =AND(#REF!=Dashboard!$E$2,IF(Dashboard!$E$3="All",TRUE,#REF!=Dashboard!$E$3)) -> #REF!
A52: =IF(Input!$A$51="","",Input!$A$51) | B52: =IFERROR(_xludf.XLOOKUP(#REF!,tblEntities[entity_id],tblEntities[canonical_name]),"") | C52: =IF(#REF!="","",COUNTIFS(tblClaimsCurrent[entity_id],#REF!,tblClaimsCurrent[status],"PROMOTED")) -> #REF! | D52: =IF(#REF!="","",COUNTIFS(tblClaimsCurrent[entity_id],#REF!,tblClaimsCurrent[status],"UNKNOWN")) -> #REF! | E52: =_xludf.LET(t,#REF!+#REF!,IF(t=0,NA(),#REF!/t)) -> #NAME? | F52: =_xludf.LET(cnt,COUNTIFS(tblClaimsCurrent[entity_id],#REF!,tblClaimsCurrent[status],"PROMOTED"),IF(cnt=0,NA(),AVERAGEIFS(tblClaimsCurrent[confidence],tblClaimsCurrent[entity_id],#REF!,tblClaimsCurrent[status],"PROMOTED"))) -> #NAME? | G52: =_xludf.LET(cnt,COUNTIFS(tblClaimsCurrent[entity_id],#REF!,tblClaimsCurrent[field_key],"pricing_acv_mid_market",tblClaimsCurrent[status],"PROMOTED"),IF(cnt=0,NA(),SUMIFS(tblClaimsCurrent[value_num],tblClaimsCurrent[entity_id],#REF!,tblClaimsCurrent[field_key],"pricing_acv_mid_market",tblClaimsCurrent[status],"PROMOTED"))) -> #NAME? | H52: =IF(OR(NOT(ISNUMBER(#REF!)),$B$5=""),"UNKNOWN",IF(#REF!<=($B$5*0.85),"Low",IF(#REF!>=($B$5*1.15),"High","Mid"))) -> UNKNOWN | I52: =_xludf.LET(v,IFERROR(LOOKUP(2,1/((tblClaimsCurrent[entity_id]=#REF!)*(tblClaimsCurrent[field_key]="features")*(tblClaimsCurrent[status]="PROMOTED")),tblClaimsCurrent[value_text]),"UNKNOWN"),IF(v="","UNKNOWN",v)) -> #NAME? | J52: =IF(OR(#REF!="UNKNOWN",#REF!=""),NA(),1+LEN(#REF!)-LEN(SUBSTITUTE(#REF!,";",""))) -> #REF! | K52: =IF(#REF!="",NA(),IF(#REF!="SEG_MM",1,0)) -> #REF! | L52: =IF(#REF!="","",IF(COUNTIFS(tblClaimsCurrent[entity_id],#REF!,tblClaimsCurrent[field_key],"funding_round",tblClaimsCurrent[status],"PROMOTED")>0,1,0)) -> #REF! | M52: =IF(OR(#REF!=FALSE,ISNA(#REF!),ISNA(#REF!),ISNA(#REF!),#REF!="UNKNOWN"),NA(),MIN(1,Config!$B$14*MIN(1,#REF!/10)+Config!$B$15*IF(#REF!="Low",1,IF(#REF!="Mid",0.5,0))+Config!$B$16*#REF!+Config!$B$17*#REF!)) -> #REF! | N52: =IF(OR(#REF!=FALSE,ISNA(#REF!),ISNA(#REF!),ISNA(#REF!)),NA(),MIN(1,Config!$B$18*(1-MIN(1,#REF!/10))+Config!$B$19*(1-#REF!)+Config!$B$20*(1-#REF!))) -> #REF! | O52: =IF(#REF!=FALSE,"OUT_OF_SCOPE",IF(ISNA(#REF!),"UNKNOWN",IF(#REF!<Config!$B$10,"FAIL_CLOSED_LOW_COVERAGE","OK"))) -> #REF! | P52: =IFERROR(_xludf.XLOOKUP(#REF!,tblEntities[entity_id],tblEntities[segment_id]),"") | Q52: =IFERROR(_xludf.XLOOKUP(#REF!,tblEntities[entity_id],tblEntities[vertical]),"") | R52: =AND(#REF!=Dashboard!$E$2,IF(Dashboard!$E$3="All",TRUE,#REF!=Dashboard!$E$3)) -> #REF!
A53: =IF(Input!$A$52="","",Input!$A$52) | B53: =IFERROR(_xludf.XLOOKUP(#REF!,tblEntities[entity_id],tblEntities[canonical_name]),"") | C53: =IF(#REF!="","",COUNTIFS(tblClaimsCurrent[entity_id],#REF!,tblClaimsCurrent[status],"PROMOTED")) -> #REF! | D53: =IF(#REF!="","",COUNTIFS(tblClaimsCurrent[entity_id],#REF!,tblClaimsCurrent[status],"UNKNOWN")) -> #REF! | E53: =_xludf.LET(t,#REF!+#REF!,IF(t=0,NA(),#REF!/t)) -> #NAME? | F53: =_xludf.LET(cnt,COUNTIFS(tblClaimsCurrent[entity_id],#REF!,tblClaimsCurrent[status],"PROMOTED"),IF(cnt=0,NA(),AVERAGEIFS(tblClaimsCurrent[confidence],tblClaimsCurrent[entity_id],#REF!,tblClaimsCurrent[status],"PROMOTED"))) -> #NAME? | G53: =_xludf.LET(cnt,COUNTIFS(tblClaimsCurrent[entity_id],#REF!,tblClaimsCurrent[field_key],"pricing_acv_mid_market",tblClaimsCurrent[status],"PROMOTED"),IF(cnt=0,NA(),SUMIFS(tblClaimsCurrent[value_num],tblClaimsCurrent[entity_id],#REF!,tblClaimsCurrent[field_key],"pricing_acv_mid_market",tblClaimsCurrent[status],"PROMOTED"))) -> #NAME? | H53: =IF(OR(NOT(ISNUMBER(#REF!)),$B$5=""),"UNKNOWN",IF(#REF!<=($B$5*0.85),"Low",IF(#REF!>=($B$5*1.15),"High","Mid"))) -> UNKNOWN | I53: =_xludf.LET(v,IFERROR(LOOKUP(2,1/((tblClaimsCurrent[entity_id]=#REF!)*(tblClaimsCurrent[field_key]="features")*(tblClaimsCurrent[status]="PROMOTED")),tblClaimsCurrent[value_text]),"UNKNOWN"),IF(v="","UNKNOWN",v)) -> #NAME? | J53: =IF(OR(#REF!="UNKNOWN",#REF!=""),NA(),1+LEN(#REF!)-LEN(SUBSTITUTE(#REF!,";",""))) -> #REF! | K53: =IF(#REF!="",NA(),IF(#REF!="SEG_MM",1,0)) -> #REF! | L53: =IF(#REF!="","",IF(COUNTIFS(tblClaimsCurrent[entity_id],#REF!,tblClaimsCurrent[field_key],"funding_round",tblClaimsCurrent[status],"PROMOTED")>0,1,0)) -> #REF! | M53: =IF(OR(#REF!=FALSE,ISNA(#REF!),ISNA(#REF!),ISNA(#REF!),#REF!="UNKNOWN"),NA(),MIN(1,Config!$B$14*MIN(1,#REF!/10)+Config!$B$15*IF(#REF!="Low",1,IF(#REF!="Mid",0.5,0))+Config!$B$16*#REF!+Config!$B$17*#REF!)) -> #REF! | N53: =IF(OR(#REF!=FALSE,ISNA(#REF!),ISNA(#REF!),ISNA(#REF!)),NA(),MIN(1,Config!$B$18*(1-MIN(1,#REF!/10))+Config!$B$19*(1-#REF!)+Config!$B$20*(1-#REF!))) -> #REF! | O53: =IF(#REF!=FALSE,"OUT_OF_SCOPE",IF(ISNA(#REF!),"UNKNOWN",IF(#REF!<Config!$B$10,"FAIL_CLOSED_LOW_COVERAGE","OK"))) -> #REF! | P53: =IFERROR(_xludf.XLOOKUP(#REF!,tblEntities[entity_id],tblEntities[segment_id]),"") | Q53: =IFERROR(_xludf.XLOOKUP(#REF!,tblEntities[entity_id],tblEntities[vertical]),"") | R53: =AND(#REF!=Dashboard!$E$2,IF(Dashboard!$E$3="All",TRUE,#REF!=Dashboard!$E$3)) -> #REF!
A54: =IF(Input!$A$53="","",Input!$A$53) | B54: =IFERROR(_xludf.XLOOKUP(#REF!,tblEntities[entity_id],tblEntities[canonical_name]),"") | C54: =IF(#REF!="","",COUNTIFS(tblClaimsCurrent[entity_id],#REF!,tblClaimsCurrent[status],"PROMOTED")) -> #REF! | D54: =IF(#REF!="","",COUNTIFS(tblClaimsCurrent[entity_id],#REF!,tblClaimsCurrent[status],"UNKNOWN")) -> #REF! | E54: =_xludf.LET(t,#REF!+#REF!,IF(t=0,NA(),#REF!/t)) -> #NAME? | F54: =_xludf.LET(cnt,COUNTIFS(tblClaimsCurrent[entity_id],#REF!,tblClaimsCurrent[status],"PROMOTED"),IF(cnt=0,NA(),AVERAGEIFS(tblClaimsCurrent[confidence],tblClaimsCurrent[entity_id],#REF!,tblClaimsCurrent[status],"PROMOTED"))) -> #NAME? | G54: =_xludf.LET(cnt,COUNTIFS(tblClaimsCurrent[entity_id],#REF!,tblClaimsCurrent[field_key],"pricing_acv_mid_market",tblClaimsCurrent[status],"PROMOTED"),IF(cnt=0,NA(),SUMIFS(tblClaimsCurrent[value_num],tblClaimsCurrent[entity_id],#REF!,tblClaimsCurrent[field_key],"pricing_acv_mid_market",tblClaimsCurrent[status],"PROMOTED"))) -> #NAME? | H54: =IF(OR(NOT(ISNUMBER(#REF!)),$B$5=""),"UNKNOWN",IF(#REF!<=($B$5*0.85),"Low",IF(#REF!>=($B$5*1.15),"High","Mid"))) -> UNKNOWN | I54: =_xludf.LET(v,IFERROR(LOOKUP(2,1/((tblClaimsCurrent[entity_id]=#REF!)*(tblClaimsCurrent[field_key]="features")*(tblClaimsCurrent[status]="PROMOTED")),tblClaimsCurrent[value_text]),"UNKNOWN"),IF(v="","UNKNOWN",v)) -> #NAME? | J54: =IF(OR(#REF!="UNKNOWN",#REF!=""),NA(),1+LEN(#REF!)-LEN(SUBSTITUTE(#REF!,";",""))) -> #REF! | K54: =IF(#REF!="",NA(),IF(#REF!="SEG_MM",1,0)) -> #REF! | L54: =IF(#REF!="","",IF(COUNTIFS(tblClaimsCurrent[entity_id],#REF!,tblClaimsCurrent[field_key],"funding_round",tblClaimsCurrent[status],"PROMOTED")>0,1,0)) -> #REF! | M54: =IF(OR(#REF!=FALSE,ISNA(#REF!),ISNA(#REF!),ISNA(#REF!),#REF!="UNKNOWN"),NA(),MIN(1,Config!$B$14*MIN(1,#REF!/10)+Config!$B$15*IF(#REF!="Low",1,IF(#REF!="Mid",0.5,0))+Config!$B$16*#REF!+Config!$B$17*#REF!)) -> #REF! | N54: =IF(OR(#REF!=FALSE,ISNA(#REF!),ISNA(#REF!),ISNA(#REF!)),NA(),MIN(1,Config!$B$18*(1-MIN(1,#REF!/10))+Config!$B$19*(1-#REF!)+Config!$B$20*(1-#REF!))) -> #REF! | O54: =IF(#REF!=FALSE,"OUT_OF_SCOPE",IF(ISNA(#REF!),"UNKNOWN",IF(#REF!<Config!$B$10,"FAIL_CLOSED_LOW_COVERAGE","OK"))) -> #REF! | P54: =IFERROR(_xludf.XLOOKUP(#REF!,tblEntities[entity_id],tblEntities[segment_id]),"") | Q54: =IFERROR(_xludf.XLOOKUP(#REF!,tblEntities[entity_id],tblEntities[vertical]),"") | R54: =AND(#REF!=Dashboard!$E$2,IF(Dashboard!$E$3="All",TRUE,#REF!=Dashboard!$E$3)) -> #REF!
A55: =IF(Input!$A$54="","",Input!$A$54) | B55: =IFERROR(_xludf.XLOOKUP(#REF!,tblEntities[entity_id],tblEntities[canonical_name]),"") | C55: =IF(#REF!="","",COUNTIFS(tblClaimsCurrent[entity_id],#REF!,tblClaimsCurrent[status],"PROMOTED")) -> #REF! | D55: =IF(#REF!="","",COUNTIFS(tblClaimsCurrent[entity_id],#REF!,tblClaimsCurrent[status],"UNKNOWN")) -> #REF! | E55: =_xludf.LET(t,#REF!+#REF!,IF(t=0,NA(),#REF!/t)) -> #NAME? | F55: =_xludf.LET(cnt,COUNTIFS(tblClaimsCurrent[entity_id],#REF!,tblClaimsCurrent[status],"PROMOTED"),IF(cnt=0,NA(),AVERAGEIFS(tblClaimsCurrent[confidence],tblClaimsCurrent[entity_id],#REF!,tblClaimsCurrent[status],"PROMOTED"))) -> #NAME? | G55: =_xludf.LET(cnt,COUNTIFS(tblClaimsCurrent[entity_id],#REF!,tblClaimsCurrent[field_key],"pricing_acv_mid_market",tblClaimsCurrent[status],"PROMOTED"),IF(cnt=0,NA(),SUMIFS(tblClaimsCurrent[value_num],tblClaimsCurrent[entity_id],#REF!,tblClaimsCurrent[field_key],"pricing_acv_mid_market",tblClaimsCurrent[status],"PROMOTED"))) -> #NAME? | H55: =IF(OR(NOT(ISNUMBER(#REF!)),$B$5=""),"UNKNOWN",IF(#REF!<=($B$5*0.85),"Low",IF(#REF!>=($B$5*1.15),"High","Mid"))) -> UNKNOWN | I55: =_xludf.LET(v,IFERROR(LOOKUP(2,1/((tblClaimsCurrent[entity_id]=#REF!)*(tblClaimsCurrent[field_key]="features")*(tblClaimsCurrent[status]="PROMOTED")),tblClaimsCurrent[value_text]),"UNKNOWN"),IF(v="","UNKNOWN",v)) -> #NAME? | J55: =IF(OR(#REF!="UNKNOWN",#REF!=""),NA(),1+LEN(#REF!)-LEN(SUBSTITUTE(#REF!,";",""))) -> #REF! | K55: =IF(#REF!="",NA(),IF(#REF!="SEG_MM",1,0)) -> #REF! | L55: =IF(#REF!="","",IF(COUNTIFS(tblClaimsCurrent[entity_id],#REF!,tblClaimsCurrent[field_key],"funding_round",tblClaimsCurrent[status],"PROMOTED")>0,1,0)) -> #REF! | M55: =IF(OR(#REF!=FALSE,ISNA(#REF!),ISNA(#REF!),ISNA(#REF!),#REF!="UNKNOWN"),NA(),MIN(1,Config!$B$14*MIN(1,#REF!/10)+Config!$B$15*IF(#REF!="Low",1,IF(#REF!="Mid",0.5,0))+Config!$B$16*#REF!+Config!$B$17*#REF!)) -> #REF! | N55: =IF(OR(#REF!=FALSE,ISNA(#REF!),ISNA(#REF!),ISNA(#REF!)),NA(),MIN(1,Config!$B$18*(1-MIN(1,#REF!/10))+Config!$B$19*(1-#REF!)+Config!$B$20*(1-#REF!))) -> #REF! | O55: =IF(#REF!=FALSE,"OUT_OF_SCOPE",IF(ISNA(#REF!),"UNKNOWN",IF(#REF!<Config!$B$10,"FAIL_CLOSED_LOW_COVERAGE","OK"))) -> #REF! | P55: =IFERROR(_xludf.XLOOKUP(#REF!,tblEntities[entity_id],tblEntities[segment_id]),"") | Q55: =IFERROR(_xludf.XLOOKUP(#REF!,tblEntities[entity_id],tblEntities[vertical]),"") | R55: =AND(#REF!=Dashboard!$E$2,IF(Dashboard!$E$3="All",TRUE,#REF!=Dashboard!$E$3)) -> #REF!
A56: =IF(Input!$A$55="","",Input!$A$55) | B56: =IFERROR(_xludf.XLOOKUP(#REF!,tblEntities[entity_id],tblEntities[canonical_name]),"") | C56: =IF(#REF!="","",COUNTIFS(tblClaimsCurrent[entity_id],#REF!,tblClaimsCurrent[status],"PROMOTED")) -> #REF! | D56: =IF(#REF!="","",COUNTIFS(tblClaimsCurrent[entity_id],#REF!,tblClaimsCurrent[status],"UNKNOWN")) -> #REF! | E56: =_xludf.LET(t,#REF!+#REF!,IF(t=0,NA(),#REF!/t)) -> #NAME? | F56: =_xludf.LET(cnt,COUNTIFS(tblClaimsCurrent[entity_id],#REF!,tblClaimsCurrent[status],"PROMOTED"),IF(cnt=0,NA(),AVERAGEIFS(tblClaimsCurrent[confidence],tblClaimsCurrent[entity_id],#REF!,tblClaimsCurrent[status],"PROMOTED"))) -> #NAME? | G56: =_xludf.LET(cnt,COUNTIFS(tblClaimsCurrent[entity_id],#REF!,tblClaimsCurrent[field_key],"pricing_acv_mid_market",tblClaimsCurrent[status],"PROMOTED"),IF(cnt=0,NA(),SUMIFS(tblClaimsCurrent[value_num],tblClaimsCurrent[entity_id],#REF!,tblClaimsCurrent[field_key],"pricing_acv_mid_market",tblClaimsCurrent[status],"PROMOTED"))) -> #NAME? | H56: =IF(OR(NOT(ISNUMBER(#REF!)),$B$5=""),"UNKNOWN",IF(#REF!<=($B$5*0.85),"Low",IF(#REF!>=($B$5*1.15),"High","Mid"))) -> UNKNOWN | I56: =_xludf.LET(v,IFERROR(LOOKUP(2,1/((tblClaimsCurrent[entity_id]=#REF!)*(tblClaimsCurrent[field_key]="features")*(tblClaimsCurrent[status]="PROMOTED")),tblClaimsCurrent[value_text]),"UNKNOWN"),IF(v="","UNKNOWN",v)) -> #NAME? | J56: =IF(OR(#REF!="UNKNOWN",#REF!=""),NA(),1+LEN(#REF!)-LEN(SUBSTITUTE(#REF!,";",""))) -> #REF! | K56: =IF(#REF!="",NA(),IF(#REF!="SEG_MM",1,0)) -> #REF! | L56: =IF(#REF!="","",IF(COUNTIFS(tblClaimsCurrent[entity_id],#REF!,tblClaimsCurrent[field_key],"funding_round",tblClaimsCurrent[status],"PROMOTED")>0,1,0)) -> #REF! | M56: =IF(OR(#REF!=FALSE,ISNA(#REF!),ISNA(#REF!),ISNA(#REF!),#REF!="UNKNOWN"),NA(),MIN(1,Config!$B$14*MIN(1,#REF!/10)+Config!$B$15*IF(#REF!="Low",1,IF(#REF!="Mid",0.5,0))+Config!$B$16*#REF!+Config!$B$17*#REF!)) -> #REF! | N56: =IF(OR(#REF!=FALSE,ISNA(#REF!),ISNA(#REF!),ISNA(#REF!)),NA(),MIN(1,Config!$B$18*(1-MIN(1,#REF!/10))+Config!$B$19*(1-#REF!)+Config!$B$20*(1-#REF!))) -> #REF! | O56: =IF(#REF!=FALSE,"OUT_OF_SCOPE",IF(ISNA(#REF!),"UNKNOWN",IF(#REF!<Config!$B$10,"FAIL_CLOSED_LOW_COVERAGE","OK"))) -> #REF! | P56: =IFERROR(_xludf.XLOOKUP(#REF!,tblEntities[entity_id],tblEntities[segment_id]),"") | Q56: =IFERROR(_xludf.XLOOKUP(#REF!,tblEntities[entity_id],tblEntities[vertical]),"") | R56: =AND(#REF!=Dashboard!$E$2,IF(Dashboard!$E$3="All",TRUE,#REF!=Dashboard!$E$3)) -> #REF!
A57: =IF(Input!$A$56="","",Input!$A$56) | B57: =IFERROR(_xludf.XLOOKUP(#REF!,tblEntities[entity_id],tblEntities[canonical_name]),"") | C57: =IF(#REF!="","",COUNTIFS(tblClaimsCurrent[entity_id],#REF!,tblClaimsCurrent[status],"PROMOTED")) -> #REF! | D57: =IF(#REF!="","",COUNTIFS(tblClaimsCurrent[entity_id],#REF!,tblClaimsCurrent[status],"UNKNOWN")) -> #REF! | E57: =_xludf.LET(t,#REF!+#REF!,IF(t=0,NA(),#REF!/t)) -> #NAME? | F57: =_xludf.LET(cnt,COUNTIFS(tblClaimsCurrent[entity_id],#REF!,tblClaimsCurrent[status],"PROMOTED"),IF(cnt=0,NA(),AVERAGEIFS(tblClaimsCurrent[confidence],tblClaimsCurrent[entity_id],#REF!,tblClaimsCurrent[status],"PROMOTED"))) -> #NAME? | G57: =_xludf.LET(cnt,COUNTIFS(tblClaimsCurrent[entity_id],#REF!,tblClaimsCurrent[field_key],"pricing_acv_mid_market",tblClaimsCurrent[status],"PROMOTED"),IF(cnt=0,NA(),SUMIFS(tblClaimsCurrent[value_num],tblClaimsCurrent[entity_id],#REF!,tblClaimsCurrent[field_key],"pricing_acv_mid_market",tblClaimsCurrent[status],"PROMOTED"))) -> #NAME? | H57: =IF(OR(NOT(ISNUMBER(#REF!)),$B$5=""),"UNKNOWN",IF(#REF!<=($B$5*0.85),"Low",IF(#REF!>=($B$5*1.15),"High","Mid"))) -> UNKNOWN | I57: =_xludf.LET(v,IFERROR(LOOKUP(2,1/((tblClaimsCurrent[entity_id]=#REF!)*(tblClaimsCurrent[field_key]="features")*(tblClaimsCurrent[status]="PROMOTED")),tblClaimsCurrent[value_text]),"UNKNOWN"),IF(v="","UNKNOWN",v)) -> #NAME? | J57: =IF(OR(#REF!="UNKNOWN",#REF!=""),NA(),1+LEN(#REF!)-LEN(SUBSTITUTE(#REF!,";",""))) -> #REF! | K57: =IF(#REF!="",NA(),IF(#REF!="SEG_MM",1,0)) -> #REF! | L57: =IF(#REF!="","",IF(COUNTIFS(tblClaimsCurrent[entity_id],#REF!,tblClaimsCurrent[field_key],"funding_round",tblClaimsCurrent[status],"PROMOTED")>0,1,0)) -> #REF! | M57: =IF(OR(#REF!=FALSE,ISNA(#REF!),ISNA(#REF!),ISNA(#REF!),#REF!="UNKNOWN"),NA(),MIN(1,Config!$B$14*MIN(1,#REF!/10)+Config!$B$15*IF(#REF!="Low",1,IF(#REF!="Mid",0.5,0))+Config!$B$16*#REF!+Config!$B$17*#REF!)) -> #REF! | N57: =IF(OR(#REF!=FALSE,ISNA(#REF!),ISNA(#REF!),ISNA(#REF!)),NA(),MIN(1,Config!$B$18*(1-MIN(1,#REF!/10))+Config!$B$19*(1-#REF!)+Config!$B$20*(1-#REF!))) -> #REF! | O57: =IF(#REF!=FALSE,"OUT_OF_SCOPE",IF(ISNA(#REF!),"UNKNOWN",IF(#REF!<Config!$B$10,"FAIL_CLOSED_LOW_COVERAGE","OK"))) -> #REF! | P57: =IFERROR(_xludf.XLOOKUP(#REF!,tblEntities[entity_id],tblEntities[segment_id]),"") | Q57: =IFERROR(_xludf.XLOOKUP(#REF!,tblEntities[entity_id],tblEntities[vertical]),"") | R57: =AND(#REF!=Dashboard!$E$2,IF(Dashboard!$E$3="All",TRUE,#REF!=Dashboard!$E$3)) -> #REF!

Sheet Tech_Dashboard
A3: Certify Intel — Technical Dashboard
A6: Last Run | D6: Runs (7d) | G6: Allowlist Violations | J6: Open Reviews
A7: =IFERROR(MAX(#REF!),"") | D7: =COUNTIF(#REF!,">="&TODAY()-7) -> #REF! | G7: =COUNTIF(tblEvidence[allowlist_ok],"<>"&TRUE) -> 5 | J7: =COUNTIF(tblReviewQueue[status],"OPEN") -> 3
A9: Timestamp | D9: Count | G9: Count | J9: Count
A14: Evidence Tier Mix
A15: Tier | B15: Count
A16: T1 | B16: =COUNTIF(tblEvidence[tier],"T1") -> 0
A17: T2 | B17: =COUNTIF(tblEvidence[tier],"T2") -> 0
A18: T3 | B18: =COUNTIF(tblEvidence[tier],"T3") -> 0
A22: Claims Status Counts
A23: Status | B23: Count
A24: PROMOTED | B24: =COUNTIF(tblClaimsCurrent[status],"PROMOTED") -> 0
A25: CANDIDATE | B25: =COUNTIF(tblClaimsCurrent[status],"CANDIDATE") -> 0
A26: FAIL_CLOSED | B26: =COUNTIF(tblClaimsCurrent[status],"FAIL_CLOSED") -> 0

Sheet Competitor_Detail
A1: Competitor Detail
A3: Select Competitor | B3: AcmeRival | C3: =IFERROR(_xludf.XLOOKUP($B$3,Metrics!$B$8:$B$57,Metrics!$A$8:$A$57,""),"") | D3: Entity ID | E3: =IF(B3="","",INDEX(Metrics!$A$8:$A$57,MATCH(B3,Metrics!$B$8:$B$57,0))) -> #N/A
A5: Summary
A6: Metric | B6: Value | D6: Key Claims
A7: Threat Score | B7: =IFERROR(INDEX(Metrics!$M$8:$M$57,MATCH(B3,Metrics!$B$8:$B$57,0)),"") | D7: field_key | E7: value | F7: confidence | G7: evidence_url
A8: Opportunity Score | B8: =IFERROR(INDEX(Metrics!$N$8:$N$57,MATCH(B3,Metrics!$B$8:$B$57,0)),"") | D8: pricing_acv_mid_market | E8: =IFERROR(LOOKUP(2,1/((Claims_Current!$A$5:$A$46=$E$3)*(Claims_Current!$D$5:$D$46=D8)),Claims_Current!$E$5:$E$46),"") | F8: =IFERROR(LOOKUP(2,1/((Claims_Current!$A$5:$A$46=$E$3)*(Claims_Current!$D$5:$D$46=D8)),Claims_Current!$H$5:$H$46),"") | G8: =IFERROR(LOOKUP(2,1/((Claims_Current!$A$5:$A$46=$E$3)*(Claims_Current!$D$5:$D$46=D8)),Claims_Current!$J$5:$J$46),"")
A9: Coverage | B9: =IFERROR(INDEX(Metrics!$E$8:$E$57,MATCH(B3,Metrics!$B$8:$B$57,0)),"") | D9: arr_estimate | E9: =IFERROR(LOOKUP(2,1/((Claims_Current!$A$5:$A$46=$E$3)*(Claims_Current!$D$5:$D$46=D9)),Claims_Current!$E$5:$E$46),"") | F9: =IFERROR(LOOKUP(2,1/((Claims_Current!$A$5:$A$46=$E$3)*(Claims_Current!$D$5:$D$46=D9)),Claims_Current!$H$5:$H$46),"") | G9: =IFERROR(LOOKUP(2,1/((Claims_Current!$A$5:$A$46=$E$3)*(Claims_Current!$D$5:$D$46=D9)),Claims_Current!$J$5:$J$46),"")
A10: ACV (USD/year) | B10: =IFERROR(INDEX(Metrics!$G$8:$G$57,MATCH(B3,Metrics!$B$8:$B$57,0)),"") | D10: contract_terms | E10: =IFERROR(LOOKUP(2,1/((Claims_Current!$A$5:$A$46=$E$3)*(Claims_Current!$D$5:$D$46=D10)),Claims_Current!$E$5:$E$46),"") | F10: =IFERROR(LOOKUP(2,1/((Claims_Current!$A$5:$A$46=$E$3)*(Claims_Current!$D$5:$D$46=D10)),Claims_Current!$H$5:$H$46),"") | G10: =IFERROR(LOOKUP(2,1/((Claims_Current!$A$5:$A$46=$E$3)*(Claims_Current!$D$5:$D$46=D10)),Claims_Current!$J$5:$J$46),"")
A11: Features | B11: =IFERROR(INDEX(Metrics!$I$8:$I$57,MATCH(B3,Metrics!$B$8:$B$57,0)),"") | D11: features | E11: =IFERROR(LOOKUP(2,1/((Claims_Current!$A$5:$A$46=$E$3)*(Claims_Current!$D$5:$D$46=D11)),Claims_Current!$E$5:$E$46),"") | F11: =IFERROR(LOOKUP(2,1/((Claims_Current!$A$5:$A$46=$E$3)*(Claims_Current!$D$5:$D$46=D11)),Claims_Current!$H$5:$H$46),"") | G11: =IFERROR(LOOKUP(2,1/((Claims_Current!$A$5:$A$46=$E$3)*(Claims_Current!$D$5:$D$46=D11)),Claims_Current!$J$5:$J$46),"")
A12: Flag | B12: =IFERROR(INDEX(Metrics!$O$8:$O$57,MATCH(B3,Metrics!$B$8:$B$57,0)),"") | D12: funding_round | E12: =IFERROR(LOOKUP(2,1/((Claims_Current!$A$5:$A$46=$E$3)*(Claims_Current!$D$5:$D$46=D12)),Claims_Current!$E$5:$E$46),"") | F12: =IFERROR(LOOKUP(2,1/((Claims_Current!$A$5:$A$46=$E$3)*(Claims_Current!$D$5:$D$46=D12)),Claims_Current!$H$5:$H$46),"") | G12: =IFERROR(LOOKUP(2,1/((Claims_Current!$A$5:$A$46=$E$3)*(Claims_Current!$D$5:$D$46=D12)),Claims_Current!$J$5:$J$46),"")
D13: geo_coverage | E13: =IFERROR(LOOKUP(2,1/((Claims_Current!$A$5:$A$46=$E$3)*(Claims_Current!$D$5:$D$46=D13)),Claims_Current!$E$5:$E$46),"") | F13: =IFERROR(LOOKUP(2,1/((Claims_Current!$A$5:$A$46=$E$3)*(Claims_Current!$D$5:$D$46=D13)),Claims_Current!$H$5:$H$46),"") | G13: =IFERROR(LOOKUP(2,1/((Claims_Current!$A$5:$A$46=$E$3)*(Claims_Current!$D$5:$D$46=D13)),Claims_Current!$J$5:$J$46),"")
A14: Evidence (Selected Competitor)
A15: evidence_id | B15: source_key | C15: tier | D15: url | E15: fetched_at | F15: snippet | G15: content_hash | H15: text_hash | I15: domain_calc | J15: allowlist_ok
B16: =Input!B18 -> E001 | C16: =Input!C18 -> DEMO | D16: =Input!D18 -> TIER1 | E16: =Input!E18 -> file://docs/demo_sources/E001_pricing.html | F16: =Input!F18 -> 2026-01-12 | G16: =Input!G18 -> DEMO evidence placeholder. Replace with allowlisted URL + snippet. | H16: =Input!H18 -> 0217e879a9ae84b4 | I16: =Input!I18 -> 46aae5c96408e7ec
A17: =Input!A19 -> EV002 | B17: =Input!B19 -> E002 | C17: =Input!C19 -> DEMO | D17: =Input!D19 -> TIER1 | E17: =Input!E19 -> file://docs/demo_sources/E002_pricing.html | F17: =Input!F19 -> 2026-01-12 | G17: =Input!G19 -> DEMO evidence placeholder. Replace with allowlisted URL + snippet. | H17: =Input!H19 -> 3deb1e85e3854868 | I17: =Input!I19 -> 46aae5c96408e7ec
A18: =Input!A20 -> EV003 | B18: =Input!B20 -> E003 | C18: =Input!C20 -> DEMO | D18: =Input!D20 -> TIER1 | E18: =Input!E20 -> file://docs/demo_sources/E003_pricing.html | F18: =Input!F20 -> 2026-01-12 | G18: =Input!G20 -> DEMO evidence placeholder. Replace with allowlisted URL + snippet. | H18: =Input!H20 -> d42285f8d1a9736f | I18: =Input!I20 -> 46aae5c96408e7ec
A19: =Input!A21 -> EV004 | B19: =Input!B21 -> E004 | C19: =Input!C21 -> DEMO | D19: =Input!D21 -> TIER1 | E19: =Input!E21 -> file://docs/demo_sources/E004_pricing.html | F19: =Input!F21 -> 2026-01-12 | G19: =Input!G21 -> DEMO evidence placeholder. Replace with allowlisted URL + snippet. | H19: =Input!H21 -> b1e3c58050111249 | I19: =Input!I21 -> 46aae5c96408e7ec
A20: =Input!A22 -> EV005 | B20: =Input!B22 -> E001 | C20: =Input!C22 -> DEMO | D20: =Input!D22 -> SIGNAL | E20: =Input!E22 -> file://docs/demo_sources/E001_pr.html | F20: =Input!F22 -> 2026-01-12 | G20: =Input!G22 -> DEMO PR mention (signal only). | H20: =Input!H22 -> 0510eddd78110203 | I20: =Input!I22 -> 41bfa2f2111d7821

Sheet Review_Queue
A1: Review Queue (All UNKNOWN / Low-Confidence / Non-Allowlisted Evidence)
A2: Fail-closed: no claim promotion until reviewed and evidence is tier-compliant.
A4: task_id | B4: created_at | C4: task_type | D4: priority | E4: entity_id | F4: canonical_name | G4: field_key | H4: value_text | I4: value_num | J4: confidence | K4: evidence_id | L4: evidence_url | M4: reason | N4: status | O4: resolution_notes
A5: T0001 | B5: 2026-01-12 | C5: UNKNOWN_OR_LOW_CONF | D5: HIGH | E5: E002 | F5: EnrollPro | G5: pricing_acv_mid_market | H5: UNKNOWN | J5: 0.2 | K5: EV002 | L5: file://docs/demo_sources/E002_pricing.html | M5: No explicit ACV on page | N5: OPEN
A6: T0002 | B6: 2026-01-12 | C6: UNKNOWN_OR_LOW_CONF | D6: HIGH | E6: E003 | F6: ComplianceFlow | G6: funding_round | H6: UNKNOWN | J6: 0.1 | K6: EV003 | L6: file://docs/demo_sources/E003_pricing.html | M6: Signal only; needs tier-1 corroboration | N6: OPEN
A7: T0003 | B7: 2026-01-12 | C7: UNKNOWN_OR_LOW_CONF | D7: HIGH | E7: E005 | F7: PracticeOps | G7: pricing_acv_mid_market | I7: 9000 | J7: 0.8 | K7: EV005 | L7: file://docs/demo_sources/E001_pr.html | M7: Pricing from signal source; needs tier-1 | N7: OPEN
A10: task_id | B10: created_at | C10: task_type | D10: priority | E10: entity_id | F10: canonical_name | G10: field_key | H10: value_text | I10: value_num | J10: confidence | K10: evidence_id | L10: evidence_url | M10: reason | N10: status | O10: resolution_notes

Sheet Logs
A1: Logs
A3: Refresh Log (append-only; use for auditability)
A5: run_id | B5: started_at | C5: ended_at | D5: mode | E5: entities_imported | F5: evidence_imported | G5: claims_promoted | H5: review_tasks_opened | I5: notes
A6: RUN_DEMO | B6: 2026-01-12 00:00 | C6: 2026-01-12 00:01 | D6: DEMO | E6: 6 | F6: 5 | G6: 6 | H6: 3 | I6: Template generated

Sheet Scraper
A1: Scraper (Optional; Autonomous Competitor Discovery)
A3: This workbook is designed to run Excel-only. For true autonomous discovery/refresh, use Power Query (From Web) or VBA/Office Script.
A5: Minimum viable workflow
A6: 1) Update Sources_Allowlist (domains + paths) and Segment_Rules.
A7: 2) Populate/refresh Input tables (Entities, Evidence, Claim Candidates) via Power Query or manual import.
A8: 3) Resolve Review_Queue items; promote claims only when evidence is tier-compliant.
A9: 4) Dashboards refresh automatically via formulas/charts.
A11: Power Query M-code (template) — Web Search → Competitor Candidates
A12: // TEMPLATE ONLY — paste into Power Query (Data > Get Data > From Other Sources > Blank Query > Advanced Editor) // Replace <API_KEY> and <QUERY>. Ensure ToS compliance for all endpoints. let Query = "<QUERY>", ApiKey = Excel.CurrentWorkbook(){[Name="BingSearchKey"]}[Content]{0}[Column1], Url = "https://api.bing.microsoft.com/v7.0/search?q=" & Uri.EscapeDataString(Query) & "&count=25", Source = Json.Document(Web.Contents(Url, [Headers=[#"Ocp-Apim-Subscription-Key"=ApiKey]])), WebPages = Source[webPages][value], Table = Table.FromList(WebPages, Splitter.SplitByNothing(), null, null, ExtraValues.Error), Expand = Table.ExpandRecordColumn(Table, "Column1", {"name","url","snippet"}, {"name","url","snippet"}) in Expand
A24: Office Script (template) — Promote resolved Review Queue items
A25: /** * TEMPLATE ONLY — paste into Excel Online > Automate > New Script. * Goal: when Review_Queue.status == RESOLVED, update Input.tblClaimCandidates status to PROMOTED * and write a log row to Logs. */ function main(workbook: ExcelScript.Workbook) { // TODO: implement based on your table names (tblReviewQueue, tblClaimCandidates, tblLogs) }

Sheet Dashboard
A4: Certify Intel — Executive Dashboard
A6: Filters | AA6: Vertical_List
A7: Segment | B7: SEG_MM
A8: Vertical | B8: All
A9: Region | B9: All | AA9: Region_List
A11: Competitors | D11: Open Reviews | G11: Evidence Items | J11: Fresh Evidence %
D12: =COUNTIF(tblReviewQueue[status],"OPEN") -> 3 | G12: =ROWS(tblEvidence[evidence_id]) -> 5 | J12: =IFERROR(1-COUNTIF(tblEvidence[fetched_at],"<"&TODAY()-30)/ROWS(tblEvidence[fetched_at]),0) -> 1 | AA12: Filtered_Names
A14: In-scope competitors | D14: Needs human review | G14: Captured evidence | J14: Fetched <30d
AA15: Filtered_Coverage
A17: Avg Coverage % | D17: Avg Threat | G17: High Threat | J17: Fail-Closed
AA18: Filtered_Threat
A20: Known / total fields | D20: Mean threat score | G20: Threat ≥ 0.75 | J20: Blocked entities
AA21: Filtered_Opp
A22: Rankings
A24: Top Threats | AA24: Filtered_Flags
A25: Competitor | B25: Threat
AA27: TopThreat_Table
A38: Threat vs Opportunity
A39: Competitor | B39: Threat | C39: Opportunity
B40: =IFERROR(_xludf.XLOOKUP(A40, tblMetrics[canonical_name], tblMetrics[threat_score], ""),"") | C40: =IFERROR(_xludf.XLOOKUP(A40, tblMetrics[canonical_name], tblMetrics[opportunity_score], ""),"")
B41: =IFERROR(_xludf.XLOOKUP(A41, tblMetrics[canonical_name], tblMetrics[threat_score], ""),"") | C41: =IFERROR(_xludf.XLOOKUP(A41, tblMetrics[canonical_name], tblMetrics[opportunity_score], ""),"")
B42: =IFERROR(_xludf.XLOOKUP(A42, tblMetrics[canonical_name], tblMetrics[threat_score], ""),"") | C42: =IFERROR(_xludf.XLOOKUP(A42, tblMetrics[canonical_name], tblMetrics[opportunity_score], ""),"")
B43: =IFERROR(_xludf.XLOOKUP(A43, tblMetrics[canonical_name], tblMetrics[threat_score], ""),"") | C43: =IFERROR(_xludf.XLOOKUP(A43, tblMetrics[canonical_name], tblMetrics[opportunity_score], ""),"")
B44: =IFERROR(_xludf.XLOOKUP(A44, tblMetrics[canonical_name], tblMetrics[threat_score], ""),"") | C44: =IFERROR(_xludf.XLOOKUP(A44, tblMetrics[canonical_name], tblMetrics[opportunity_score], ""),"")
B45: =IFERROR(_xludf.XLOOKUP(A45, tblMetrics[canonical_name], tblMetrics[threat_score], ""),"") | C45: =IFERROR(_xludf.XLOOKUP(A45, tblMetrics[canonical_name], tblMetrics[opportunity_score], ""),"")
B46: =IFERROR(_xludf.XLOOKUP(A46, tblMetrics[canonical_name], tblMetrics[threat_score], ""),"") | C46: =IFERROR(_xludf.XLOOKUP(A46, tblMetrics[canonical_name], tblMetrics[opportunity_score], ""),"")
B47: =IFERROR(_xludf.XLOOKUP(A47, tblMetrics[canonical_name], tblMetrics[threat_score], ""),"") | C47: =IFERROR(_xludf.XLOOKUP(A47, tblMetrics[canonical_name], tblMetrics[opportunity_score], ""),"")
B48: =IFERROR(_xludf.XLOOKUP(A48, tblMetrics[canonical_name], tblMetrics[threat_score], ""),"") | C48: =IFERROR(_xludf.XLOOKUP(A48, tblMetrics[canonical_name], tblMetrics[opportunity_score], ""),"")
B49: =IFERROR(_xludf.XLOOKUP(A49, tblMetrics[canonical_name], tblMetrics[threat_score], ""),"") | C49: =IFERROR(_xludf.XLOOKUP(A49, tblMetrics[canonical_name], tblMetrics[opportunity_score], ""),"")
B50: =IFERROR(_xludf.XLOOKUP(A50, tblMetrics[canonical_name], tblMetrics[threat_score], ""),"") | C50: =IFERROR(_xludf.XLOOKUP(A50, tblMetrics[canonical_name], tblMetrics[opportunity_score], ""),"")
B51: =IFERROR(_xludf.XLOOKUP(A51, tblMetrics[canonical_name], tblMetrics[threat_score], ""),"") | C51: =IFERROR(_xludf.XLOOKUP(A51, tblMetrics[canonical_name], tblMetrics[opportunity_score], ""),"")
... B69: =IFERROR(_xludf.XLOOKUP(A69, tblMetrics[canonical_name], tblMetrics[threat_score], ""),"") | C69: =IFERROR(_xludf.XLOOKUP(A69, tblMetrics[canonical_name], tblMetrics[opportunity_score], ""),"")
A72: Review Queue (Open Items)
A73: Competitor | B73: Field | C73: Reason
AA74: OpenReviews_Table

Sheet Scripts
A1: Scripts (VBA + Power Query Templates)
A3: VBA module (import into an .xlsm copy) | C3: Power Query templates (optional)
A5: '=============================== | C5: // Power Query templates live here.
A6: ' Certify Intel v1 — VBA MODULES | C6: // Use a licensed web search provider; do not scrape prohibited sources.
A7: '=============================== | C7: // Load output into Input.tblEntities and Input.tblEvidence.
A8: ' Steps:
A9: ' 1) Save this workbook as .xlsm
A10: ' 2) ALT+F11 → Insert → Module → paste this module
A11: ' 3) Add a button on Dashboard linked to RunPipeline
A12: '
A13: Option Explicit
A15: Public Sub RunPipeline()
A16: On Error GoTo EH
A18: Application.ScreenUpdating = False
A19: Application.EnableEvents = False
A20: Application.Calculation = xlCalculationManual
A22: LogRun "START", "RunPipeline started"
... A182: End Sub

Sheet Claim_Versions
A1: Claim Versions (append-only history)
A3: version_id | B3: claim_id | C3: entity_id | D3: field_key | E3: value_type | F3: value_num | G3: value_text | H3: value_bool | I3: confidence | J3: source_tier | K3: evidence_id | L3: evidence_url | M3: span_start | N3: span_end | O3: snippet | P3: segment_id | Q3: created_at_utc | R3: created_by | S3: reason | T3: status
A4: version_id | B4: claim_id | C4: entity_id | D4: field_key | E4: value_type | F4: value_num | G4: value_text | H4: value_bool | I4: confidence | J4: tier | K4: evidence_id | L4: evidence_url | M4: span_start | N4: span_end | O4: snippet | P4: segment_id | Q4: created_at_utc | R4: created_by | S4: reason | T4: status

Sheet Evidence_Snapshots
A1: Evidence Snapshots (for diff/change detection)
A3: snapshot_id | B3: url | C3: domain | D3: source_key | E3: entity_id | F3: fetched_at_utc | G3: http_status | H3: content_hash | I3: text_hash | J3: text_len | K3: notes
A4: snapshot_id | B4: url | C4: domain | D4: source_key | E4: entity_id | F4: fetched_at_utc | G4: http_status | H4: content_hash | I4: text_hash | J4: text_len | K4: notes

Sheet Events
A1: Events (auto-generated)
A3: event_id | B3: event_type | C3: severity | D3: entity_id | E3: url | F3: detected_at_utc | G3: prev_text_hash | H3: new_text_hash | I3: summary | J3: evidence_id | K3: review_task_id | L3: status
A4: event_id | B4: event_type | C4: severity | D4: entity_id | E4: url | F4: detected_at_utc | G4: prev_text_hash | H4: new_text_hash | I4: summary | J4: evidence_id | K4: review_task_id | L4: status

Sheet Alerts
A1: Alerts (rules)
A3: alert_id | B3: rule_key | C3: enabled | D3: severity | E3: scope | F3: condition | G3: message_template | H3: last_fired_at_utc | I3: notes
A4: alert_id | B4: rule_key | C4: enabled | D4: severity | E4: scope | F4: condition | G4: message_template | H4: last_fired_at_utc | I4: notes

Sheet Self_Tests
A1: Self Tests (PASS/FAIL)
A3: Test | B3: Result | C3: Notes
A4: No PROMOTED candidate without evidence_id | B4: =IF(COUNTIFS(tblClaimCandidates[status_final],"PROMOTED",tblClaimCandidates[evidence_id],"")=0,"PASS","FAIL") -> PASS | C4: Fail-closed: promoted claims must have evidence_id
A5: No PROMOTED candidate with UNKNOWN/blank value | B5: =IF(COUNTIFS(tblClaimCandidates[status_final],"PROMOTED",tblClaimCandidates[value_text],"UNKNOWN") + COUNTIFS(tblClaimCandidates[status_final],"PROMOTED",tblClaimCandidates[value_text],"")>0,"FAIL","PASS") -> PASS | C5: Fail-closed: promoted claims cannot be UNKNOWN/blank
A6: All Evidence rows allowlist_ok must be TRUE | B6: =IF(COUNTIF(tblEvidence[allowlist_ok],"FALSE")=0,"PASS","FAIL") -> PASS | C6: Allowlist enforcement sanity check
A7: Claims_Current status computed | B7: =IF(COUNTIF(tblClaimsCurrent[status],"")=0,"PASS","FAIL") -> PASS | C7: No blank statuses

Sheet Macro_Install
A1: Macro Install & One-Click Setup (Excel)
A3: 1) Save this workbook as .XLSM (File → Save As → Excel Macro-Enabled Workbook). 2) Press ALT+F11 to open the VBA editor. 3) File → Import File… and import all .BAS modules from the provided zip. 4) In VBA editor: Run macro SetupUI once (creates Dashboard buttons and binds them). 5) In Config tab: set SEARCH_PROVIDER, SEARCH_API_KEY, and allowed domains in Sources_Allowlist. 6) Use the Dashboard button: Run Pipeline (Refresh → Validate → Diff → Extract → Promote → Alerts). Fail-closed rules: - If API key missing or a URL is not allowlisted, ingestion is skipped and a Review Task is created. - If extraction cannot find an explicit value, value is set to UNKNOWN and a Review Task is created.

Sheet Run_Log
A1: Pipeline Run Log
A3: run_id | B3: started_at_utc | C3: ended_at_utc | D3: mode | E3: status | F3: discovered_candidates | G3: evidence_fetched | H3: candidates_written | I3: promoted_versions | J3: events_created | K3: alerts_fired | L3: unknowns_created | M3: notes
A4: run_id | B4: started_at_utc | C4: ended_at_utc | D4: mode | E4: status | F4: discovered_candidates | G4: evidence_fetched | H4: candidates_written | I4: promoted_versions | J4: events_created | K4: alerts_fired | L4: unknowns_created | M4: notes

Sheet Feature_Matrix
A1: Competitor Feature Matrix (heatmap-ready)
A3: Competitor | B3: =IFERROR(INDEX(tblFeatureTaxonomy[feature_name],1),"") -> Eligibility Verification | C3: =IFERROR(INDEX(tblFeatureTaxonomy[feature_name],2),"") -> Prior Authorization | D3: =IFERROR(INDEX(tblFeatureTaxonomy[feature_name],3),"") -> Patient Payments | E3: =IFERROR(INDEX(tblFeatureTaxonomy[feature_name],4),"") -> Scheduling | F3: =IFERROR(INDEX(tblFeatureTaxonomy[feature_name],5),"") -> 0 | G3: =IFERROR(INDEX(tblFeatureTaxonomy[feature_name],6),"") -> 0 | H3: =IFERROR(INDEX(tblFeatureTaxonomy[feature_name],7),"") -> 0 | I3: =IFERROR(INDEX(tblFeatureTaxonomy[feature_name],8),"") -> 0 | J3: =IFERROR(INDEX(tblFeatureTaxonomy[feature_name],9),"") -> 0 | K3: =IFERROR(INDEX(tblFeatureTaxonomy[feature_name],10),"") -> 0 | L3: =IFERROR(INDEX(tblFeatureTaxonomy[feature_name],11),"") -> 0 | M3: =IFERROR(INDEX(tblFeatureTaxonomy[feature_name],12),"") -> 0 | N3: =IFERROR(INDEX(tblFeatureTaxonomy[feature_name],13),"") -> 0 | O3: =IFERROR(INDEX(tblFeatureTaxonomy[feature_name],14),"") -> 0 | P3: =IFERROR(INDEX(tblFeatureTaxonomy[feature_name],15),"") -> 0 | Q3: =IFERROR(INDEX(tblFeatureTaxonomy[feature_name],16),"") -> 0 | R3: =IFERROR(INDEX(tblFeatureTaxonomy[feature_name],17),"") -> 0 | S3: =IFERROR(INDEX(tblFeatureTaxonomy[feature_name],18),"") -> 0 | T3: =IFERROR(INDEX(tblFeatureTaxonomy[feature_name],19),"") -> 0 | U3: =IFERROR(INDEX(tblFeatureTaxonomy[feature_name],20),"") -> 0
B4: =IF($A4="","",IFERROR(--ISNUMBER(SEARCH(B$3, _xludf.XLOOKUP($A4, Metrics!$B$8:$B$57, Metrics!$H$8:$H$57, ""))),0)) | C4: =IF($A4="","",IFERROR(--ISNUMBER(SEARCH(C$3, _xludf.XLOOKUP($A4, Metrics!$B$8:$B$57, Metrics!$H$8:$H$57, ""))),0)) | D4: =IF($A4="","",IFERROR(--ISNUMBER(SEARCH(D$3, _xludf.XLOOKUP($A4, Metrics!$B$8:$B$57, Metrics!$H$8:$H$57, ""))),0)) | E4: =IF($A4="","",IFERROR(--ISNUMBER(SEARCH(E$3, _xludf.XLOOKUP($A4, Metrics!$B$8:$B$57, Metrics!$H$8:$H$57, ""))),0)) | F4: =IF($A4="","",IFERROR(--ISNUMBER(SEARCH(F$3, _xludf.XLOOKUP($A4, Metrics!$B$8:$B$57, Metrics!$H$8:$H$57, ""))),0)) | G4: =IF($A4="","",IFERROR(--ISNUMBER(SEARCH(G$3, _xludf.XLOOKUP($A4, Metrics!$B$8:$B$57, Metrics!$H$8:$H$57, ""))),0)) | H4: =IF($A4="","",IFERROR(--ISNUMBER(SEARCH(H$3, _xludf.XLOOKUP($A4, Metrics!$B$8:$B$57, Metrics!$H$8:$H$57, ""))),0)) | I4: =IF($A4="","",IFERROR(--ISNUMBER(SEARCH(I$3, _xludf.XLOOKUP($A4, Metrics!$B$8:$B$57, Metrics!$H$8:$H$57, ""))),0)) | ... U4: =IF($A4="","",IFERROR(--ISNUMBER(SEARCH(U$3, _xludf.XLOOKUP($A4, Metrics!$B$8:$B$57, Metrics!$H$8:$H$57, ""))),0))
B5: =IF($A5="","",IFERROR(--ISNUMBER(SEARCH(B$3, _xludf.XLOOKUP($A5, Metrics!$B$8:$B$57, Metrics!$H$8:$H$57, ""))),0)) | C5: =IF($A5="","",IFERROR(--ISNUMBER(SEARCH(C$3, _xludf.XLOOKUP($A5, Metrics!$B$8:$B$57, Metrics!$H$8:$H$57, ""))),0)) | D5: =IF($A5="","",IFERROR(--ISNUMBER(SEARCH(D$3, _xludf.XLOOKUP($A5, Metrics!$B$8:$B$57, Metrics!$H$8:$H$57, ""))),0)) | E5: =IF($A5="","",IFERROR(--ISNUMBER(SEARCH(E$3, _xludf.XLOOKUP($A5, Metrics!$B$8:$B$57, Metrics!$H$8:$H$57, ""))),0)) | F5: =IF($A5="","",IFERROR(--ISNUMBER(SEARCH(F$3, _xludf.XLOOKUP($A5, Metrics!$B$8:$B$57, Metrics!$H$8:$H$57, ""))),0)) | G5: =IF($A5="","",IFERROR(--ISNUMBER(SEARCH(G$3, _xludf.XLOOKUP($A5, Metrics!$B$8:$B$57, Metrics!$H$8:$H$57, ""))),0)) | H5: =IF($A5="","",IFERROR(--ISNUMBER(SEARCH(H$3, _xludf.XLOOKUP($A5, Metrics!$B$8:$B$57, Metrics!$H$8:$H$57, ""))),0)) | I5: =IF($A5="","",IFERROR(--ISNUMBER(SEARCH(I$3, _xludf.XLOOKUP($A5, Metrics!$B$8:$B$57, Metrics!$H$8:$H$57, ""))),0)) | ... U5: =IF($A5="","",IFERROR(--ISNUMBER(SEARCH(U$3, _xludf.XLOOKUP($A5, Metrics!$B$8:$B$57, Metrics!$H$8:$H$57, ""))),0))
B6: =IF($A6="","",IFERROR(--ISNUMBER(SEARCH(B$3, _xludf.XLOOKUP($A6, Metrics!$B$8:$B$57, Metrics!$H$8:$H$57, ""))),0)) | C6: =IF($A6="","",IFERROR(--ISNUMBER(SEARCH(C$3, _xludf.XLOOKUP($A6, Metrics!$B$8:$B$57, Metrics!$H$8:$H$57, ""))),0)) | D6: =IF($A6="","",IFERROR(--ISNUMBER(SEARCH(D$3, _xludf.XLOOKUP($A6, Metrics!$B$8:$B$57, Metrics!$H$8:$H$57, ""))),0)) | E6: =IF($A6="","",IFERROR(--ISNUMBER(SEARCH(E$3, _xludf.XLOOKUP($A6, Metrics!$B$8:$B$57, Metrics!$H$8:$H$57, ""))),0)) | F6: =IF($A6="","",IFERROR(--ISNUMBER(SEARCH(F$3, _xludf.XLOOKUP($A6, Metrics!$B$8:$B$57, Metrics!$H$8:$H$57, ""))),0)) | G6: =IF($A6="","",IFERROR(--ISNUMBER(SEARCH(G$3, _xludf.XLOOKUP($A6, Metrics!$B$8:$B$57, Metrics!$H$8:$H$57, ""))),0)) | H6: =IF($A6="","",IFERROR(--ISNUMBER(SEARCH(H$3, _xludf.XLOOKUP($A6, Metrics!$B$8:$B$57, Metrics!$H$8:$H$57, ""))),0)) | I6: =IF($A6="","",IFERROR(--ISNUMBER(SEARCH(I$3, _xludf.XLOOKUP($A6, Metrics!$B$8:$B$57, Metrics!$H$8:$H$57, ""))),0)) | ... U6: =IF($A6="","",IFERROR(--ISNUMBER(SEARCH(U$3, _xludf.XLOOKUP($A6, Metrics!$B$8:$B$57, Metrics!$H$8:$H$57, ""))),0))
B7: =IF($A7="","",IFERROR(--ISNUMBER(SEARCH(B$3, _xludf.XLOOKUP($A7, Metrics!$B$8:$B$57, Metrics!$H$8:$H$57, ""))),0)) | C7: =IF($A7="","",IFERROR(--ISNUMBER(SEARCH(C$3, _xludf.XLOOKUP($A7, Metrics!$B$8:$B$57, Metrics!$H$8:$H$57, ""))),0)) | D7: =IF($A7="","",IFERROR(--ISNUMBER(SEARCH(D$3, _xludf.XLOOKUP($A7, Metrics!$B$8:$B$57, Metrics!$H$8:$H$57, ""))),0)) | E7: =IF($A7="","",IFERROR(--ISNUMBER(SEARCH(E$3, _xludf.XLOOKUP($A7, Metrics!$B$8:$B$57, Metrics!$H$8:$H$57, ""))),0)) | F7: =IF($A7="","",IFERROR(--ISNUMBER(SEARCH(F$3, _xludf.XLOOKUP($A7, Metrics!$B$8:$B$57, Metrics!$H$8:$H$57, ""))),0)) | G7: =IF($A7="","",IFERROR(--ISNUMBER(SEARCH(G$3, _xludf.XLOOKUP($A7, Metrics!$B$8:$B$57, Metrics!$H$8:$H$57, ""))),0)) | H7: =IF($A7="","",IFERROR(--ISNUMBER(SEARCH(H$3, _xludf.XLOOKUP($A7, Metrics!$B$8:$B$57, Metrics!$H$8:$H$57, ""))),0)) | I7: =IF($A7="","",IFERROR(--ISNUMBER(SEARCH(I$3, _xludf.XLOOKUP($A7, Metrics!$B$8:$B$57, Metrics!$H$8:$H$57, ""))),0)) | ... U7: =IF($A7="","",IFERROR(--ISNUMBER(SEARCH(U$3, _xludf.XLOOKUP($A7, Metrics!$B$8:$B$57, Metrics!$H$8:$H$57, ""))),0))
B8: =IF($A8="","",IFERROR(--ISNUMBER(SEARCH(B$3, _xludf.XLOOKUP($A8, Metrics!$B$8:$B$57, Metrics!$H$8:$H$57, ""))),0)) | C8: =IF($A8="","",IFERROR(--ISNUMBER(SEARCH(C$3, _xludf.XLOOKUP($A8, Metrics!$B$8:$B$57, Metrics!$H$8:$H$57, ""))),0)) | D8: =IF($A8="","",IFERROR(--ISNUMBER(SEARCH(D$3, _xludf.XLOOKUP($A8, Metrics!$B$8:$B$57, Metrics!$H$8:$H$57, ""))),0)) | E8: =IF($A8="","",IFERROR(--ISNUMBER(SEARCH(E$3, _xludf.XLOOKUP($A8, Metrics!$B$8:$B$57, Metrics!$H$8:$H$57, ""))),0)) | F8: =IF($A8="","",IFERROR(--ISNUMBER(SEARCH(F$3, _xludf.XLOOKUP($A8, Metrics!$B$8:$B$57, Metrics!$H$8:$H$57, ""))),0)) | G8: =IF($A8="","",IFERROR(--ISNUMBER(SEARCH(G$3, _xludf.XLOOKUP($A8, Metrics!$B$8:$B$57, Metrics!$H$8:$H$57, ""))),0)) | H8: =IF($A8="","",IFERROR(--ISNUMBER(SEARCH(H$3, _xludf.XLOOKUP($A8, Metrics!$B$8:$B$57, Metrics!$H$8:$H$57, ""))),0)) | I8: =IF($A8="","",IFERROR(--ISNUMBER(SEARCH(I$3, _xludf.XLOOKUP($A8, Metrics!$B$8:$B$57, Metrics!$H$8:$H$57, ""))),0)) | ... U8: =IF($A8="","",IFERROR(--ISNUMBER(SEARCH(U$3, _xludf.XLOOKUP($A8, Metrics!$B$8:$B$57, Metrics!$H$8:$H$57, ""))),0))
B9: =IF($A9="","",IFERROR(--ISNUMBER(SEARCH(B$3, _xludf.XLOOKUP($A9, Metrics!$B$8:$B$57, Metrics!$H$8:$H$57, ""))),0)) | C9: =IF($A9="","",IFERROR(--ISNUMBER(SEARCH(C$3, _xludf.XLOOKUP($A9, Metrics!$B$8:$B$57, Metrics!$H$8:$H$57, ""))),0)) | D9: =IF($A9="","",IFERROR(--ISNUMBER(SEARCH(D$3, _xludf.XLOOKUP($A9, Metrics!$B$8:$B$57, Metrics!$H$8:$H$57, ""))),0)) | E9: =IF($A9="","",IFERROR(--ISNUMBER(SEARCH(E$3, _xludf.XLOOKUP($A9, Metrics!$B$8:$B$57, Metrics!$H$8:$H$57, ""))),0)) | F9: =IF($A9="","",IFERROR(--ISNUMBER(SEARCH(F$3, _xludf.XLOOKUP($A9, Metrics!$B$8:$B$57, Metrics!$H$8:$H$57, ""))),0)) | G9: =IF($A9="","",IFERROR(--ISNUMBER(SEARCH(G$3, _xludf.XLOOKUP($A9, Metrics!$B$8:$B$57, Metrics!$H$8:$H$57, ""))),0)) | H9: =IF($A9="","",IFERROR(--ISNUMBER(SEARCH(H$3, _xludf.XLOOKUP($A9, Metrics!$B$8:$B$57, Metrics!$H$8:$H$57, ""))),0)) | I9: =IF($A9="","",IFERROR(--ISNUMBER(SEARCH(I$3, _xludf.XLOOKUP($A9, Metrics!$B$8:$B$57, Metrics!$H$8:$H$57, ""))),0)) | ... U9: =IF($A9="","",IFERROR(--ISNUMBER(SEARCH(U$3, _xludf.XLOOKUP($A9, Metrics!$B$8:$B$57, Metrics!$H$8:$H$57, ""))),0))
B10: =IF($A10="","",IFERROR(--ISNUMBER(SEARCH(B$3, _xludf.XLOOKUP($A10, Metrics!$B$8:$B$57, Metrics!$H$8:$H$57, ""))),0)) | C10: =IF($A10="","",IFERROR(--ISNUMBER(SEARCH(C$3, _xludf.XLOOKUP($A10, Metrics!$B$8:$B$57, Metrics!$H$8:$H$57, ""))),0)) | D10: =IF($A10="","",IFERROR(--ISNUMBER(SEARCH(D$3, _xludf.XLOOKUP($A10, Metrics!$B$8:$B$57, Metrics!$H$8:$H$57, ""))),0)) | E10: =IF($A10="","",IFERROR(--ISNUMBER(SEARCH(E$3, _xludf.XLOOKUP($A10, Metrics!$B$8:$B$57, Metrics!$H$8:$H$57, ""))),0)) | F10: =IF($A10="","",IFERROR(--ISNUMBER(SEARCH(F$3, _xludf.XLOOKUP($A10, Metrics!$B$8:$B$57, Metrics!$H$8:$H$57, ""))),0)) | G10: =IF($A10="","",IFERROR(--ISNUMBER(SEARCH(G$3, _xludf.XLOOKUP($A10, Metrics!$B$8:$B$57, Metrics!$H$8:$H$57, ""))),0)) | H10: =IF($A10="","",IFERROR(--ISNUMBER(SEARCH(H$3, _xludf.XLOOKUP($A10, Metrics!$B$8:$B$57, Metrics!$H$8:$H$57, ""))),0)) | I10: =IF($A10="","",IFERROR(--ISNUMBER(SEARCH(I$3, _xludf.XLOOKUP($A10, Metrics!$B$8:$B$57, Metrics!$H$8:$H$57, ""))),0)) | ... U10: =IF($A10="","",IFERROR(--ISNUMBER(SEARCH(U$3, _xludf.XLOOKUP($A10, Metrics!$B$8:$B$57, Metrics!$H$8:$H$57, ""))),0))
B11: =IF($A11="","",IFERROR(--ISNUMBER(SEARCH(B$3, _xludf.XLOOKUP($A11, Metrics!$B$8:$B$57, Metrics!$H$8:$H$57, ""))),0)) | C11: =IF($A11="","",IFERROR(--ISNUMBER(SEARCH(C$3, _xludf.XLOOKUP($A11, Metrics!$B$8:$B$57, Metrics!$H$8:$H$57, ""))),0)) | D11: =IF($A11="","",IFERROR(--ISNUMBER(SEARCH(D$3, _xludf.XLOOKUP($A11, Metrics!$B$8:$B$57, Metrics!$H$8:$H$57, ""))),0)) | E11: =IF($A11="","",IFERROR(--ISNUMBER(SEARCH(E$3, _xludf.XLOOKUP($A11, Metrics!$B$8:$B$57, Metrics!$H$8:$H$57, ""))),0)) | F11: =IF($A11="","",IFERROR(--ISNUMBER(SEARCH(F$3, _xludf.XLOOKUP($A11, Metrics!$B$8:$B$57, Metrics!$H$8:$H$57, ""))),0)) | G11: =IF($A11="","",IFERROR(--ISNUMBER(SEARCH(G$3, _xludf.XLOOKUP($A11, Metrics!$B$8:$B$57, Metrics!$H$8:$H$57, ""))),0)) | H11: =IF($A11="","",IFERROR(--ISNUMBER(SEARCH(H$3, _xludf.XLOOKUP($A11, Metrics!$B$8:$B$57, Metrics!$H$8:$H$57, ""))),0)) | I11: =IF($A11="","",IFERROR(--ISNUMBER(SEARCH(I$3, _xludf.XLOOKUP($A11, Metrics!$B$8:$B$57, Metrics!$H$8:$H$57, ""))),0)) | ... U11: =IF($A11="","",IFERROR(--ISNUMBER(SEARCH(U$3, _xludf.XLOOKUP($A11, Metrics!$B$8:$B$57, Metrics!$H$8:$H$57, ""))),0))
B12: =IF($A12="","",IFERROR(--ISNUMBER(SEARCH(B$3, _xludf.XLOOKUP($A12, Metrics!$B$8:$B$57, Metrics!$H$8:$H$57, ""))),0)) | C12: =IF($A12="","",IFERROR(--ISNUMBER(SEARCH(C$3, _xludf.XLOOKUP($A12, Metrics!$B$8:$B$57, Metrics!$H$8:$H$57, ""))),0)) | D12: =IF($A12="","",IFERROR(--ISNUMBER(SEARCH(D$3, _xludf.XLOOKUP($A12, Metrics!$B$8:$B$57, Metrics!$H$8:$H$57, ""))),0)) | E12: =IF($A12="","",IFERROR(--ISNUMBER(SEARCH(E$3, _xludf.XLOOKUP($A12, Metrics!$B$8:$B$57, Metrics!$H$8:$H$57, ""))),0)) | F12: =IF($A12="","",IFERROR(--ISNUMBER(SEARCH(F$3, _xludf.XLOOKUP($A12, Metrics!$B$8:$B$57, Metrics!$H$8:$H$57, ""))),0)) | G12: =IF($A12="","",IFERROR(--ISNUMBER(SEARCH(G$3, _xludf.XLOOKUP($A12, Metrics!$B$8:$B$57, Metrics!$H$8:$H$57, ""))),0)) | H12: =IF($A12="","",IFERROR(--ISNUMBER(SEARCH(H$3, _xludf.XLOOKUP($A12, Metrics!$B$8:$B$57, Metrics!$H$8:$H$57, ""))),0)) | I12: =IF($A12="","",IFERROR(--ISNUMBER(SEARCH(I$3, _xludf.XLOOKUP($A12, Metrics!$B$8:$B$57, Metrics!$H$8:$H$57, ""))),0)) | ... U12: =IF($A12="","",IFERROR(--ISNUMBER(SEARCH(U$3, _xludf.XLOOKUP($A12, Metrics!$B$8:$B$57, Metrics!$H$8:$H$57, ""))),0))
