Workbook
Name BingSearchKey: Config!$B$4
Name SerpApiKey: Config!$B$5
Name SegmentId: Dashboard!$E$2

Sheet Brand_Kit
A1: Certify Intel v1 — Excel-Only (Brand Kit)
A3: PLACEHOLDER BRANDING: Replace with official Certify Health assets (logo + hex colors).
A5: Logo (placeholder):
A12: Colors
A13: Name | B13: Hex | D13: Swatch
A14: Primary | B14: #0B2E4A
A15: Secondary | B15: #1E9FB3
A16: Accent | B16: #F2A900
A17: Background | B17: #F5F7FA
A18: Border | B18: #D0D7DE
A20: Typography
A21: Header Font | B21: Aptos Display
A22: Body Font | B22: Aptos

Sheet Config
A1: Config (Inputs in BLUE)
A3: API Keys (optional; for autonomous competitor discovery via web search APIs)
A4: Bing Search API Key | B4: ENTER_KEY
A5: SerpAPI Key | B5: ENTER_KEY
A6: Max Competitors to Import | B6: 50
A8: Refresh Settings
A9: Evidence freshness threshold (days) | B9: 30
A10: Minimum allowed known-coverage (fail closed below) | B10: 0.6
A12: Scoring Weights (editable)
A13: Weight | B13: Value
A14: Threat_FeatureOverlap | B14: 0.35
A15: Threat_PricingAggressive | B15: 0.25
A16: Threat_FundingVelocity | B16: 0.2
A17: Threat_SegmentFit | B17: 0.2
A18: Opp_FeatureGap | B18: 0.5
A19: Opp_WeakSegmentFit | B19: 0.25
A20: Opp_LowCoverage | B20: 0.25

Sheet Sources_Allowlist
A1: Sources Allowlist (Fail-Closed)
A3: Only allowlisted domains/paths can be ingested. Non-allowlisted URLs must be BLOCKED and reviewed.
A4: source_key | B4: tier | C4: domain | D4: allow_path_prefix | E4: deny_path_prefix | F4: enabled | G4: license_notes | H4: owner
A5: DEMO | B5: TIER1 | C5: file | D5: / | F5: TRUE | G5: Local demo evidence (offline) | H5: system
A6: SEC_EDGAR | B6: TIER1 | C6: www.sec.gov | D6: /Archives | E6: /cgi-bin | F6: FALSE | G6: Public filings; respect ToS/rate limits | H6: system
A7: Company_PR | B7: TIER2 | F7: FALSE | G7: Per-entity allowlist required | H7: user
A8: G2 | B8: SIGNAL | C8: www.g2.com | D8: /products | E8: / | F8: FALSE | G8: Requires license / ToS review | H8: user
A9: Capterra | B9: SIGNAL | C9: www.capterra.com | D9: / | E9: / | F9: FALSE | G9: Requires license / ToS review | H9: user

Sheet Segment_Rules
A1: Middle Market Segmentation Rules (Always Applied)
A3: Edit thresholds in BLUE. All metrics and dashboards must filter to this segment.
A4: segment_id | B4: segment_name | C4: revenue_min_usd | D4: revenue_max_usd | E4: practice_size_min | F4: practice_size_max | G4: region_includes | H4: notes
A5: SEG_MM | B5: Middle Market | C5: 5000000 | D5: 200000000 | E5: 5 | F5: 200 | G5: US (all) | H5: Placeholder thresholds; replace with Certify definition

Sheet Field_Dictionary
A1: Field Dictionary (Claim Keys + Quality Gates)
A3: Fail-closed: missing/ambiguous evidence must output UNKNOWN and create review tasks.
A4: field_key | B4: category | C4: value_type | D4: units | E4: min_confidence | F4: requires_tier1 | G4: promotion_rule | H4: example_source | I4: notes
A5: pricing_acv_mid_market | B5: Pricing | C5: number | D5: USD/year | E5: 0.8 | F5: TRUE | G5: PROMOTE_IF>=MINCONF_AND_TIER | H5: pricing page | I5: Explicit annual price or ACV
A6: arr_estimate | B6: Financial | C6: number | D6: USD/year | E6: 0.85 | F6: TRUE | G6: PROMOTE_IF_TIER1_ONLY | H6: 10-K/press | I6: Only explicit ARR mention
A7: contract_terms | B7: Pricing | C7: text | E7: 0.7 | F7: FALSE | G7: PROMOTE_IF>=MINCONF | H7: pricing/terms | I7: Explicit contract duration/cancellation
A8: features | B8: Product | C8: text | E8: 0.65 | F8: FALSE | G8: PROMOTE_IF>=MINCONF | H8: product page | I8: Semicolon-separated feature tags
A9: funding_round | B9: Funding | C9: text | E9: 0.8 | F9: TRUE | G9: PROMOTE_IF_TIER1_ONLY | H9: filings/press | I9: Explicit round amount and date
A10: geo_coverage | B10: Market | C10: text | E10: 0.7 | F10: FALSE | G10: PROMOTE_IF>=MINCONF | H10: about page | I10: Regions served
A11: practice_size_target | B11: Market | C11: text | E11: 0.7 | F11: FALSE | G11: PROMOTE_IF>=MINCONF | H11: case studies | I11: Explicit ICP statements

Sheet Feature_Taxonomy
A1: Feature Taxonomy (canonical features + synonyms)
A4: feature_id | B4: feature_name | C4: category | D4: synonyms_csv | E4: notes
A5: F001 | B5: Eligibility Verification | C5: Revenue Cycle | D5: eligibility check;insurance eligibility
A6: F002 | B6: Prior Authorization | C6: Revenue Cycle | D6: prior auth;pre-authorization
A7: F003 | B7: Patient Payments | C7: Billing | D7: payment portal;online payments
A8: F004 | B8: Scheduling | C8: Front Office | D8: appointment scheduling;calendar

Sheet Input
A1: Input (Normalized; Evidence-Led)
A2: Green = imported/linked; Blue = editable inputs; Yellow/Red = review required.
A4: Entities
A6: entity_id | B6: canonical_name | C6: domain | D6: vertical | E6: region | F6: segment_id | G6: discovered_via | H6: discovered_at | I6: status | J6: hq_city | K6: hq_state | L6: notes
A7: E001 | B7: AcmeRival | C7: acmerival.com | D7: Provider Credentialing | E7: US | F7: SEG_MM | G7: DEMO | H7: 2026-01-12 | I7: ACTIVE | J7: New York | K7: NY | L7: DEMO ROW
A8: E002 | B8: EnrollPro | C8: enrollpro.io | D8: Provider Enrollment | E8: US | F8: SEG_MM | G8: DEMO | H8: 2026-01-12 | I8: ACTIVE | J8: Austin | K8: TX | L8: DEMO ROW
A9: E003 | B9: ComplianceFlow | C9: complianceflow.health | D9: Compliance Automation | E9: US | F9: SEG_MM | G9: DEMO | H9: 2026-01-12 | I9: ACTIVE | J9: Chicago | K9: IL | L9: DEMO ROW
A10: E004 | B10: CredentiSure | C10: credentisure.com | D10: Credentialing | E10: US | F10: SEG_MM | G10: DEMO | H10: 2026-01-12 | I10: ACTIVE | J10: Boston | K10: MA | L10: DEMO ROW
A11: E005 | B11: PracticeOps | C11: practiceops.com | D11: Practice Ops Suite | E11: US | F11: SEG_MM | G11: DEMO | H11: 2026-01-12 | I11: ACTIVE | J11: Miami | K11: FL | L11: DEMO ROW
A12: E006 | B12: MidMarketMedTech | C12: mmmedtech.com | D12: Healthcare IT | E12: US | F12: SEG_MM | G12: DEMO | H12: 2026-01-12 | I12: ACTIVE | J12: Seattle | K12: WA | L12: DEMO ROW
A15: Evidence (Claims must link here)
A17: evidence_id | B17: entity_id | C17: source_key | D17: tier | E17: url | F17: fetched_at | G17: snippet | H17: content_hash | I17: text_hash | J17: domain_calc | K17: allowlist_ok
A18: EV001 | B18: E001 | C18: DEMO | D18: TIER1 | E18: file://docs/demo_sources/E001_pricing.html | F18: 2026-01-12 | G18: DEMO evidence placeholder. Replace with allowlisted URL + snippet. | H18: 0217e879a9ae84b4 | I18: 46aae5c96408e7ec | J18: =IF(LEFT([@url],7)="file://","file",LOWER(TEXTBEFORE(TEXTAFTER([@url],"//"),"/"))) | K18: =LET(sk,[@source_key],en,IFERROR(XLOOKUP(sk,tblSourcesAllowlist[source_key],tblSourcesAllowlist[enabled]),"FALSE"),dom,[@domain_calc],domOK,IF(dom="file",TRUE,ISNUMBER(MATCH(dom,FILTER(tblSourcesAllowlist[domain],tblSourcesAllowlist[enabled]="TRUE"),0))),AND(en="TRUE",domOK))
A19: EV002 | B19: E002 | C19: DEMO | D19: TIER1 | E19: file://docs/demo_sources/E002_pricing.html | F19: 2026-01-12 | G19: DEMO evidence placeholder. Replace with allowlisted URL + snippet. | H19: 3deb1e85e3854868 | I19: 46aae5c96408e7ec | J19: =IF(LEFT([@url],7)="file://","file",LOWER(TEXTBEFORE(TEXTAFTER([@url],"//"),"/"))) | K19: =LET(sk,[@source_key],en,IFERROR(XLOOKUP(sk,tblSourcesAllowlist[source_key],tblSourcesAllowlist[enabled]),"FALSE"),dom,[@domain_calc],domOK,IF(dom="file",TRUE,ISNUMBER(MATCH(dom,FILTER(tblSourcesAllowlist[domain],tblSourcesAllowlist[enabled]="TRUE"),0))),AND(en="TRUE",domOK))
A20: EV003 | B20: E003 | C20: DEMO | D20: TIER1 | E20: file://docs/demo_sources/E003_pricing.html | F20: 2026-01-12 | G20: DEMO evidence placeholder. Replace with allowlisted URL + snippet. | H20: d42285f8d1a9736f | I20: 46aae5c96408e7ec | J20: =IF(LEFT([@url],7)="file://","file",LOWER(TEXTBEFORE(TEXTAFTER([@url],"//"),"/"))) | K20: =LET(sk,[@source_key],en,IFERROR(XLOOKUP(sk,tblSourcesAllowlist[source_key],tblSourcesAllowlist[enabled]),"FALSE"),dom,[@domain_calc],domOK,IF(dom="file",TRUE,ISNUMBER(MATCH(dom,FILTER(tblSourcesAllowlist[domain],tblSourcesAllowlist[enabled]="TRUE"),0))),AND(en="TRUE",domOK))
A21: EV004 | B21: E004 | C21: DEMO | D21: TIER1 | E21: file://docs/demo_sources/E004_pricing.html | F21: 2026-01-12 | G21: DEMO evidence placeholder. Replace with allowlisted URL + snippet. | H21: b1e3c58050111249 | I21: 46aae5c96408e7ec | J21: =IF(LEFT([@url],7)="file://","file",LOWER(TEXTBEFORE(TEXTAFTER([@url],"//"),"/"))) | K21: =LET(sk,[@source_key],en,IFERROR(XLOOKUP(sk,tblSourcesAllowlist[source_key],tblSourcesAllowlist[enabled]),"FALSE"),dom,[@domain_calc],domOK,IF(dom="file",TRUE,ISNUMBER(MATCH(dom,FILTER(tblSourcesAllowlist[domain],tblSourcesAllowlist[enabled]="TRUE"),0))),AND(en="TRUE",domOK))
A22: EV005 | B22: E001 | C22: DEMO | D22: SIGNAL | E22: file://docs/demo_sources/E001_pr.html | F22: 2026-01-12 | G22: DEMO PR mention (signal only). | H22: 0510eddd78110203 | I22: 41bfa2f2111d7821 | J22: =IF(LEFT([@url],7)="file://","file",LOWER(TEXTBEFORE(TEXTAFTER([@url],"//"),"/"))) | K22: =LET(sk,[@source_key],en,IFERROR(XLOOKUP(sk,tblSourcesAllowlist[source_key],tblSourcesAllowlist[enabled]),"FALSE"),dom,[@domain_calc],domOK,IF(dom="file",TRUE,ISNUMBER(MATCH(dom,FILTER(tblSourcesAllowlist[domain],tblSourcesAllowlist[enabled]="TRUE"),0))),AND(en="TRUE",domOK))
A25: Claim Candidates (Fail-Closed; UNKNOWN → Review)
A27: candidate_id | B27: entity_id | C27: segment_id | D27: field_key | E27: value_text | F27: value_num | G27: units | H27: confidence | I27: evidence_id | J27: span_start | K27: span_end | L27: tier | M27: status_final | N27: status_manual | O27: status_auto | P27: auto_reason | Q27: reviewer_notes
A28: C001 | B28: E001 | C28: SEG_MM | D28: pricing_acv_mid_market | F28: 12000 | G28: USD/year | H28: 0.9 | I28: EV001 | J28: 0 | K28: 200 | L28: TIER1 | M28: =LET(man,[@status_manual],auto,[@status_auto],IF(man="REJECTED","REJECTED",IF(man="IN_REVIEW","IN_REVIEW",IF(man="PROMOTED",IF(auto="PROMOTABLE","PROMOTED","REVIEW_REQUIRED"),IF(auto="PROMOTABLE","PROMOTED","REVIEW_REQUIRED"))))) | N28: PROMOTED | O28: =LET(minc,IFERROR(XLOOKUP([@field_key],tblFieldDictionary[field_key],tblFieldDictionary[min_confidence]),1),req1,IFERROR(XLOOKUP([@field_key],tblFieldDictionary[field_key],tblFieldDictionary[requires_tier1]),"FALSE"),hasEvid,ISNUMBER(MATCH([@evidence_id],tblEvidence[evidence_id],0)),hasVal,OR(AND([@value_text]<>"",[@value_text]<>"UNKNOWN"),[@value_num]<>""),confOK,[@confidence]>=minc,tierOK,IF(req1="TRUE",[@tier]="TIER1",TRUE),IF(NOT(hasEvid),"REVIEW_REQUIRED",IF(NOT(hasVal),"REVIEW_REQUIRED",IF(NOT(confOK),"REVIEW_REQUIRED",IF(NOT(tierOK),"REVIEW_REQUIRED","PROMOTABLE"))))) | P28: =LET(minc,IFERROR(XLOOKUP([@field_key],tblFieldDictionary[field_key],tblFieldDictionary[min_confidence]),1),req1,IFERROR(XLOOKUP([@field_key],tblFieldDictionary[field_key],tblFieldDictionary[requires_tier1]),"FALSE"),hasEvid,ISNUMBER(MATCH([@evidence_id],tblEvidence[evidence_id],0)),hasVal,OR(AND([@value_text]<>"",[@value_text]<>"UNKNOWN"),[@value_num]<>""),confOK,[@confidence]>=minc,tierOK,IF(req1="TRUE",[@tier]="TIER1",TRUE),IF(NOT(hasEvid),"MISSING_EVIDENCE",IF(NOT(hasVal),"MISSING_VALUE",IF(NOT(confOK),"LOW_CONFIDENCE",IF(NOT(tierOK),"TIER1_REQUIRED","OK")))))
A29: C002 | B29: E001 | C29: SEG_MM | D29: contract_terms | E29: Annual contract, cancel with 30 days notice | H29: 0.75 | I29: EV001 | J29: 201 | K29: 320 | L29: TIER1 | M29: =LET(man,[@status_manual],auto,[@status_auto],IF(man="REJECTED","REJECTED",IF(man="IN_REVIEW","IN_REVIEW",IF(man="PROMOTED",IF(auto="PROMOTABLE","PROMOTED","REVIEW_REQUIRED"),IF(auto="PROMOTABLE","PROMOTED","REVIEW_REQUIRED"))))) | N29: PROMOTED | O29: =LET(minc,IFERROR(XLOOKUP([@field_key],tblFieldDictionary[field_key],tblFieldDictionary[min_confidence]),1),req1,IFERROR(XLOOKUP([@field_key],tblFieldDictionary[field_key],tblFieldDictionary[requires_tier1]),"FALSE"),hasEvid,ISNUMBER(MATCH([@evidence_id],tblEvidence[evidence_id],0)),hasVal,OR(AND([@value_text]<>"",[@value_text]<>"UNKNOWN"),[@value_num]<>""),confOK,[@confidence]>=minc,tierOK,IF(req1="TRUE",[@tier]="TIER1",TRUE),IF(NOT(hasEvid),"REVIEW_REQUIRED",IF(NOT(hasVal),"REVIEW_REQUIRED",IF(NOT(confOK),"REVIEW_REQUIRED",IF(NOT(tierOK),"REVIEW_REQUIRED","PROMOTABLE"))))) | P29: =LET(minc,IFERROR(XLOOKUP([@field_key],tblFieldDictionary[field_key],tblFieldDictionary[min_confidence]),1),req1,IFERROR(XLOOKUP([@field_key],tblFieldDictionary[field_key],tblFieldDictionary[requires_tier1]),"FALSE"),hasEvid,ISNUMBER(MATCH([@evidence_id],tblEvidence[evidence_id],0)),hasVal,OR(AND([@value_text]<>"",[@value_text]<>"UNKNOWN"),[@value_num]<>""),confOK,[@confidence]>=minc,tierOK,IF(req1="TRUE",[@tier]="TIER1",TRUE),IF(NOT(hasEvid),"MISSING_EVIDENCE",IF(NOT(hasVal),"MISSING_VALUE",IF(NOT(confOK),"LOW_CONFIDENCE",IF(NOT(tierOK),"TIER1_REQUIRED","OK")))))
A30: C003 | B30: E001 | C30: SEG_MM | D30: features | E30: Credentialing; Enrollment; Payer Roster | H30: 0.7 | I30: EV001 | J30: 321 | K30: 520 | L30: TIER1 | M30: =LET(man,[@status_manual],auto,[@status_auto],IF(man="REJECTED","REJECTED",IF(man="IN_REVIEW","IN_REVIEW",IF(man="PROMOTED",IF(auto="PROMOTABLE","PROMOTED","REVIEW_REQUIRED"),IF(auto="PROMOTABLE","PROMOTED","REVIEW_REQUIRED"))))) | N30: PROMOTED | O30: =LET(minc,IFERROR(XLOOKUP([@field_key],tblFieldDictionary[field_key],tblFieldDictionary[min_confidence]),1),req1,IFERROR(XLOOKUP([@field_key],tblFieldDictionary[field_key],tblFieldDictionary[requires_tier1]),"FALSE"),hasEvid,ISNUMBER(MATCH([@evidence_id],tblEvidence[evidence_id],0)),hasVal,OR(AND([@value_text]<>"",[@value_text]<>"UNKNOWN"),[@value_num]<>""),confOK,[@confidence]>=minc,tierOK,IF(req1="TRUE",[@tier]="TIER1",TRUE),IF(NOT(hasEvid),"REVIEW_REQUIRED",IF(NOT(hasVal),"REVIEW_REQUIRED",IF(NOT(confOK),"REVIEW_REQUIRED",IF(NOT(tierOK),"REVIEW_REQUIRED","PROMOTABLE"))))) | P30: =LET(minc,IFERROR(XLOOKUP([@field_key],tblFieldDictionary[field_key],tblFieldDictionary[min_confidence]),1),req1,IFERROR(XLOOKUP([@field_key],tblFieldDictionary[field_key],tblFieldDictionary[requires_tier1]),"FALSE"),hasEvid,ISNUMBER(MATCH([@evidence_id],tblEvidence[evidence_id],0)),hasVal,OR(AND([@value_text]<>"",[@value_text]<>"UNKNOWN"),[@value_num]<>""),confOK,[@confidence]>=minc,tierOK,IF(req1="TRUE",[@tier]="TIER1",TRUE),IF(NOT(hasEvid),"MISSING_EVIDENCE",IF(NOT(hasVal),"MISSING_VALUE",IF(NOT(confOK),"LOW_CONFIDENCE",IF(NOT(tierOK),"TIER1_REQUIRED","OK")))))
A31: C004 | B31: E002 | C31: SEG_MM | D31: pricing_acv_mid_market | E31: UNKNOWN | G31: USD/year | H31: 0.2 | I31: EV002 | J31: 0 | K31: 180 | L31: TIER1 | M31: =LET(man,[@status_manual],auto,[@status_auto],IF(man="REJECTED","REJECTED",IF(man="IN_REVIEW","IN_REVIEW",IF(man="PROMOTED",IF(auto="PROMOTABLE","PROMOTED","REVIEW_REQUIRED"),IF(auto="PROMOTABLE","PROMOTED","REVIEW_REQUIRED"))))) | N31: REVIEW_REQUIRED | O31: =LET(minc,IFERROR(XLOOKUP([@field_key],tblFieldDictionary[field_key],tblFieldDictionary[min_confidence]),1),req1,IFERROR(XLOOKUP([@field_key],tblFieldDictionary[field_key],tblFieldDictionary[requires_tier1]),"FALSE"),hasEvid,ISNUMBER(MATCH([@evidence_id],tblEvidence[evidence_id],0)),hasVal,OR(AND([@value_text]<>"",[@value_text]<>"UNKNOWN"),[@value_num]<>""),confOK,[@confidence]>=minc,tierOK,IF(req1="TRUE",[@tier]="TIER1",TRUE),IF(NOT(hasEvid),"REVIEW_REQUIRED",IF(NOT(hasVal),"REVIEW_REQUIRED",IF(NOT(confOK),"REVIEW_REQUIRED",IF(NOT(tierOK),"REVIEW_REQUIRED","PROMOTABLE"))))) | P31: =LET(minc,IFERROR(XLOOKUP([@field_key],tblFieldDictionary[field_key],tblFieldDictionary[min_confidence]),1),req1,IFERROR(XLOOKUP([@field_key],tblFieldDictionary[field_key],tblFieldDictionary[requires_tier1]),"FALSE"),hasEvid,ISNUMBER(MATCH([@evidence_id],tblEvidence[evidence_id],0)),hasVal,OR(AND([@value_text]<>"",[@value_text]<>"UNKNOWN"),[@value_num]<>""),confOK,[@confidence]>=minc,tierOK,IF(req1="TRUE",[@tier]="TIER1",TRUE),IF(NOT(hasEvid),"MISSING_EVIDENCE",IF(NOT(hasVal),"MISSING_VALUE",IF(NOT(confOK),"LOW_CONFIDENCE",IF(NOT(tierOK),"TIER1_REQUIRED","OK"))))) | Q31: No explicit ACV on page
A32: C005 | B32: E002 | C32: SEG_MM | D32: features | E32: Enrollment; Automated forms; Integrations | H32: 0.7 | I32: EV002 | J32: 181 | K32: 420 | L32: TIER1 | M32: =LET(man,[@status_manual],auto,[@status_auto],IF(man="REJECTED","REJECTED",IF(man="IN_REVIEW","IN_REVIEW",IF(man="PROMOTED",IF(auto="PROMOTABLE","PROMOTED","REVIEW_REQUIRED"),IF(auto="PROMOTABLE","PROMOTED","REVIEW_REQUIRED"))))) | N32: PROMOTED | O32: =LET(minc,IFERROR(XLOOKUP([@field_key],tblFieldDictionary[field_key],tblFieldDictionary[min_confidence]),1),req1,IFERROR(XLOOKUP([@field_key],tblFieldDictionary[field_key],tblFieldDictionary[requires_tier1]),"FALSE"),hasEvid,ISNUMBER(MATCH([@evidence_id],tblEvidence[evidence_id],0)),hasVal,OR(AND([@value_text]<>"",[@value_text]<>"UNKNOWN"),[@value_num]<>""),confOK,[@confidence]>=minc,tierOK,IF(req1="TRUE",[@tier]="TIER1",TRUE),IF(NOT(hasEvid),"REVIEW_REQUIRED",IF(NOT(hasVal),"REVIEW_REQUIRED",IF(NOT(confOK),"REVIEW_REQUIRED",IF(NOT(tierOK),"REVIEW_REQUIRED","PROMOTABLE"))))) | P32: =LET(minc,IFERROR(XLOOKUP([@field_key],tblFieldDictionary[field_key],tblFieldDictionary[min_confidence]),1),req1,IFERROR(XLOOKUP([@field_key],tblFieldDictionary[field_key],tblFieldDictionary[requires_tier1]),"FALSE"),hasEvid,ISNUMBER(MATCH([@evidence_id],tblEvidence[evidence_id],0)),hasVal,OR(AND([@value_text]<>"",[@value_text]<>"UNKNOWN"),[@value_num]<>""),confOK,[@confidence]>=minc,tierOK,IF(req1="TRUE",[@tier]="TIER1",TRUE),IF(NOT(hasEvid),"MISSING_EVIDENCE",IF(NOT(hasVal),"MISSING_VALUE",IF(NOT(confOK),"LOW_CONFIDENCE",IF(NOT(tierOK),"TIER1_REQUIRED","OK")))))
A33: C006 | B33: E003 | C33: SEG_MM | D33: funding_round | E33: UNKNOWN | H33: 0.1 | I33: EV003 | J33: 0 | K33: 250 | L33: SIGNAL | M33: =LET(man,[@status_manual],auto,[@status_auto],IF(man="REJECTED","REJECTED",IF(man="IN_REVIEW","IN_REVIEW",IF(man="PROMOTED",IF(auto="PROMOTABLE","PROMOTED","REVIEW_REQUIRED"),IF(auto="PROMOTABLE","PROMOTED","REVIEW_REQUIRED"))))) | N33: REVIEW_REQUIRED | O33: =LET(minc,IFERROR(XLOOKUP([@field_key],tblFieldDictionary[field_key],tblFieldDictionary[min_confidence]),1),req1,IFERROR(XLOOKUP([@field_key],tblFieldDictionary[field_key],tblFieldDictionary[requires_tier1]),"FALSE"),hasEvid,ISNUMBER(MATCH([@evidence_id],tblEvidence[evidence_id],0)),hasVal,OR(AND([@value_text]<>"",[@value_text]<>"UNKNOWN"),[@value_num]<>""),confOK,[@confidence]>=minc,tierOK,IF(req1="TRUE",[@tier]="TIER1",TRUE),IF(NOT(hasEvid),"REVIEW_REQUIRED",IF(NOT(hasVal),"REVIEW_REQUIRED",IF(NOT(confOK),"REVIEW_REQUIRED",IF(NOT(tierOK),"REVIEW_REQUIRED","PROMOTABLE"))))) | P33: =LET(minc,IFERROR(XLOOKUP([@field_key],tblFieldDictionary[field_key],tblFieldDictionary[min_confidence]),1),req1,IFERROR(XLOOKUP([@field_key],tblFieldDictionary[field_key],tblFieldDictionary[requires_tier1]),"FALSE"),hasEvid,ISNUMBER(MATCH([@evidence_id],tblEvidence[evidence_id],0)),hasVal,OR(AND([@value_text]<>"",[@value_text]<>"UNKNOWN"),[@value_num]<>""),confOK,[@confidence]>=minc,tierOK,IF(req1="TRUE",[@tier]="TIER1",TRUE),IF(NOT(hasEvid),"MISSING_EVIDENCE",IF(NOT(hasVal),"MISSING_VALUE",IF(NOT(confOK),"LOW_CONFIDENCE",IF(NOT(tierOK),"TIER1_REQUIRED","OK"))))) | Q33: Signal only; needs tier-1 corroboration
A34: C007 | B34: E004 | C34: SEG_MM | D34: pricing_acv_mid_market | F34: 18000 | G34: USD/year | H34: 0.82 | I34: EV004 | J34: 0 | K34: 210 | L34: TIER1 | M34: =LET(man,[@status_manual],auto,[@status_auto],IF(man="REJECTED","REJECTED",IF(man="IN_REVIEW","IN_REVIEW",IF(man="PROMOTED",IF(auto="PROMOTABLE","PROMOTED","REVIEW_REQUIRED"),IF(auto="PROMOTABLE","PROMOTED","REVIEW_REQUIRED"))))) | N34: PROMOTED | O34: =LET(minc,IFERROR(XLOOKUP([@field_key],tblFieldDictionary[field_key],tblFieldDictionary[min_confidence]),1),req1,IFERROR(XLOOKUP([@field_key],tblFieldDictionary[field_key],tblFieldDictionary[requires_tier1]),"FALSE"),hasEvid,ISNUMBER(MATCH([@evidence_id],tblEvidence[evidence_id],0)),hasVal,OR(AND([@value_text]<>"",[@value_text]<>"UNKNOWN"),[@value_num]<>""),confOK,[@confidence]>=minc,tierOK,IF(req1="TRUE",[@tier]="TIER1",TRUE),IF(NOT(hasEvid),"REVIEW_REQUIRED",IF(NOT(hasVal),"REVIEW_REQUIRED",IF(NOT(confOK),"REVIEW_REQUIRED",IF(NOT(tierOK),"REVIEW_REQUIRED","PROMOTABLE"))))) | P34: =LET(minc,IFERROR(XLOOKUP([@field_key],tblFieldDictionary[field_key],tblFieldDictionary[min_confidence]),1),req1,IFERROR(XLOOKUP([@field_key],tblFieldDictionary[field_key],tblFieldDictionary[requires_tier1]),"FALSE"),hasEvid,ISNUMBER(MATCH([@evidence_id],tblEvidence[evidence_id],0)),hasVal,OR(AND([@value_text]<>"",[@value_text]<>"UNKNOWN"),[@value_num]<>""),confOK,[@confidence]>=minc,tierOK,IF(req1="TRUE",[@tier]="TIER1",TRUE),IF(NOT(hasEvid),"MISSING_EVIDENCE",IF(NOT(hasVal),"MISSING_VALUE",IF(NOT(confOK),"LOW_CONFIDENCE",IF(NOT(tierOK),"TIER1_REQUIRED","OK")))))
A35: C008 | B35: E004 | C35: SEG_MM | D35: features | E35: Credentialing; Compliance; Analytics | H35: 0.68 | I35: EV004 | J35: 211 | K35: 400 | L35: TIER1 | M35: =LET(man,[@status_manual],auto,[@status_auto],IF(man="REJECTED","REJECTED",IF(man="IN_REVIEW","IN_REVIEW",IF(man="PROMOTED",IF(auto="PROMOTABLE","PROMOTED","REVIEW_REQUIRED"),IF(auto="PROMOTABLE","PROMOTED","REVIEW_REQUIRED"))))) | N35: PROMOTED | O35: =LET(minc,IFERROR(XLOOKUP([@field_key],tblFieldDictionary[field_key],tblFieldDictionary[min_confidence]),1),req1,IFERROR(XLOOKUP([@field_key],tblFieldDictionary[field_key],tblFieldDictionary[requires_tier1]),"FALSE"),hasEvid,ISNUMBER(MATCH([@evidence_id],tblEvidence[evidence_id],0)),hasVal,OR(AND([@value_text]<>"",[@value_text]<>"UNKNOWN"),[@value_num]<>""),confOK,[@confidence]>=minc,tierOK,IF(req1="TRUE",[@tier]="TIER1",TRUE),IF(NOT(hasEvid),"REVIEW_REQUIRED",IF(NOT(hasVal),"REVIEW_REQUIRED",IF(NOT(confOK),"REVIEW_REQUIRED",IF(NOT(tierOK),"REVIEW_REQUIRED","PROMOTABLE"))))) | P35: =LET(minc,IFERROR(XLOOKUP([@field_key],tblFieldDictionary[field_key],tblFieldDictionary[min_confidence]),1),req1,IFERROR(XLOOKUP([@field_key],tblFieldDictionary[field_key],tblFieldDictionary[requires_tier1]),"FALSE"),hasEvid,ISNUMBER(MATCH([@evidence_id],tblEvidence[evidence_id],0)),hasVal,OR(AND([@value_text]<>"",[@value_text]<>"UNKNOWN"),[@value_num]<>""),confOK,[@confidence]>=minc,tierOK,IF(req1="TRUE",[@tier]="TIER1",TRUE),IF(NOT(hasEvid),"MISSING_EVIDENCE",IF(NOT(hasVal),"MISSING_VALUE",IF(NOT(confOK),"LOW_CONFIDENCE",IF(NOT(tierOK),"TIER1_REQUIRED","OK")))))
A36: C009 | B36: E005 | C36: SEG_MM | D36: pricing_acv_mid_market | F36: 9000 | G36: USD/year | H36: 0.8 | I36: EV005 | J36: 0 | K36: 200 | L36: SIGNAL | M36: =LET(man,[@status_manual],auto,[@status_auto],IF(man="REJECTED","REJECTED",IF(man="IN_REVIEW","IN_REVIEW",IF(man="PROMOTED",IF(auto="PROMOTABLE","PROMOTED","REVIEW_REQUIRED"),IF(auto="PROMOTABLE","PROMOTED","REVIEW_REQUIRED"))))) | N36: REVIEW_REQUIRED | O36: =LET(minc,IFERROR(XLOOKUP([@field_key],tblFieldDictionary[field_key],tblFieldDictionary[min_confidence]),1),req1,IFERROR(XLOOKUP([@field_key],tblFieldDictionary[field_key],tblFieldDictionary[requires_tier1]),"FALSE"),hasEvid,ISNUMBER(MATCH([@evidence_id],tblEvidence[evidence_id],0)),hasVal,OR(AND([@value_text]<>"",[@value_text]<>"UNKNOWN"),[@value_num]<>""),confOK,[@confidence]>=minc,tierOK,IF(req1="TRUE",[@tier]="TIER1",TRUE),IF(NOT(hasEvid),"REVIEW_REQUIRED",IF(NOT(hasVal),"REVIEW_REQUIRED",IF(NOT(confOK),"REVIEW_REQUIRED",IF(NOT(tierOK),"REVIEW_REQUIRED","PROMOTABLE"))))) | P36: =LET(minc,IFERROR(XLOOKUP([@field_key],tblFieldDictionary[field_key],tblFieldDictionary[min_confidence]),1),req1,IFERROR(XLOOKUP([@field_key],tblFieldDictionary[field_key],tblFieldDictionary[requires_tier1]),"FALSE"),hasEvid,ISNUMBER(MATCH([@evidence_id],tblEvidence[evidence_id],0)),hasVal,OR(AND([@value_text]<>"",[@value_text]<>"UNKNOWN"),[@value_num]<>""),confOK,[@confidence]>=minc,tierOK,IF(req1="TRUE",[@tier]="TIER1",TRUE),IF(NOT(hasEvid),"MISSING_EVIDENCE",IF(NOT(hasVal),"MISSING_VALUE",IF(NOT(confOK),"LOW_CONFIDENCE",IF(NOT(tierOK),"TIER1_REQUIRED","OK"))))) | Q36: Pricing from signal source; needs tier-1

Sheet Claims_Current
A1: Claims_Current (Normalized Claims; Versioned via Review Workflow)
A2: This sheet is the contract consumed by Metrics and Dashboards. Values must be evidence-backed; missing/uncertain → UNKNOWN.
A4: entity_id | B4: canonical_name | C4: segment_id | D4: field_key | E4: value_text | F4: value_num | G4: units | H4: confidence | I4: evidence_id | J4: evidence_url | K4: tier | L4: status | M4: last_updated | N4: explain
A5: E001 | B5: AcmeRival | C5: SEG_MM | D5: pricing_acv_mid_market | E5: =LET(v,IFERROR(LOOKUP(2,1/((tblClaimCandidates[entity_id]=[@entity_id])*(tblClaimCandidates[field_key]=[@field_key])*(tblClaimCandidates[status_final]="PROMOTED")),tblClaimCandidates[value_text]),""),IF(v="","UNKNOWN",v)) | F5: =LET(cnt,COUNTIFS(tblClaimCandidates[entity_id],[@entity_id],tblClaimCandidates[field_key],[@field_key],tblClaimCandidates[status_final],"PROMOTED"),IF(cnt=0,NA(),SUMIFS(tblClaimCandidates[value_num],tblClaimCandidates[entity_id],[@entity_id],tblClaimCandidates[field_key],[@field_key],tblClaimCandidates[status_final],"PROMOTED"))) | G5: =IFERROR(XLOOKUP([@field_key],tblFieldDictionary[field_key],tblFieldDictionary[units]),"") | H5: =LET(cnt,COUNTIFS(tblClaimCandidates[entity_id],[@entity_id],tblClaimCandidates[field_key],[@field_key],tblClaimCandidates[status_final],"PROMOTED"),IF(cnt=0,NA(),AVERAGEIFS(tblClaimCandidates[confidence],tblClaimCandidates[entity_id],[@entity_id],tblClaimCandidates[field_key],[@field_key],tblClaimCandidates[status_final],"PROMOTED"))) | I5: =IFERROR(LOOKUP(2,1/((tblClaimCandidates[entity_id]=[@entity_id])*(tblClaimCandidates[field_key]=[@field_key])*(tblClaimCandidates[status_final]="PROMOTED")),tblClaimCandidates[evidence_id]),"") | J5: =IF([@evidence_id]="","",IFERROR(XLOOKUP([@evidence_id],tblEvidence[evidence_id],tblEvidence[url],""),"")) | K5: =IFERROR(LOOKUP(2,1/((tblClaimCandidates[entity_id]=[@entity_id])*(tblClaimCandidates[field_key]=[@field_key])*(tblClaimCandidates[status_final]="PROMOTED")),tblClaimCandidates[tier]),"") | L5: =IF([@value_text]="UNKNOWN","UNKNOWN","PROMOTED") | M5: =IF([@status]="PROMOTED",TODAY(),"") | N5: =IF([@status]="PROMOTED","evidence_linked","UNKNOWN_or_unverified")
A6: E001 | B6: AcmeRival | C6: SEG_MM | D6: arr_estimate | E6: =LET(v,IFERROR(LOOKUP(2,1/((tblClaimCandidates[entity_id]=[@entity_id])*(tblClaimCandidates[field_key]=[@field_key])*(tblClaimCandidates[status_final]="PROMOTED")),tblClaimCandidates[value_text]),""),IF(v="","UNKNOWN",v)) | F6: =LET(cnt,COUNTIFS(tblClaimCandidates[entity_id],[@entity_id],tblClaimCandidates[field_key],[@field_key],tblClaimCandidates[status_final],"PROMOTED"),IF(cnt=0,NA(),SUMIFS(tblClaimCandidates[value_num],tblClaimCandidates[entity_id],[@entity_id],tblClaimCandidates[field_key],[@field_key],tblClaimCandidates[status_final],"PROMOTED"))) | G6: =IFERROR(XLOOKUP([@field_key],tblFieldDictionary[field_key],tblFieldDictionary[units]),"") | H6: =LET(cnt,COUNTIFS(tblClaimCandidates[entity_id],[@entity_id],tblClaimCandidates[field_key],[@field_key],tblClaimCandidates[status_final],"PROMOTED"),IF(cnt=0,NA(),AVERAGEIFS(tblClaimCandidates[confidence],tblClaimCandidates[entity_id],[@entity_id],tblClaimCandidates[field_key],[@field_key],tblClaimCandidates[status_final],"PROMOTED"))) | I6: =IFERROR(LOOKUP(2,1/((tblClaimCandidates[entity_id]=[@entity_id])*(tblClaimCandidates[field_key]=[@field_key])*(tblClaimCandidates[status_final]="PROMOTED")),tblClaimCandidates[evidence_id]),"") | J6: =IF([@evidence_id]="","",IFERROR(XLOOKUP([@evidence_id],tblEvidence[evidence_id],tblEvidence[url],""),"")) | K6: =IFERROR(LOOKUP(2,1/((tblClaimCandidates[entity_id]=[@entity_id])*(tblClaimCandidates[field_key]=[@field_key])*(tblClaimCandidates[status_final]="PROMOTED")),tblClaimCandidates[tier]),"") | L6: =IF([@value_text]="UNKNOWN","UNKNOWN","PROMOTED") | M6: =IF([@status]="PROMOTED",TODAY(),"") | N6: =IF([@status]="PROMOTED","evidence_linked","UNKNOWN_or_unverified")
A7: E001 | B7: AcmeRival | C7: SEG_MM | D7: contract_terms | E7: =LET(v,IFERROR(LOOKUP(2,1/((tblClaimCandidates[entity_id]=[@entity_id])*(tblClaimCandidates[field_key]=[@field_key])*(tblClaimCandidates[status_final]="PROMOTED")),tblClaimCandidates[value_text]),""),IF(v="","UNKNOWN",v)) | F7: =LET(cnt,COUNTIFS(tblClaimCandidates[entity_id],[@entity_id],tblClaimCandidates[field_key],[@field_key],tblClaimCandidates[status_final],"PROMOTED"),IF(cnt=0,NA(),SUMIFS(tblClaimCandidates[value_num],tblClaimCandidates[entity_id],[@entity_id],tblClaimCandidates[field_key],[@field_key],tblClaimCandidates[status_final],"PROMOTED"))) | G7: =IFERROR(XLOOKUP([@field_key],tblFieldDictionary[field_key],tblFieldDictionary[units]),"") | H7: =LET(cnt,COUNTIFS(tblClaimCandidates[entity_id],[@entity_id],tblClaimCandidates[field_key],[@field_key],tblClaimCandidates[status_final],"PROMOTED"),IF(cnt=0,NA(),AVERAGEIFS(tblClaimCandidates[confidence],tblClaimCandidates[entity_id],[@entity_id],tblClaimCandidates[field_key],[@field_key],tblClaimCandidates[status_final],"PROMOTED"))) | I7: =IFERROR(LOOKUP(2,1/((tblClaimCandidates[entity_id]=[@entity_id])*(tblClaimCandidates[field_key]=[@field_key])*(tblClaimCandidates[status_final]="PROMOTED")),tblClaimCandidates[evidence_id]),"") | J7: =IF([@evidence_id]="","",IFERROR(XLOOKUP([@evidence_id],tblEvidence[evidence_id],tblEvidence[url],""),"")) | K7: =IFERROR(LOOKUP(2,1/((tblClaimCandidates[entity_id]=[@entity_id])*(tblClaimCandidates[field_key]=[@field_key])*(tblClaimCandidates[status_final]="PROMOTED")),tblClaimCandidates[tier]),"") | L7: =IF([@value_text]="UNKNOWN","UNKNOWN","PROMOTED") | M7: =IF([@status]="PROMOTED",TODAY(),"") | N7: =IF([@status]="PROMOTED","evidence_linked","UNKNOWN_or_unverified")
A8: E001 | B8: AcmeRival | C8: SEG_MM | D8: features | E8: =LET(v,IFERROR(LOOKUP(2,1/((tblClaimCandidates[entity_id]=[@entity_id])*(tblClaimCandidates[field_key]=[@field_key])*(tblClaimCandidates[status_final]="PROMOTED")),tblClaimCandidates[value_text]),""),IF(v="","UNKNOWN",v)) | F8: =LET(cnt,COUNTIFS(tblClaimCandidates[entity_id],[@entity_id],tblClaimCandidates[field_key],[@field_key],tblClaimCandidates[status_final],"PROMOTED"),IF(cnt=0,NA(),SUMIFS(tblClaimCandidates[value_num],tblClaimCandidates[entity_id],[@entity_id],tblClaimCandidates[field_key],[@field_key],tblClaimCandidates[status_final],"PROMOTED"))) | G8: =IFERROR(XLOOKUP([@field_key],tblFieldDictionary[field_key],tblFieldDictionary[units]),"") | H8: =LET(cnt,COUNTIFS(tblClaimCandidates[entity_id],[@entity_id],tblClaimCandidates[field_key],[@field_key],tblClaimCandidates[status_final],"PROMOTED"),IF(cnt=0,NA(),AVERAGEIFS(tblClaimCandidates[confidence],tblClaimCandidates[entity_id],[@entity_id],tblClaimCandidates[field_key],[@field_key],tblClaimCandidates[status_final],"PROMOTED"))) | I8: =IFERROR(LOOKUP(2,1/((tblClaimCandidates[entity_id]=[@entity_id])*(tblClaimCandidates[field_key]=[@field_key])*(tblClaimCandidates[status_final]="PROMOTED")),tblClaimCandidates[evidence_id]),"") | J8: =IF([@evidence_id]="","",IFERROR(XLOOKUP([@evidence_id],tblEvidence[evidence_id],tblEvidence[url],""),"")) | K8: =IFERROR(LOOKUP(2,1/((tblClaimCandidates[entity_id]=[@entity_id])*(tblClaimCandidates[field_key]=[@field_key])*(tblClaimCandidates[status_final]="PROMOTED")),tblClaimCandidates[tier]),"") | L8: =IF([@value_text]="UNKNOWN","UNKNOWN","PROMOTED") | M8: =IF([@status]="PROMOTED",TODAY(),"") | N8: =IF([@status]="PROMOTED","evidence_linked","UNKNOWN_or_unverified")
A9: E001 | B9: AcmeRival | C9: SEG_MM | D9: funding_round | E9: =LET(v,IFERROR(LOOKUP(2,1/((tblClaimCandidates[entity_id]=[@entity_id])*(tblClaimCandidates[field_key]=[@field_key])*(tblClaimCandidates[status_final]="PROMOTED")),tblClaimCandidates[value_text]),""),IF(v="","UNKNOWN",v)) | F9: =LET(cnt,COUNTIFS(tblClaimCandidates[entity_id],[@entity_id],tblClaimCandidates[field_key],[@field_key],tblClaimCandidates[status_final],"PROMOTED"),IF(cnt=0,NA(),SUMIFS(tblClaimCandidates[value_num],tblClaimCandidates[entity_id],[@entity_id],tblClaimCandidates[field_key],[@field_key],tblClaimCandidates[status_final],"PROMOTED"))) | G9: =IFERROR(XLOOKUP([@field_key],tblFieldDictionary[field_key],tblFieldDictionary[units]),"") | H9: =LET(cnt,COUNTIFS(tblClaimCandidates[entity_id],[@entity_id],tblClaimCandidates[field_key],[@field_key],tblClaimCandidates[status_final],"PROMOTED"),IF(cnt=0,NA(),AVERAGEIFS(tblClaimCandidates[confidence],tblClaimCandidates[entity_id],[@entity_id],tblClaimCandidates[field_key],[@field_key],tblClaimCandidates[status_final],"PROMOTED"))) | I9: =IFERROR(LOOKUP(2,1/((tblClaimCandidates[entity_id]=[@entity_id])*(tblClaimCandidates[field_key]=[@field_key])*(tblClaimCandidates[status_final]="PROMOTED")),tblClaimCandidates[evidence_id]),"") | J9: =IF([@evidence_id]="","",IFERROR(XLOOKUP([@evidence_id],tblEvidence[evidence_id],tblEvidence[url],""),"")) | K9: =IFERROR(LOOKUP(2,1/((tblClaimCandidates[entity_id]=[@entity_id])*(tblClaimCandidates[field_key]=[@field_key])*(tblClaimCandidates[status_final]="PROMOTED")),tblClaimCandidates[tier]),"") | L9: =IF([@value_text]="UNKNOWN","UNKNOWN","PROMOTED") | M9: =IF([@status]="PROMOTED",TODAY(),"") | N9: =IF([@status]="PROMOTED","evidence_linked","UNKNOWN_or_unverified")
A10: E001 | B10: AcmeRival | C10: SEG_MM | D10: geo_coverage | E10: =LET(v,IFERROR(LOOKUP(2,1/((tblClaimCandidates[entity_id]=[@entity_id])*(tblClaimCandidates[field_key]=[@field_key])*(tblClaimCandidates[status_final]="PROMOTED")),tblClaimCandidates[value_text]),""),IF(v="","UNKNOWN",v)) | F10: =LET(cnt,COUNTIFS(tblClaimCandidates[entity_id],[@entity_id],tblClaimCandidates[field_key],[@field_key],tblClaimCandidates[status_final],"PROMOTED"),IF(cnt=0,NA(),SUMIFS(tblClaimCandidates[value_num],tblClaimCandidates[entity_id],[@entity_id],tblClaimCandidates[field_key],[@field_key],tblClaimCandidates[status_final],"PROMOTED"))) | G10: =IFERROR(XLOOKUP([@field_key],tblFieldDictionary[field_key],tblFieldDictionary[units]),"") | H10: =LET(cnt,COUNTIFS(tblClaimCandidates[entity_id],[@entity_id],tblClaimCandidates[field_key],[@field_key],tblClaimCandidates[status_final],"PROMOTED"),IF(cnt=0,NA(),AVERAGEIFS(tblClaimCandidates[confidence],tblClaimCandidates[entity_id],[@entity_id],tblClaimCandidates[field_key],[@field_key],tblClaimCandidates[status_final],"PROMOTED"))) | I10: =IFERROR(LOOKUP(2,1/((tblClaimCandidates[entity_id]=[@entity_id])*(tblClaimCandidates[field_key]=[@field_key])*(tblClaimCandidates[status_final]="PROMOTED")),tblClaimCandidates[evidence_id]),"") | J10: =IF([@evidence_id]="","",IFERROR(XLOOKUP([@evidence_id],tblEvidence[evidence_id],tblEvidence[url],""),"")) | K10: =IFERROR(LOOKUP(2,1/((tblClaimCandidates[entity_id]=[@entity_id])*(tblClaimCandidates[field_key]=[@field_key])*(tblClaimCandidates[status_final]="PROMOTED")),tblClaimCandidates[tier]),"") | L10: =IF([@value_text]="UNKNOWN","UNKNOWN","PROMOTED") | M10: =IF([@status]="PROMOTED",TODAY(),"") | N10: =IF([@status]="PROMOTED","evidence_linked","UNKNOWN_or_unverified")
A11: E001 | B11: AcmeRival | C11: SEG_MM | D11: practice_size_target | E11: =LET(v,IFERROR(LOOKUP(2,1/((tblClaimCandidates[entity_id]=[@entity_id])*(tblClaimCandidates[field_key]=[@field_key])*(tblClaimCandidates[status_final]="PROMOTED")),tblClaimCandidates[value_text]),""),IF(v="","UNKNOWN",v)) | F11: =LET(cnt,COUNTIFS(tblClaimCandidates[entity_id],[@entity_id],tblClaimCandidates[field_key],[@field_key],tblClaimCandidates[status_final],"PROMOTED"),IF(cnt=0,NA(),SUMIFS(tblClaimCandidates[value_num],tblClaimCandidates[entity_id],[@entity_id],tblClaimCandidates[field_key],[@field_key],tblClaimCandidates[status_final],"PROMOTED"))) | G11: =IFERROR(XLOOKUP([@field_key],tblFieldDictionary[field_key],tblFieldDictionary[units]),"") | H11: =LET(cnt,COUNTIFS(tblClaimCandidates[entity_id],[@entity_id],tblClaimCandidates[field_key],[@field_key],tblClaimCandidates[status_final],"PROMOTED"),IF(cnt=0,NA(),AVERAGEIFS(tblClaimCandidates[confidence],tblClaimCandidates[entity_id],[@entity_id],tblClaimCandidates[field_key],[@field_key],tblClaimCandidates[status_final],"PROMOTED"))) | I11: =IFERROR(LOOKUP(2,1/((tblClaimCandidates[entity_id]=[@entity_id])*(tblClaimCandidates[field_key]=[@field_key])*(tblClaimCandidates[status_final]="PROMOTED")),tblClaimCandidates[evidence_id]),"") | J11: =IF([@evidence_id]="","",IFERROR(XLOOKUP([@evidence_id],tblEvidence[evidence_id],tblEvidence[url],""),"")) | K11: =IFERROR(LOOKUP(2,1/((tblClaimCandidates[entity_id]=[@entity_id])*(tblClaimCandidates[field_key]=[@field_key])*(tblClaimCandidates[status_final]="PROMOTED")),tblClaimCandidates[tier]),"") | L11: =IF([@value_text]="UNKNOWN","UNKNOWN","PROMOTED") | M11: =IF([@status]="PROMOTED",TODAY(),"") | N11: =IF([@status]="PROMOTED","evidence_linked","UNKNOWN_or_unverified")
A12: E002 | B12: EnrollPro | C12: SEG_MM | D12: pricing_acv_mid_market | E12: =LET(v,IFERROR(LOOKUP(2,1/((tblClaimCandidates[entity_id]=[@entity_id])*(tblClaimCandidates[field_key]=[@field_key])*(tblClaimCandidates[status_final]="PROMOTED")),tblClaimCandidates[value_text]),""),IF(v="","UNKNOWN",v)) | F12: =LET(cnt,COUNTIFS(tblClaimCandidates[entity_id],[@entity_id],tblClaimCandidates[field_key],[@field_key],tblClaimCandidates[status_final],"PROMOTED"),IF(cnt=0,NA(),SUMIFS(tblClaimCandidates[value_num],tblClaimCandidates[entity_id],[@entity_id],tblClaimCandidates[field_key],[@field_key],tblClaimCandidates[status_final],"PROMOTED"))) | G12: =IFERROR(XLOOKUP([@field_key],tblFieldDictionary[field_key],tblFieldDictionary[units]),"") | H12: =LET(cnt,COUNTIFS(tblClaimCandidates[entity_id],[@entity_id],tblClaimCandidates[field_key],[@field_key],tblClaimCandidates[status_final],"PROMOTED"),IF(cnt=0,NA(),AVERAGEIFS(tblClaimCandidates[confidence],tblClaimCandidates[entity_id],[@entity_id],tblClaimCandidates[field_key],[@field_key],tblClaimCandidates[status_final],"PROMOTED"))) | I12: =IFERROR(LOOKUP(2,1/((tblClaimCandidates[entity_id]=[@entity_id])*(tblClaimCandidates[field_key]=[@field_key])*(tblClaimCandidates[status_final]="PROMOTED")),tblClaimCandidates[evidence_id]),"") | J12: =IF([@evidence_id]="","",IFERROR(XLOOKUP([@evidence_id],tblEvidence[evidence_id],tblEvidence[url],""),"")) | K12: =IFERROR(LOOKUP(2,1/((tblClaimCandidates[entity_id]=[@entity_id])*(tblClaimCandidates[field_key]=[@field_key])*(tblClaimCandidates[status_final]="PROMOTED")),tblClaimCandidates[tier]),"") | L12: =IF([@value_text]="UNKNOWN","UNKNOWN","PROMOTED") | M12: =IF([@status]="PROMOTED",TODAY(),"") | N12: =IF([@status]="PROMOTED","evidence_linked","UNKNOWN_or_unverified")
A13: E002 | B13: EnrollPro | C13: SEG_MM | D13: arr_estimate | E13: =LET(v,IFERROR(LOOKUP(2,1/((tblClaimCandidates[entity_id]=[@entity_id])*(tblClaimCandidates[field_key]=[@field_key])*(tblClaimCandidates[status_final]="PROMOTED")),tblClaimCandidates[value_text]),""),IF(v="","UNKNOWN",v)) | F13: =LET(cnt,COUNTIFS(tblClaimCandidates[entity_id],[@entity_id],tblClaimCandidates[field_key],[@field_key],tblClaimCandidates[status_final],"PROMOTED"),IF(cnt=0,NA(),SUMIFS(tblClaimCandidates[value_num],tblClaimCandidates[entity_id],[@entity_id],tblClaimCandidates[field_key],[@field_key],tblClaimCandidates[status_final],"PROMOTED"))) | G13: =IFERROR(XLOOKUP([@field_key],tblFieldDictionary[field_key],tblFieldDictionary[units]),"") | H13: =LET(cnt,COUNTIFS(tblClaimCandidates[entity_id],[@entity_id],tblClaimCandidates[field_key],[@field_key],tblClaimCandidates[status_final],"PROMOTED"),IF(cnt=0,NA(),AVERAGEIFS(tblClaimCandidates[confidence],tblClaimCandidates[entity_id],[@entity_id],tblClaimCandidates[field_key],[@field_key],tblClaimCandidates[status_final],"PROMOTED"))) | I13: =IFERROR(LOOKUP(2,1/((tblClaimCandidates[entity_id]=[@entity_id])*(tblClaimCandidates[field_key]=[@field_key])*(tblClaimCandidates[status_final]="PROMOTED")),tblClaimCandidates[evidence_id]),"") | J13: =IF([@evidence_id]="","",IFERROR(XLOOKUP([@evidence_id],tblEvidence[evidence_id],tblEvidence[url],""),"")) | K13: =IFERROR(LOOKUP(2,1/((tblClaimCandidates[entity_id]=[@entity_id])*(tblClaimCandidates[field_key]=[@field_key])*(tblClaimCandidates[status_final]="PROMOTED")),tblClaimCandidates[tier]),"") | L13: =IF([@value_text]="UNKNOWN","UNKNOWN","PROMOTED") | M13: =IF([@status]="PROMOTED",TODAY(),"") | N13: =IF([@status]="PROMOTED","evidence_linked","UNKNOWN_or_unverified")
A14: E002 | B14: EnrollPro | C14: SEG_MM | D14: contract_terms | E14: =LET(v,IFERROR(LOOKUP(2,1/((tblClaimCandidates[entity_id]=[@entity_id])*(tblClaimCandidates[field_key]=[@field_key])*(tblClaimCandidates[status_final]="PROMOTED")),tblClaimCandidates[value_text]),""),IF(v="","UNKNOWN",v)) | F14: =LET(cnt,COUNTIFS(tblClaimCandidates[entity_id],[@entity_id],tblClaimCandidates[field_key],[@field_key],tblClaimCandidates[status_final],"PROMOTED"),IF(cnt=0,NA(),SUMIFS(tblClaimCandidates[value_num],tblClaimCandidates[entity_id],[@entity_id],tblClaimCandidates[field_key],[@field_key],tblClaimCandidates[status_final],"PROMOTED"))) | G14: =IFERROR(XLOOKUP([@field_key],tblFieldDictionary[field_key],tblFieldDictionary[units]),"") | H14: =LET(cnt,COUNTIFS(tblClaimCandidates[entity_id],[@entity_id],tblClaimCandidates[field_key],[@field_key],tblClaimCandidates[status_final],"PROMOTED"),IF(cnt=0,NA(),AVERAGEIFS(tblClaimCandidates[confidence],tblClaimCandidates[entity_id],[@entity_id],tblClaimCandidates[field_key],[@field_key],tblClaimCandidates[status_final],"PROMOTED"))) | I14: =IFERROR(LOOKUP(2,1/((tblClaimCandidates[entity_id]=[@entity_id])*(tblClaimCandidates[field_key]=[@field_key])*(tblClaimCandidates[status_final]="PROMOTED")),tblClaimCandidates[evidence_id]),"") | J14: =IF([@evidence_id]="","",IFERROR(XLOOKUP([@evidence_id],tblEvidence[evidence_id],tblEvidence[url],""),"")) | K14: =IFERROR(LOOKUP(2,1/((tblClaimCandidates[entity_id]=[@entity_id])*(tblClaimCandidates[field_key]=[@field_key])*(tblClaimCandidates[status_final]="PROMOTED")),tblClaimCandidates[tier]),"") | L14: =IF([@value_text]="UNKNOWN","UNKNOWN","PROMOTED") | M14: =IF([@status]="PROMOTED",TODAY(),"") | N14: =IF([@status]="PROMOTED","evidence_linked","UNKNOWN_or_unverified")
A15: E002 | B15: EnrollPro | C15: SEG_MM | D15: features | E15: =LET(v,IFERROR(LOOKUP(2,1/((tblClaimCandidates[entity_id]=[@entity_id])*(tblClaimCandidates[field_key]=[@field_key])*(tblClaimCandidates[status_final]="PROMOTED")),tblClaimCandidates[value_text]),""),IF(v="","UNKNOWN",v)) | F15: =LET(cnt,COUNTIFS(tblClaimCandidates[entity_id],[@entity_id],tblClaimCandidates[field_key],[@field_key],tblClaimCandidates[status_final],"PROMOTED"),IF(cnt=0,NA(),SUMIFS(tblClaimCandidates[value_num],tblClaimCandidates[entity_id],[@entity_id],tblClaimCandidates[field_key],[@field_key],tblClaimCandidates[status_final],"PROMOTED"))) | G15: =IFERROR(XLOOKUP([@field_key],tblFieldDictionary[field_key],tblFieldDictionary[units]),"") | H15: =LET(cnt,COUNTIFS(tblClaimCandidates[entity_id],[@entity_id],tblClaimCandidates[field_key],[@field_key],tblClaimCandidates[status_final],"PROMOTED"),IF(cnt=0,NA(),AVERAGEIFS(tblClaimCandidates[confidence],tblClaimCandidates[entity_id],[@entity_id],tblClaimCandidates[field_key],[@field_key],tblClaimCandidates[status_final],"PROMOTED"))) | I15: =IFERROR(LOOKUP(2,1/((tblClaimCandidates[entity_id]=[@entity_id])*(tblClaimCandidates[field_key]=[@field_key])*(tblClaimCandidates[status_final]="PROMOTED")),tblClaimCandidates[evidence_id]),"") | J15: =IF([@evidence_id]="","",IFERROR(XLOOKUP([@evidence_id],tblEvidence[evidence_id],tblEvidence[url],""),"")) | K15: =IFERROR(LOOKUP(2,1/((tblClaimCandidates[entity_id]=[@entity_id])*(tblClaimCandidates[field_key]=[@field_key])*(tblClaimCandidates[status_final]="PROMOTED")),tblClaimCandidates[tier]),"") | L15: =IF([@value_text]="UNKNOWN","UNKNOWN","PROMOTED") | M15: =IF([@status]="PROMOTED",TODAY(),"") | N15: =IF([@status]="PROMOTED","evidence_linked","UNKNOWN_or_unverified")
A16: E002 | B16: EnrollPro | C16: SEG_MM | D16: funding_round | E16: =LET(v,IFERROR(LOOKUP(2,1/((tblClaimCandidates[entity_id]=[@entity_id])*(tblClaimCandidates[field_key]=[@field_key])*(tblClaimCandidates[status_final]="PROMOTED")),tblClaimCandidates[value_text]),""),IF(v="","UNKNOWN",v)) | F16: =LET(cnt,COUNTIFS(tblClaimCandidates[entity_id],[@entity_id],tblClaimCandidates[field_key],[@field_key],tblClaimCandidates[status_final],"PROMOTED"),IF(cnt=0,NA(),SUMIFS(tblClaimCandidates[value_num],tblClaimCandidates[entity_id],[@entity_id],tblClaimCandidates[field_key],[@field_key],tblClaimCandidates[status_final],"PROMOTED"))) | G16: =IFERROR(XLOOKUP([@field_key],tblFieldDictionary[field_key],tblFieldDictionary[units]),"") | H16: =LET(cnt,COUNTIFS(tblClaimCandidates[entity_id],[@entity_id],tblClaimCandidates[field_key],[@field_key],tblClaimCandidates[status_final],"PROMOTED"),IF(cnt=0,NA(),AVERAGEIFS(tblClaimCandidates[confidence],tblClaimCandidates[entity_id],[@entity_id],tblClaimCandidates[field_key],[@field_key],tblClaimCandidates[status_final],"PROMOTED"))) | I16: =IFERROR(LOOKUP(2,1/((tblClaimCandidates[entity_id]=[@entity_id])*(tblClaimCandidates[field_key]=[@field_key])*(tblClaimCandidates[status_final]="PROMOTED")),tblClaimCandidates[evidence_id]),"") | J16: =IF([@evidence_id]="","",IFERROR(XLOOKUP([@evidence_id],tblEvidence[evidence_id],tblEvidence[url],""),"")) | K16: =IFERROR(LOOKUP(2,1/((tblClaimCandidates[entity_id]=[@entity_id])*(tblClaimCandidates[field_key]=[@field_key])*(tblClaimCandidates[status_final]="PROMOTED")),tblClaimCandidates[tier]),"") | L16: =IF([@value_text]="UNKNOWN","UNKNOWN","PROMOTED") | M16: =IF([@status]="PROMOTED",TODAY(),"") | N16: =IF([@status]="PROMOTED","evidence_linked","UNKNOWN_or_unverified")
... A46: E006 | B46: MidMarketMedTech | C46: SEG_MM | D46: practice_size_target | E46: =LET(v,IFERROR(LOOKUP(2,1/((tblClaimCandidates[entity_id]=[@entity_id])*(tblClaimCandidates[field_key]=[@field_key])*(tblClaimCandidates[status_final]="PROMOTED")),tblClaimCandidates[value_text]),""),IF(v="","UNKNOWN",v)) | F46: =LET(cnt,COUNTIFS(tblClaimCandidates[entity_id],[@entity_id],tblClaimCandidates[field_key],[@field_key],tblClaimCandidates[status_final],"PROMOTED"),IF(cnt=0,NA(),SUMIFS(tblClaimCandidates[value_num],tblClaimCandidates[entity_id],[@entity_id],tblClaimCandidates[field_key],[@field_key],tblClaimCandidates[status_final],"PROMOTED"))) | G46: =IFERROR(XLOOKUP([@field_key],tblFieldDictionary[field_key],tblFieldDictionary[units]),"") | H46: =LET(cnt,COUNTIFS(tblClaimCandidates[entity_id],[@entity_id],tblClaimCandidates[field_key],[@field_key],tblClaimCandidates[status_final],"PROMOTED"),IF(cnt=0,NA(),AVERAGEIFS(tblClaimCandidates[confidence],tblClaimCandidates[entity_id],[@entity_id],tblClaimCandidates[field_key],[@field_key],tblClaimCandidates[status_final],"PROMOTED"))) | I46: =IFERROR(LOOKUP(2,1/((tblClaimCandidates[entity_id]=[@entity_id])*(tblClaimCandidates[field_key]=[@field_key])*(tblClaimCandidates[status_final]="PROMOTED")),tblClaimCandidates[evidence_id]),"") | J46: =IF([@evidence_id]="","",IFERROR(XLOOKUP([@evidence_id],tblEvidence[evidence_id],tblEvidence[url],""),"")) | K46: =IFERROR(LOOKUP(2,1/((tblClaimCandidates[entity_id]=[@entity_id])*(tblClaimCandidates[field_key]=[@field_key])*(tblClaimCandidates[status_final]="PROMOTED")),tblClaimCandidates[tier]),"") | L46: =IF([@value_text]="UNKNOWN","UNKNOWN","PROMOTED") | M46: =IF([@status]="PROMOTED",TODAY(),"") | N46: =IF([@status]="PROMOTED","evidence_linked","UNKNOWN_or_unverified")

Sheet Metrics
A1: Metrics (Derived; Formula-Driven)
A2: All figures are derived from Claims_Current (which must be evidence-backed). UNKNOWN propagates to Review Queue and fail-closed flags.
A4: Global Drivers
A5: Median ACV (USD/year) | B5: =IFERROR(MEDIAN(FILTER($G$8:$G$57,ISNUMBER($G$8:$G$57))),"") | D5: Evidence Freshness Threshold (days) | E5: =Config!$B$9 | G5: Min Coverage (fail-closed) | H5: =Config!$B$10
A7: entity_id | B7: canonical_name | C7: known_claims | D7: unknown_claims | E7: coverage_pct | F7: avg_conf | G7: acv_usd | H7: acv_band | I7: features_text | J7: feature_count | K7: segment_fit | L7: funding_present | M7: threat_score | N7: opportunity_score | O7: flags | P7: segment_id | Q7: vertical | R7: in_scope | AA7: competitors_in_scope
A8: =IF(Input!$A$7="","",Input!$A$7) | B8: =IFERROR(XLOOKUP([@entity_id],tblEntities[entity_id],tblEntities[canonical_name]),"") | C8: =IF([@entity_id]="","",COUNTIFS(tblClaimsCurrent[entity_id],[@entity_id],tblClaimsCurrent[status],"PROMOTED")) | D8: =IF([@entity_id]="","",COUNTIFS(tblClaimsCurrent[entity_id],[@entity_id],tblClaimsCurrent[status],"UNKNOWN")) | E8: =LET(t,[@known_claims]+[@unknown_claims],IF(t=0,NA(),[@known_claims]/t)) | F8: =LET(cnt,COUNTIFS(tblClaimsCurrent[entity_id],[@entity_id],tblClaimsCurrent[status],"PROMOTED"),IF(cnt=0,NA(),AVERAGEIFS(tblClaimsCurrent[confidence],tblClaimsCurrent[entity_id],[@entity_id],tblClaimsCurrent[status],"PROMOTED"))) | G8: =LET(cnt,COUNTIFS(tblClaimsCurrent[entity_id],[@entity_id],tblClaimsCurrent[field_key],"pricing_acv_mid_market",tblClaimsCurrent[status],"PROMOTED"),IF(cnt=0,NA(),SUMIFS(tblClaimsCurrent[value_num],tblClaimsCurrent[entity_id],[@entity_id],tblClaimsCurrent[field_key],"pricing_acv_mid_market",tblClaimsCurrent[status],"PROMOTED"))) | H8: =IF(OR(NOT(ISNUMBER([@acv_usd])),$B$5=""),"UNKNOWN",IF([@acv_usd]<=($B$5*0.85),"Low",IF([@acv_usd]>=($B$5*1.15),"High","Mid"))) | I8: =LET(v,IFERROR(LOOKUP(2,1/((tblClaimsCurrent[entity_id]=[@entity_id])*(tblClaimsCurrent[field_key]="features")*(tblClaimsCurrent[status]="PROMOTED")),tblClaimsCurrent[value_text]),"UNKNOWN"),IF(v="","UNKNOWN",v)) | J8: =IF(OR([@features_text]="UNKNOWN",[@features_text]=""),NA(),1+LEN([@features_text])-LEN(SUBSTITUTE([@features_text],";",""))) | K8: =IF([@segment_id]="",NA(),IF([@segment_id]="SEG_MM",1,0)) | L8: =IF([@entity_id]="","",IF(COUNTIFS(tblClaimsCurrent[entity_id],[@entity_id],tblClaimsCurrent[field_key],"funding_round",tblClaimsCurrent[status],"PROMOTED")>0,1,0)) | M8: =IF(OR([@in_scope]=FALSE,ISNA([@coverage_pct]),ISNA([@feature_count]),ISNA([@segment_fit]),[@acv_band]="UNKNOWN"),NA(),MIN(1,Config!$B$14*MIN(1,[@feature_count]/10)+Config!$B$15*IF([@acv_band]="Low",1,IF([@acv_band]="Mid",0.5,0))+Config!$B$16*[@segment_fit]+Config!$B$17*[@funding_present])) | N8: =IF(OR([@in_scope]=FALSE,ISNA([@coverage_pct]),ISNA([@feature_count]),ISNA([@segment_fit])),NA(),MIN(1,Config!$B$18*(1-MIN(1,[@feature_count]/10))+Config!$B$19*(1-[@segment_fit])+Config!$B$20*(1-[@coverage_pct]))) | O8: =IF([@in_scope]=FALSE,"OUT_OF_SCOPE",IF(ISNA([@coverage_pct]),"UNKNOWN",IF([@coverage_pct]<Config!$B$10,"FAIL_CLOSED_LOW_COVERAGE","OK"))) | P8: =IFERROR(XLOOKUP([@entity_id],tblEntities[entity_id],tblEntities[segment_id]),"") | Q8: =IFERROR(XLOOKUP([@entity_id],tblEntities[entity_id],tblEntities[vertical]),"") | R8: =AND([@segment_id]=Dashboard!$E$2,IF(Dashboard!$E$3="All",TRUE,[@vertical]=Dashboard!$E$3)) | AA8: =LET(seg,Dashboard!$E$2,vert,Dashboard!$E$3,n,FILTER(tblEntities[canonical_name],(tblEntities[segment_id]=seg)*IF(vert="All",1,(tblEntities[vertical]=vert))*(tblEntities[status]<>"ARCHIVED")),IFERROR(SORT(n),""))
A9: =IF(Input!$A$8="","",Input!$A$8) | B9: =IFERROR(XLOOKUP([@entity_id],tblEntities[entity_id],tblEntities[canonical_name]),"") | C9: =IF([@entity_id]="","",COUNTIFS(tblClaimsCurrent[entity_id],[@entity_id],tblClaimsCurrent[status],"PROMOTED")) | D9: =IF([@entity_id]="","",COUNTIFS(tblClaimsCurrent[entity_id],[@entity_id],tblClaimsCurrent[status],"UNKNOWN")) | E9: =LET(t,[@known_claims]+[@unknown_claims],IF(t=0,NA(),[@known_claims]/t)) | F9: =LET(cnt,COUNTIFS(tblClaimsCurrent[entity_id],[@entity_id],tblClaimsCurrent[status],"PROMOTED"),IF(cnt=0,NA(),AVERAGEIFS(tblClaimsCurrent[confidence],tblClaimsCurrent[entity_id],[@entity_id],tblClaimsCurrent[status],"PROMOTED"))) | G9: =LET(cnt,COUNTIFS(tblClaimsCurrent[entity_id],[@entity_id],tblClaimsCurrent[field_key],"pricing_acv_mid_market",tblClaimsCurrent[status],"PROMOTED"),IF(cnt=0,NA(),SUMIFS(tblClaimsCurrent[value_num],tblClaimsCurrent[entity_id],[@entity_id],tblClaimsCurrent[field_key],"pricing_acv_mid_market",tblClaimsCurrent[status],"PROMOTED"))) | H9: =IF(OR(NOT(ISNUMBER([@acv_usd])),$B$5=""),"UNKNOWN",IF([@acv_usd]<=($B$5*0.85),"Low",IF([@acv_usd]>=($B$5*1.15),"High","Mid"))) | I9: =LET(v,IFERROR(LOOKUP(2,1/((tblClaimsCurrent[entity_id]=[@entity_id])*(tblClaimsCurrent[field_key]="features")*(tblClaimsCurrent[status]="PROMOTED")),tblClaimsCurrent[value_text]),"UNKNOWN"),IF(v="","UNKNOWN",v)) | J9: =IF(OR([@features_text]="UNKNOWN",[@features_text]=""),NA(),1+LEN([@features_text])-LEN(SUBSTITUTE([@features_text],";",""))) | K9: =IF([@segment_id]="",NA(),IF([@segment_id]="SEG_MM",1,0)) | L9: =IF([@entity_id]="","",IF(COUNTIFS(tblClaimsCurrent[entity_id],[@entity_id],tblClaimsCurrent[field_key],"funding_round",tblClaimsCurrent[status],"PROMOTED")>0,1,0)) | M9: =IF(OR([@in_scope]=FALSE,ISNA([@coverage_pct]),ISNA([@feature_count]),ISNA([@segment_fit]),[@acv_band]="UNKNOWN"),NA(),MIN(1,Config!$B$14*MIN(1,[@feature_count]/10)+Config!$B$15*IF([@acv_band]="Low",1,IF([@acv_band]="Mid",0.5,0))+Config!$B$16*[@segment_fit]+Config!$B$17*[@funding_present])) | N9: =IF(OR([@in_scope]=FALSE,ISNA([@coverage_pct]),ISNA([@feature_count]),ISNA([@segment_fit])),NA(),MIN(1,Config!$B$18*(1-MIN(1,[@feature_count]/10))+Config!$B$19*(1-[@segment_fit])+Config!$B$20*(1-[@coverage_pct]))) | O9: =IF([@in_scope]=FALSE,"OUT_OF_SCOPE",IF(ISNA([@coverage_pct]),"UNKNOWN",IF([@coverage_pct]<Config!$B$10,"FAIL_CLOSED_LOW_COVERAGE","OK"))) | P9: =IFERROR(XLOOKUP([@entity_id],tblEntities[entity_id],tblEntities[segment_id]),"") | Q9: =IFERROR(XLOOKUP([@entity_id],tblEntities[entity_id],tblEntities[vertical]),"") | R9: =AND([@segment_id]=Dashboard!$E$2,IF(Dashboard!$E$3="All",TRUE,[@vertical]=Dashboard!$E$3))
A10: =IF(Input!$A$9="","",Input!$A$9) | B10: =IFERROR(XLOOKUP([@entity_id],tblEntities[entity_id],tblEntities[canonical_name]),"") | C10: =IF([@entity_id]="","",COUNTIFS(tblClaimsCurrent[entity_id],[@entity_id],tblClaimsCurrent[status],"PROMOTED")) | D10: =IF([@entity_id]="","",COUNTIFS(tblClaimsCurrent[entity_id],[@entity_id],tblClaimsCurrent[status],"UNKNOWN")) | E10: =LET(t,[@known_claims]+[@unknown_claims],IF(t=0,NA(),[@known_claims]/t)) | F10: =LET(cnt,COUNTIFS(tblClaimsCurrent[entity_id],[@entity_id],tblClaimsCurrent[status],"PROMOTED"),IF(cnt=0,NA(),AVERAGEIFS(tblClaimsCurrent[confidence],tblClaimsCurrent[entity_id],[@entity_id],tblClaimsCurrent[status],"PROMOTED"))) | G10: =LET(cnt,COUNTIFS(tblClaimsCurrent[entity_id],[@entity_id],tblClaimsCurrent[field_key],"pricing_acv_mid_market",tblClaimsCurrent[status],"PROMOTED"),IF(cnt=0,NA(),SUMIFS(tblClaimsCurrent[value_num],tblClaimsCurrent[entity_id],[@entity_id],tblClaimsCurrent[field_key],"pricing_acv_mid_market",tblClaimsCurrent[status],"PROMOTED"))) | H10: =IF(OR(NOT(ISNUMBER([@acv_usd])),$B$5=""),"UNKNOWN",IF([@acv_usd]<=($B$5*0.85),"Low",IF([@acv_usd]>=($B$5*1.15),"High","Mid"))) | I10: =LET(v,IFERROR(LOOKUP(2,1/((tblClaimsCurrent[entity_id]=[@entity_id])*(tblClaimsCurrent[field_key]="features")*(tblClaimsCurrent[status]="PROMOTED")),tblClaimsCurrent[value_text]),"UNKNOWN"),IF(v="","UNKNOWN",v)) | J10: =IF(OR([@features_text]="UNKNOWN",[@features_text]=""),NA(),1+LEN([@features_text])-LEN(SUBSTITUTE([@features_text],";",""))) | K10: =IF([@segment_id]="",NA(),IF([@segment_id]="SEG_MM",1,0)) | L10: =IF([@entity_id]="","",IF(COUNTIFS(tblClaimsCurrent[entity_id],[@entity_id],tblClaimsCurrent[field_key],"funding_round",tblClaimsCurrent[status],"PROMOTED")>0,1,0)) | M10: =IF(OR([@in_scope]=FALSE,ISNA([@coverage_pct]),ISNA([@feature_count]),ISNA([@segment_fit]),[@acv_band]="UNKNOWN"),NA(),MIN(1,Config!$B$14*MIN(1,[@feature_count]/10)+Config!$B$15*IF([@acv_band]="Low",1,IF([@acv_band]="Mid",0.5,0))+Config!$B$16*[@segment_fit]+Config!$B$17*[@funding_present])) | N10: =IF(OR([@in_scope]=FALSE,ISNA([@coverage_pct]),ISNA([@feature_count]),ISNA([@segment_fit])),NA(),MIN(1,Config!$B$18*(1-MIN(1,[@feature_count]/10))+Config!$B$19*(1-[@segment_fit])+Config!$B$20*(1-[@coverage_pct]))) | O10: =IF([@in_scope]=FALSE,"OUT_OF_SCOPE",IF(ISNA([@coverage_pct]),"UNKNOWN",IF([@coverage_pct]<Config!$B$10,"FAIL_CLOSED_LOW_COVERAGE","OK"))) | P10: =IFERROR(XLOOKUP([@entity_id],tblEntities[entity_id],tblEntities[segment_id]),"") | Q10: =IFERROR(XLOOKUP([@entity_id],tblEntities[entity_id],tblEntities[vertical]),"") | R10: =AND([@segment_id]=Dashboard!$E$2,IF(Dashboard!$E$3="All",TRUE,[@vertical]=Dashboard!$E$3))
A11: =IF(Input!$A$10="","",Input!$A$10) | B11: =IFERROR(XLOOKUP([@entity_id],tblEntities[entity_id],tblEntities[canonical_name]),"") | C11: =IF([@entity_id]="","",COUNTIFS(tblClaimsCurrent[entity_id],[@entity_id],tblClaimsCurrent[status],"PROMOTED")) | D11: =IF([@entity_id]="","",COUNTIFS(tblClaimsCurrent[entity_id],[@entity_id],tblClaimsCurrent[status],"UNKNOWN")) | E11: =LET(t,[@known_claims]+[@unknown_claims],IF(t=0,NA(),[@known_claims]/t)) | F11: =LET(cnt,COUNTIFS(tblClaimsCurrent[entity_id],[@entity_id],tblClaimsCurrent[status],"PROMOTED"),IF(cnt=0,NA(),AVERAGEIFS(tblClaimsCurrent[confidence],tblClaimsCurrent[entity_id],[@entity_id],tblClaimsCurrent[status],"PROMOTED"))) | G11: =LET(cnt,COUNTIFS(tblClaimsCurrent[entity_id],[@entity_id],tblClaimsCurrent[field_key],"pricing_acv_mid_market",tblClaimsCurrent[status],"PROMOTED"),IF(cnt=0,NA(),SUMIFS(tblClaimsCurrent[value_num],tblClaimsCurrent[entity_id],[@entity_id],tblClaimsCurrent[field_key],"pricing_acv_mid_market",tblClaimsCurrent[status],"PROMOTED"))) | H11: =IF(OR(NOT(ISNUMBER([@acv_usd])),$B$5=""),"UNKNOWN",IF([@acv_usd]<=($B$5*0.85),"Low",IF([@acv_usd]>=($B$5*1.15),"High","Mid"))) | I11: =LET(v,IFERROR(LOOKUP(2,1/((tblClaimsCurrent[entity_id]=[@entity_id])*(tblClaimsCurrent[field_key]="features")*(tblClaimsCurrent[status]="PROMOTED")),tblClaimsCurrent[value_text]),"UNKNOWN"),IF(v="","UNKNOWN",v)) | J11: =IF(OR([@features_text]="UNKNOWN",[@features_text]=""),NA(),1+LEN([@features_text])-LEN(SUBSTITUTE([@features_text],";",""))) | K11: =IF([@segment_id]="",NA(),IF([@segment_id]="SEG_MM",1,0)) | L11: =IF([@entity_id]="","",IF(COUNTIFS(tblClaimsCurrent[entity_id],[@entity_id],tblClaimsCurrent[field_key],"funding_round",tblClaimsCurrent[status],"PROMOTED")>0,1,0)) | M11: =IF(OR([@in_scope]=FALSE,ISNA([@coverage_pct]),ISNA([@feature_count]),ISNA([@segment_fit]),[@acv_band]="UNKNOWN"),NA(),MIN(1,Config!$B$14*MIN(1,[@feature_count]/10)+Config!$B$15*IF([@acv_band]="Low",1,IF([@acv_band]="Mid",0.5,0))+Config!$B$16*[@segment_fit]+Config!$B$17*[@funding_present])) | N11: =IF(OR([@in_scope]=FALSE,ISNA([@coverage_pct]),ISNA([@feature_count]),ISNA([@segment_fit])),NA(),MIN(1,Config!$B$18*(1-MIN(1,[@feature_count]/10))+Config!$B$19*(1-[@segment_fit])+Config!$B$20*(1-[@coverage_pct]))) | O11: =IF([@in_scope]=FALSE,"OUT_OF_SCOPE",IF(ISNA([@coverage_pct]),"UNKNOWN",IF([@coverage_pct]<Config!$B$10,"FAIL_CLOSED_LOW_COVERAGE","OK"))) | P11: =IFERROR(XLOOKUP([@entity_id],tblEntities[entity_id],tblEntities[segment_id]),"") | Q11: =IFERROR(XLOOKUP([@entity_id],tblEntities[entity_id],tblEntities[vertical]),"") | R11: =AND([@segment_id]=Dashboard!$E$2,IF(Dashboard!$E$3="All",TRUE,[@vertical]=Dashboard!$E$3))
A12: =IF(Input!$A$11="","",Input!$A$11) | B12: =IFERROR(XLOOKUP([@entity_id],tblEntities[entity_id],tblEntities[canonical_name]),"") | C12: =IF([@entity_id]="","",COUNTIFS(tblClaimsCurrent[entity_id],[@entity_id],tblClaimsCurrent[status],"PROMOTED")) | D12: =IF([@entity_id]="","",COUNTIFS(tblClaimsCurrent[entity_id],[@entity_id],tblClaimsCurrent[status],"UNKNOWN")) | E12: =LET(t,[@known_claims]+[@unknown_claims],IF(t=0,NA(),[@known_claims]/t)) | F12: =LET(cnt,COUNTIFS(tblClaimsCurrent[entity_id],[@entity_id],tblClaimsCurrent[status],"PROMOTED"),IF(cnt=0,NA(),AVERAGEIFS(tblClaimsCurrent[confidence],tblClaimsCurrent[entity_id],[@entity_id],tblClaimsCurrent[status],"PROMOTED"))) | G12: =LET(cnt,COUNTIFS(tblClaimsCurrent[entity_id],[@entity_id],tblClaimsCurrent[field_key],"pricing_acv_mid_market",tblClaimsCurrent[status],"PROMOTED"),IF(cnt=0,NA(),SUMIFS(tblClaimsCurrent[value_num],tblClaimsCurrent[entity_id],[@entity_id],tblClaimsCurrent[field_key],"pricing_acv_mid_market",tblClaimsCurrent[status],"PROMOTED"))) | H12: =IF(OR(NOT(ISNUMBER([@acv_usd])),$B$5=""),"UNKNOWN",IF([@acv_usd]<=($B$5*0.85),"Low",IF([@acv_usd]>=($B$5*1.15),"High","Mid"))) | I12: =LET(v,IFERROR(LOOKUP(2,1/((tblClaimsCurrent[entity_id]=[@entity_id])*(tblClaimsCurrent[field_key]="features")*(tblClaimsCurrent[status]="PROMOTED")),tblClaimsCurrent[value_text]),"UNKNOWN"),IF(v="","UNKNOWN",v)) | J12: =IF(OR([@features_text]="UNKNOWN",[@features_text]=""),NA(),1+LEN([@features_text])-LEN(SUBSTITUTE([@features_text],";",""))) | K12: =IF([@segment_id]="",NA(),IF([@segment_id]="SEG_MM",1,0)) | L12: =IF([@entity_id]="","",IF(COUNTIFS(tblClaimsCurrent[entity_id],[@entity_id],tblClaimsCurrent[field_key],"funding_round",tblClaimsCurrent[status],"PROMOTED")>0,1,0)) | M12: =IF(OR([@in_scope]=FALSE,ISNA([@coverage_pct]),ISNA([@feature_count]),ISNA([@segment_fit]),[@acv_band]="UNKNOWN"),NA(),MIN(1,Config!$B$14*MIN(1,[@feature_count]/10)+Config!$B$15*IF([@acv_band]="Low",1,IF([@acv_band]="Mid",0.5,0))+Config!$B$16*[@segment_fit]+Config!$B$17*[@funding_present])) | N12: =IF(OR([@in_scope]=FALSE,ISNA([@coverage_pct]),ISNA([@feature_count]),ISNA([@segment_fit])),NA(),MIN(1,Config!$B$18*(1-MIN(1,[@feature_count]/10))+Config!$B$19*(1-[@segment_fit])+Config!$B$20*(1-[@coverage_pct]))) | O12: =IF([@in_scope]=FALSE,"OUT_OF_SCOPE",IF(ISNA([@coverage_pct]),"UNKNOWN",IF([@coverage_pct]<Config!$B$10,"FAIL_CLOSED_LOW_COVERAGE","OK"))) | P12: =IFERROR(XLOOKUP([@entity_id],tblEntities[entity_id],tblEntities[segment_id]),"") | Q12: =IFERROR(XLOOKUP([@entity_id],tblEntities[entity_id],tblEntities[vertical]),"") | R12: =AND([@segment_id]=Dashboard!$E$2,IF(Dashboard!$E$3="All",TRUE,[@vertical]=Dashboard!$E$3))
A13: =IF(Input!$A$12="","",Input!$A$12) | B13: =IFERROR(XLOOKUP([@entity_id],tblEntities[entity_id],tblEntities[canonical_name]),"") | C13: =IF([@entity_id]="","",COUNTIFS(tblClaimsCurrent[entity_id],[@entity_id],tblClaimsCurrent[status],"PROMOTED")) | D13: =IF([@entity_id]="","",COUNTIFS(tblClaimsCurrent[entity_id],[@entity_id],tblClaimsCurrent[status],"UNKNOWN")) | E13: =LET(t,[@known_claims]+[@unknown_claims],IF(t=0,NA(),[@known_claims]/t)) | F13: =LET(cnt,COUNTIFS(tblClaimsCurrent[entity_id],[@entity_id],tblClaimsCurrent[status],"PROMOTED"),IF(cnt=0,NA(),AVERAGEIFS(tblClaimsCurrent[confidence],tblClaimsCurrent[entity_id],[@entity_id],tblClaimsCurrent[status],"PROMOTED"))) | G13: =LET(cnt,COUNTIFS(tblClaimsCurrent[entity_id],[@entity_id],tblClaimsCurrent[field_key],"pricing_acv_mid_market",tblClaimsCurrent[status],"PROMOTED"),IF(cnt=0,NA(),SUMIFS(tblClaimsCurrent[value_num],tblClaimsCurrent[entity_id],[@entity_id],tblClaimsCurrent[field_key],"pricing_acv_mid_market",tblClaimsCurrent[status],"PROMOTED"))) | H13: =IF(OR(NOT(ISNUMBER([@acv_usd])),$B$5=""),"UNKNOWN",IF([@acv_usd]<=($B$5*0.85),"Low",IF([@acv_usd]>=($B$5*1.15),"High","Mid"))) | I13: =LET(v,IFERROR(LOOKUP(2,1/((tblClaimsCurrent[entity_id]=[@entity_id])*(tblClaimsCurrent[field_key]="features")*(tblClaimsCurrent[status]="PROMOTED")),tblClaimsCurrent[value_text]),"UNKNOWN"),IF(v="","UNKNOWN",v)) | J13: =IF(OR([@features_text]="UNKNOWN",[@features_text]=""),NA(),1+LEN([@features_text])-LEN(SUBSTITUTE([@features_text],";",""))) | K13: =IF([@segment_id]="",NA(),IF([@segment_id]="SEG_MM",1,0)) | L13: =IF([@entity_id]="","",IF(COUNTIFS(tblClaimsCurrent[entity_id],[@entity_id],tblClaimsCurrent[field_key],"funding_round",tblClaimsCurrent[status],"PROMOTED")>0,1,0)) | M13: =IF(OR([@in_scope]=FALSE,ISNA([@coverage_pct]),ISNA([@feature_count]),ISNA([@segment_fit]),[@acv_band]="UNKNOWN"),NA(),MIN(1,Config!$B$14*MIN(1,[@feature_count]/10)+Config!$B$15*IF([@acv_band]="Low",1,IF([@acv_band]="Mid",0.5,0))+Config!$B$16*[@segment_fit]+Config!$B$17*[@funding_present])) | N13: =IF(OR([@in_scope]=FALSE,ISNA([@coverage_pct]),ISNA([@feature_count]),ISNA([@segment_fit])),NA(),MIN(1,Config!$B$18*(1-MIN(1,[@feature_count]/10))+Config!$B$19*(1-[@segment_fit])+Config!$B$20*(1-[@coverage_pct]))) | O13: =IF([@in_scope]=FALSE,"OUT_OF_SCOPE",IF(ISNA([@coverage_pct]),"UNKNOWN",IF([@coverage_pct]<Config!$B$10,"FAIL_CLOSED_LOW_COVERAGE","OK"))) | P13: =IFERROR(XLOOKUP([@entity_id],tblEntities[entity_id],tblEntities[segment_id]),"") | Q13: =IFERROR(XLOOKUP([@entity_id],tblEntities[entity_id],tblEntities[vertical]),"") | R13: =AND([@segment_id]=Dashboard!$E$2,IF(Dashboard!$E$3="All",TRUE,[@vertical]=Dashboard!$E$3))
A14: =IF(Input!$A$13="","",Input!$A$13) | B14: =IFERROR(XLOOKUP([@entity_id],tblEntities[entity_id],tblEntities[canonical_name]),"") | C14: =IF([@entity_id]="","",COUNTIFS(tblClaimsCurrent[entity_id],[@entity_id],tblClaimsCurrent[status],"PROMOTED")) | D14: =IF([@entity_id]="","",COUNTIFS(tblClaimsCurrent[entity_id],[@entity_id],tblClaimsCurrent[status],"UNKNOWN")) | E14: =LET(t,[@known_claims]+[@unknown_claims],IF(t=0,NA(),[@known_claims]/t)) | F14: =LET(cnt,COUNTIFS(tblClaimsCurrent[entity_id],[@entity_id],tblClaimsCurrent[status],"PROMOTED"),IF(cnt=0,NA(),AVERAGEIFS(tblClaimsCurrent[confidence],tblClaimsCurrent[entity_id],[@entity_id],tblClaimsCurrent[status],"PROMOTED"))) | G14: =LET(cnt,COUNTIFS(tblClaimsCurrent[entity_id],[@entity_id],tblClaimsCurrent[field_key],"pricing_acv_mid_market",tblClaimsCurrent[status],"PROMOTED"),IF(cnt=0,NA(),SUMIFS(tblClaimsCurrent[value_num],tblClaimsCurrent[entity_id],[@entity_id],tblClaimsCurrent[field_key],"pricing_acv_mid_market",tblClaimsCurrent[status],"PROMOTED"))) | H14: =IF(OR(NOT(ISNUMBER([@acv_usd])),$B$5=""),"UNKNOWN",IF([@acv_usd]<=($B$5*0.85),"Low",IF([@acv_usd]>=($B$5*1.15),"High","Mid"))) | I14: =LET(v,IFERROR(LOOKUP(2,1/((tblClaimsCurrent[entity_id]=[@entity_id])*(tblClaimsCurrent[field_key]="features")*(tblClaimsCurrent[status]="PROMOTED")),tblClaimsCurrent[value_text]),"UNKNOWN"),IF(v="","UNKNOWN",v)) | J14: =IF(OR([@features_text]="UNKNOWN",[@features_text]=""),NA(),1+LEN([@features_text])-LEN(SUBSTITUTE([@features_text],";",""))) | K14: =IF([@segment_id]="",NA(),IF([@segment_id]="SEG_MM",1,0)) | L14: =IF([@entity_id]="","",IF(COUNTIFS(tblClaimsCurrent[entity_id],[@entity_id],tblClaimsCurrent[field_key],"funding_round",tblClaimsCurrent[status],"PROMOTED")>0,1,0)) | M14: =IF(OR([@in_scope]=FALSE,ISNA([@coverage_pct]),ISNA([@feature_count]),ISNA([@segment_fit]),[@acv_band]="UNKNOWN"),NA(),MIN(1,Config!$B$14*MIN(1,[@feature_count]/10)+Config!$B$15*IF([@acv_band]="Low",1,IF([@acv_band]="Mid",0.5,0))+Config!$B$16*[@segment_fit]+Config!$B$17*[@funding_present])) | N14: =IF(OR([@in_scope]=FALSE,ISNA([@coverage_pct]),ISNA([@feature_count]),ISNA([@segment_fit])),NA(),MIN(1,Config!$B$18*(1-MIN(1,[@feature_count]/10))+Config!$B$19*(1-[@segment_fit])+Config!$B$20*(1-[@coverage_pct]))) | O14: =IF([@in_scope]=FALSE,"OUT_OF_SCOPE",IF(ISNA([@coverage_pct]),"UNKNOWN",IF([@coverage_pct]<Config!$B$10,"FAIL_CLOSED_LOW_COVERAGE","OK"))) | P14: =IFERROR(XLOOKUP([@entity_id],tblEntities[entity_id],tblEntities[segment_id]),"") | Q14: =IFERROR(XLOOKUP([@entity_id],tblEntities[entity_id],tblEntities[vertical]),"") | R14: =AND([@segment_id]=Dashboard!$E$2,IF(Dashboard!$E$3="All",TRUE,[@vertical]=Dashboard!$E$3))
A15: =IF(Input!$A$14="","",Input!$A$14) | B15: =IFERROR(XLOOKUP([@entity_id],tblEntities[entity_id],tblEntities[canonical_name]),"") | C15: =IF([@entity_id]="","",COUNTIFS(tblClaimsCurrent[entity_id],[@entity_id],tblClaimsCurrent[status],"PROMOTED")) | D15: =IF([@entity_id]="","",COUNTIFS(tblClaimsCurrent[entity_id],[@entity_id],tblClaimsCurrent[status],"UNKNOWN")) | E15: =LET(t,[@known_claims]+[@unknown_claims],IF(t=0,NA(),[@known_claims]/t)) | F15: =LET(cnt,COUNTIFS(tblClaimsCurrent[entity_id],[@entity_id],tblClaimsCurrent[status],"PROMOTED"),IF(cnt=0,NA(),AVERAGEIFS(tblClaimsCurrent[confidence],tblClaimsCurrent[entity_id],[@entity_id],tblClaimsCurrent[status],"PROMOTED"))) | G15: =LET(cnt,COUNTIFS(tblClaimsCurrent[entity_id],[@entity_id],tblClaimsCurrent[field_key],"pricing_acv_mid_market",tblClaimsCurrent[status],"PROMOTED"),IF(cnt=0,NA(),SUMIFS(tblClaimsCurrent[value_num],tblClaimsCurrent[entity_id],[@entity_id],tblClaimsCurrent[field_key],"pricing_acv_mid_market",tblClaimsCurrent[status],"PROMOTED"))) | H15: =IF(OR(NOT(ISNUMBER([@acv_usd])),$B$5=""),"UNKNOWN",IF([@acv_usd]<=($B$5*0.85),"Low",IF([@acv_usd]>=($B$5*1.15),"High","Mid"))) | I15: =LET(v,IFERROR(LOOKUP(2,1/((tblClaimsCurrent[entity_id]=[@entity_id])*(tblClaimsCurrent[field_key]="features")*(tblClaimsCurrent[status]="PROMOTED")),tblClaimsCurrent[value_text]),"UNKNOWN"),IF(v="","UNKNOWN",v)) | J15: =IF(OR([@features_text]="UNKNOWN",[@features_text]=""),NA(),1+LEN([@features_text])-LEN(SUBSTITUTE([@features_text],";",""))) | K15: =IF([@segment_id]="",NA(),IF([@segment_id]="SEG_MM",1,0)) | L15: =IF([@entity_id]="","",IF(COUNTIFS(tblClaimsCurrent[entity_id],[@entity_id],tblClaimsCurrent[field_key],"funding_round",tblClaimsCurrent[status],"PROMOTED")>0,1,0)) | M15: =IF(OR([@in_scope]=FALSE,ISNA([@coverage_pct]),ISNA([@feature_count]),ISNA([@segment_fit]),[@acv_band]="UNKNOWN"),NA(),MIN(1,Config!$B$14*MIN(1,[@feature_count]/10)+Config!$B$15*IF([@acv_band]="Low",1,IF([@acv_band]="Mid",0.5,0))+Config!$B$16*[@segment_fit]+Config!$B$17*[@funding_present])) | N15: =IF(OR([@in_scope]=FALSE,ISNA([@coverage_pct]),ISNA([@feature_count]),ISNA([@segment_fit])),NA(),MIN(1,Config!$B$18*(1-MIN(1,[@feature_count]/10))+Config!$B$19*(1-[@segment_fit])+Config!$B$20*(1-[@coverage_pct]))) | O15: =IF([@in_scope]=FALSE,"OUT_OF_SCOPE",IF(ISNA([@coverage_pct]),"UNKNOWN",IF([@coverage_pct]<Config!$B$10,"FAIL_CLOSED_LOW_COVERAGE","OK"))) | P15: =IFERROR(XLOOKUP([@entity_id],tblEntities[entity_id],tblEntities[segment_id]),"") | Q15: =IFERROR(XLOOKUP([@entity_id],tblEntities[entity_id],tblEntities[vertical]),"") | R15: =AND([@segment_id]=Dashboard!$E$2,IF(Dashboard!$E$3="All",TRUE,[@vertical]=Dashboard!$E$3))
A16: =IF(Input!$A$15="","",Input!$A$15) | B16: =IFERROR(XLOOKUP([@entity_id],tblEntities[entity_id],tblEntities[canonical_name]),"") | C16: =IF([@entity_id]="","",COUNTIFS(tblClaimsCurrent[entity_id],[@entity_id],tblClaimsCurrent[status],"PROMOTED")) | D16: =IF([@entity_id]="","",COUNTIFS(tblClaimsCurrent[entity_id],[@entity_id],tblClaimsCurrent[status],"UNKNOWN")) | E16: =LET(t,[@known_claims]+[@unknown_claims],IF(t=0,NA(),[@known_claims]/t)) | F16: =LET(cnt,COUNTIFS(tblClaimsCurrent[entity_id],[@entity_id],tblClaimsCurrent[status],"PROMOTED"),IF(cnt=0,NA(),AVERAGEIFS(tblClaimsCurrent[confidence],tblClaimsCurrent[entity_id],[@entity_id],tblClaimsCurrent[status],"PROMOTED"))) | G16: =LET(cnt,COUNTIFS(tblClaimsCurrent[entity_id],[@entity_id],tblClaimsCurrent[field_key],"pricing_acv_mid_market",tblClaimsCurrent[status],"PROMOTED"),IF(cnt=0,NA(),SUMIFS(tblClaimsCurrent[value_num],tblClaimsCurrent[entity_id],[@entity_id],tblClaimsCurrent[field_key],"pricing_acv_mid_market",tblClaimsCurrent[status],"PROMOTED"))) | H16: =IF(OR(NOT(ISNUMBER([@acv_usd])),$B$5=""),"UNKNOWN",IF([@acv_usd]<=($B$5*0.85),"Low",IF([@acv_usd]>=($B$5*1.15),"High","Mid"))) | I16: =LET(v,IFERROR(LOOKUP(2,1/((tblClaimsCurrent[entity_id]=[@entity_id])*(tblClaimsCurrent[field_key]="features")*(tblClaimsCurrent[status]="PROMOTED")),tblClaimsCurrent[value_text]),"UNKNOWN"),IF(v="","UNKNOWN",v)) | J16: =IF(OR([@features_text]="UNKNOWN",[@features_text]=""),NA(),1+LEN([@features_text])-LEN(SUBSTITUTE([@features_text],";",""))) | K16: =IF([@segment_id]="",NA(),IF([@segment_id]="SEG_MM",1,0)) | L16: =IF([@entity_id]="","",IF(COUNTIFS(tblClaimsCurrent[entity_id],[@entity_id],tblClaimsCurrent[field_key],"funding_round",tblClaimsCurrent[status],"PROMOTED")>0,1,0)) | M16: =IF(OR([@in_scope]=FALSE,ISNA([@coverage_pct]),ISNA([@feature_count]),ISNA([@segment_fit]),[@acv_band]="UNKNOWN"),NA(),MIN(1,Config!$B$14*MIN(1,[@feature_count]/10)+Config!$B$15*IF([@acv_band]="Low",1,IF([@acv_band]="Mid",0.5,0))+Config!$B$16*[@segment_fit]+Config!$B$17*[@funding_present])) | N16: =IF(OR([@in_scope]=FALSE,ISNA([@coverage_pct]),ISNA([@feature_count]),ISNA([@segment_fit])),NA(),MIN(1,Config!$B$18*(1-MIN(1,[@feature_count]/10))+Config!$B$19*(1-[@segment_fit])+Config!$B$20*(1-[@coverage_pct]))) | O16: =IF([@in_scope]=FALSE,"OUT_OF_SCOPE",IF(ISNA([@coverage_pct]),"UNKNOWN",IF([@coverage_pct]<Config!$B$10,"FAIL_CLOSED_LOW_COVERAGE","OK"))) | P16: =IFERROR(XLOOKUP([@entity_id],tblEntities[entity_id],tblEntities[segment_id]),"") | Q16: =IFERROR(XLOOKUP([@entity_id],tblEntities[entity_id],tblEntities[vertical]),"") | R16: =AND([@segment_id]=Dashboard!$E$2,IF(Dashboard!$E$3="All",TRUE,[@vertical]=Dashboard!$E$3))
A17: =IF(Input!$A$16="","",Input!$A$16) | B17: =IFERROR(XLOOKUP([@entity_id],tblEntities[entity_id],tblEntities[canonical_name]),"") | C17: =IF([@entity_id]="","",COUNTIFS(tblClaimsCurrent[entity_id],[@entity_id],tblClaimsCurrent[status],"PROMOTED")) | D17: =IF([@entity_id]="","",COUNTIFS(tblClaimsCurrent[entity_id],[@entity_id],tblClaimsCurrent[status],"UNKNOWN")) | E17: =LET(t,[@known_claims]+[@unknown_claims],IF(t=0,NA(),[@known_claims]/t)) | F17: =LET(cnt,COUNTIFS(tblClaimsCurrent[entity_id],[@entity_id],tblClaimsCurrent[status],"PROMOTED"),IF(cnt=0,NA(),AVERAGEIFS(tblClaimsCurrent[confidence],tblClaimsCurrent[entity_id],[@entity_id],tblClaimsCurrent[status],"PROMOTED"))) | G17: =LET(cnt,COUNTIFS(tblClaimsCurrent[entity_id],[@entity_id],tblClaimsCurrent[field_key],"pricing_acv_mid_market",tblClaimsCurrent[status],"PROMOTED"),IF(cnt=0,NA(),SUMIFS(tblClaimsCurrent[value_num],tblClaimsCurrent[entity_id],[@entity_id],tblClaimsCurrent[field_key],"pricing_acv_mid_market",tblClaimsCurrent[status],"PROMOTED"))) | H17: =IF(OR(NOT(ISNUMBER([@acv_usd])),$B$5=""),"UNKNOWN",IF([@acv_usd]<=($B$5*0.85),"Low",IF([@acv_usd]>=($B$5*1.15),"High","Mid"))) | I17: =LET(v,IFERROR(LOOKUP(2,1/((tblClaimsCurrent[entity_id]=[@entity_id])*(tblClaimsCurrent[field_key]="features")*(tblClaimsCurrent[status]="PROMOTED")),tblClaimsCurrent[value_text]),"UNKNOWN"),IF(v="","UNKNOWN",v)) | J17: =IF(OR([@features_text]="UNKNOWN",[@features_text]=""),NA(),1+LEN([@features_text])-LEN(SUBSTITUTE([@features_text],";",""))) | K17: =IF([@segment_id]="",NA(),IF([@segment_id]="SEG_MM",1,0)) | L17: =IF([@entity_id]="","",IF(COUNTIFS(tblClaimsCurrent[entity_id],[@entity_id],tblClaimsCurrent[field_key],"funding_round",tblClaimsCurrent[status],"PROMOTED")>0,1,0)) | M17: =IF(OR([@in_scope]=FALSE,ISNA([@coverage_pct]),ISNA([@feature_count]),ISNA([@segment_fit]),[@acv_band]="UNKNOWN"),NA(),MIN(1,Config!$B$14*MIN(1,[@feature_count]/10)+Config!$B$15*IF([@acv_band]="Low",1,IF([@acv_band]="Mid",0.5,0))+Config!$B$16*[@segment_fit]+Config!$B$17*[@funding_present])) | N17: =IF(OR([@in_scope]=FALSE,ISNA([@coverage_pct]),ISNA([@feature_count]),ISNA([@segment_fit])),NA(),MIN(1,Config!$B$18*(1-MIN(1,[@feature_count]/10))+Config!$B$19*(1-[@segment_fit])+Config!$B$20*(1-[@coverage_pct]))) | O17: =IF([@in_scope]=FALSE,"OUT_OF_SCOPE",IF(ISNA([@coverage_pct]),"UNKNOWN",IF([@coverage_pct]<Config!$B$10,"FAIL_CLOSED_LOW_COVERAGE","OK"))) | P17: =IFERROR(XLOOKUP([@entity_id],tblEntities[entity_id],tblEntities[segment_id]),"") | Q17: =IFERROR(XLOOKUP([@entity_id],tblEntities[entity_id],tblEntities[vertical]),"") | R17: =AND([@segment_id]=Dashboard!$E$2,IF(Dashboard!$E$3="All",TRUE,[@vertical]=Dashboard!$E$3))
A18: =IF(Input!$A$17="","",Input!$A$17) | B18: =IFERROR(XLOOKUP([@entity_id],tblEntities[entity_id],tblEntities[canonical_name]),"") | C18: =IF([@entity_id]="","",COUNTIFS(tblClaimsCurrent[entity_id],[@entity_id],tblClaimsCurrent[status],"PROMOTED")) | D18: =IF([@entity_id]="","",COUNTIFS(tblClaimsCurrent[entity_id],[@entity_id],tblClaimsCurrent[status],"UNKNOWN")) | E18: =LET(t,[@known_claims]+[@unknown_claims],IF(t=0,NA(),[@known_claims]/t)) | F18: =LET(cnt,COUNTIFS(tblClaimsCurrent[entity_id],[@entity_id],tblClaimsCurrent[status],"PROMOTED"),IF(cnt=0,NA(),AVERAGEIFS(tblClaimsCurrent[confidence],tblClaimsCurrent[entity_id],[@entity_id],tblClaimsCurrent[status],"PROMOTED"))) | G18: =LET(cnt,COUNTIFS(tblClaimsCurrent[entity_id],[@entity_id],tblClaimsCurrent[field_key],"pricing_acv_mid_market",tblClaimsCurrent[status],"PROMOTED"),IF(cnt=0,NA(),SUMIFS(tblClaimsCurrent[value_num],tblClaimsCurrent[entity_id],[@entity_id],tblClaimsCurrent[field_key],"pricing_acv_mid_market",tblClaimsCurrent[status],"PROMOTED"))) | H18: =IF(OR(NOT(ISNUMBER([@acv_usd])),$B$5=""),"UNKNOWN",IF([@acv_usd]<=($B$5*0.85),"Low",IF([@acv_usd]>=($B$5*1.15),"High","Mid"))) | I18: =LET(v,IFERROR(LOOKUP(2,1/((tblClaimsCurrent[entity_id]=[@entity_id])*(tblClaimsCurrent[field_key]="features")*(tblClaimsCurrent[status]="PROMOTED")),tblClaimsCurrent[value_text]),"UNKNOWN"),IF(v="","UNKNOWN",v)) | J18: =IF(OR([@features_text]="UNKNOWN",[@features_text]=""),NA(),1+LEN([@features_text])-LEN(SUBSTITUTE([@features_text],";",""))) | K18: =IF([@segment_id]="",NA(),IF([@segment_id]="SEG_MM",1,0)) | L18: =IF([@entity_id]="","",IF(COUNTIFS(tblClaimsCurrent[entity_id],[@entity_id],tblClaimsCurrent[field_key],"funding_round",tblClaimsCurrent[status],"PROMOTED")>0,1,0)) | M18: =IF(OR([@in_scope]=FALSE,ISNA([@coverage_pct]),ISNA([@feature_count]),ISNA([@segment_fit]),[@acv_band]="UNKNOWN"),NA(),MIN(1,Config!$B$14*MIN(1,[@feature_count]/10)+Config!$B$15*IF([@acv_band]="Low",1,IF([@acv_band]="Mid",0.5,0))+Config!$B$16*[@segment_fit]+Config!$B$17*[@funding_present])) | N18: =IF(OR([@in_scope]=FALSE,ISNA([@coverage_pct]),ISNA([@feature_count]),ISNA([@segment_fit])),NA(),MIN(1,Config!$B$18*(1-MIN(1,[@feature_count]/10))+Config!$B$19*(1-[@segment_fit])+Config!$B$20*(1-[@coverage_pct]))) | O18: =IF([@in_scope]=FALSE,"OUT_OF_SCOPE",IF(ISNA([@coverage_pct]),"UNKNOWN",IF([@coverage_pct]<Config!$B$10,"FAIL_CLOSED_LOW_COVERAGE","OK"))) | P18: =IFERROR(XLOOKUP([@entity_id],tblEntities[entity_id],tblEntities[segment_id]),"") | Q18: =IFERROR(XLOOKUP([@entity_id],tblEntities[entity_id],tblEntities[vertical]),"") | R18: =AND([@segment_id]=Dashboard!$E$2,IF(Dashboard!$E$3="All",TRUE,[@vertical]=Dashboard!$E$3))
A19: =IF(Input!$A$18="","",Input!$A$18) | B19: =IFERROR(XLOOKUP([@entity_id],tblEntities[entity_id],tblEntities[canonical_name]),"") | C19: =IF([@entity_id]="","",COUNTIFS(tblClaimsCurrent[entity_id],[@entity_id],tblClaimsCurrent[status],"PROMOTED")) | D19: =IF([@entity_id]="","",COUNTIFS(tblClaimsCurrent[entity_id],[@entity_id],tblClaimsCurrent[status],"UNKNOWN")) | E19: =LET(t,[@known_claims]+[@unknown_claims],IF(t=0,NA(),[@known_claims]/t)) | F19: =LET(cnt,COUNTIFS(tblClaimsCurrent[entity_id],[@entity_id],tblClaimsCurrent[status],"PROMOTED"),IF(cnt=0,NA(),AVERAGEIFS(tblClaimsCurrent[confidence],tblClaimsCurrent[entity_id],[@entity_id],tblClaimsCurrent[status],"PROMOTED"))) | G19: =LET(cnt,COUNTIFS(tblClaimsCurrent[entity_id],[@entity_id],tblClaimsCurrent[field_key],"pricing_acv_mid_market",tblClaimsCurrent[status],"PROMOTED"),IF(cnt=0,NA(),SUMIFS(tblClaimsCurrent[value_num],tblClaimsCurrent[entity_id],[@entity_id],tblClaimsCurrent[field_key],"pricing_acv_mid_market",tblClaimsCurrent[status],"PROMOTED"))) | H19: =IF(OR(NOT(ISNUMBER([@acv_usd])),$B$5=""),"UNKNOWN",IF([@acv_usd]<=($B$5*0.85),"Low",IF([@acv_usd]>=($B$5*1.15),"High","Mid"))) | I19: =LET(v,IFERROR(LOOKUP(2,1/((tblClaimsCurrent[entity_id]=[@entity_id])*(tblClaimsCurrent[field_key]="features")*(tblClaimsCurrent[status]="PROMOTED")),tblClaimsCurrent[value_text]),"UNKNOWN"),IF(v="","UNKNOWN",v)) | J19: =IF(OR([@features_text]="UNKNOWN",[@features_text]=""),NA(),1+LEN([@features_text])-LEN(SUBSTITUTE([@features_text],";",""))) | K19: =IF([@segment_id]="",NA(),IF([@segment_id]="SEG_MM",1,0)) | L19: =IF([@entity_id]="","",IF(COUNTIFS(tblClaimsCurrent[entity_id],[@entity_id],tblClaimsCurrent[field_key],"funding_round",tblClaimsCurrent[status],"PROMOTED")>0,1,0)) | M19: =IF(OR([@in_scope]=FALSE,ISNA([@coverage_pct]),ISNA([@feature_count]),ISNA([@segment_fit]),[@acv_band]="UNKNOWN"),NA(),MIN(1,Config!$B$14*MIN(1,[@feature_count]/10)+Config!$B$15*IF([@acv_band]="Low",1,IF([@acv_band]="Mid",0.5,0))+Config!$B$16*[@segment_fit]+Config!$B$17*[@funding_present])) | N19: =IF(OR([@in_scope]=FALSE,ISNA([@coverage_pct]),ISNA([@feature_count]),ISNA([@segment_fit])),NA(),MIN(1,Config!$B$18*(1-MIN(1,[@feature_count]/10))+Config!$B$19*(1-[@segment_fit])+Config!$B$20*(1-[@coverage_pct]))) | O19: =IF([@in_scope]=FALSE,"OUT_OF_SCOPE",IF(ISNA([@coverage_pct]),"UNKNOWN",IF([@coverage_pct]<Config!$B$10,"FAIL_CLOSED_LOW_COVERAGE","OK"))) | P19: =IFERROR(XLOOKUP([@entity_id],tblEntities[entity_id],tblEntities[segment_id]),"") | Q19: =IFERROR(XLOOKUP([@entity_id],tblEntities[entity_id],tblEntities[vertical]),"") | R19: =AND([@segment_id]=Dashboard!$E$2,IF(Dashboard!$E$3="All",TRUE,[@vertical]=Dashboard!$E$3))
A20: =IF(Input!$A$19="","",Input!$A$19) | B20: =IFERROR(XLOOKUP([@entity_id],tblEntities[entity_id],tblEntities[canonical_name]),"") | C20: =IF([@entity_id]="","",COUNTIFS(tblClaimsCurrent[entity_id],[@entity_id],tblClaimsCurrent[status],"PROMOTED")) | D20: =IF([@entity_id]="","",COUNTIFS(tblClaimsCurrent[entity_id],[@entity_id],tblClaimsCurrent[status],"UNKNOWN")) | E20: =LET(t,[@known_claims]+[@unknown_claims],IF(t=0,NA(),[@known_claims]/t)) | F20: =LET(cnt,COUNTIFS(tblClaimsCurrent[entity_id],[@entity_id],tblClaimsCurrent[status],"PROMOTED"),IF(cnt=0,NA(),AVERAGEIFS(tblClaimsCurrent[confidence],tblClaimsCurrent[entity_id],[@entity_id],tblClaimsCurrent[status],"PROMOTED"))) | G20: =LET(cnt,COUNTIFS(tblClaimsCurrent[entity_id],[@entity_id],tblClaimsCurrent[field_key],"pricing_acv_mid_market",tblClaimsCurrent[status],"PROMOTED"),IF(cnt=0,NA(),SUMIFS(tblClaimsCurrent[value_num],tblClaimsCurrent[entity_id],[@entity_id],tblClaimsCurrent[field_key],"pricing_acv_mid_market",tblClaimsCurrent[status],"PROMOTED"))) | H20: =IF(OR(NOT(ISNUMBER([@acv_usd])),$B$5=""),"UNKNOWN",IF([@acv_usd]<=($B$5*0.85),"Low",IF([@acv_usd]>=($B$5*1.15),"High","Mid"))) | I20: =LET(v,IFERROR(LOOKUP(2,1/((tblClaimsCurrent[entity_id]=[@entity_id])*(tblClaimsCurrent[field_key]="features")*(tblClaimsCurrent[status]="PROMOTED")),tblClaimsCurrent[value_text]),"UNKNOWN"),IF(v="","UNKNOWN",v)) | J20: =IF(OR([@features_text]="UNKNOWN",[@features_text]=""),NA(),1+LEN([@features_text])-LEN(SUBSTITUTE([@features_text],";",""))) | K20: =IF([@segment_id]="",NA(),IF([@segment_id]="SEG_MM",1,0)) | L20: =IF([@entity_id]="","",IF(COUNTIFS(tblClaimsCurrent[entity_id],[@entity_id],tblClaimsCurrent[field_key],"funding_round",tblClaimsCurrent[status],"PROMOTED")>0,1,0)) | M20: =IF(OR([@in_scope]=FALSE,ISNA([@coverage_pct]),ISNA([@feature_count]),ISNA([@segment_fit]),[@acv_band]="UNKNOWN"),NA(),MIN(1,Config!$B$14*MIN(1,[@feature_count]/10)+Config!$B$15*IF([@acv_band]="Low",1,IF([@acv_band]="Mid",0.5,0))+Config!$B$16*[@segment_fit]+Config!$B$17*[@funding_present])) | N20: =IF(OR([@in_scope]=FALSE,ISNA([@coverage_pct]),ISNA([@feature_count]),ISNA([@segment_fit])),NA(),MIN(1,Config!$B$18*(1-MIN(1,[@feature_count]/10))+Config!$B$19*(1-[@segment_fit])+Config!$B$20*(1-[@coverage_pct]))) | O20: =IF([@in_scope]=FALSE,"OUT_OF_SCOPE",IF(ISNA([@coverage_pct]),"UNKNOWN",IF([@coverage_pct]<Config!$B$10,"FAIL_CLOSED_LOW_COVERAGE","OK"))) | P20: =IFERROR(XLOOKUP([@entity_id],tblEntities[entity_id],tblEntities[segment_id]),"") | Q20: =IFERROR(XLOOKUP([@entity_id],tblEntities[entity_id],tblEntities[vertical]),"") | R20: =AND([@segment_id]=Dashboard!$E$2,IF(Dashboard!$E$3="All",TRUE,[@vertical]=Dashboard!$E$3))
A21: =IF(Input!$A$20="","",Input!$A$20) | B21: =IFERROR(XLOOKUP([@entity_id],tblEntities[entity_id],tblEntities[canonical_name]),"") | C21: =IF([@entity_id]="","",COUNTIFS(tblClaimsCurrent[entity_id],[@entity_id],tblClaimsCurrent[status],"PROMOTED")) | D21: =IF([@entity_id]="","",COUNTIFS(tblClaimsCurrent[entity_id],[@entity_id],tblClaimsCurrent[status],"UNKNOWN")) | E21: =LET(t,[@known_claims]+[@unknown_claims],IF(t=0,NA(),[@known_claims]/t)) | F21: =LET(cnt,COUNTIFS(tblClaimsCurrent[entity_id],[@entity_id],tblClaimsCurrent[status],"PROMOTED"),IF(cnt=0,NA(),AVERAGEIFS(tblClaimsCurrent[confidence],tblClaimsCurrent[entity_id],[@entity_id],tblClaimsCurrent[status],"PROMOTED"))) | G21: =LET(cnt,COUNTIFS(tblClaimsCurrent[entity_id],[@entity_id],tblClaimsCurrent[field_key],"pricing_acv_mid_market",tblClaimsCurrent[status],"PROMOTED"),IF(cnt=0,NA(),SUMIFS(tblClaimsCurrent[value_num],tblClaimsCurrent[entity_id],[@entity_id],tblClaimsCurrent[field_key],"pricing_acv_mid_market",tblClaimsCurrent[status],"PROMOTED"))) | H21: =IF(OR(NOT(ISNUMBER([@acv_usd])),$B$5=""),"UNKNOWN",IF([@acv_usd]<=($B$5*0.85),"Low",IF([@acv_usd]>=($B$5*1.15),"High","Mid"))) | I21: =LET(v,IFERROR(LOOKUP(2,1/((tblClaimsCurrent[entity_id]=[@entity_id])*(tblClaimsCurrent[field_key]="features")*(tblClaimsCurrent[status]="PROMOTED")),tblClaimsCurrent[value_text]),"UNKNOWN"),IF(v="","UNKNOWN",v)) | J21: =IF(OR([@features_text]="UNKNOWN",[@features_text]=""),NA(),1+LEN([@features_text])-LEN(SUBSTITUTE([@features_text],";",""))) | K21: =IF([@segment_id]="",NA(),IF([@segment_id]="SEG_MM",1,0)) | L21: =IF([@entity_id]="","",IF(COUNTIFS(tblClaimsCurrent[entity_id],[@entity_id],tblClaimsCurrent[field_key],"funding_round",tblClaimsCurrent[status],"PROMOTED")>0,1,0)) | M21: =IF(OR([@in_scope]=FALSE,ISNA([@coverage_pct]),ISNA([@feature_count]),ISNA([@segment_fit]),[@acv_band]="UNKNOWN"),NA(),MIN(1,Config!$B$14*MIN(1,[@feature_count]/10)+Config!$B$15*IF([@acv_band]="Low",1,IF([@acv_band]="Mid",0.5,0))+Config!$B$16*[@segment_fit]+Config!$B$17*[@funding_present])) | N21: =IF(OR([@in_scope]=FALSE,ISNA([@coverage_pct]),ISNA([@feature_count]),ISNA([@segment_fit])),NA(),MIN(1,Config!$B$18*(1-MIN(1,[@feature_count]/10))+Config!$B$19*(1-[@segment_fit])+Config!$B$20*(1-[@coverage_pct]))) | O21: =IF([@in_scope]=FALSE,"OUT_OF_SCOPE",IF(ISNA([@coverage_pct]),"UNKNOWN",IF([@coverage_pct]<Config!$B$10,"FAIL_CLOSED_LOW_COVERAGE","OK"))) | P21: =IFERROR(XLOOKUP([@entity_id],tblEntities[entity_id],tblEntities[segment_id]),"") | Q21: =IFERROR(XLOOKUP([@entity_id],tblEntities[entity_id],tblEntities[vertical]),"") | R21: =AND([@segment_id]=Dashboard!$E$2,IF(Dashboard!$E$3="All",TRUE,[@vertical]=Dashboard!$E$3))
A22: =IF(Input!$A$21="","",Input!$A$21) | B22: =IFERROR(XLOOKUP([@entity_id],tblEntities[entity_id],tblEntities[canonical_name]),"") | C22: =IF([@entity_id]="","",COUNTIFS(tblClaimsCurrent[entity_id],[@entity_id],tblClaimsCurrent[status],"PROMOTED")) | D22: =IF([@entity_id]="","",COUNTIFS(tblClaimsCurrent[entity_id],[@entity_id],tblClaimsCurrent[status],"UNKNOWN")) | E22: =LET(t,[@known_claims]+[@unknown_claims],IF(t=0,NA(),[@known_claims]/t)) | F22: =LET(cnt,COUNTIFS(tblClaimsCurrent[entity_id],[@entity_id],tblClaimsCurrent[status],"PROMOTED"),IF(cnt=0,NA(),AVERAGEIFS(tblClaimsCurrent[confidence],tblClaimsCurrent[entity_id],[@entity_id],tblClaimsCurrent[status],"PROMOTED"))) | G22: =LET(cnt,COUNTIFS(tblClaimsCurrent[entity_id],[@entity_id],tblClaimsCurrent[field_key],"pricing_acv_mid_market",tblClaimsCurrent[status],"PROMOTED"),IF(cnt=0,NA(),SUMIFS(tblClaimsCurrent[value_num],tblClaimsCurrent[entity_id],[@entity_id],tblClaimsCurrent[field_key],"pricing_acv_mid_market",tblClaimsCurrent[status],"PROMOTED"))) | H22: =IF(OR(NOT(ISNUMBER([@acv_usd])),$B$5=""),"UNKNOWN",IF([@acv_usd]<=($B$5*0.85),"Low",IF([@acv_usd]>=($B$5*1.15),"High","Mid"))) | I22: =LET(v,IFERROR(LOOKUP(2,1/((tblClaimsCurrent[entity_id]=[@entity_id])*(tblClaimsCurrent[field_key]="features")*(tblClaimsCurrent[status]="PROMOTED")),tblClaimsCurrent[value_text]),"UNKNOWN"),IF(v="","UNKNOWN",v)) | J22: =IF(OR([@features_text]="UNKNOWN",[@features_text]=""),NA(),1+LEN([@features_text])-LEN(SUBSTITUTE([@features_text],";",""))) | K22: =IF([@segment_id]="",NA(),IF([@segment_id]="SEG_MM",1,0)) | L22: =IF([@entity_id]="","",IF(COUNTIFS(tblClaimsCurrent[entity_id],[@entity_id],tblClaimsCurrent[field_key],"funding_round",tblClaimsCurrent[status],"PROMOTED")>0,1,0)) | M22: =IF(OR([@in_scope]=FALSE,ISNA([@coverage_pct]),ISNA([@feature_count]),ISNA([@segment_fit]),[@acv_band]="UNKNOWN"),NA(),MIN(1,Config!$B$14*MIN(1,[@feature_count]/10)+Config!$B$15*IF([@acv_band]="Low",1,IF([@acv_band]="Mid",0.5,0))+Config!$B$16*[@segment_fit]+Config!$B$17*[@funding_present])) | N22: =IF(OR([@in_scope]=FALSE,ISNA([@coverage_pct]),ISNA([@feature_count]),ISNA([@segment_fit])),NA(),MIN(1,Config!$B$18*(1-MIN(1,[@feature_count]/10))+Config!$B$19*(1-[@segment_fit])+Config!$B$20*(1-[@coverage_pct]))) | O22: =IF([@in_scope]=FALSE,"OUT_OF_SCOPE",IF(ISNA([@coverage_pct]),"UNKNOWN",IF([@coverage_pct]<Config!$B$10,"FAIL_CLOSED_LOW_COVERAGE","OK"))) | P22: =IFERROR(XLOOKUP([@entity_id],tblEntities[entity_id],tblEntities[segment_id]),"") | Q22: =IFERROR(XLOOKUP([@entity_id],tblEntities[entity_id],tblEntities[vertical]),"") | R22: =AND([@segment_id]=Dashboard!$E$2,IF(Dashboard!$E$3="All",TRUE,[@vertical]=Dashboard!$E$3))
A23: =IF(Input!$A$22="","",Input!$A$22) | B23: =IFERROR(XLOOKUP([@entity_id],tblEntities[entity_id],tblEntities[canonical_name]),"") | C23: =IF([@entity_id]="","",COUNTIFS(tblClaimsCurrent[entity_id],[@entity_id],tblClaimsCurrent[status],"PROMOTED")) | D23: =IF([@entity_id]="","",COUNTIFS(tblClaimsCurrent[entity_id],[@entity_id],tblClaimsCurrent[status],"UNKNOWN")) | E23: =LET(t,[@known_claims]+[@unknown_claims],IF(t=0,NA(),[@known_claims]/t)) | F23: =LET(cnt,COUNTIFS(tblClaimsCurrent[entity_id],[@entity_id],tblClaimsCurrent[status],"PROMOTED"),IF(cnt=0,NA(),AVERAGEIFS(tblClaimsCurrent[confidence],tblClaimsCurrent[entity_id],[@entity_id],tblClaimsCurrent[status],"PROMOTED"))) | G23: =LET(cnt,COUNTIFS(tblClaimsCurrent[entity_id],[@entity_id],tblClaimsCurrent[field_key],"pricing_acv_mid_market",tblClaimsCurrent[status],"PROMOTED"),IF(cnt=0,NA(),SUMIFS(tblClaimsCurrent[value_num],tblClaimsCurrent[entity_id],[@entity_id],tblClaimsCurrent[field_key],"pricing_acv_mid_market",tblClaimsCurrent[status],"PROMOTED"))) | H23: =IF(OR(NOT(ISNUMBER([@acv_usd])),$B$5=""),"UNKNOWN",IF([@acv_usd]<=($B$5*0.85),"Low",IF([@acv_usd]>=($B$5*1.15),"High","Mid"))) | I23: =LET(v,IFERROR(LOOKUP(2,1/((tblClaimsCurrent[entity_id]=[@entity_id])*(tblClaimsCurrent[field_key]="features")*(tblClaimsCurrent[status]="PROMOTED")),tblClaimsCurrent[value_text]),"UNKNOWN"),IF(v="","UNKNOWN",v)) | J23: =IF(OR([@features_text]="UNKNOWN",[@features_text]=""),NA(),1+LEN([@features_text])-LEN(SUBSTITUTE([@features_text],";",""))) | K23: =IF([@segment_id]="",NA(),IF([@segment_id]="SEG_MM",1,0)) | L23: =IF([@entity_id]="","",IF(COUNTIFS(tblClaimsCurrent[entity_id],[@entity_id],tblClaimsCurrent[field_key],"funding_round",tblClaimsCurrent[status],"PROMOTED")>0,1,0)) | M23: =IF(OR([@in_scope]=FALSE,ISNA([@coverage_pct]),ISNA([@feature_count]),ISNA([@segment_fit]),[@acv_band]="UNKNOWN"),NA(),MIN(1,Config!$B$14*MIN(1,[@feature_count]/10)+Config!$B$15*IF([@acv_band]="Low",1,IF([@acv_band]="Mid",0.5,0))+Config!$B$16*[@segment_fit]+Config!$B$17*[@funding_present])) | N23: =IF(OR([@in_scope]=FALSE,ISNA([@coverage_pct]),ISNA([@feature_count]),ISNA([@segment_fit])),NA(),MIN(1,Config!$B$18*(1-MIN(1,[@feature_count]/10))+Config!$B$19*(1-[@segment_fit])+Config!$B$20*(1-[@coverage_pct]))) | O23: =IF([@in_scope]=FALSE,"OUT_OF_SCOPE",IF(ISNA([@coverage_pct]),"UNKNOWN",IF([@coverage_pct]<Config!$B$10,"FAIL_CLOSED_LOW_COVERAGE","OK"))) | P23: =IFERROR(XLOOKUP([@entity_id],tblEntities[entity_id],tblEntities[segment_id]),"") | Q23: =IFERROR(XLOOKUP([@entity_id],tblEntities[entity_id],tblEntities[vertical]),"") | R23: =AND([@segment_id]=Dashboard!$E$2,IF(Dashboard!$E$3="All",TRUE,[@vertical]=Dashboard!$E$3))
A24: =IF(Input!$A$23="","",Input!$A$23) | B24: =IFERROR(XLOOKUP([@entity_id],tblEntities[entity_id],tblEntities[canonical_name]),"") | C24: =IF([@entity_id]="","",COUNTIFS(tblClaimsCurrent[entity_id],[@entity_id],tblClaimsCurrent[status],"PROMOTED")) | D24: =IF([@entity_id]="","",COUNTIFS(tblClaimsCurrent[entity_id],[@entity_id],tblClaimsCurrent[status],"UNKNOWN")) | E24: =LET(t,[@known_claims]+[@unknown_claims],IF(t=0,NA(),[@known_claims]/t)) | F24: =LET(cnt,COUNTIFS(tblClaimsCurrent[entity_id],[@entity_id],tblClaimsCurrent[status],"PROMOTED"),IF(cnt=0,NA(),AVERAGEIFS(tblClaimsCurrent[confidence],tblClaimsCurrent[entity_id],[@entity_id],tblClaimsCurrent[status],"PROMOTED"))) | G24: =LET(cnt,COUNTIFS(tblClaimsCurrent[entity_id],[@entity_id],tblClaimsCurrent[field_key],"pricing_acv_mid_market",tblClaimsCurrent[status],"PROMOTED"),IF(cnt=0,NA(),SUMIFS(tblClaimsCurrent[value_num],tblClaimsCurrent[entity_id],[@entity_id],tblClaimsCurrent[field_key],"pricing_acv_mid_market",tblClaimsCurrent[status],"PROMOTED"))) | H24: =IF(OR(NOT(ISNUMBER([@acv_usd])),$B$5=""),"UNKNOWN",IF([@acv_usd]<=($B$5*0.85),"Low",IF([@acv_usd]>=($B$5*1.15),"High","Mid"))) | I24: =LET(v,IFERROR(LOOKUP(2,1/((tblClaimsCurrent[entity_id]=[@entity_id])*(tblClaimsCurrent[field_key]="features")*(tblClaimsCurrent[status]="PROMOTED")),tblClaimsCurrent[value_text]),"UNKNOWN"),IF(v="","UNKNOWN",v)) | J24: =IF(OR([@features_text]="UNKNOWN",[@features_text]=""),NA(),1+LEN([@features_text])-LEN(SUBSTITUTE([@features_text],";",""))) | K24: =IF([@segment_id]="",NA(),IF([@segment_id]="SEG_MM",1,0)) | L24: =IF([@entity_id]="","",IF(COUNTIFS(tblClaimsCurrent[entity_id],[@entity_id],tblClaimsCurrent[field_key],"funding_round",tblClaimsCurrent[status],"PROMOTED")>0,1,0)) | M24: =IF(OR([@in_scope]=FALSE,ISNA([@coverage_pct]),ISNA([@feature_count]),ISNA([@segment_fit]),[@acv_band]="UNKNOWN"),NA(),MIN(1,Config!$B$14*MIN(1,[@feature_count]/10)+Config!$B$15*IF([@acv_band]="Low",1,IF([@acv_band]="Mid",0.5,0))+Config!$B$16*[@segment_fit]+Config!$B$17*[@funding_present])) | N24: =IF(OR([@in_scope]=FALSE,ISNA([@coverage_pct]),ISNA([@feature_count]),ISNA([@segment_fit])),NA(),MIN(1,Config!$B$18*(1-MIN(1,[@feature_count]/10))+Config!$B$19*(1-[@segment_fit])+Config!$B$20*(1-[@coverage_pct]))) | O24: =IF([@in_scope]=FALSE,"OUT_OF_SCOPE",IF(ISNA([@coverage_pct]),"UNKNOWN",IF([@coverage_pct]<Config!$B$10,"FAIL_CLOSED_LOW_COVERAGE","OK"))) | P24: =IFERROR(XLOOKUP([@entity_id],tblEntities[entity_id],tblEntities[segment_id]),"") | Q24: =IFERROR(XLOOKUP([@entity_id],tblEntities[entity_id],tblEntities[vertical]),"") | R24: =AND([@segment_id]=Dashboard!$E$2,IF(Dashboard!$E$3="All",TRUE,[@vertical]=Dashboard!$E$3))
A25: =IF(Input!$A$24="","",Input!$A$24) | B25: =IFERROR(XLOOKUP([@entity_id],tblEntities[entity_id],tblEntities[canonical_name]),"") | C25: =IF([@entity_id]="","",COUNTIFS(tblClaimsCurrent[entity_id],[@entity_id],tblClaimsCurrent[status],"PROMOTED")) | D25: =IF([@entity_id]="","",COUNTIFS(tblClaimsCurrent[entity_id],[@entity_id],tblClaimsCurrent[status],"UNKNOWN")) | E25: =LET(t,[@known_claims]+[@unknown_claims],IF(t=0,NA(),[@known_claims]/t)) | F25: =LET(cnt,COUNTIFS(tblClaimsCurrent[entity_id],[@entity_id],tblClaimsCurrent[status],"PROMOTED"),IF(cnt=0,NA(),AVERAGEIFS(tblClaimsCurrent[confidence],tblClaimsCurrent[entity_id],[@entity_id],tblClaimsCurrent[status],"PROMOTED"))) | G25: =LET(cnt,COUNTIFS(tblClaimsCurrent[entity_id],[@entity_id],tblClaimsCurrent[field_key],"pricing_acv_mid_market",tblClaimsCurrent[status],"PROMOTED"),IF(cnt=0,NA(),SUMIFS(tblClaimsCurrent[value_num],tblClaimsCurrent[entity_id],[@entity_id],tblClaimsCurrent[field_key],"pricing_acv_mid_market",tblClaimsCurrent[status],"PROMOTED"))) | H25: =IF(OR(NOT(ISNUMBER([@acv_usd])),$B$5=""),"UNKNOWN",IF([@acv_usd]<=($B$5*0.85),"Low",IF([@acv_usd]>=($B$5*1.15),"High","Mid"))) | I25: =LET(v,IFERROR(LOOKUP(2,1/((tblClaimsCurrent[entity_id]=[@entity_id])*(tblClaimsCurrent[field_key]="features")*(tblClaimsCurrent[status]="PROMOTED")),tblClaimsCurrent[value_text]),"UNKNOWN"),IF(v="","UNKNOWN",v)) | J25: =IF(OR([@features_text]="UNKNOWN",[@features_text]=""),NA(),1+LEN([@features_text])-LEN(SUBSTITUTE([@features_text],";",""))) | K25: =IF([@segment_id]="",NA(),IF([@segment_id]="SEG_MM",1,0)) | L25: =IF([@entity_id]="","",IF(COUNTIFS(tblClaimsCurrent[entity_id],[@entity_id],tblClaimsCurrent[field_key],"funding_round",tblClaimsCurrent[status],"PROMOTED")>0,1,0)) | M25: =IF(OR([@in_scope]=FALSE,ISNA([@coverage_pct]),ISNA([@feature_count]),ISNA([@segment_fit]),[@acv_band]="UNKNOWN"),NA(),MIN(1,Config!$B$14*MIN(1,[@feature_count]/10)+Config!$B$15*IF([@acv_band]="Low",1,IF([@acv_band]="Mid",0.5,0))+Config!$B$16*[@segment_fit]+Config!$B$17*[@funding_present])) | N25: =IF(OR([@in_scope]=FALSE,ISNA([@coverage_pct]),ISNA([@feature_count]),ISNA([@segment_fit])),NA(),MIN(1,Config!$B$18*(1-MIN(1,[@feature_count]/10))+Config!$B$19*(1-[@segment_fit])+Config!$B$20*(1-[@coverage_pct]))) | O25: =IF([@in_scope]=FALSE,"OUT_OF_SCOPE",IF(ISNA([@coverage_pct]),"UNKNOWN",IF([@coverage_pct]<Config!$B$10,"FAIL_CLOSED_LOW_COVERAGE","OK"))) | P25: =IFERROR(XLOOKUP([@entity_id],tblEntities[entity_id],tblEntities[segment_id]),"") | Q25: =IFERROR(XLOOKUP([@entity_id],tblEntities[entity_id],tblEntities[vertical]),"") | R25: =AND([@segment_id]=Dashboard!$E$2,IF(Dashboard!$E$3="All",TRUE,[@vertical]=Dashboard!$E$3))
A26: =IF(Input!$A$25="","",Input!$A$25) | B26: =IFERROR(XLOOKUP([@entity_id],tblEntities[entity_id],tblEntities[canonical_name]),"") | C26: =IF([@entity_id]="","",COUNTIFS(tblClaimsCurrent[entity_id],[@entity_id],tblClaimsCurrent[status],"PROMOTED")) | D26: =IF([@entity_id]="","",COUNTIFS(tblClaimsCurrent[entity_id],[@entity_id],tblClaimsCurrent[status],"UNKNOWN")) | E26: =LET(t,[@known_claims]+[@unknown_claims],IF(t=0,NA(),[@known_claims]/t)) | F26: =LET(cnt,COUNTIFS(tblClaimsCurrent[entity_id],[@entity_id],tblClaimsCurrent[status],"PROMOTED"),IF(cnt=0,NA(),AVERAGEIFS(tblClaimsCurrent[confidence],tblClaimsCurrent[entity_id],[@entity_id],tblClaimsCurrent[status],"PROMOTED"))) | G26: =LET(cnt,COUNTIFS(tblClaimsCurrent[entity_id],[@entity_id],tblClaimsCurrent[field_key],"pricing_acv_mid_market",tblClaimsCurrent[status],"PROMOTED"),IF(cnt=0,NA(),SUMIFS(tblClaimsCurrent[value_num],tblClaimsCurrent[entity_id],[@entity_id],tblClaimsCurrent[field_key],"pricing_acv_mid_market",tblClaimsCurrent[status],"PROMOTED"))) | H26: =IF(OR(NOT(ISNUMBER([@acv_usd])),$B$5=""),"UNKNOWN",IF([@acv_usd]<=($B$5*0.85),"Low",IF([@acv_usd]>=($B$5*1.15),"High","Mid"))) | I26: =LET(v,IFERROR(LOOKUP(2,1/((tblClaimsCurrent[entity_id]=[@entity_id])*(tblClaimsCurrent[field_key]="features")*(tblClaimsCurrent[status]="PROMOTED")),tblClaimsCurrent[value_text]),"UNKNOWN"),IF(v="","UNKNOWN",v)) | J26: =IF(OR([@features_text]="UNKNOWN",[@features_text]=""),NA(),1+LEN([@features_text])-LEN(SUBSTITUTE([@features_text],";",""))) | K26: =IF([@segment_id]="",NA(),IF([@segment_id]="SEG_MM",1,0)) | L26: =IF([@entity_id]="","",IF(COUNTIFS(tblClaimsCurrent[entity_id],[@entity_id],tblClaimsCurrent[field_key],"funding_round",tblClaimsCurrent[status],"PROMOTED")>0,1,0)) | M26: =IF(OR([@in_scope]=FALSE,ISNA([@coverage_pct]),ISNA([@feature_count]),ISNA([@segment_fit]),[@acv_band]="UNKNOWN"),NA(),MIN(1,Config!$B$14*MIN(1,[@feature_count]/10)+Config!$B$15*IF([@acv_band]="Low",1,IF([@acv_band]="Mid",0.5,0))+Config!$B$16*[@segment_fit]+Config!$B$17*[@funding_present])) | N26: =IF(OR([@in_scope]=FALSE,ISNA([@coverage_pct]),ISNA([@feature_count]),ISNA([@segment_fit])),NA(),MIN(1,Config!$B$18*(1-MIN(1,[@feature_count]/10))+Config!$B$19*(1-[@segment_fit])+Config!$B$20*(1-[@coverage_pct]))) | O26: =IF([@in_scope]=FALSE,"OUT_OF_SCOPE",IF(ISNA([@coverage_pct]),"UNKNOWN",IF([@coverage_pct]<Config!$B$10,"FAIL_CLOSED_LOW_COVERAGE","OK"))) | P26: =IFERROR(XLOOKUP([@entity_id],tblEntities[entity_id],tblEntities[segment_id]),"") | Q26: =IFERROR(XLOOKUP([@entity_id],tblEntities[entity_id],tblEntities[vertical]),"") | R26: =AND([@segment_id]=Dashboard!$E$2,IF(Dashboard!$E$3="All",TRUE,[@vertical]=Dashboard!$E$3))
A27: =IF(Input!$A$26="","",Input!$A$26) | B27: =IFERROR(XLOOKUP([@entity_id],tblEntities[entity_id],tblEntities[canonical_name]),"") | C27: =IF([@entity_id]="","",COUNTIFS(tblClaimsCurrent[entity_id],[@entity_id],tblClaimsCurrent[status],"PROMOTED")) | D27: =IF([@entity_id]="","",COUNTIFS(tblClaimsCurrent[entity_id],[@entity_id],tblClaimsCurrent[status],"UNKNOWN")) | E27: =LET(t,[@known_claims]+[@unknown_claims],IF(t=0,NA(),[@known_claims]/t)) | F27: =LET(cnt,COUNTIFS(tblClaimsCurrent[entity_id],[@entity_id],tblClaimsCurrent[status],"PROMOTED"),IF(cnt=0,NA(),AVERAGEIFS(tblClaimsCurrent[confidence],tblClaimsCurrent[entity_id],[@entity_id],tblClaimsCurrent[status],"PROMOTED"))) | G27: =LET(cnt,COUNTIFS(tblClaimsCurrent[entity_id],[@entity_id],tblClaimsCurrent[field_key],"pricing_acv_mid_market",tblClaimsCurrent[status],"PROMOTED"),IF(cnt=0,NA(),SUMIFS(tblClaimsCurrent[value_num],tblClaimsCurrent[entity_id],[@entity_id],tblClaimsCurrent[field_key],"pricing_acv_mid_market",tblClaimsCurrent[status],"PROMOTED"))) | H27: =IF(OR(NOT(ISNUMBER([@acv_usd])),$B$5=""),"UNKNOWN",IF([@acv_usd]<=($B$5*0.85),"Low",IF([@acv_usd]>=($B$5*1.15),"High","Mid"))) | I27: =LET(v,IFERROR(LOOKUP(2,1/((tblClaimsCurrent[entity_id]=[@entity_id])*(tblClaimsCurrent[field_key]="features")*(tblClaimsCurrent[status]="PROMOTED")),tblClaimsCurrent[value_text]),"UNKNOWN"),IF(v="","UNKNOWN",v)) | J27: =IF(OR([@features_text]="UNKNOWN",[@features_text]=""),NA(),1+LEN([@features_text])-LEN(SUBSTITUTE([@features_text],";",""))) | K27: =IF([@segment_id]="",NA(),IF([@segment_id]="SEG_MM",1,0)) | L27: =IF([@entity_id]="","",IF(COUNTIFS(tblClaimsCurrent[entity_id],[@entity_id],tblClaimsCurrent[field_key],"funding_round",tblClaimsCurrent[status],"PROMOTED")>0,1,0)) | M27: =IF(OR([@in_scope]=FALSE,ISNA([@coverage_pct]),ISNA([@feature_count]),ISNA([@segment_fit]),[@acv_band]="UNKNOWN"),NA(),MIN(1,Config!$B$14*MIN(1,[@feature_count]/10)+Config!$B$15*IF([@acv_band]="Low",1,IF([@acv_band]="Mid",0.5,0))+Config!$B$16*[@segment_fit]+Config!$B$17*[@funding_present])) | N27: =IF(OR([@in_scope]=FALSE,ISNA([@coverage_pct]),ISNA([@feature_count]),ISNA([@segment_fit])),NA(),MIN(1,Config!$B$18*(1-MIN(1,[@feature_count]/10))+Config!$B$19*(1-[@segment_fit])+Config!$B$20*(1-[@coverage_pct]))) | O27: =IF([@in_scope]=FALSE,"OUT_OF_SCOPE",IF(ISNA([@coverage_pct]),"UNKNOWN",IF([@coverage_pct]<Config!$B$10,"FAIL_CLOSED_LOW_COVERAGE","OK"))) | P27: =IFERROR(XLOOKUP([@entity_id],tblEntities[entity_id],tblEntities[segment_id]),"") | Q27: =IFERROR(XLOOKUP([@entity_id],tblEntities[entity_id],tblEntities[vertical]),"") | R27: =AND([@segment_id]=Dashboard!$E$2,IF(Dashboard!$E$3="All",TRUE,[@vertical]=Dashboard!$E$3))
A28: =IF(Input!$A$27="","",Input!$A$27) | B28: =IFERROR(XLOOKUP([@entity_id],tblEntities[entity_id],tblEntities[canonical_name]),"") | C28: =IF([@entity_id]="","",COUNTIFS(tblClaimsCurrent[entity_id],[@entity_id],tblClaimsCurrent[status],"PROMOTED")) | D28: =IF([@entity_id]="","",COUNTIFS(tblClaimsCurrent[entity_id],[@entity_id],tblClaimsCurrent[status],"UNKNOWN")) | E28: =LET(t,[@known_claims]+[@unknown_claims],IF(t=0,NA(),[@known_claims]/t)) | F28: =LET(cnt,COUNTIFS(tblClaimsCurrent[entity_id],[@entity_id],tblClaimsCurrent[status],"PROMOTED"),IF(cnt=0,NA(),AVERAGEIFS(tblClaimsCurrent[confidence],tblClaimsCurrent[entity_id],[@entity_id],tblClaimsCurrent[status],"PROMOTED"))) | G28: =LET(cnt,COUNTIFS(tblClaimsCurrent[entity_id],[@entity_id],tblClaimsCurrent[field_key],"pricing_acv_mid_market",tblClaimsCurrent[status],"PROMOTED"),IF(cnt=0,NA(),SUMIFS(tblClaimsCurrent[value_num],tblClaimsCurrent[entity_id],[@entity_id],tblClaimsCurrent[field_key],"pricing_acv_mid_market",tblClaimsCurrent[status],"PROMOTED"))) | H28: =IF(OR(NOT(ISNUMBER([@acv_usd])),$B$5=""),"UNKNOWN",IF([@acv_usd]<=($B$5*0.85),"Low",IF([@acv_usd]>=($B$5*1.15),"High","Mid"))) | I28: =LET(v,IFERROR(LOOKUP(2,1/((tblClaimsCurrent[entity_id]=[@entity_id])*(tblClaimsCurrent[field_key]="features")*(tblClaimsCurrent[status]="PROMOTED")),tblClaimsCurrent[value_text]),"UNKNOWN"),IF(v="","UNKNOWN",v)) | J28: =IF(OR([@features_text]="UNKNOWN",[@features_text]=""),NA(),1+LEN([@features_text])-LEN(SUBSTITUTE([@features_text],";",""))) | K28: =IF([@segment_id]="",NA(),IF([@segment_id]="SEG_MM",1,0)) | L28: =IF([@entity_id]="","",IF(COUNTIFS(tblClaimsCurrent[entity_id],[@entity_id],tblClaimsCurrent[field_key],"funding_round",tblClaimsCurrent[status],"PROMOTED")>0,1,0)) | M28: =IF(OR([@in_scope]=FALSE,ISNA([@coverage_pct]),ISNA([@feature_count]),ISNA([@segment_fit]),[@acv_band]="UNKNOWN"),NA(),MIN(1,Config!$B$14*MIN(1,[@feature_count]/10)+Config!$B$15*IF([@acv_band]="Low",1,IF([@acv_band]="Mid",0.5,0))+Config!$B$16*[@segment_fit]+Config!$B$17*[@funding_present])) | N28: =IF(OR([@in_scope]=FALSE,ISNA([@coverage_pct]),ISNA([@feature_count]),ISNA([@segment_fit])),NA(),MIN(1,Config!$B$18*(1-MIN(1,[@feature_count]/10))+Config!$B$19*(1-[@segment_fit])+Config!$B$20*(1-[@coverage_pct]))) | O28: =IF([@in_scope]=FALSE,"OUT_OF_SCOPE",IF(ISNA([@coverage_pct]),"UNKNOWN",IF([@coverage_pct]<Config!$B$10,"FAIL_CLOSED_LOW_COVERAGE","OK"))) | P28: =IFERROR(XLOOKUP([@entity_id],tblEntities[entity_id],tblEntities[segment_id]),"") | Q28: =IFERROR(XLOOKUP([@entity_id],tblEntities[entity_id],tblEntities[vertical]),"") | R28: =AND([@segment_id]=Dashboard!$E$2,IF(Dashboard!$E$3="All",TRUE,[@vertical]=Dashboard!$E$3))
A29: =IF(Input!$A$28="","",Input!$A$28) | B29: =IFERROR(XLOOKUP([@entity_id],tblEntities[entity_id],tblEntities[canonical_name]),"") | C29: =IF([@entity_id]="","",COUNTIFS(tblClaimsCurrent[entity_id],[@entity_id],tblClaimsCurrent[status],"PROMOTED")) | D29: =IF([@entity_id]="","",COUNTIFS(tblClaimsCurrent[entity_id],[@entity_id],tblClaimsCurrent[status],"UNKNOWN")) | E29: =LET(t,[@known_claims]+[@unknown_claims],IF(t=0,NA(),[@known_claims]/t)) | F29: =LET(cnt,COUNTIFS(tblClaimsCurrent[entity_id],[@entity_id],tblClaimsCurrent[status],"PROMOTED"),IF(cnt=0,NA(),AVERAGEIFS(tblClaimsCurrent[confidence],tblClaimsCurrent[entity_id],[@entity_id],tblClaimsCurrent[status],"PROMOTED"))) | G29: =LET(cnt,COUNTIFS(tblClaimsCurrent[entity_id],[@entity_id],tblClaimsCurrent[field_key],"pricing_acv_mid_market",tblClaimsCurrent[status],"PROMOTED"),IF(cnt=0,NA(),SUMIFS(tblClaimsCurrent[value_num],tblClaimsCurrent[entity_id],[@entity_id],tblClaimsCurrent[field_key],"pricing_acv_mid_market",tblClaimsCurrent[status],"PROMOTED"))) | H29: =IF(OR(NOT(ISNUMBER([@acv_usd])),$B$5=""),"UNKNOWN",IF([@acv_usd]<=($B$5*0.85),"Low",IF([@acv_usd]>=($B$5*1.15),"High","Mid"))) | I29: =LET(v,IFERROR(LOOKUP(2,1/((tblClaimsCurrent[entity_id]=[@entity_id])*(tblClaimsCurrent[field_key]="features")*(tblClaimsCurrent[status]="PROMOTED")),tblClaimsCurrent[value_text]),"UNKNOWN"),IF(v="","UNKNOWN",v)) | J29: =IF(OR([@features_text]="UNKNOWN",[@features_text]=""),NA(),1+LEN([@features_text])-LEN(SUBSTITUTE([@features_text],";",""))) | K29: =IF([@segment_id]="",NA(),IF([@segment_id]="SEG_MM",1,0)) | L29: =IF([@entity_id]="","",IF(COUNTIFS(tblClaimsCurrent[entity_id],[@entity_id],tblClaimsCurrent[field_key],"funding_round",tblClaimsCurrent[status],"PROMOTED")>0,1,0)) | M29: =IF(OR([@in_scope]=FALSE,ISNA([@coverage_pct]),ISNA([@feature_count]),ISNA([@segment_fit]),[@acv_band]="UNKNOWN"),NA(),MIN(1,Config!$B$14*MIN(1,[@feature_count]/10)+Config!$B$15*IF([@acv_band]="Low",1,IF([@acv_band]="Mid",0.5,0))+Config!$B$16*[@segment_fit]+Config!$B$17*[@funding_present])) | N29: =IF(OR([@in_scope]=FALSE,ISNA([@coverage_pct]),ISNA([@feature_count]),ISNA([@segment_fit])),NA(),MIN(1,Config!$B$18*(1-MIN(1,[@feature_count]/10))+Config!$B$19*(1-[@segment_fit])+Config!$B$20*(1-[@coverage_pct]))) | O29: =IF([@in_scope]=FALSE,"OUT_OF_SCOPE",IF(ISNA([@coverage_pct]),"UNKNOWN",IF([@coverage_pct]<Config!$B$10,"FAIL_CLOSED_LOW_COVERAGE","OK"))) | P29: =IFERROR(XLOOKUP([@entity_id],tblEntities[entity_id],tblEntities[segment_id]),"") | Q29: =IFERROR(XLOOKUP([@entity_id],tblEntities[entity_id],tblEntities[vertical]),"") | R29: =AND([@segment_id]=Dashboard!$E$2,IF(Dashboard!$E$3="All",TRUE,[@vertical]=Dashboard!$E$3))
A30: =IF(Input!$A$29="","",Input!$A$29) | B30: =IFERROR(XLOOKUP([@entity_id],tblEntities[entity_id],tblEntities[canonical_name]),"") | C30: =IF([@entity_id]="","",COUNTIFS(tblClaimsCurrent[entity_id],[@entity_id],tblClaimsCurrent[status],"PROMOTED")) | D30: =IF([@entity_id]="","",COUNTIFS(tblClaimsCurrent[entity_id],[@entity_id],tblClaimsCurrent[status],"UNKNOWN")) | E30: =LET(t,[@known_claims]+[@unknown_claims],IF(t=0,NA(),[@known_claims]/t)) | F30: =LET(cnt,COUNTIFS(tblClaimsCurrent[entity_id],[@entity_id],tblClaimsCurrent[status],"PROMOTED"),IF(cnt=0,NA(),AVERAGEIFS(tblClaimsCurrent[confidence],tblClaimsCurrent[entity_id],[@entity_id],tblClaimsCurrent[status],"PROMOTED"))) | G30: =LET(cnt,COUNTIFS(tblClaimsCurrent[entity_id],[@entity_id],tblClaimsCurrent[field_key],"pricing_acv_mid_market",tblClaimsCurrent[status],"PROMOTED"),IF(cnt=0,NA(),SUMIFS(tblClaimsCurrent[value_num],tblClaimsCurrent[entity_id],[@entity_id],tblClaimsCurrent[field_key],"pricing_acv_mid_market",tblClaimsCurrent[status],"PROMOTED"))) | H30: =IF(OR(NOT(ISNUMBER([@acv_usd])),$B$5=""),"UNKNOWN",IF([@acv_usd]<=($B$5*0.85),"Low",IF([@acv_usd]>=($B$5*1.15),"High","Mid"))) | I30: =LET(v,IFERROR(LOOKUP(2,1/((tblClaimsCurrent[entity_id]=[@entity_id])*(tblClaimsCurrent[field_key]="features")*(tblClaimsCurrent[status]="PROMOTED")),tblClaimsCurrent[value_text]),"UNKNOWN"),IF(v="","UNKNOWN",v)) | J30: =IF(OR([@features_text]="UNKNOWN",[@features_text]=""),NA(),1+LEN([@features_text])-LEN(SUBSTITUTE([@features_text],";",""))) | K30: =IF([@segment_id]="",NA(),IF([@segment_id]="SEG_MM",1,0)) | L30: =IF([@entity_id]="","",IF(COUNTIFS(tblClaimsCurrent[entity_id],[@entity_id],tblClaimsCurrent[field_key],"funding_round",tblClaimsCurrent[status],"PROMOTED")>0,1,0)) | M30: =IF(OR([@in_scope]=FALSE,ISNA([@coverage_pct]),ISNA([@feature_count]),ISNA([@segment_fit]),[@acv_band]="UNKNOWN"),NA(),MIN(1,Config!$B$14*MIN(1,[@feature_count]/10)+Config!$B$15*IF([@acv_band]="Low",1,IF([@acv_band]="Mid",0.5,0))+Config!$B$16*[@segment_fit]+Config!$B$17*[@funding_present])) | N30: =IF(OR([@in_scope]=FALSE,ISNA([@coverage_pct]),ISNA([@feature_count]),ISNA([@segment_fit])),NA(),MIN(1,Config!$B$18*(1-MIN(1,[@feature_count]/10))+Config!$B$19*(1-[@segment_fit])+Config!$B$20*(1-[@coverage_pct]))) | O30: =IF([@in_scope]=FALSE,"OUT_OF_SCOPE",IF(ISNA([@coverage_pct]),"UNKNOWN",IF([@coverage_pct]<Config!$B$10,"FAIL_CLOSED_LOW_COVERAGE","OK"))) | P30: =IFERROR(XLOOKUP([@entity_id],tblEntities[entity_id],tblEntities[segment_id]),"") | Q30: =IFERROR(XLOOKUP([@entity_id],tblEntities[entity_id],tblEntities[vertical]),"") | R30: =AND([@segment_id]=Dashboard!$E$2,IF(Dashboard!$E$3="All",TRUE,[@vertical]=Dashboard!$E$3))
A31: =IF(Input!$A$30="","",Input!$A$30) | B31: =IFERROR(XLOOKUP([@entity_id],tblEntities[entity_id],tblEntities[canonical_name]),"") | C31: =IF([@entity_id]="","",COUNTIFS(tblClaimsCurrent[entity_id],[@entity_id],tblClaimsCurrent[status],"PROMOTED")) | D31: =IF([@entity_id]="","",COUNTIFS(tblClaimsCurrent[entity_id],[@entity_id],tblClaimsCurrent[status],"UNKNOWN")) | E31: =LET(t,[@known_claims]+[@unknown_claims],IF(t=0,NA(),[@known_claims]/t)) | F31: =LET(cnt,COUNTIFS(tblClaimsCurrent[entity_id],[@entity_id],tblClaimsCurrent[status],"PROMOTED"),IF(cnt=0,NA(),AVERAGEIFS(tblClaimsCurrent[confidence],tblClaimsCurrent[entity_id],[@entity_id],tblClaimsCurrent[status],"PROMOTED"))) | G31: =LET(cnt,COUNTIFS(tblClaimsCurrent[entity_id],[@entity_id],tblClaimsCurrent[field_key],"pricing_acv_mid_market",tblClaimsCurrent[status],"PROMOTED"),IF(cnt=0,NA(),SUMIFS(tblClaimsCurrent[value_num],tblClaimsCurrent[entity_id],[@entity_id],tblClaimsCurrent[field_key],"pricing_acv_mid_market",tblClaimsCurrent[status],"PROMOTED"))) | H31: =IF(OR(NOT(ISNUMBER([@acv_usd])),$B$5=""),"UNKNOWN",IF([@acv_usd]<=($B$5*0.85),"Low",IF([@acv_usd]>=($B$5*1.15),"High","Mid"))) | I31: =LET(v,IFERROR(LOOKUP(2,1/((tblClaimsCurrent[entity_id]=[@entity_id])*(tblClaimsCurrent[field_key]="features")*(tblClaimsCurrent[status]="PROMOTED")),tblClaimsCurrent[value_text]),"UNKNOWN"),IF(v="","UNKNOWN",v)) | J31: =IF(OR([@features_text]="UNKNOWN",[@features_text]=""),NA(),1+LEN([@features_text])-LEN(SUBSTITUTE([@features_text],";",""))) | K31: =IF([@segment_id]="",NA(),IF([@segment_id]="SEG_MM",1,0)) | L31: =IF([@entity_id]="","",IF(COUNTIFS(tblClaimsCurrent[entity_id],[@entity_id],tblClaimsCurrent[field_key],"funding_round",tblClaimsCurrent[status],"PROMOTED")>0,1,0)) | M31: =IF(OR([@in_scope]=FALSE,ISNA([@coverage_pct]),ISNA([@feature_count]),ISNA([@segment_fit]),[@acv_band]="UNKNOWN"),NA(),MIN(1,Config!$B$14*MIN(1,[@feature_count]/10)+Config!$B$15*IF([@acv_band]="Low",1,IF([@acv_band]="Mid",0.5,0))+Config!$B$16*[@segment_fit]+Config!$B$17*[@funding_present])) | N31: =IF(OR([@in_scope]=FALSE,ISNA([@coverage_pct]),ISNA([@feature_count]),ISNA([@segment_fit])),NA(),MIN(1,Config!$B$18*(1-MIN(1,[@feature_count]/10))+Config!$B$19*(1-[@segment_fit])+Config!$B$20*(1-[@coverage_pct]))) | O31: =IF([@in_scope]=FALSE,"OUT_OF_SCOPE",IF(ISNA([@coverage_pct]),"UNKNOWN",IF([@coverage_pct]<Config!$B$10,"FAIL_CLOSED_LOW_COVERAGE","OK"))) | P31: =IFERROR(XLOOKUP([@entity_id],tblEntities[entity_id],tblEntities[segment_id]),"") | Q31: =IFERROR(XLOOKUP([@entity_id],tblEntities[entity_id],tblEntities[vertical]),"") | R31: =AND([@segment_id]=Dashboard!$E$2,IF(Dashboard!$E$3="All",TRUE,[@vertical]=Dashboard!$E$3))
A32: =IF(Input!$A$31="","",Input!$A$31) | B32: =IFERROR(XLOOKUP([@entity_id],tblEntities[entity_id],tblEntities[canonical_name]),"") | C32: =IF([@entity_id]="","",COUNTIFS(tblClaimsCurrent[entity_id],[@entity_id],tblClaimsCurrent[status],"PROMOTED")) | D32: =IF([@entity_id]="","",COUNTIFS(tblClaimsCurrent[entity_id],[@entity_id],tblClaimsCurrent[status],"UNKNOWN")) | E32: =LET(t,[@known_claims]+[@unknown_claims],IF(t=0,NA(),[@known_claims]/t)) | F32: =LET(cnt,COUNTIFS(tblClaimsCurrent[entity_id],[@entity_id],tblClaimsCurrent[status],"PROMOTED"),IF(cnt=0,NA(),AVERAGEIFS(tblClaimsCurrent[confidence],tblClaimsCurrent[entity_id],[@entity_id],tblClaimsCurrent[status],"PROMOTED"))) | G32: =LET(cnt,COUNTIFS(tblClaimsCurrent[entity_id],[@entity_id],tblClaimsCurrent[field_key],"pricing_acv_mid_market",tblClaimsCurrent[status],"PROMOTED"),IF(cnt=0,NA(),SUMIFS(tblClaimsCurrent[value_num],tblClaimsCurrent[entity_id],[@entity_id],tblClaimsCurrent[field_key],"pricing_acv_mid_market",tblClaimsCurrent[status],"PROMOTED"))) | H32: =IF(OR(NOT(ISNUMBER([@acv_usd])),$B$5=""),"UNKNOWN",IF([@acv_usd]<=($B$5*0.85),"Low",IF([@acv_usd]>=($B$5*1.15),"High","Mid"))) | I32: =LET(v,IFERROR(LOOKUP(2,1/((tblClaimsCurrent[entity_id]=[@entity_id])*(tblClaimsCurrent[field_key]="features")*(tblClaimsCurrent[status]="PROMOTED")),tblClaimsCurrent[value_text]),"UNKNOWN"),IF(v="","UNKNOWN",v)) | J32: =IF(OR([@features_text]="UNKNOWN",[@features_text]=""),NA(),1+LEN([@features_text])-LEN(SUBSTITUTE([@features_text],";",""))) | K32: =IF([@segment_id]="",NA(),IF([@segment_id]="SEG_MM",1,0)) | L32: =IF([@entity_id]="","",IF(COUNTIFS(tblClaimsCurrent[entity_id],[@entity_id],tblClaimsCurrent[field_key],"funding_round",tblClaimsCurrent[status],"PROMOTED")>0,1,0)) | M32: =IF(OR([@in_scope]=FALSE,ISNA([@coverage_pct]),ISNA([@feature_count]),ISNA([@segment_fit]),[@acv_band]="UNKNOWN"),NA(),MIN(1,Config!$B$14*MIN(1,[@feature_count]/10)+Config!$B$15*IF([@acv_band]="Low",1,IF([@acv_band]="Mid",0.5,0))+Config!$B$16*[@segment_fit]+Config!$B$17*[@funding_present])) | N32: =IF(OR([@in_scope]=FALSE,ISNA([@coverage_pct]),ISNA([@feature_count]),ISNA([@segment_fit])),NA(),MIN(1,Config!$B$18*(1-MIN(1,[@feature_count]/10))+Config!$B$19*(1-[@segment_fit])+Config!$B$20*(1-[@coverage_pct]))) | O32: =IF([@in_scope]=FALSE,"OUT_OF_SCOPE",IF(ISNA([@coverage_pct]),"UNKNOWN",IF([@coverage_pct]<Config!$B$10,"FAIL_CLOSED_LOW_COVERAGE","OK"))) | P32: =IFERROR(XLOOKUP([@entity_id],tblEntities[entity_id],tblEntities[segment_id]),"") | Q32: =IFERROR(XLOOKUP([@entity_id],tblEntities[entity_id],tblEntities[vertical]),"") | R32: =AND([@segment_id]=Dashboard!$E$2,IF(Dashboard!$E$3="All",TRUE,[@vertical]=Dashboard!$E$3))
A33: =IF(Input!$A$32="","",Input!$A$32) | B33: =IFERROR(XLOOKUP([@entity_id],tblEntities[entity_id],tblEntities[canonical_name]),"") | C33: =IF([@entity_id]="","",COUNTIFS(tblClaimsCurrent[entity_id],[@entity_id],tblClaimsCurrent[status],"PROMOTED")) | D33: =IF([@entity_id]="","",COUNTIFS(tblClaimsCurrent[entity_id],[@entity_id],tblClaimsCurrent[status],"UNKNOWN")) | E33: =LET(t,[@known_claims]+[@unknown_claims],IF(t=0,NA(),[@known_claims]/t)) | F33: =LET(cnt,COUNTIFS(tblClaimsCurrent[entity_id],[@entity_id],tblClaimsCurrent[status],"PROMOTED"),IF(cnt=0,NA(),AVERAGEIFS(tblClaimsCurrent[confidence],tblClaimsCurrent[entity_id],[@entity_id],tblClaimsCurrent[status],"PROMOTED"))) | G33: =LET(cnt,COUNTIFS(tblClaimsCurrent[entity_id],[@entity_id],tblClaimsCurrent[field_key],"pricing_acv_mid_market",tblClaimsCurrent[status],"PROMOTED"),IF(cnt=0,NA(),SUMIFS(tblClaimsCurrent[value_num],tblClaimsCurrent[entity_id],[@entity_id],tblClaimsCurrent[field_key],"pricing_acv_mid_market",tblClaimsCurrent[status],"PROMOTED"))) | H33: =IF(OR(NOT(ISNUMBER([@acv_usd])),$B$5=""),"UNKNOWN",IF([@acv_usd]<=($B$5*0.85),"Low",IF([@acv_usd]>=($B$5*1.15),"High","Mid"))) | I33: =LET(v,IFERROR(LOOKUP(2,1/((tblClaimsCurrent[entity_id]=[@entity_id])*(tblClaimsCurrent[field_key]="features")*(tblClaimsCurrent[status]="PROMOTED")),tblClaimsCurrent[value_text]),"UNKNOWN"),IF(v="","UNKNOWN",v)) | J33: =IF(OR([@features_text]="UNKNOWN",[@features_text]=""),NA(),1+LEN([@features_text])-LEN(SUBSTITUTE([@features_text],";",""))) | K33: =IF([@segment_id]="",NA(),IF([@segment_id]="SEG_MM",1,0)) | L33: =IF([@entity_id]="","",IF(COUNTIFS(tblClaimsCurrent[entity_id],[@entity_id],tblClaimsCurrent[field_key],"funding_round",tblClaimsCurrent[status],"PROMOTED")>0,1,0)) | M33: =IF(OR([@in_scope]=FALSE,ISNA([@coverage_pct]),ISNA([@feature_count]),ISNA([@segment_fit]),[@acv_band]="UNKNOWN"),NA(),MIN(1,Config!$B$14*MIN(1,[@feature_count]/10)+Config!$B$15*IF([@acv_band]="Low",1,IF([@acv_band]="Mid",0.5,0))+Config!$B$16*[@segment_fit]+Config!$B$17*[@funding_present])) | N33: =IF(OR([@in_scope]=FALSE,ISNA([@coverage_pct]),ISNA([@feature_count]),ISNA([@segment_fit])),NA(),MIN(1,Config!$B$18*(1-MIN(1,[@feature_count]/10))+Config!$B$19*(1-[@segment_fit])+Config!$B$20*(1-[@coverage_pct]))) | O33: =IF([@in_scope]=FALSE,"OUT_OF_SCOPE",IF(ISNA([@coverage_pct]),"UNKNOWN",IF([@coverage_pct]<Config!$B$10,"FAIL_CLOSED_LOW_COVERAGE","OK"))) | P33: =IFERROR(XLOOKUP([@entity_id],tblEntities[entity_id],tblEntities[segment_id]),"") | Q33: =IFERROR(XLOOKUP([@entity_id],tblEntities[entity_id],tblEntities[vertical]),"") | R33: =AND([@segment_id]=Dashboard!$E$2,IF(Dashboard!$E$3="All",TRUE,[@vertical]=Dashboard!$E$3))
A34: =IF(Input!$A$33="","",Input!$A$33) | B34: =IFERROR(XLOOKUP([@entity_id],tblEntities[entity_id],tblEntities[canonical_name]),"") | C34: =IF([@entity_id]="","",COUNTIFS(tblClaimsCurrent[entity_id],[@entity_id],tblClaimsCurrent[status],"PROMOTED")) | D34: =IF([@entity_id]="","",COUNTIFS(tblClaimsCurrent[entity_id],[@entity_id],tblClaimsCurrent[status],"UNKNOWN")) | E34: =LET(t,[@known_claims]+[@unknown_claims],IF(t=0,NA(),[@known_claims]/t)) | F34: =LET(cnt,COUNTIFS(tblClaimsCurrent[entity_id],[@entity_id],tblClaimsCurrent[status],"PROMOTED"),IF(cnt=0,NA(),AVERAGEIFS(tblClaimsCurrent[confidence],tblClaimsCurrent[entity_id],[@entity_id],tblClaimsCurrent[status],"PROMOTED"))) | G34: =LET(cnt,COUNTIFS(tblClaimsCurrent[entity_id],[@entity_id],tblClaimsCurrent[field_key],"pricing_acv_mid_market",tblClaimsCurrent[status],"PROMOTED"),IF(cnt=0,NA(),SUMIFS(tblClaimsCurrent[value_num],tblClaimsCurrent[entity_id],[@entity_id],tblClaimsCurrent[field_key],"pricing_acv_mid_market",tblClaimsCurrent[status],"PROMOTED"))) | H34: =IF(OR(NOT(ISNUMBER([@acv_usd])),$B$5=""),"UNKNOWN",IF([@acv_usd]<=($B$5*0.85),"Low",IF([@acv_usd]>=($B$5*1.15),"High","Mid"))) | I34: =LET(v,IFERROR(LOOKUP(2,1/((tblClaimsCurrent[entity_id]=[@entity_id])*(tblClaimsCurrent[field_key]="features")*(tblClaimsCurrent[status]="PROMOTED")),tblClaimsCurrent[value_text]),"UNKNOWN"),IF(v="","UNKNOWN",v)) | J34: =IF(OR([@features_text]="UNKNOWN",[@features_text]=""),NA(),1+LEN([@features_text])-LEN(SUBSTITUTE([@features_text],";",""))) | K34: =IF([@segment_id]="",NA(),IF([@segment_id]="SEG_MM",1,0)) | L34: =IF([@entity_id]="","",IF(COUNTIFS(tblClaimsCurrent[entity_id],[@entity_id],tblClaimsCurrent[field_key],"funding_round",tblClaimsCurrent[status],"PROMOTED")>0,1,0)) | M34: =IF(OR([@in_scope]=FALSE,ISNA([@coverage_pct]),ISNA([@feature_count]),ISNA([@segment_fit]),[@acv_band]="UNKNOWN"),NA(),MIN(1,Config!$B$14*MIN(1,[@feature_count]/10)+Config!$B$15*IF([@acv_band]="Low",1,IF([@acv_band]="Mid",0.5,0))+Config!$B$16*[@segment_fit]+Config!$B$17*[@funding_present])) | N34: =IF(OR([@in_scope]=FALSE,ISNA([@coverage_pct]),ISNA([@feature_count]),ISNA([@segment_fit])),NA(),MIN(1,Config!$B$18*(1-MIN(1,[@feature_count]/10))+Config!$B$19*(1-[@segment_fit])+Config!$B$20*(1-[@coverage_pct]))) | O34: =IF([@in_scope]=FALSE,"OUT_OF_SCOPE",IF(ISNA([@coverage_pct]),"UNKNOWN",IF([@coverage_pct]<Config!$B$10,"FAIL_CLOSED_LOW_COVERAGE","OK"))) | P34: =IFERROR(XLOOKUP([@entity_id],tblEntities[entity_id],tblEntities[segment_id]),"") | Q34: =IFERROR(XLOOKUP([@entity_id],tblEntities[entity_id],tblEntities[vertical]),"") | R34: =AND([@segment_id]=Dashboard!$E$2,IF(Dashboard!$E$3="All",TRUE,[@vertical]=Dashboard!$E$3))
A35: =IF(Input!$A$34="","",Input!$A$34) | B35: =IFERROR(XLOOKUP([@entity_id],tblEntities[entity_id],tblEntities[canonical_name]),"") | C35: =IF([@entity_id]="","",COUNTIFS(tblClaimsCurrent[entity_id],[@entity_id],tblClaimsCurrent[status],"PROMOTED")) | D35: =IF([@entity_id]="","",COUNTIFS(tblClaimsCurrent[entity_id],[@entity_id],tblClaimsCurrent[status],"UNKNOWN")) | E35: =LET(t,[@known_claims]+[@unknown_claims],IF(t=0,NA(),[@known_claims]/t)) | F35: =LET(cnt,COUNTIFS(tblClaimsCurrent[entity_id],[@entity_id],tblClaimsCurrent[status],"PROMOTED"),IF(cnt=0,NA(),AVERAGEIFS(tblClaimsCurrent[confidence],tblClaimsCurrent[entity_id],[@entity_id],tblClaimsCurrent[status],"PROMOTED"))) | G35: =LET(cnt,COUNTIFS(tblClaimsCurrent[entity_id],[@entity_id],tblClaimsCurrent[field_key],"pricing_acv_mid_market",tblClaimsCurrent[status],"PROMOTED"),IF(cnt=0,NA(),SUMIFS(tblClaimsCurrent[value_num],tblClaimsCurrent[entity_id],[@entity_id],tblClaimsCurrent[field_key],"pricing_acv_mid_market",tblClaimsCurrent[status],"PROMOTED"))) | H35: =IF(OR(NOT(ISNUMBER([@acv_usd])),$B$5=""),"UNKNOWN",IF([@acv_usd]<=($B$5*0.85),"Low",IF([@acv_usd]>=($B$5*1.15),"High","Mid"))) | I35: =LET(v,IFERROR(LOOKUP(2,1/((tblClaimsCurrent[entity_id]=[@entity_id])*(tblClaimsCurrent[field_key]="features")*(tblClaimsCurrent[status]="PROMOTED")),tblClaimsCurrent[value_text]),"UNKNOWN"),IF(v="","UNKNOWN",v)) | J35: =IF(OR([@features_text]="UNKNOWN",[@features_text]=""),NA(),1+LEN([@features_text])-LEN(SUBSTITUTE([@features_text],";",""))) | K35: =IF([@segment_id]="",NA(),IF([@segment_id]="SEG_MM",1,0)) | L35: =IF([@entity_id]="","",IF(COUNTIFS(tblClaimsCurrent[entity_id],[@entity_id],tblClaimsCurrent[field_key],"funding_round",tblClaimsCurrent[status],"PROMOTED")>0,1,0)) | M35: =IF(OR([@in_scope]=FALSE,ISNA([@coverage_pct]),ISNA([@feature_count]),ISNA([@segment_fit]),[@acv_band]="UNKNOWN"),NA(),MIN(1,Config!$B$14*MIN(1,[@feature_count]/10)+Config!$B$15*IF([@acv_band]="Low",1,IF([@acv_band]="Mid",0.5,0))+Config!$B$16*[@segment_fit]+Config!$B$17*[@funding_present])) | N35: =IF(OR([@in_scope]=FALSE,ISNA([@coverage_pct]),ISNA([@feature_count]),ISNA([@segment_fit])),NA(),MIN(1,Config!$B$18*(1-MIN(1,[@feature_count]/10))+Config!$B$19*(1-[@segment_fit])+Config!$B$20*(1-[@coverage_pct]))) | O35: =IF([@in_scope]=FALSE,"OUT_OF_SCOPE",IF(ISNA([@coverage_pct]),"UNKNOWN",IF([@coverage_pct]<Config!$B$10,"FAIL_CLOSED_LOW_COVERAGE","OK"))) | P35: =IFERROR(XLOOKUP([@entity_id],tblEntities[entity_id],tblEntities[segment_id]),"") | Q35: =IFERROR(XLOOKUP([@entity_id],tblEntities[entity_id],tblEntities[vertical]),"") | R35: =AND([@segment_id]=Dashboard!$E$2,IF(Dashboard!$E$3="All",TRUE,[@vertical]=Dashboard!$E$3))
A36: =IF(Input!$A$35="","",Input!$A$35) | B36: =IFERROR(XLOOKUP([@entity_id],tblEntities[entity_id],tblEntities[canonical_name]),"") | C36: =IF([@entity_id]="","",COUNTIFS(tblClaimsCurrent[entity_id],[@entity_id],tblClaimsCurrent[status],"PROMOTED")) | D36: =IF([@entity_id]="","",COUNTIFS(tblClaimsCurrent[entity_id],[@entity_id],tblClaimsCurrent[status],"UNKNOWN")) | E36: =LET(t,[@known_claims]+[@unknown_claims],IF(t=0,NA(),[@known_claims]/t)) | F36: =LET(cnt,COUNTIFS(tblClaimsCurrent[entity_id],[@entity_id],tblClaimsCurrent[status],"PROMOTED"),IF(cnt=0,NA(),AVERAGEIFS(tblClaimsCurrent[confidence],tblClaimsCurrent[entity_id],[@entity_id],tblClaimsCurrent[status],"PROMOTED"))) | G36: =LET(cnt,COUNTIFS(tblClaimsCurrent[entity_id],[@entity_id],tblClaimsCurrent[field_key],"pricing_acv_mid_market",tblClaimsCurrent[status],"PROMOTED"),IF(cnt=0,NA(),SUMIFS(tblClaimsCurrent[value_num],tblClaimsCurrent[entity_id],[@entity_id],tblClaimsCurrent[field_key],"pricing_acv_mid_market",tblClaimsCurrent[status],"PROMOTED"))) | H36: =IF(OR(NOT(ISNUMBER([@acv_usd])),$B$5=""),"UNKNOWN",IF([@acv_usd]<=($B$5*0.85),"Low",IF([@acv_usd]>=($B$5*1.15),"High","Mid"))) | I36: =LET(v,IFERROR(LOOKUP(2,1/((tblClaimsCurrent[entity_id]=[@entity_id])*(tblClaimsCurrent[field_key]="features")*(tblClaimsCurrent[status]="PROMOTED")),tblClaimsCurrent[value_text]),"UNKNOWN"),IF(v="","UNKNOWN",v)) | J36: =IF(OR([@features_text]="UNKNOWN",[@features_text]=""),NA(),1+LEN([@features_text])-LEN(SUBSTITUTE([@features_text],";",""))) | K36: =IF([@segment_id]="",NA(),IF([@segment_id]="SEG_MM",1,0)) | L36: =IF([@entity_id]="","",IF(COUNTIFS(tblClaimsCurrent[entity_id],[@entity_id],tblClaimsCurrent[field_key],"funding_round",tblClaimsCurrent[status],"PROMOTED")>0,1,0)) | M36: =IF(OR([@in_scope]=FALSE,ISNA([@coverage_pct]),ISNA([@feature_count]),ISNA([@segment_fit]),[@acv_band]="UNKNOWN"),NA(),MIN(1,Config!$B$14*MIN(1,[@feature_count]/10)+Config!$B$15*IF([@acv_band]="Low",1,IF([@acv_band]="Mid",0.5,0))+Config!$B$16*[@segment_fit]+Config!$B$17*[@funding_present])) | N36: =IF(OR([@in_scope]=FALSE,ISNA([@coverage_pct]),ISNA([@feature_count]),ISNA([@segment_fit])),NA(),MIN(1,Config!$B$18*(1-MIN(1,[@feature_count]/10))+Config!$B$19*(1-[@segment_fit])+Config!$B$20*(1-[@coverage_pct]))) | O36: =IF([@in_scope]=FALSE,"OUT_OF_SCOPE",IF(ISNA([@coverage_pct]),"UNKNOWN",IF([@coverage_pct]<Config!$B$10,"FAIL_CLOSED_LOW_COVERAGE","OK"))) | P36: =IFERROR(XLOOKUP([@entity_id],tblEntities[entity_id],tblEntities[segment_id]),"") | Q36: =IFERROR(XLOOKUP([@entity_id],tblEntities[entity_id],tblEntities[vertical]),"") | R36: =AND([@segment_id]=Dashboard!$E$2,IF(Dashboard!$E$3="All",TRUE,[@vertical]=Dashboard!$E$3))
A37: =IF(Input!$A$36="","",Input!$A$36) | B37: =IFERROR(XLOOKUP([@entity_id],tblEntities[entity_id],tblEntities[canonical_name]),"") | C37: =IF([@entity_id]="","",COUNTIFS(tblClaimsCurrent[entity_id],[@entity_id],tblClaimsCurrent[status],"PROMOTED")) | D37: =IF([@entity_id]="","",COUNTIFS(tblClaimsCurrent[entity_id],[@entity_id],tblClaimsCurrent[status],"UNKNOWN")) | E37: =LET(t,[@known_claims]+[@unknown_claims],IF(t=0,NA(),[@known_claims]/t)) | F37: =LET(cnt,COUNTIFS(tblClaimsCurrent[entity_id],[@entity_id],tblClaimsCurrent[status],"PROMOTED"),IF(cnt=0,NA(),AVERAGEIFS(tblClaimsCurrent[confidence],tblClaimsCurrent[entity_id],[@entity_id],tblClaimsCurrent[status],"PROMOTED"))) | G37: =LET(cnt,COUNTIFS(tblClaimsCurrent[entity_id],[@entity_id],tblClaimsCurrent[field_key],"pricing_acv_mid_market",tblClaimsCurrent[status],"PROMOTED"),IF(cnt=0,NA(),SUMIFS(tblClaimsCurrent[value_num],tblClaimsCurrent[entity_id],[@entity_id],tblClaimsCurrent[field_key],"pricing_acv_mid_market",tblClaimsCurrent[status],"PROMOTED"))) | H37: =IF(OR(NOT(ISNUMBER([@acv_usd])),$B$5=""),"UNKNOWN",IF([@acv_usd]<=($B$5*0.85),"Low",IF([@acv_usd]>=($B$5*1.15),"High","Mid"))) | I37: =LET(v,IFERROR(LOOKUP(2,1/((tblClaimsCurrent[entity_id]=[@entity_id])*(tblClaimsCurrent[field_key]="features")*(tblClaimsCurrent[status]="PROMOTED")),tblClaimsCurrent[value_text]),"UNKNOWN"),IF(v="","UNKNOWN",v)) | J37: =IF(OR([@features_text]="UNKNOWN",[@features_text]=""),NA(),1+LEN([@features_text])-LEN(SUBSTITUTE([@features_text],";",""))) | K37: =IF([@segment_id]="",NA(),IF([@segment_id]="SEG_MM",1,0)) | L37: =IF([@entity_id]="","",IF(COUNTIFS(tblClaimsCurrent[entity_id],[@entity_id],tblClaimsCurrent[field_key],"funding_round",tblClaimsCurrent[status],"PROMOTED")>0,1,0)) | M37: =IF(OR([@in_scope]=FALSE,ISNA([@coverage_pct]),ISNA([@feature_count]),ISNA([@segment_fit]),[@acv_band]="UNKNOWN"),NA(),MIN(1,Config!$B$14*MIN(1,[@feature_count]/10)+Config!$B$15*IF([@acv_band]="Low",1,IF([@acv_band]="Mid",0.5,0))+Config!$B$16*[@segment_fit]+Config!$B$17*[@funding_present])) | N37: =IF(OR([@in_scope]=FALSE,ISNA([@coverage_pct]),ISNA([@feature_count]),ISNA([@segment_fit])),NA(),MIN(1,Config!$B$18*(1-MIN(1,[@feature_count]/10))+Config!$B$19*(1-[@segment_fit])+Config!$B$20*(1-[@coverage_pct]))) | O37: =IF([@in_scope]=FALSE,"OUT_OF_SCOPE",IF(ISNA([@coverage_pct]),"UNKNOWN",IF([@coverage_pct]<Config!$B$10,"FAIL_CLOSED_LOW_COVERAGE","OK"))) | P37: =IFERROR(XLOOKUP([@entity_id],tblEntities[entity_id],tblEntities[segment_id]),"") | Q37: =IFERROR(XLOOKUP([@entity_id],tblEntities[entity_id],tblEntities[vertical]),"") | R37: =AND([@segment_id]=Dashboard!$E$2,IF(Dashboard!$E$3="All",TRUE,[@vertical]=Dashboard!$E$3))
A38: =IF(Input!$A$37="","",Input!$A$37) | B38: =IFERROR(XLOOKUP([@entity_id],tblEntities[entity_id],tblEntities[canonical_name]),"") | C38: =IF([@entity_id]="","",COUNTIFS(tblClaimsCurrent[entity_id],[@entity_id],tblClaimsCurrent[status],"PROMOTED")) | D38: =IF([@entity_id]="","",COUNTIFS(tblClaimsCurrent[entity_id],[@entity_id],tblClaimsCurrent[status],"UNKNOWN")) | E38: =LET(t,[@known_claims]+[@unknown_claims],IF(t=0,NA(),[@known_claims]/t)) | F38: =LET(cnt,COUNTIFS(tblClaimsCurrent[entity_id],[@entity_id],tblClaimsCurrent[status],"PROMOTED"),IF(cnt=0,NA(),AVERAGEIFS(tblClaimsCurrent[confidence],tblClaimsCurrent[entity_id],[@entity_id],tblClaimsCurrent[status],"PROMOTED"))) | G38: =LET(cnt,COUNTIFS(tblClaimsCurrent[entity_id],[@entity_id],tblClaimsCurrent[field_key],"pricing_acv_mid_market",tblClaimsCurrent[status],"PROMOTED"),IF(cnt=0,NA(),SUMIFS(tblClaimsCurrent[value_num],tblClaimsCurrent[entity_id],[@entity_id],tblClaimsCurrent[field_key],"pricing_acv_mid_market",tblClaimsCurrent[status],"PROMOTED"))) | H38: =IF(OR(NOT(ISNUMBER([@acv_usd])),$B$5=""),"UNKNOWN",IF([@acv_usd]<=($B$5*0.85),"Low",IF([@acv_usd]>=($B$5*1.15),"High","Mid"))) | I38: =LET(v,IFERROR(LOOKUP(2,1/((tblClaimsCurrent[entity_id]=[@entity_id])*(tblClaimsCurrent[field_key]="features")*(tblClaimsCurrent[status]="PROMOTED")),tblClaimsCurrent[value_text]),"UNKNOWN"),IF(v="","UNKNOWN",v)) | J38: =IF(OR([@features_text]="UNKNOWN",[@features_text]=""),NA(),1+LEN([@features_text])-LEN(SUBSTITUTE([@features_text],";",""))) | K38: =IF([@segment_id]="",NA(),IF([@segment_id]="SEG_MM",1,0)) | L38: =IF([@entity_id]="","",IF(COUNTIFS(tblClaimsCurrent[entity_id],[@entity_id],tblClaimsCurrent[field_key],"funding_round",tblClaimsCurrent[status],"PROMOTED")>0,1,0)) | M38: =IF(OR([@in_scope]=FALSE,ISNA([@coverage_pct]),ISNA([@feature_count]),ISNA([@segment_fit]),[@acv_band]="UNKNOWN"),NA(),MIN(1,Config!$B$14*MIN(1,[@feature_count]/10)+Config!$B$15*IF([@acv_band]="Low",1,IF([@acv_band]="Mid",0.5,0))+Config!$B$16*[@segment_fit]+Config!$B$17*[@funding_present])) | N38: =IF(OR([@in_scope]=FALSE,ISNA([@coverage_pct]),ISNA([@feature_count]),ISNA([@segment_fit])),NA(),MIN(1,Config!$B$18*(1-MIN(1,[@feature_count]/10))+Config!$B$19*(1-[@segment_fit])+Config!$B$20*(1-[@coverage_pct]))) | O38: =IF([@in_scope]=FALSE,"OUT_OF_SCOPE",IF(ISNA([@coverage_pct]),"UNKNOWN",IF([@coverage_pct]<Config!$B$10,"FAIL_CLOSED_LOW_COVERAGE","OK"))) | P38: =IFERROR(XLOOKUP([@entity_id],tblEntities[entity_id],tblEntities[segment_id]),"") | Q38: =IFERROR(XLOOKUP([@entity_id],tblEntities[entity_id],tblEntities[vertical]),"") | R38: =AND([@segment_id]=Dashboard!$E$2,IF(Dashboard!$E$3="All",TRUE,[@vertical]=Dashboard!$E$3))
A39: =IF(Input!$A$38="","",Input!$A$38) | B39: =IFERROR(XLOOKUP([@entity_id],tblEntities[entity_id],tblEntities[canonical_name]),"") | C39: =IF([@entity_id]="","",COUNTIFS(tblClaimsCurrent[entity_id],[@entity_id],tblClaimsCurrent[status],"PROMOTED")) | D39: =IF([@entity_id]="","",COUNTIFS(tblClaimsCurrent[entity_id],[@entity_id],tblClaimsCurrent[status],"UNKNOWN")) | E39: =LET(t,[@known_claims]+[@unknown_claims],IF(t=0,NA(),[@known_claims]/t)) | F39: =LET(cnt,COUNTIFS(tblClaimsCurrent[entity_id],[@entity_id],tblClaimsCurrent[status],"PROMOTED"),IF(cnt=0,NA(),AVERAGEIFS(tblClaimsCurrent[confidence],tblClaimsCurrent[entity_id],[@entity_id],tblClaimsCurrent[status],"PROMOTED"))) | G39: =LET(cnt,COUNTIFS(tblClaimsCurrent[entity_id],[@entity_id],tblClaimsCurrent[field_key],"pricing_acv_mid_market",tblClaimsCurrent[status],"PROMOTED"),IF(cnt=0,NA(),SUMIFS(tblClaimsCurrent[value_num],tblClaimsCurrent[entity_id],[@entity_id],tblClaimsCurrent[field_key],"pricing_acv_mid_market",tblClaimsCurrent[status],"PROMOTED"))) | H39: =IF(OR(NOT(ISNUMBER([@acv_usd])),$B$5=""),"UNKNOWN",IF([@acv_usd]<=($B$5*0.85),"Low",IF([@acv_usd]>=($B$5*1.15),"High","Mid"))) | I39: =LET(v,IFERROR(LOOKUP(2,1/((tblClaimsCurrent[entity_id]=[@entity_id])*(tblClaimsCurrent[field_key]="features")*(tblClaimsCurrent[status]="PROMOTED")),tblClaimsCurrent[value_text]),"UNKNOWN"),IF(v="","UNKNOWN",v)) | J39: =IF(OR([@features_text]="UNKNOWN",[@features_text]=""),NA(),1+LEN([@features_text])-LEN(SUBSTITUTE([@features_text],";",""))) | K39: =IF([@segment_id]="",NA(),IF([@segment_id]="SEG_MM",1,0)) | L39: =IF([@entity_id]="","",IF(COUNTIFS(tblClaimsCurrent[entity_id],[@entity_id],tblClaimsCurrent[field_key],"funding_round",tblClaimsCurrent[status],"PROMOTED")>0,1,0)) | M39: =IF(OR([@in_scope]=FALSE,ISNA([@coverage_pct]),ISNA([@feature_count]),ISNA([@segment_fit]),[@acv_band]="UNKNOWN"),NA(),MIN(1,Config!$B$14*MIN(1,[@feature_count]/10)+Config!$B$15*IF([@acv_band]="Low",1,IF([@acv_band]="Mid",0.5,0))+Config!$B$16*[@segment_fit]+Config!$B$17*[@funding_present])) | N39: =IF(OR([@in_scope]=FALSE,ISNA([@coverage_pct]),ISNA([@feature_count]),ISNA([@segment_fit])),NA(),MIN(1,Config!$B$18*(1-MIN(1,[@feature_count]/10))+Config!$B$19*(1-[@segment_fit])+Config!$B$20*(1-[@coverage_pct]))) | O39: =IF([@in_scope]=FALSE,"OUT_OF_SCOPE",IF(ISNA([@coverage_pct]),"UNKNOWN",IF([@coverage_pct]<Config!$B$10,"FAIL_CLOSED_LOW_COVERAGE","OK"))) | P39: =IFERROR(XLOOKUP([@entity_id],tblEntities[entity_id],tblEntities[segment_id]),"") | Q39: =IFERROR(XLOOKUP([@entity_id],tblEntities[entity_id],tblEntities[vertical]),"") | R39: =AND([@segment_id]=Dashboard!$E$2,IF(Dashboard!$E$3="All",TRUE,[@vertical]=Dashboard!$E$3))
A40: =IF(Input!$A$39="","",Input!$A$39) | B40: =IFERROR(XLOOKUP([@entity_id],tblEntities[entity_id],tblEntities[canonical_name]),"") | C40: =IF([@entity_id]="","",COUNTIFS(tblClaimsCurrent[entity_id],[@entity_id],tblClaimsCurrent[status],"PROMOTED")) | D40: =IF([@entity_id]="","",COUNTIFS(tblClaimsCurrent[entity_id],[@entity_id],tblClaimsCurrent[status],"UNKNOWN")) | E40: =LET(t,[@known_claims]+[@unknown_claims],IF(t=0,NA(),[@known_claims]/t)) | F40: =LET(cnt,COUNTIFS(tblClaimsCurrent[entity_id],[@entity_id],tblClaimsCurrent[status],"PROMOTED"),IF(cnt=0,NA(),AVERAGEIFS(tblClaimsCurrent[confidence],tblClaimsCurrent[entity_id],[@entity_id],tblClaimsCurrent[status],"PROMOTED"))) | G40: =LET(cnt,COUNTIFS(tblClaimsCurrent[entity_id],[@entity_id],tblClaimsCurrent[field_key],"pricing_acv_mid_market",tblClaimsCurrent[status],"PROMOTED"),IF(cnt=0,NA(),SUMIFS(tblClaimsCurrent[value_num],tblClaimsCurrent[entity_id],[@entity_id],tblClaimsCurrent[field_key],"pricing_acv_mid_market",tblClaimsCurrent[status],"PROMOTED"))) | H40: =IF(OR(NOT(ISNUMBER([@acv_usd])),$B$5=""),"UNKNOWN",IF([@acv_usd]<=($B$5*0.85),"Low",IF([@acv_usd]>=($B$5*1.15),"High","Mid"))) | I40: =LET(v,IFERROR(LOOKUP(2,1/((tblClaimsCurrent[entity_id]=[@entity_id])*(tblClaimsCurrent[field_key]="features")*(tblClaimsCurrent[status]="PROMOTED")),tblClaimsCurrent[value_text]),"UNKNOWN"),IF(v="","UNKNOWN",v)) | J40: =IF(OR([@features_text]="UNKNOWN",[@features_text]=""),NA(),1+LEN([@features_text])-LEN(SUBSTITUTE([@features_text],";",""))) | K40: =IF([@segment_id]="",NA(),IF([@segment_id]="SEG_MM",1,0)) | L40: =IF([@entity_id]="","",IF(COUNTIFS(tblClaimsCurrent[entity_id],[@entity_id],tblClaimsCurrent[field_key],"funding_round",tblClaimsCurrent[status],"PROMOTED")>0,1,0)) | M40: =IF(OR([@in_scope]=FALSE,ISNA([@coverage_pct]),ISNA([@feature_count]),ISNA([@segment_fit]),[@acv_band]="UNKNOWN"),NA(),MIN(1,Config!$B$14*MIN(1,[@feature_count]/10)+Config!$B$15*IF([@acv_band]="Low",1,IF([@acv_band]="Mid",0.5,0))+Config!$B$16*[@segment_fit]+Config!$B$17*[@funding_present])) | N40: =IF(OR([@in_scope]=FALSE,ISNA([@coverage_pct]),ISNA([@feature_count]),ISNA([@segment_fit])),NA(),MIN(1,Config!$B$18*(1-MIN(1,[@feature_count]/10))+Config!$B$19*(1-[@segment_fit])+Config!$B$20*(1-[@coverage_pct]))) | O40: =IF([@in_scope]=FALSE,"OUT_OF_SCOPE",IF(ISNA([@coverage_pct]),"UNKNOWN",IF([@coverage_pct]<Config!$B$10,"FAIL_CLOSED_LOW_COVERAGE","OK"))) | P40: =IFERROR(XLOOKUP([@entity_id],tblEntities[entity_id],tblEntities[segment_id]),"") | Q40: =IFERROR(XLOOKUP([@entity_id],tblEntities[entity_id],tblEntities[vertical]),"") | R40: =AND([@segment_id]=Dashboard!$E$2,IF(Dashboard!$E$3="All",TRUE,[@vertical]=Dashboard!$E$3))
A41: =IF(Input!$A$40="","",Input!$A$40) | B41: =IFERROR(XLOOKUP([@entity_id],tblEntities[entity_id],tblEntities[canonical_name]),"") | C41: =IF([@entity_id]="","",COUNTIFS(tblClaimsCurrent[entity_id],[@entity_id],tblClaimsCurrent[status],"PROMOTED")) | D41: =IF([@entity_id]="","",COUNTIFS(tblClaimsCurrent[entity_id],[@entity_id],tblClaimsCurrent[status],"UNKNOWN")) | E41: =LET(t,[@known_claims]+[@unknown_claims],IF(t=0,NA(),[@known_claims]/t)) | F41: =LET(cnt,COUNTIFS(tblClaimsCurrent[entity_id],[@entity_id],tblClaimsCurrent[status],"PROMOTED"),IF(cnt=0,NA(),AVERAGEIFS(tblClaimsCurrent[confidence],tblClaimsCurrent[entity_id],[@entity_id],tblClaimsCurrent[status],"PROMOTED"))) | G41: =LET(cnt,COUNTIFS(tblClaimsCurrent[entity_id],[@entity_id],tblClaimsCurrent[field_key],"pricing_acv_mid_market",tblClaimsCurrent[status],"PROMOTED"),IF(cnt=0,NA(),SUMIFS(tblClaimsCurrent[value_num],tblClaimsCurrent[entity_id],[@entity_id],tblClaimsCurrent[field_key],"pricing_acv_mid_market",tblClaimsCurrent[status],"PROMOTED"))) | H41: =IF(OR(NOT(ISNUMBER([@acv_usd])),$B$5=""),"UNKNOWN",IF([@acv_usd]<=($B$5*0.85),"Low",IF([@acv_usd]>=($B$5*1.15),"High","Mid"))) | I41: =LET(v,IFERROR(LOOKUP(2,1/((tblClaimsCurrent[entity_id]=[@entity_id])*(tblClaimsCurrent[field_key]="features")*(tblClaimsCurrent[status]="PROMOTED")),tblClaimsCurrent[value_text]),"UNKNOWN"),IF(v="","UNKNOWN",v)) | J41: =IF(OR([@features_text]="UNKNOWN",[@features_text]=""),NA(),1+LEN([@features_text])-LEN(SUBSTITUTE([@features_text],";",""))) | K41: =IF([@segment_id]="",NA(),IF([@segment_id]="SEG_MM",1,0)) | L41: =IF([@entity_id]="","",IF(COUNTIFS(tblClaimsCurrent[entity_id],[@entity_id],tblClaimsCurrent[field_key],"funding_round",tblClaimsCurrent[status],"PROMOTED")>0,1,0)) | M41: =IF(OR([@in_scope]=FALSE,ISNA([@coverage_pct]),ISNA([@feature_count]),ISNA([@segment_fit]),[@acv_band]="UNKNOWN"),NA(),MIN(1,Config!$B$14*MIN(1,[@feature_count]/10)+Config!$B$15*IF([@acv_band]="Low",1,IF([@acv_band]="Mid",0.5,0))+Config!$B$16*[@segment_fit]+Config!$B$17*[@funding_present])) | N41: =IF(OR([@in_scope]=FALSE,ISNA([@coverage_pct]),ISNA([@feature_count]),ISNA([@segment_fit])),NA(),MIN(1,Config!$B$18*(1-MIN(1,[@feature_count]/10))+Config!$B$19*(1-[@segment_fit])+Config!$B$20*(1-[@coverage_pct]))) | O41: =IF([@in_scope]=FALSE,"OUT_OF_SCOPE",IF(ISNA([@coverage_pct]),"UNKNOWN",IF([@coverage_pct]<Config!$B$10,"FAIL_CLOSED_LOW_COVERAGE","OK"))) | P41: =IFERROR(XLOOKUP([@entity_id],tblEntities[entity_id],tblEntities[segment_id]),"") | Q41: =IFERROR(XLOOKUP([@entity_id],tblEntities[entity_id],tblEntities[vertical]),"") | R41: =AND([@segment_id]=Dashboard!$E$2,IF(Dashboard!$E$3="All",TRUE,[@vertical]=Dashboard!$E$3))
A42: =IF(Input!$A$41="","",Input!$A$41) | B42: =IFERROR(XLOOKUP([@entity_id],tblEntities[entity_id],tblEntities[canonical_name]),"") | C42: =IF([@entity_id]="","",COUNTIFS(tblClaimsCurrent[entity_id],[@entity_id],tblClaimsCurrent[status],"PROMOTED")) | D42: =IF([@entity_id]="","",COUNTIFS(tblClaimsCurrent[entity_id],[@entity_id],tblClaimsCurrent[status],"UNKNOWN")) | E42: =LET(t,[@known_claims]+[@unknown_claims],IF(t=0,NA(),[@known_claims]/t)) | F42: =LET(cnt,COUNTIFS(tblClaimsCurrent[entity_id],[@entity_id],tblClaimsCurrent[status],"PROMOTED"),IF(cnt=0,NA(),AVERAGEIFS(tblClaimsCurrent[confidence],tblClaimsCurrent[entity_id],[@entity_id],tblClaimsCurrent[status],"PROMOTED"))) | G42: =LET(cnt,COUNTIFS(tblClaimsCurrent[entity_id],[@entity_id],tblClaimsCurrent[field_key],"pricing_acv_mid_market",tblClaimsCurrent[status],"PROMOTED"),IF(cnt=0,NA(),SUMIFS(tblClaimsCurrent[value_num],tblClaimsCurrent[entity_id],[@entity_id],tblClaimsCurrent[field_key],"pricing_acv_mid_market",tblClaimsCurrent[status],"PROMOTED"))) | H42: =IF(OR(NOT(ISNUMBER([@acv_usd])),$B$5=""),"UNKNOWN",IF([@acv_usd]<=($B$5*0.85),"Low",IF([@acv_usd]>=($B$5*1.15),"High","Mid"))) | I42: =LET(v,IFERROR(LOOKUP(2,1/((tblClaimsCurrent[entity_id]=[@entity_id])*(tblClaimsCurrent[field_key]="features")*(tblClaimsCurrent[status]="PROMOTED")),tblClaimsCurrent[value_text]),"UNKNOWN"),IF(v="","UNKNOWN",v)) | J42: =IF(OR([@features_text]="UNKNOWN",[@features_text]=""),NA(),1+LEN([@features_text])-LEN(SUBSTITUTE([@features_text],";",""))) | K42: =IF([@segment_id]="",NA(),IF([@segment_id]="SEG_MM",1,0)) | L42: =IF([@entity_id]="","",IF(COUNTIFS(tblClaimsCurrent[entity_id],[@entity_id],tblClaimsCurrent[field_key],"funding_round",tblClaimsCurrent[status],"PROMOTED")>0,1,0)) | M42: =IF(OR([@in_scope]=FALSE,ISNA([@coverage_pct]),ISNA([@feature_count]),ISNA([@segment_fit]),[@acv_band]="UNKNOWN"),NA(),MIN(1,Config!$B$14*MIN(1,[@feature_count]/10)+Config!$B$15*IF([@acv_band]="Low",1,IF([@acv_band]="Mid",0.5,0))+Config!$B$16*[@segment_fit]+Config!$B$17*[@funding_present])) | N42: =IF(OR([@in_scope]=FALSE,ISNA([@coverage_pct]),ISNA([@feature_count]),ISNA([@segment_fit])),NA(),MIN(1,Config!$B$18*(1-MIN(1,[@feature_count]/10))+Config!$B$19*(1-[@segment_fit])+Config!$B$20*(1-[@coverage_pct]))) | O42: =IF([@in_scope]=FALSE,"OUT_OF_SCOPE",IF(ISNA([@coverage_pct]),"UNKNOWN",IF([@coverage_pct]<Config!$B$10,"FAIL_CLOSED_LOW_COVERAGE","OK"))) | P42: =IFERROR(XLOOKUP([@entity_id],tblEntities[entity_id],tblEntities[segment_id]),"") | Q42: =IFERROR(XLOOKUP([@entity_id],tblEntities[entity_id],tblEntities[vertical]),"") | R42: =AND([@segment_id]=Dashboard!$E$2,IF(Dashboard!$E$3="All",TRUE,[@vertical]=Dashboard!$E$3))
A43: =IF(Input!$A$42="","",Input!$A$42) | B43: =IFERROR(XLOOKUP([@entity_id],tblEntities[entity_id],tblEntities[canonical_name]),"") | C43: =IF([@entity_id]="","",COUNTIFS(tblClaimsCurrent[entity_id],[@entity_id],tblClaimsCurrent[status],"PROMOTED")) | D43: =IF([@entity_id]="","",COUNTIFS(tblClaimsCurrent[entity_id],[@entity_id],tblClaimsCurrent[status],"UNKNOWN")) | E43: =LET(t,[@known_claims]+[@unknown_claims],IF(t=0,NA(),[@known_claims]/t)) | F43: =LET(cnt,COUNTIFS(tblClaimsCurrent[entity_id],[@entity_id],tblClaimsCurrent[status],"PROMOTED"),IF(cnt=0,NA(),AVERAGEIFS(tblClaimsCurrent[confidence],tblClaimsCurrent[entity_id],[@entity_id],tblClaimsCurrent[status],"PROMOTED"))) | G43: =LET(cnt,COUNTIFS(tblClaimsCurrent[entity_id],[@entity_id],tblClaimsCurrent[field_key],"pricing_acv_mid_market",tblClaimsCurrent[status],"PROMOTED"),IF(cnt=0,NA(),SUMIFS(tblClaimsCurrent[value_num],tblClaimsCurrent[entity_id],[@entity_id],tblClaimsCurrent[field_key],"pricing_acv_mid_market",tblClaimsCurrent[status],"PROMOTED"))) | H43: =IF(OR(NOT(ISNUMBER([@acv_usd])),$B$5=""),"UNKNOWN",IF([@acv_usd]<=($B$5*0.85),"Low",IF([@acv_usd]>=($B$5*1.15),"High","Mid"))) | I43: =LET(v,IFERROR(LOOKUP(2,1/((tblClaimsCurrent[entity_id]=[@entity_id])*(tblClaimsCurrent[field_key]="features")*(tblClaimsCurrent[status]="PROMOTED")),tblClaimsCurrent[value_text]),"UNKNOWN"),IF(v="","UNKNOWN",v)) | J43: =IF(OR([@features_text]="UNKNOWN",[@features_text]=""),NA(),1+LEN([@features_text])-LEN(SUBSTITUTE([@features_text],";",""))) | K43: =IF([@segment_id]="",NA(),IF([@segment_id]="SEG_MM",1,0)) | L43: =IF([@entity_id]="","",IF(COUNTIFS(tblClaimsCurrent[entity_id],[@entity_id],tblClaimsCurrent[field_key],"funding_round",tblClaimsCurrent[status],"PROMOTED")>0,1,0)) | M43: =IF(OR([@in_scope]=FALSE,ISNA([@coverage_pct]),ISNA([@feature_count]),ISNA([@segment_fit]),[@acv_band]="UNKNOWN"),NA(),MIN(1,Config!$B$14*MIN(1,[@feature_count]/10)+Config!$B$15*IF([@acv_band]="Low",1,IF([@acv_band]="Mid",0.5,0))+Config!$B$16*[@segment_fit]+Config!$B$17*[@funding_present])) | N43: =IF(OR([@in_scope]=FALSE,ISNA([@coverage_pct]),ISNA([@feature_count]),ISNA([@segment_fit])),NA(),MIN(1,Config!$B$18*(1-MIN(1,[@feature_count]/10))+Config!$B$19*(1-[@segment_fit])+Config!$B$20*(1-[@coverage_pct]))) | O43: =IF([@in_scope]=FALSE,"OUT_OF_SCOPE",IF(ISNA([@coverage_pct]),"UNKNOWN",IF([@coverage_pct]<Config!$B$10,"FAIL_CLOSED_LOW_COVERAGE","OK"))) | P43: =IFERROR(XLOOKUP([@entity_id],tblEntities[entity_id],tblEntities[segment_id]),"") | Q43: =IFERROR(XLOOKUP([@entity_id],tblEntities[entity_id],tblEntities[vertical]),"") | R43: =AND([@segment_id]=Dashboard!$E$2,IF(Dashboard!$E$3="All",TRUE,[@vertical]=Dashboard!$E$3))
A44: =IF(Input!$A$43="","",Input!$A$43) | B44: =IFERROR(XLOOKUP([@entity_id],tblEntities[entity_id],tblEntities[canonical_name]),"") | C44: =IF([@entity_id]="","",COUNTIFS(tblClaimsCurrent[entity_id],[@entity_id],tblClaimsCurrent[status],"PROMOTED")) | D44: =IF([@entity_id]="","",COUNTIFS(tblClaimsCurrent[entity_id],[@entity_id],tblClaimsCurrent[status],"UNKNOWN")) | E44: =LET(t,[@known_claims]+[@unknown_claims],IF(t=0,NA(),[@known_claims]/t)) | F44: =LET(cnt,COUNTIFS(tblClaimsCurrent[entity_id],[@entity_id],tblClaimsCurrent[status],"PROMOTED"),IF(cnt=0,NA(),AVERAGEIFS(tblClaimsCurrent[confidence],tblClaimsCurrent[entity_id],[@entity_id],tblClaimsCurrent[status],"PROMOTED"))) | G44: =LET(cnt,COUNTIFS(tblClaimsCurrent[entity_id],[@entity_id],tblClaimsCurrent[field_key],"pricing_acv_mid_market",tblClaimsCurrent[status],"PROMOTED"),IF(cnt=0,NA(),SUMIFS(tblClaimsCurrent[value_num],tblClaimsCurrent[entity_id],[@entity_id],tblClaimsCurrent[field_key],"pricing_acv_mid_market",tblClaimsCurrent[status],"PROMOTED"))) | H44: =IF(OR(NOT(ISNUMBER([@acv_usd])),$B$5=""),"UNKNOWN",IF([@acv_usd]<=($B$5*0.85),"Low",IF([@acv_usd]>=($B$5*1.15),"High","Mid"))) | I44: =LET(v,IFERROR(LOOKUP(2,1/((tblClaimsCurrent[entity_id]=[@entity_id])*(tblClaimsCurrent[field_key]="features")*(tblClaimsCurrent[status]="PROMOTED")),tblClaimsCurrent[value_text]),"UNKNOWN"),IF(v="","UNKNOWN",v)) | J44: =IF(OR([@features_text]="UNKNOWN",[@features_text]=""),NA(),1+LEN([@features_text])-LEN(SUBSTITUTE([@features_text],";",""))) | K44: =IF([@segment_id]="",NA(),IF([@segment_id]="SEG_MM",1,0)) | L44: =IF([@entity_id]="","",IF(COUNTIFS(tblClaimsCurrent[entity_id],[@entity_id],tblClaimsCurrent[field_key],"funding_round",tblClaimsCurrent[status],"PROMOTED")>0,1,0)) | M44: =IF(OR([@in_scope]=FALSE,ISNA([@coverage_pct]),ISNA([@feature_count]),ISNA([@segment_fit]),[@acv_band]="UNKNOWN"),NA(),MIN(1,Config!$B$14*MIN(1,[@feature_count]/10)+Config!$B$15*IF([@acv_band]="Low",1,IF([@acv_band]="Mid",0.5,0))+Config!$B$16*[@segment_fit]+Config!$B$17*[@funding_present])) | N44: =IF(OR([@in_scope]=FALSE,ISNA([@coverage_pct]),ISNA([@feature_count]),ISNA([@segment_fit])),NA(),MIN(1,Config!$B$18*(1-MIN(1,[@feature_count]/10))+Config!$B$19*(1-[@segment_fit])+Config!$B$20*(1-[@coverage_pct]))) | O44: =IF([@in_scope]=FALSE,"OUT_OF_SCOPE",IF(ISNA([@coverage_pct]),"UNKNOWN",IF([@coverage_pct]<Config!$B$10,"FAIL_CLOSED_LOW_COVERAGE","OK"))) | P44: =IFERROR(XLOOKUP([@entity_id],tblEntities[entity_id],tblEntities[segment_id]),"") | Q44: =IFERROR(XLOOKUP([@entity_id],tblEntities[entity_id],tblEntities[vertical]),"") | R44: =AND([@segment_id]=Dashboard!$E$2,IF(Dashboard!$E$3="All",TRUE,[@vertical]=Dashboard!$E$3))
A45: =IF(Input!$A$44="","",Input!$A$44) | B45: =IFERROR(XLOOKUP([@entity_id],tblEntities[entity_id],tblEntities[canonical_name]),"") | C45: =IF([@entity_id]="","",COUNTIFS(tblClaimsCurrent[entity_id],[@entity_id],tblClaimsCurrent[status],"PROMOTED")) | D45: =IF([@entity_id]="","",COUNTIFS(tblClaimsCurrent[entity_id],[@entity_id],tblClaimsCurrent[status],"UNKNOWN")) | E45: =LET(t,[@known_claims]+[@unknown_claims],IF(t=0,NA(),[@known_claims]/t)) | F45: =LET(cnt,COUNTIFS(tblClaimsCurrent[entity_id],[@entity_id],tblClaimsCurrent[status],"PROMOTED"),IF(cnt=0,NA(),AVERAGEIFS(tblClaimsCurrent[confidence],tblClaimsCurrent[entity_id],[@entity_id],tblClaimsCurrent[status],"PROMOTED"))) | G45: =LET(cnt,COUNTIFS(tblClaimsCurrent[entity_id],[@entity_id],tblClaimsCurrent[field_key],"pricing_acv_mid_market",tblClaimsCurrent[status],"PROMOTED"),IF(cnt=0,NA(),SUMIFS(tblClaimsCurrent[value_num],tblClaimsCurrent[entity_id],[@entity_id],tblClaimsCurrent[field_key],"pricing_acv_mid_market",tblClaimsCurrent[status],"PROMOTED"))) | H45: =IF(OR(NOT(ISNUMBER([@acv_usd])),$B$5=""),"UNKNOWN",IF([@acv_usd]<=($B$5*0.85),"Low",IF([@acv_usd]>=($B$5*1.15),"High","Mid"))) | I45: =LET(v,IFERROR(LOOKUP(2,1/((tblClaimsCurrent[entity_id]=[@entity_id])*(tblClaimsCurrent[field_key]="features")*(tblClaimsCurrent[status]="PROMOTED")),tblClaimsCurrent[value_text]),"UNKNOWN"),IF(v="","UNKNOWN",v)) | J45: =IF(OR([@features_text]="UNKNOWN",[@features_text]=""),NA(),1+LEN([@features_text])-LEN(SUBSTITUTE([@features_text],";",""))) | K45: =IF([@segment_id]="",NA(),IF([@segment_id]="SEG_MM",1,0)) | L45: =IF([@entity_id]="","",IF(COUNTIFS(tblClaimsCurrent[entity_id],[@entity_id],tblClaimsCurrent[field_key],"funding_round",tblClaimsCurrent[status],"PROMOTED")>0,1,0)) | M45: =IF(OR([@in_scope]=FALSE,ISNA([@coverage_pct]),ISNA([@feature_count]),ISNA([@segment_fit]),[@acv_band]="UNKNOWN"),NA(),MIN(1,Config!$B$14*MIN(1,[@feature_count]/10)+Config!$B$15*IF([@acv_band]="Low",1,IF([@acv_band]="Mid",0.5,0))+Config!$B$16*[@segment_fit]+Config!$B$17*[@funding_present])) | N45: =IF(OR([@in_scope]=FALSE,ISNA([@coverage_pct]),ISNA([@feature_count]),ISNA([@segment_fit])),NA(),MIN(1,Config!$B$18*(1-MIN(1,[@feature_count]/10))+Config!$B$19*(1-[@segment_fit])+Config!$B$20*(1-[@coverage_pct]))) | O45: =IF([@in_scope]=FALSE,"OUT_OF_SCOPE",IF(ISNA([@coverage_pct]),"UNKNOWN",IF([@coverage_pct]<Config!$B$10,"FAIL_CLOSED_LOW_COVERAGE","OK"))) | P45: =IFERROR(XLOOKUP([@entity_id],tblEntities[entity_id],tblEntities[segment_id]),"") | Q45: =IFERROR(XLOOKUP([@entity_id],tblEntities[entity_id],tblEntities[vertical]),"") | R45: =AND([@segment_id]=Dashboard!$E$2,IF(Dashboard!$E$3="All",TRUE,[@vertical]=Dashboard!$E$3))
A46: =IF(Input!$A$45="","",Input!$A$45) | B46: =IFERROR(XLOOKUP([@entity_id],tblEntities[entity_id],tblEntities[canonical_name]),"") | C46: =IF([@entity_id]="","",COUNTIFS(tblClaimsCurrent[entity_id],[@entity_id],tblClaimsCurrent[status],"PROMOTED")) | D46: =IF([@entity_id]="","",COUNTIFS(tblClaimsCurrent[entity_id],[@entity_id],tblClaimsCurrent[status],"UNKNOWN")) | E46: =LET(t,[@known_claims]+[@unknown_claims],IF(t=0,NA(),[@known_claims]/t)) | F46: =LET(cnt,COUNTIFS(tblClaimsCurrent[entity_id],[@entity_id],tblClaimsCurrent[status],"PROMOTED"),IF(cnt=0,NA(),AVERAGEIFS(tblClaimsCurrent[confidence],tblClaimsCurrent[entity_id],[@entity_id],tblClaimsCurrent[status],"PROMOTED"))) | G46: =LET(cnt,COUNTIFS(tblClaimsCurrent[entity_id],[@entity_id],tblClaimsCurrent[field_key],"pricing_acv_mid_market",tblClaimsCurrent[status],"PROMOTED"),IF(cnt=0,NA(),SUMIFS(tblClaimsCurrent[value_num],tblClaimsCurrent[entity_id],[@entity_id],tblClaimsCurrent[field_key],"pricing_acv_mid_market",tblClaimsCurrent[status],"PROMOTED"))) | H46: =IF(OR(NOT(ISNUMBER([@acv_usd])),$B$5=""),"UNKNOWN",IF([@acv_usd]<=($B$5*0.85),"Low",IF([@acv_usd]>=($B$5*1.15),"High","Mid"))) | I46: =LET(v,IFERROR(LOOKUP(2,1/((tblClaimsCurrent[entity_id]=[@entity_id])*(tblClaimsCurrent[field_key]="features")*(tblClaimsCurrent[status]="PROMOTED")),tblClaimsCurrent[value_text]),"UNKNOWN"),IF(v="","UNKNOWN",v)) | J46: =IF(OR([@features_text]="UNKNOWN",[@features_text]=""),NA(),1+LEN([@features_text])-LEN(SUBSTITUTE([@features_text],";",""))) | K46: =IF([@segment_id]="",NA(),IF([@segment_id]="SEG_MM",1,0)) | L46: =IF([@entity_id]="","",IF(COUNTIFS(tblClaimsCurrent[entity_id],[@entity_id],tblClaimsCurrent[field_key],"funding_round",tblClaimsCurrent[status],"PROMOTED")>0,1,0)) | M46: =IF(OR([@in_scope]=FALSE,ISNA([@coverage_pct]),ISNA([@feature_count]),ISNA([@segment_fit]),[@acv_band]="UNKNOWN"),NA(),MIN(1,Config!$B$14*MIN(1,[@feature_count]/10)+Config!$B$15*IF([@acv_band]="Low",1,IF([@acv_band]="Mid",0.5,0))+Config!$B$16*[@segment_fit]+Config!$B$17*[@funding_present])) | N46: =IF(OR([@in_scope]=FALSE,ISNA([@coverage_pct]),ISNA([@feature_count]),ISNA([@segment_fit])),NA(),MIN(1,Config!$B$18*(1-MIN(1,[@feature_count]/10))+Config!$B$19*(1-[@segment_fit])+Config!$B$20*(1-[@coverage_pct]))) | O46: =IF([@in_scope]=FALSE,"OUT_OF_SCOPE",IF(ISNA([@coverage_pct]),"UNKNOWN",IF([@coverage_pct]<Config!$B$10,"FAIL_CLOSED_LOW_COVERAGE","OK"))) | P46: =IFERROR(XLOOKUP([@entity_id],tblEntities[entity_id],tblEntities[segment_id]),"") | Q46: =IFERROR(XLOOKUP([@entity_id],tblEntities[entity_id],tblEntities[vertical]),"") | R46: =AND([@segment_id]=Dashboard!$E$2,IF(Dashboard!$E$3="All",TRUE,[@vertical]=Dashboard!$E$3))
A47: =IF(Input!$A$46="","",Input!$A$46) | B47: =IFERROR(XLOOKUP([@entity_id],tblEntities[entity_id],tblEntities[canonical_name]),"") | C47: =IF([@entity_id]="","",COUNTIFS(tblClaimsCurrent[entity_id],[@entity_id],tblClaimsCurrent[status],"PROMOTED")) | D47: =IF([@entity_id]="","",COUNTIFS(tblClaimsCurrent[entity_id],[@entity_id],tblClaimsCurrent[status],"UNKNOWN")) | E47: =LET(t,[@known_claims]+[@unknown_claims],IF(t=0,NA(),[@known_claims]/t)) | F47: =LET(cnt,COUNTIFS(tblClaimsCurrent[entity_id],[@entity_id],tblClaimsCurrent[status],"PROMOTED"),IF(cnt=0,NA(),AVERAGEIFS(tblClaimsCurrent[confidence],tblClaimsCurrent[entity_id],[@entity_id],tblClaimsCurrent[status],"PROMOTED"))) | G47: =LET(cnt,COUNTIFS(tblClaimsCurrent[entity_id],[@entity_id],tblClaimsCurrent[field_key],"pricing_acv_mid_market",tblClaimsCurrent[status],"PROMOTED"),IF(cnt=0,NA(),SUMIFS(tblClaimsCurrent[value_num],tblClaimsCurrent[entity_id],[@entity_id],tblClaimsCurrent[field_key],"pricing_acv_mid_market",tblClaimsCurrent[status],"PROMOTED"))) | H47: =IF(OR(NOT(ISNUMBER([@acv_usd])),$B$5=""),"UNKNOWN",IF([@acv_usd]<=($B$5*0.85),"Low",IF([@acv_usd]>=($B$5*1.15),"High","Mid"))) | I47: =LET(v,IFERROR(LOOKUP(2,1/((tblClaimsCurrent[entity_id]=[@entity_id])*(tblClaimsCurrent[field_key]="features")*(tblClaimsCurrent[status]="PROMOTED")),tblClaimsCurrent[value_text]),"UNKNOWN"),IF(v="","UNKNOWN",v)) | J47: =IF(OR([@features_text]="UNKNOWN",[@features_text]=""),NA(),1+LEN([@features_text])-LEN(SUBSTITUTE([@features_text],";",""))) | K47: =IF([@segment_id]="",NA(),IF([@segment_id]="SEG_MM",1,0)) | L47: =IF([@entity_id]="","",IF(COUNTIFS(tblClaimsCurrent[entity_id],[@entity_id],tblClaimsCurrent[field_key],"funding_round",tblClaimsCurrent[status],"PROMOTED")>0,1,0)) | M47: =IF(OR([@in_scope]=FALSE,ISNA([@coverage_pct]),ISNA([@feature_count]),ISNA([@segment_fit]),[@acv_band]="UNKNOWN"),NA(),MIN(1,Config!$B$14*MIN(1,[@feature_count]/10)+Config!$B$15*IF([@acv_band]="Low",1,IF([@acv_band]="Mid",0.5,0))+Config!$B$16*[@segment_fit]+Config!$B$17*[@funding_present])) | N47: =IF(OR([@in_scope]=FALSE,ISNA([@coverage_pct]),ISNA([@feature_count]),ISNA([@segment_fit])),NA(),MIN(1,Config!$B$18*(1-MIN(1,[@feature_count]/10))+Config!$B$19*(1-[@segment_fit])+Config!$B$20*(1-[@coverage_pct]))) | O47: =IF([@in_scope]=FALSE,"OUT_OF_SCOPE",IF(ISNA([@coverage_pct]),"UNKNOWN",IF([@coverage_pct]<Config!$B$10,"FAIL_CLOSED_LOW_COVERAGE","OK"))) | P47: =IFERROR(XLOOKUP([@entity_id],tblEntities[entity_id],tblEntities[segment_id]),"") | Q47: =IFERROR(XLOOKUP([@entity_id],tblEntities[entity_id],tblEntities[vertical]),"") | R47: =AND([@segment_id]=Dashboard!$E$2,IF(Dashboard!$E$3="All",TRUE,[@vertical]=Dashboard!$E$3))
A48: =IF(Input!$A$47="","",Input!$A$47) | B48: =IFERROR(XLOOKUP([@entity_id],tblEntities[entity_id],tblEntities[canonical_name]),"") | C48: =IF([@entity_id]="","",COUNTIFS(tblClaimsCurrent[entity_id],[@entity_id],tblClaimsCurrent[status],"PROMOTED")) | D48: =IF([@entity_id]="","",COUNTIFS(tblClaimsCurrent[entity_id],[@entity_id],tblClaimsCurrent[status],"UNKNOWN")) | E48: =LET(t,[@known_claims]+[@unknown_claims],IF(t=0,NA(),[@known_claims]/t)) | F48: =LET(cnt,COUNTIFS(tblClaimsCurrent[entity_id],[@entity_id],tblClaimsCurrent[status],"PROMOTED"),IF(cnt=0,NA(),AVERAGEIFS(tblClaimsCurrent[confidence],tblClaimsCurrent[entity_id],[@entity_id],tblClaimsCurrent[status],"PROMOTED"))) | G48: =LET(cnt,COUNTIFS(tblClaimsCurrent[entity_id],[@entity_id],tblClaimsCurrent[field_key],"pricing_acv_mid_market",tblClaimsCurrent[status],"PROMOTED"),IF(cnt=0,NA(),SUMIFS(tblClaimsCurrent[value_num],tblClaimsCurrent[entity_id],[@entity_id],tblClaimsCurrent[field_key],"pricing_acv_mid_market",tblClaimsCurrent[status],"PROMOTED"))) | H48: =IF(OR(NOT(ISNUMBER([@acv_usd])),$B$5=""),"UNKNOWN",IF([@acv_usd]<=($B$5*0.85),"Low",IF([@acv_usd]>=($B$5*1.15),"High","Mid"))) | I48: =LET(v,IFERROR(LOOKUP(2,1/((tblClaimsCurrent[entity_id]=[@entity_id])*(tblClaimsCurrent[field_key]="features")*(tblClaimsCurrent[status]="PROMOTED")),tblClaimsCurrent[value_text]),"UNKNOWN"),IF(v="","UNKNOWN",v)) | J48: =IF(OR([@features_text]="UNKNOWN",[@features_text]=""),NA(),1+LEN([@features_text])-LEN(SUBSTITUTE([@features_text],";",""))) | K48: =IF([@segment_id]="",NA(),IF([@segment_id]="SEG_MM",1,0)) | L48: =IF([@entity_id]="","",IF(COUNTIFS(tblClaimsCurrent[entity_id],[@entity_id],tblClaimsCurrent[field_key],"funding_round",tblClaimsCurrent[status],"PROMOTED")>0,1,0)) | M48: =IF(OR([@in_scope]=FALSE,ISNA([@coverage_pct]),ISNA([@feature_count]),ISNA([@segment_fit]),[@acv_band]="UNKNOWN"),NA(),MIN(1,Config!$B$14*MIN(1,[@feature_count]/10)+Config!$B$15*IF([@acv_band]="Low",1,IF([@acv_band]="Mid",0.5,0))+Config!$B$16*[@segment_fit]+Config!$B$17*[@funding_present])) | N48: =IF(OR([@in_scope]=FALSE,ISNA([@coverage_pct]),ISNA([@feature_count]),ISNA([@segment_fit])),NA(),MIN(1,Config!$B$18*(1-MIN(1,[@feature_count]/10))+Config!$B$19*(1-[@segment_fit])+Config!$B$20*(1-[@coverage_pct]))) | O48: =IF([@in_scope]=FALSE,"OUT_OF_SCOPE",IF(ISNA([@coverage_pct]),"UNKNOWN",IF([@coverage_pct]<Config!$B$10,"FAIL_CLOSED_LOW_COVERAGE","OK"))) | P48: =IFERROR(XLOOKUP([@entity_id],tblEntities[entity_id],tblEntities[segment_id]),"") | Q48: =IFERROR(XLOOKUP([@entity_id],tblEntities[entity_id],tblEntities[vertical]),"") | R48: =AND([@segment_id]=Dashboard!$E$2,IF(Dashboard!$E$3="All",TRUE,[@vertical]=Dashboard!$E$3))
A49: =IF(Input!$A$48="","",Input!$A$48) | B49: =IFERROR(XLOOKUP([@entity_id],tblEntities[entity_id],tblEntities[canonical_name]),"") | C49: =IF([@entity_id]="","",COUNTIFS(tblClaimsCurrent[entity_id],[@entity_id],tblClaimsCurrent[status],"PROMOTED")) | D49: =IF([@entity_id]="","",COUNTIFS(tblClaimsCurrent[entity_id],[@entity_id],tblClaimsCurrent[status],"UNKNOWN")) | E49: =LET(t,[@known_claims]+[@unknown_claims],IF(t=0,NA(),[@known_claims]/t)) | F49: =LET(cnt,COUNTIFS(tblClaimsCurrent[entity_id],[@entity_id],tblClaimsCurrent[status],"PROMOTED"),IF(cnt=0,NA(),AVERAGEIFS(tblClaimsCurrent[confidence],tblClaimsCurrent[entity_id],[@entity_id],tblClaimsCurrent[status],"PROMOTED"))) | G49: =LET(cnt,COUNTIFS(tblClaimsCurrent[entity_id],[@entity_id],tblClaimsCurrent[field_key],"pricing_acv_mid_market",tblClaimsCurrent[status],"PROMOTED"),IF(cnt=0,NA(),SUMIFS(tblClaimsCurrent[value_num],tblClaimsCurrent[entity_id],[@entity_id],tblClaimsCurrent[field_key],"pricing_acv_mid_market",tblClaimsCurrent[status],"PROMOTED"))) | H49: =IF(OR(NOT(ISNUMBER([@acv_usd])),$B$5=""),"UNKNOWN",IF([@acv_usd]<=($B$5*0.85),"Low",IF([@acv_usd]>=($B$5*1.15),"High","Mid"))) | I49: =LET(v,IFERROR(LOOKUP(2,1/((tblClaimsCurrent[entity_id]=[@entity_id])*(tblClaimsCurrent[field_key]="features")*(tblClaimsCurrent[status]="PROMOTED")),tblClaimsCurrent[value_text]),"UNKNOWN"),IF(v="","UNKNOWN",v)) | J49: =IF(OR([@features_text]="UNKNOWN",[@features_text]=""),NA(),1+LEN([@features_text])-LEN(SUBSTITUTE([@features_text],";",""))) | K49: =IF([@segment_id]="",NA(),IF([@segment_id]="SEG_MM",1,0)) | L49: =IF([@entity_id]="","",IF(COUNTIFS(tblClaimsCurrent[entity_id],[@entity_id],tblClaimsCurrent[field_key],"funding_round",tblClaimsCurrent[status],"PROMOTED")>0,1,0)) | M49: =IF(OR([@in_scope]=FALSE,ISNA([@coverage_pct]),ISNA([@feature_count]),ISNA([@segment_fit]),[@acv_band]="UNKNOWN"),NA(),MIN(1,Config!$B$14*MIN(1,[@feature_count]/10)+Config!$B$15*IF([@acv_band]="Low",1,IF([@acv_band]="Mid",0.5,0))+Config!$B$16*[@segment_fit]+Config!$B$17*[@funding_present])) | N49: =IF(OR([@in_scope]=FALSE,ISNA([@coverage_pct]),ISNA([@feature_count]),ISNA([@segment_fit])),NA(),MIN(1,Config!$B$18*(1-MIN(1,[@feature_count]/10))+Config!$B$19*(1-[@segment_fit])+Config!$B$20*(1-[@coverage_pct]))) | O49: =IF([@in_scope]=FALSE,"OUT_OF_SCOPE",IF(ISNA([@coverage_pct]),"UNKNOWN",IF([@coverage_pct]<Config!$B$10,"FAIL_CLOSED_LOW_COVERAGE","OK"))) | P49: =IFERROR(XLOOKUP([@entity_id],tblEntities[entity_id],tblEntities[segment_id]),"") | Q49: =IFERROR(XLOOKUP([@entity_id],tblEntities[entity_id],tblEntities[vertical]),"") | R49: =AND([@segment_id]=Dashboard!$E$2,IF(Dashboard!$E$3="All",TRUE,[@vertical]=Dashboard!$E$3))
A50: =IF(Input!$A$49="","",Input!$A$49) | B50: =IFERROR(XLOOKUP([@entity_id],tblEntities[entity_id],tblEntities[canonical_name]),"") | C50: =IF([@entity_id]="","",COUNTIFS(tblClaimsCurrent[entity_id],[@entity_id],tblClaimsCurrent[status],"PROMOTED")) | D50: =IF([@entity_id]="","",COUNTIFS(tblClaimsCurrent[entity_id],[@entity_id],tblClaimsCurrent[status],"UNKNOWN")) | E50: =LET(t,[@known_claims]+[@unknown_claims],IF(t=0,NA(),[@known_claims]/t)) | F50: =LET(cnt,COUNTIFS(tblClaimsCurrent[entity_id],[@entity_id],tblClaimsCurrent[status],"PROMOTED"),IF(cnt=0,NA(),AVERAGEIFS(tblClaimsCurrent[confidence],tblClaimsCurrent[entity_id],[@entity_id],tblClaimsCurrent[status],"PROMOTED"))) | G50: =LET(cnt,COUNTIFS(tblClaimsCurrent[entity_id],[@entity_id],tblClaimsCurrent[field_key],"pricing_acv_mid_market",tblClaimsCurrent[status],"PROMOTED"),IF(cnt=0,NA(),SUMIFS(tblClaimsCurrent[value_num],tblClaimsCurrent[entity_id],[@entity_id],tblClaimsCurrent[field_key],"pricing_acv_mid_market",tblClaimsCurrent[status],"PROMOTED"))) | H50: =IF(OR(NOT(ISNUMBER([@acv_usd])),$B$5=""),"UNKNOWN",IF([@acv_usd]<=($B$5*0.85),"Low",IF([@acv_usd]>=($B$5*1.15),"High","Mid"))) | I50: =LET(v,IFERROR(LOOKUP(2,1/((tblClaimsCurrent[entity_id]=[@entity_id])*(tblClaimsCurrent[field_key]="features")*(tblClaimsCurrent[status]="PROMOTED")),tblClaimsCurrent[value_text]),"UNKNOWN"),IF(v="","UNKNOWN",v)) | J50: =IF(OR([@features_text]="UNKNOWN",[@features_text]=""),NA(),1+LEN([@features_text])-LEN(SUBSTITUTE([@features_text],";",""))) | K50: =IF([@segment_id]="",NA(),IF([@segment_id]="SEG_MM",1,0)) | L50: =IF([@entity_id]="","",IF(COUNTIFS(tblClaimsCurrent[entity_id],[@entity_id],tblClaimsCurrent[field_key],"funding_round",tblClaimsCurrent[status],"PROMOTED")>0,1,0)) | M50: =IF(OR([@in_scope]=FALSE,ISNA([@coverage_pct]),ISNA([@feature_count]),ISNA([@segment_fit]),[@acv_band]="UNKNOWN"),NA(),MIN(1,Config!$B$14*MIN(1,[@feature_count]/10)+Config!$B$15*IF([@acv_band]="Low",1,IF([@acv_band]="Mid",0.5,0))+Config!$B$16*[@segment_fit]+Config!$B$17*[@funding_present])) | N50: =IF(OR([@in_scope]=FALSE,ISNA([@coverage_pct]),ISNA([@feature_count]),ISNA([@segment_fit])),NA(),MIN(1,Config!$B$18*(1-MIN(1,[@feature_count]/10))+Config!$B$19*(1-[@segment_fit])+Config!$B$20*(1-[@coverage_pct]))) | O50: =IF([@in_scope]=FALSE,"OUT_OF_SCOPE",IF(ISNA([@coverage_pct]),"UNKNOWN",IF([@coverage_pct]<Config!$B$10,"FAIL_CLOSED_LOW_COVERAGE","OK"))) | P50: =IFERROR(XLOOKUP([@entity_id],tblEntities[entity_id],tblEntities[segment_id]),"") | Q50: =IFERROR(XLOOKUP([@entity_id],tblEntities[entity_id],tblEntities[vertical]),"") | R50: =AND([@segment_id]=Dashboard!$E$2,IF(Dashboard!$E$3="All",TRUE,[@vertical]=Dashboard!$E$3))
A51: =IF(Input!$A$50="","",Input!$A$50) | B51: =IFERROR(XLOOKUP([@entity_id],tblEntities[entity_id],tblEntities[canonical_name]),"") | C51: =IF([@entity_id]="","",COUNTIFS(tblClaimsCurrent[entity_id],[@entity_id],tblClaimsCurrent[status],"PROMOTED")) | D51: =IF([@entity_id]="","",COUNTIFS(tblClaimsCurrent[entity_id],[@entity_id],tblClaimsCurrent[status],"UNKNOWN")) | E51: =LET(t,[@known_claims]+[@unknown_claims],IF(t=0,NA(),[@known_claims]/t)) | F51: =LET(cnt,COUNTIFS(tblClaimsCurrent[entity_id],[@entity_id],tblClaimsCurrent[status],"PROMOTED"),IF(cnt=0,NA(),AVERAGEIFS(tblClaimsCurrent[confidence],tblClaimsCurrent[entity_id],[@entity_id],tblClaimsCurrent[status],"PROMOTED"))) | G51: =LET(cnt,COUNTIFS(tblClaimsCurrent[entity_id],[@entity_id],tblClaimsCurrent[field_key],"pricing_acv_mid_market",tblClaimsCurrent[status],"PROMOTED"),IF(cnt=0,NA(),SUMIFS(tblClaimsCurrent[value_num],tblClaimsCurrent[entity_id],[@entity_id],tblClaimsCurrent[field_key],"pricing_acv_mid_market",tblClaimsCurrent[status],"PROMOTED"))) | H51: =IF(OR(NOT(ISNUMBER([@acv_usd])),$B$5=""),"UNKNOWN",IF([@acv_usd]<=($B$5*0.85),"Low",IF([@acv_usd]>=($B$5*1.15),"High","Mid"))) | I51: =LET(v,IFERROR(LOOKUP(2,1/((tblClaimsCurrent[entity_id]=[@entity_id])*(tblClaimsCurrent[field_key]="features")*(tblClaimsCurrent[status]="PROMOTED")),tblClaimsCurrent[value_text]),"UNKNOWN"),IF(v="","UNKNOWN",v)) | J51: =IF(OR([@features_text]="UNKNOWN",[@features_text]=""),NA(),1+LEN([@features_text])-LEN(SUBSTITUTE([@features_text],";",""))) | K51: =IF([@segment_id]="",NA(),IF([@segment_id]="SEG_MM",1,0)) | L51: =IF([@entity_id]="","",IF(COUNTIFS(tblClaimsCurrent[entity_id],[@entity_id],tblClaimsCurrent[field_key],"funding_round",tblClaimsCurrent[status],"PROMOTED")>0,1,0)) | M51: =IF(OR([@in_scope]=FALSE,ISNA([@coverage_pct]),ISNA([@feature_count]),ISNA([@segment_fit]),[@acv_band]="UNKNOWN"),NA(),MIN(1,Config!$B$14*MIN(1,[@feature_count]/10)+Config!$B$15*IF([@acv_band]="Low",1,IF([@acv_band]="Mid",0.5,0))+Config!$B$16*[@segment_fit]+Config!$B$17*[@funding_present])) | N51: =IF(OR([@in_scope]=FALSE,ISNA([@coverage_pct]),ISNA([@feature_count]),ISNA([@segment_fit])),NA(),MIN(1,Config!$B$18*(1-MIN(1,[@feature_count]/10))+Config!$B$19*(1-[@segment_fit])+Config!$B$20*(1-[@coverage_pct]))) | O51: =IF([@in_scope]=FALSE,"OUT_OF_SCOPE",IF(ISNA([@coverage_pct]),"UNKNOWN",IF([@coverage_pct]<Config!$B$10,"FAIL_CLOSED_LOW_COVERAGE","OK"))) | P51: =IFERROR(XLOOKUP([@entity_id],tblEntities[entity_id],tblEntities[segment_id]),"") | Q51: =IFERROR(XLOOKUP([@entity_id],tblEntities[entity_id],tblEntities[vertical]),"") | R51: =AND([@segment_id]=Dashboard!$E$2,IF(Dashboard!$E$3="All",TRUE,[@vertical]=Dashboard!$E$3))
A52: =IF(Input!$A$51="","",Input!$A$51) | B52: =IFERROR(XLOOKUP([@entity_id],tblEntities[entity_id],tblEntities[canonical_name]),"") | C52: =IF([@entity_id]="","",COUNTIFS(tblClaimsCurrent[entity_id],[@entity_id],tblClaimsCurrent[status],"PROMOTED")) | D52: =IF([@entity_id]="","",COUNTIFS(tblClaimsCurrent[entity_id],[@entity_id],tblClaimsCurrent[status],"UNKNOWN")) | E52: =LET(t,[@known_claims]+[@unknown_claims],IF(t=0,NA(),[@known_claims]/t)) | F52: =LET(cnt,COUNTIFS(tblClaimsCurrent[entity_id],[@entity_id],tblClaimsCurrent[status],"PROMOTED"),IF(cnt=0,NA(),AVERAGEIFS(tblClaimsCurrent[confidence],tblClaimsCurrent[entity_id],[@entity_id],tblClaimsCurrent[status],"PROMOTED"))) | G52: =LET(cnt,COUNTIFS(tblClaimsCurrent[entity_id],[@entity_id],tblClaimsCurrent[field_key],"pricing_acv_mid_market",tblClaimsCurrent[status],"PROMOTED"),IF(cnt=0,NA(),SUMIFS(tblClaimsCurrent[value_num],tblClaimsCurrent[entity_id],[@entity_id],tblClaimsCurrent[field_key],"pricing_acv_mid_market",tblClaimsCurrent[status],"PROMOTED"))) | H52: =IF(OR(NOT(ISNUMBER([@acv_usd])),$B$5=""),"UNKNOWN",IF([@acv_usd]<=($B$5*0.85),"Low",IF([@acv_usd]>=($B$5*1.15),"High","Mid"))) | I52: =LET(v,IFERROR(LOOKUP(2,1/((tblClaimsCurrent[entity_id]=[@entity_id])*(tblClaimsCurrent[field_key]="features")*(tblClaimsCurrent[status]="PROMOTED")),tblClaimsCurrent[value_text]),"UNKNOWN"),IF(v="","UNKNOWN",v)) | J52: =IF(OR([@features_text]="UNKNOWN",[@features_text]=""),NA(),1+LEN([@features_text])-LEN(SUBSTITUTE([@features_text],";",""))) | K52: =IF([@segment_id]="",NA(),IF([@segment_id]="SEG_MM",1,0)) | L52: =IF([@entity_id]="","",IF(COUNTIFS(tblClaimsCurrent[entity_id],[@entity_id],tblClaimsCurrent[field_key],"funding_round",tblClaimsCurrent[status],"PROMOTED")>0,1,0)) | M52: =IF(OR([@in_scope]=FALSE,ISNA([@coverage_pct]),ISNA([@feature_count]),ISNA([@segment_fit]),[@acv_band]="UNKNOWN"),NA(),MIN(1,Config!$B$14*MIN(1,[@feature_count]/10)+Config!$B$15*IF([@acv_band]="Low",1,IF([@acv_band]="Mid",0.5,0))+Config!$B$16*[@segment_fit]+Config!$B$17*[@funding_present])) | N52: =IF(OR([@in_scope]=FALSE,ISNA([@coverage_pct]),ISNA([@feature_count]),ISNA([@segment_fit])),NA(),MIN(1,Config!$B$18*(1-MIN(1,[@feature_count]/10))+Config!$B$19*(1-[@segment_fit])+Config!$B$20*(1-[@coverage_pct]))) | O52: =IF([@in_scope]=FALSE,"OUT_OF_SCOPE",IF(ISNA([@coverage_pct]),"UNKNOWN",IF([@coverage_pct]<Config!$B$10,"FAIL_CLOSED_LOW_COVERAGE","OK"))) | P52: =IFERROR(XLOOKUP([@entity_id],tblEntities[entity_id],tblEntities[segment_id]),"") | Q52: =IFERROR(XLOOKUP([@entity_id],tblEntities[entity_id],tblEntities[vertical]),"") | R52: =AND([@segment_id]=Dashboard!$E$2,IF(Dashboard!$E$3="All",TRUE,[@vertical]=Dashboard!$E$3))
A53: =IF(Input!$A$52="","",Input!$A$52) | B53: =IFERROR(XLOOKUP([@entity_id],tblEntities[entity_id],tblEntities[canonical_name]),"") | C53: =IF([@entity_id]="","",COUNTIFS(tblClaimsCurrent[entity_id],[@entity_id],tblClaimsCurrent[status],"PROMOTED")) | D53: =IF([@entity_id]="","",COUNTIFS(tblClaimsCurrent[entity_id],[@entity_id],tblClaimsCurrent[status],"UNKNOWN")) | E53: =LET(t,[@known_claims]+[@unknown_claims],IF(t=0,NA(),[@known_claims]/t)) | F53: =LET(cnt,COUNTIFS(tblClaimsCurrent[entity_id],[@entity_id],tblClaimsCurrent[status],"PROMOTED"),IF(cnt=0,NA(),AVERAGEIFS(tblClaimsCurrent[confidence],tblClaimsCurrent[entity_id],[@entity_id],tblClaimsCurrent[status],"PROMOTED"))) | G53: =LET(cnt,COUNTIFS(tblClaimsCurrent[entity_id],[@entity_id],tblClaimsCurrent[field_key],"pricing_acv_mid_market",tblClaimsCurrent[status],"PROMOTED"),IF(cnt=0,NA(),SUMIFS(tblClaimsCurrent[value_num],tblClaimsCurrent[entity_id],[@entity_id],tblClaimsCurrent[field_key],"pricing_acv_mid_market",tblClaimsCurrent[status],"PROMOTED"))) | H53: =IF(OR(NOT(ISNUMBER([@acv_usd])),$B$5=""),"UNKNOWN",IF([@acv_usd]<=($B$5*0.85),"Low",IF([@acv_usd]>=($B$5*1.15),"High","Mid"))) | I53: =LET(v,IFERROR(LOOKUP(2,1/((tblClaimsCurrent[entity_id]=[@entity_id])*(tblClaimsCurrent[field_key]="features")*(tblClaimsCurrent[status]="PROMOTED")),tblClaimsCurrent[value_text]),"UNKNOWN"),IF(v="","UNKNOWN",v)) | J53: =IF(OR([@features_text]="UNKNOWN",[@features_text]=""),NA(),1+LEN([@features_text])-LEN(SUBSTITUTE([@features_text],";",""))) | K53: =IF([@segment_id]="",NA(),IF([@segment_id]="SEG_MM",1,0)) | L53: =IF([@entity_id]="","",IF(COUNTIFS(tblClaimsCurrent[entity_id],[@entity_id],tblClaimsCurrent[field_key],"funding_round",tblClaimsCurrent[status],"PROMOTED")>0,1,0)) | M53: =IF(OR([@in_scope]=FALSE,ISNA([@coverage_pct]),ISNA([@feature_count]),ISNA([@segment_fit]),[@acv_band]="UNKNOWN"),NA(),MIN(1,Config!$B$14*MIN(1,[@feature_count]/10)+Config!$B$15*IF([@acv_band]="Low",1,IF([@acv_band]="Mid",0.5,0))+Config!$B$16*[@segment_fit]+Config!$B$17*[@funding_present])) | N53: =IF(OR([@in_scope]=FALSE,ISNA([@coverage_pct]),ISNA([@feature_count]),ISNA([@segment_fit])),NA(),MIN(1,Config!$B$18*(1-MIN(1,[@feature_count]/10))+Config!$B$19*(1-[@segment_fit])+Config!$B$20*(1-[@coverage_pct]))) | O53: =IF([@in_scope]=FALSE,"OUT_OF_SCOPE",IF(ISNA([@coverage_pct]),"UNKNOWN",IF([@coverage_pct]<Config!$B$10,"FAIL_CLOSED_LOW_COVERAGE","OK"))) | P53: =IFERROR(XLOOKUP([@entity_id],tblEntities[entity_id],tblEntities[segment_id]),"") | Q53: =IFERROR(XLOOKUP([@entity_id],tblEntities[entity_id],tblEntities[vertical]),"") | R53: =AND([@segment_id]=Dashboard!$E$2,IF(Dashboard!$E$3="All",TRUE,[@vertical]=Dashboard!$E$3))
A54: =IF(Input!$A$53="","",Input!$A$53) | B54: =IFERROR(XLOOKUP([@entity_id],tblEntities[entity_id],tblEntities[canonical_name]),"") | C54: =IF([@entity_id]="","",COUNTIFS(tblClaimsCurrent[entity_id],[@entity_id],tblClaimsCurrent[status],"PROMOTED")) | D54: =IF([@entity_id]="","",COUNTIFS(tblClaimsCurrent[entity_id],[@entity_id],tblClaimsCurrent[status],"UNKNOWN")) | E54: =LET(t,[@known_claims]+[@unknown_claims],IF(t=0,NA(),[@known_claims]/t)) | F54: =LET(cnt,COUNTIFS(tblClaimsCurrent[entity_id],[@entity_id],tblClaimsCurrent[status],"PROMOTED"),IF(cnt=0,NA(),AVERAGEIFS(tblClaimsCurrent[confidence],tblClaimsCurrent[entity_id],[@entity_id],tblClaimsCurrent[status],"PROMOTED"))) | G54: =LET(cnt,COUNTIFS(tblClaimsCurrent[entity_id],[@entity_id],tblClaimsCurrent[field_key],"pricing_acv_mid_market",tblClaimsCurrent[status],"PROMOTED"),IF(cnt=0,NA(),SUMIFS(tblClaimsCurrent[value_num],tblClaimsCurrent[entity_id],[@entity_id],tblClaimsCurrent[field_key],"pricing_acv_mid_market",tblClaimsCurrent[status],"PROMOTED"))) | H54: =IF(OR(NOT(ISNUMBER([@acv_usd])),$B$5=""),"UNKNOWN",IF([@acv_usd]<=($B$5*0.85),"Low",IF([@acv_usd]>=($B$5*1.15),"High","Mid"))) | I54: =LET(v,IFERROR(LOOKUP(2,1/((tblClaimsCurrent[entity_id]=[@entity_id])*(tblClaimsCurrent[field_key]="features")*(tblClaimsCurrent[status]="PROMOTED")),tblClaimsCurrent[value_text]),"UNKNOWN"),IF(v="","UNKNOWN",v)) | J54: =IF(OR([@features_text]="UNKNOWN",[@features_text]=""),NA(),1+LEN([@features_text])-LEN(SUBSTITUTE([@features_text],";",""))) | K54: =IF([@segment_id]="",NA(),IF([@segment_id]="SEG_MM",1,0)) | L54: =IF([@entity_id]="","",IF(COUNTIFS(tblClaimsCurrent[entity_id],[@entity_id],tblClaimsCurrent[field_key],"funding_round",tblClaimsCurrent[status],"PROMOTED")>0,1,0)) | M54: =IF(OR([@in_scope]=FALSE,ISNA([@coverage_pct]),ISNA([@feature_count]),ISNA([@segment_fit]),[@acv_band]="UNKNOWN"),NA(),MIN(1,Config!$B$14*MIN(1,[@feature_count]/10)+Config!$B$15*IF([@acv_band]="Low",1,IF([@acv_band]="Mid",0.5,0))+Config!$B$16*[@segment_fit]+Config!$B$17*[@funding_present])) | N54: =IF(OR([@in_scope]=FALSE,ISNA([@coverage_pct]),ISNA([@feature_count]),ISNA([@segment_fit])),NA(),MIN(1,Config!$B$18*(1-MIN(1,[@feature_count]/10))+Config!$B$19*(1-[@segment_fit])+Config!$B$20*(1-[@coverage_pct]))) | O54: =IF([@in_scope]=FALSE,"OUT_OF_SCOPE",IF(ISNA([@coverage_pct]),"UNKNOWN",IF([@coverage_pct]<Config!$B$10,"FAIL_CLOSED_LOW_COVERAGE","OK"))) | P54: =IFERROR(XLOOKUP([@entity_id],tblEntities[entity_id],tblEntities[segment_id]),"") | Q54: =IFERROR(XLOOKUP([@entity_id],tblEntities[entity_id],tblEntities[vertical]),"") | R54: =AND([@segment_id]=Dashboard!$E$2,IF(Dashboard!$E$3="All",TRUE,[@vertical]=Dashboard!$E$3))
A55: =IF(Input!$A$54="","",Input!$A$54) | B55: =IFERROR(XLOOKUP([@entity_id],tblEntities[entity_id],tblEntities[canonical_name]),"") | C55: =IF([@entity_id]="","",COUNTIFS(tblClaimsCurrent[entity_id],[@entity_id],tblClaimsCurrent[status],"PROMOTED")) | D55: =IF([@entity_id]="","",COUNTIFS(tblClaimsCurrent[entity_id],[@entity_id],tblClaimsCurrent[status],"UNKNOWN")) | E55: =LET(t,[@known_claims]+[@unknown_claims],IF(t=0,NA(),[@known_claims]/t)) | F55: =LET(cnt,COUNTIFS(tblClaimsCurrent[entity_id],[@entity_id],tblClaimsCurrent[status],"PROMOTED"),IF(cnt=0,NA(),AVERAGEIFS(tblClaimsCurrent[confidence],tblClaimsCurrent[entity_id],[@entity_id],tblClaimsCurrent[status],"PROMOTED"))) | G55: =LET(cnt,COUNTIFS(tblClaimsCurrent[entity_id],[@entity_id],tblClaimsCurrent[field_key],"pricing_acv_mid_market",tblClaimsCurrent[status],"PROMOTED"),IF(cnt=0,NA(),SUMIFS(tblClaimsCurrent[value_num],tblClaimsCurrent[entity_id],[@entity_id],tblClaimsCurrent[field_key],"pricing_acv_mid_market",tblClaimsCurrent[status],"PROMOTED"))) | H55: =IF(OR(NOT(ISNUMBER([@acv_usd])),$B$5=""),"UNKNOWN",IF([@acv_usd]<=($B$5*0.85),"Low",IF([@acv_usd]>=($B$5*1.15),"High","Mid"))) | I55: =LET(v,IFERROR(LOOKUP(2,1/((tblClaimsCurrent[entity_id]=[@entity_id])*(tblClaimsCurrent[field_key]="features")*(tblClaimsCurrent[status]="PROMOTED")),tblClaimsCurrent[value_text]),"UNKNOWN"),IF(v="","UNKNOWN",v)) | J55: =IF(OR([@features_text]="UNKNOWN",[@features_text]=""),NA(),1+LEN([@features_text])-LEN(SUBSTITUTE([@features_text],";",""))) | K55: =IF([@segment_id]="",NA(),IF([@segment_id]="SEG_MM",1,0)) | L55: =IF([@entity_id]="","",IF(COUNTIFS(tblClaimsCurrent[entity_id],[@entity_id],tblClaimsCurrent[field_key],"funding_round",tblClaimsCurrent[status],"PROMOTED")>0,1,0)) | M55: =IF(OR([@in_scope]=FALSE,ISNA([@coverage_pct]),ISNA([@feature_count]),ISNA([@segment_fit]),[@acv_band]="UNKNOWN"),NA(),MIN(1,Config!$B$14*MIN(1,[@feature_count]/10)+Config!$B$15*IF([@acv_band]="Low",1,IF([@acv_band]="Mid",0.5,0))+Config!$B$16*[@segment_fit]+Config!$B$17*[@funding_present])) | N55: =IF(OR([@in_scope]=FALSE,ISNA([@coverage_pct]),ISNA([@feature_count]),ISNA([@segment_fit])),NA(),MIN(1,Config!$B$18*(1-MIN(1,[@feature_count]/10))+Config!$B$19*(1-[@segment_fit])+Config!$B$20*(1-[@coverage_pct]))) | O55: =IF([@in_scope]=FALSE,"OUT_OF_SCOPE",IF(ISNA([@coverage_pct]),"UNKNOWN",IF([@coverage_pct]<Config!$B$10,"FAIL_CLOSED_LOW_COVERAGE","OK"))) | P55: =IFERROR(XLOOKUP([@entity_id],tblEntities[entity_id],tblEntities[segment_id]),"") | Q55: =IFERROR(XLOOKUP([@entity_id],tblEntities[entity_id],tblEntities[vertical]),"") | R55: =AND([@segment_id]=Dashboard!$E$2,IF(Dashboard!$E$3="All",TRUE,[@vertical]=Dashboard!$E$3))
A56: =IF(Input!$A$55="","",Input!$A$55) | B56: =IFERROR(XLOOKUP([@entity_id],tblEntities[entity_id],tblEntities[canonical_name]),"") | C56: =IF([@entity_id]="","",COUNTIFS(tblClaimsCurrent[entity_id],[@entity_id],tblClaimsCurrent[status],"PROMOTED")) | D56: =IF([@entity_id]="","",COUNTIFS(tblClaimsCurrent[entity_id],[@entity_id],tblClaimsCurrent[status],"UNKNOWN")) | E56: =LET(t,[@known_claims]+[@unknown_claims],IF(t=0,NA(),[@known_claims]/t)) | F56: =LET(cnt,COUNTIFS(tblClaimsCurrent[entity_id],[@entity_id],tblClaimsCurrent[status],"PROMOTED"),IF(cnt=0,NA(),AVERAGEIFS(tblClaimsCurrent[confidence],tblClaimsCurrent[entity_id],[@entity_id],tblClaimsCurrent[status],"PROMOTED"))) | G56: =LET(cnt,COUNTIFS(tblClaimsCurrent[entity_id],[@entity_id],tblClaimsCurrent[field_key],"pricing_acv_mid_market",tblClaimsCurrent[status],"PROMOTED"),IF(cnt=0,NA(),SUMIFS(tblClaimsCurrent[value_num],tblClaimsCurrent[entity_id],[@entity_id],tblClaimsCurrent[field_key],"pricing_acv_mid_market",tblClaimsCurrent[status],"PROMOTED"))) | H56: =IF(OR(NOT(ISNUMBER([@acv_usd])),$B$5=""),"UNKNOWN",IF([@acv_usd]<=($B$5*0.85),"Low",IF([@acv_usd]>=($B$5*1.15),"High","Mid"))) | I56: =LET(v,IFERROR(LOOKUP(2,1/((tblClaimsCurrent[entity_id]=[@entity_id])*(tblClaimsCurrent[field_key]="features")*(tblClaimsCurrent[status]="PROMOTED")),tblClaimsCurrent[value_text]),"UNKNOWN"),IF(v="","UNKNOWN",v)) | J56: =IF(OR([@features_text]="UNKNOWN",[@features_text]=""),NA(),1+LEN([@features_text])-LEN(SUBSTITUTE([@features_text],";",""))) | K56: =IF([@segment_id]="",NA(),IF([@segment_id]="SEG_MM",1,0)) | L56: =IF([@entity_id]="","",IF(COUNTIFS(tblClaimsCurrent[entity_id],[@entity_id],tblClaimsCurrent[field_key],"funding_round",tblClaimsCurrent[status],"PROMOTED")>0,1,0)) | M56: =IF(OR([@in_scope]=FALSE,ISNA([@coverage_pct]),ISNA([@feature_count]),ISNA([@segment_fit]),[@acv_band]="UNKNOWN"),NA(),MIN(1,Config!$B$14*MIN(1,[@feature_count]/10)+Config!$B$15*IF([@acv_band]="Low",1,IF([@acv_band]="Mid",0.5,0))+Config!$B$16*[@segment_fit]+Config!$B$17*[@funding_present])) | N56: =IF(OR([@in_scope]=FALSE,ISNA([@coverage_pct]),ISNA([@feature_count]),ISNA([@segment_fit])),NA(),MIN(1,Config!$B$18*(1-MIN(1,[@feature_count]/10))+Config!$B$19*(1-[@segment_fit])+Config!$B$20*(1-[@coverage_pct]))) | O56: =IF([@in_scope]=FALSE,"OUT_OF_SCOPE",IF(ISNA([@coverage_pct]),"UNKNOWN",IF([@coverage_pct]<Config!$B$10,"FAIL_CLOSED_LOW_COVERAGE","OK"))) | P56: =IFERROR(XLOOKUP([@entity_id],tblEntities[entity_id],tblEntities[segment_id]),"") | Q56: =IFERROR(XLOOKUP([@entity_id],tblEntities[entity_id],tblEntities[vertical]),"") | R56: =AND([@segment_id]=Dashboard!$E$2,IF(Dashboard!$E$3="All",TRUE,[@vertical]=Dashboard!$E$3))
A57: =IF(Input!$A$56="","",Input!$A$56) | B57: =IFERROR(XLOOKUP([@entity_id],tblEntities[entity_id],tblEntities[canonical_name]),"") | C57: =IF([@entity_id]="","",COUNTIFS(tblClaimsCurrent[entity_id],[@entity_id],tblClaimsCurrent[status],"PROMOTED")) | D57: =IF([@entity_id]="","",COUNTIFS(tblClaimsCurrent[entity_id],[@entity_id],tblClaimsCurrent[status],"UNKNOWN")) | E57: =LET(t,[@known_claims]+[@unknown_claims],IF(t=0,NA(),[@known_claims]/t)) | F57: =LET(cnt,COUNTIFS(tblClaimsCurrent[entity_id],[@entity_id],tblClaimsCurrent[status],"PROMOTED"),IF(cnt=0,NA(),AVERAGEIFS(tblClaimsCurrent[confidence],tblClaimsCurrent[entity_id],[@entity_id],tblClaimsCurrent[status],"PROMOTED"))) | G57: =LET(cnt,COUNTIFS(tblClaimsCurrent[entity_id],[@entity_id],tblClaimsCurrent[field_key],"pricing_acv_mid_market",tblClaimsCurrent[status],"PROMOTED"),IF(cnt=0,NA(),SUMIFS(tblClaimsCurrent[value_num],tblClaimsCurrent[entity_id],[@entity_id],tblClaimsCurrent[field_key],"pricing_acv_mid_market",tblClaimsCurrent[status],"PROMOTED"))) | H57: =IF(OR(NOT(ISNUMBER([@acv_usd])),$B$5=""),"UNKNOWN",IF([@acv_usd]<=($B$5*0.85),"Low",IF([@acv_usd]>=($B$5*1.15),"High","Mid"))) | I57: =LET(v,IFERROR(LOOKUP(2,1/((tblClaimsCurrent[entity_id]=[@entity_id])*(tblClaimsCurrent[field_key]="features")*(tblClaimsCurrent[status]="PROMOTED")),tblClaimsCurrent[value_text]),"UNKNOWN"),IF(v="","UNKNOWN",v)) | J57: =IF(OR([@features_text]="UNKNOWN",[@features_text]=""),NA(),1+LEN([@features_text])-LEN(SUBSTITUTE([@features_text],";",""))) | K57: =IF([@segment_id]="",NA(),IF([@segment_id]="SEG_MM",1,0)) | L57: =IF([@entity_id]="","",IF(COUNTIFS(tblClaimsCurrent[entity_id],[@entity_id],tblClaimsCurrent[field_key],"funding_round",tblClaimsCurrent[status],"PROMOTED")>0,1,0)) | M57: =IF(OR([@in_scope]=FALSE,ISNA([@coverage_pct]),ISNA([@feature_count]),ISNA([@segment_fit]),[@acv_band]="UNKNOWN"),NA(),MIN(1,Config!$B$14*MIN(1,[@feature_count]/10)+Config!$B$15*IF([@acv_band]="Low",1,IF([@acv_band]="Mid",0.5,0))+Config!$B$16*[@segment_fit]+Config!$B$17*[@funding_present])) | N57: =IF(OR([@in_scope]=FALSE,ISNA([@coverage_pct]),ISNA([@feature_count]),ISNA([@segment_fit])),NA(),MIN(1,Config!$B$18*(1-MIN(1,[@feature_count]/10))+Config!$B$19*(1-[@segment_fit])+Config!$B$20*(1-[@coverage_pct]))) | O57: =IF([@in_scope]=FALSE,"OUT_OF_SCOPE",IF(ISNA([@coverage_pct]),"UNKNOWN",IF([@coverage_pct]<Config!$B$10,"FAIL_CLOSED_LOW_COVERAGE","OK"))) | P57: =IFERROR(XLOOKUP([@entity_id],tblEntities[entity_id],tblEntities[segment_id]),"") | Q57: =IFERROR(XLOOKUP([@entity_id],tblEntities[entity_id],tblEntities[vertical]),"") | R57: =AND([@segment_id]=Dashboard!$E$2,IF(Dashboard!$E$3="All",TRUE,[@vertical]=Dashboard!$E$3))

Sheet Tech_Dashboard
A3: Certify Intel — Technical Dashboard
A6: Last Run | D6: Runs (7d) | G6: Allowlist Violations | J6: Open Reviews
A7: =IFERROR(MAX(Logs!tblRuns[timestamp]),"") | D7: =COUNTIF(Logs!tblRuns[timestamp],">="&TODAY()-7) | G7: =COUNTIF(Input!tblEvidence[allowlist_ok],"<>"&TRUE) | J7: =COUNTIF(Review_Queue!tblReviewQueue[status],"OPEN")
A9: Timestamp | D9: Count | G9: Count | J9: Count
A14: Evidence Tier Mix
A15: Tier | B15: Count
A16: T1 | B16: =COUNTIF(Input!tblEvidence[tier],"T1")
A17: T2 | B17: =COUNTIF(Input!tblEvidence[tier],"T2")
A18: T3 | B18: =COUNTIF(Input!tblEvidence[tier],"T3")
A22: Claims Status Counts
A23: Status | B23: Count
A24: PROMOTED | B24: =COUNTIF(Claims_Current!tblClaimsCurrent[status],"PROMOTED")
A25: CANDIDATE | B25: =COUNTIF(Claims_Current!tblClaimsCurrent[status],"CANDIDATE")
A26: FAIL_CLOSED | B26: =COUNTIF(Claims_Current!tblClaimsCurrent[status],"FAIL_CLOSED")

Sheet Competitor_Detail
A1: Competitor Detail
A3: Select Competitor | B3: AcmeRival | C3: =IFERROR(XLOOKUP($B$3,Metrics!$B$8:$B$57,Metrics!$A$8:$A$57,""),"") | D3: Entity ID | E3: =IF(B3="","",INDEX(Metrics!$A$8:$A$57,MATCH(B3,Metrics!$B$8:$B$57,0)))
A5: Summary
A6: Metric | B6: Value | D6: Key Claims
A7: Threat Score | B7: =IFERROR(INDEX(Metrics!$M$8:$M$57,MATCH(B3,Metrics!$B$8:$B$57,0)),"") | D7: field_key | E7: value | F7: confidence | G7: evidence_url
A8: Opportunity Score | B8: =IFERROR(INDEX(Metrics!$N$8:$N$57,MATCH(B3,Metrics!$B$8:$B$57,0)),"") | D8: pricing_acv_mid_market | E8: =IFERROR(LOOKUP(2,1/((Claims_Current!$A$5:$A$46=$E$3)*(Claims_Current!$D$5:$D$46=D8)),Claims_Current!$E$5:$E$46),"") | F8: =IFERROR(LOOKUP(2,1/((Claims_Current!$A$5:$A$46=$E$3)*(Claims_Current!$D$5:$D$46=D8)),Claims_Current!$H$5:$H$46),"") | G8: =IFERROR(LOOKUP(2,1/((Claims_Current!$A$5:$A$46=$E$3)*(Claims_Current!$D$5:$D$46=D8)),Claims_Current!$J$5:$J$46),"")
A9: Coverage | B9: =IFERROR(INDEX(Metrics!$E$8:$E$57,MATCH(B3,Metrics!$B$8:$B$57,0)),"") | D9: arr_estimate | E9: =IFERROR(LOOKUP(2,1/((Claims_Current!$A$5:$A$46=$E$3)*(Claims_Current!$D$5:$D$46=D9)),Claims_Current!$E$5:$E$46),"") | F9: =IFERROR(LOOKUP(2,1/((Claims_Current!$A$5:$A$46=$E$3)*(Claims_Current!$D$5:$D$46=D9)),Claims_Current!$H$5:$H$46),"") | G9: =IFERROR(LOOKUP(2,1/((Claims_Current!$A$5:$A$46=$E$3)*(Claims_Current!$D$5:$D$46=D9)),Claims_Current!$J$5:$J$46),"")
A10: ACV (USD/year) | B10: =IFERROR(INDEX(Metrics!$G$8:$G$57,MATCH(B3,Metrics!$B$8:$B$57,0)),"") | D10: contract_terms | E10: =IFERROR(LOOKUP(2,1/((Claims_Current!$A$5:$A$46=$E$3)*(Claims_Current!$D$5:$D$46=D10)),Claims_Current!$E$5:$E$46),"") | F10: =IFERROR(LOOKUP(2,1/((Claims_Current!$A$5:$A$46=$E$3)*(Claims_Current!$D$5:$D$46=D10)),Claims_Current!$H$5:$H$46),"") | G10: =IFERROR(LOOKUP(2,1/((Claims_Current!$A$5:$A$46=$E$3)*(Claims_Current!$D$5:$D$46=D10)),Claims_Current!$J$5:$J$46),"")
A11: Features | B11: =IFERROR(INDEX(Metrics!$I$8:$I$57,MATCH(B3,Metrics!$B$8:$B$57,0)),"") | D11: features | E11: =IFERROR(LOOKUP(2,1/((Claims_Current!$A$5:$A$46=$E$3)*(Claims_Current!$D$5:$D$46=D11)),Claims_Current!$E$5:$E$46),"") | F11: =IFERROR(LOOKUP(2,1/((Claims_Current!$A$5:$A$46=$E$3)*(Claims_Current!$D$5:$D$46=D11)),Claims_Current!$H$5:$H$46),"") | G11: =IFERROR(LOOKUP(2,1/((Claims_Current!$A$5:$A$46=$E$3)*(Claims_Current!$D$5:$D$46=D11)),Claims_Current!$J$5:$J$46),"")
A12: Flag | B12: =IFERROR(INDEX(Metrics!$O$8:$O$57,MATCH(B3,Metrics!$B$8:$B$57,0)),"") | D12: funding_round | E12: =IFERROR(LOOKUP(2,1/((Claims_Current!$A$5:$A$46=$E$3)*(Claims_Current!$D$5:$D$46=D12)),Claims_Current!$E$5:$E$46),"") | F12: =IFERROR(LOOKUP(2,1/((Claims_Current!$A$5:$A$46=$E$3)*(Claims_Current!$D$5:$D$46=D12)),Claims_Current!$H$5:$H$46),"") | G12: =IFERROR(LOOKUP(2,1/((Claims_Current!$A$5:$A$46=$E$3)*(Claims_Current!$D$5:$D$46=D12)),Claims_Current!$J$5:$J$46),"")
D13: geo_coverage | E13: =IFERROR(LOOKUP(2,1/((Claims_Current!$A$5:$A$46=$E$3)*(Claims_Current!$D$5:$D$46=D13)),Claims_Current!$E$5:$E$46),"") | F13: =IFERROR(LOOKUP(2,1/((Claims_Current!$A$5:$A$46=$E$3)*(Claims_Current!$D$5:$D$46=D13)),Claims_Current!$H$5:$H$46),"") | G13: =IFERROR(LOOKUP(2,1/((Claims_Current!$A$5:$A$46=$E$3)*(Claims_Current!$D$5:$D$46=D13)),Claims_Current!$J$5:$J$46),"")
A14: Evidence (Selected Competitor)
A15: evidence_id | B15: source_key | C15: tier | D15: url | E15: fetched_at | F15: snippet | G15: content_hash | H15: text_hash | I15: domain_calc | J15: allowlist_ok
A16: =LET(eid,$C$3,FILTER(Input!tblEvidence[[evidence_id]:[allowlist_ok]],Input!tblEvidence[entity_id]=eid,"")) | B16: =Input!B18 | C16: =Input!C18 | D16: =Input!D18 | E16: =Input!E18 | F16: =Input!F18 | G16: =Input!G18 | H16: =Input!H18 | I16: =Input!I18
A17: =Input!A19 | B17: =Input!B19 | C17: =Input!C19 | D17: =Input!D19 | E17: =Input!E19 | F17: =Input!F19 | G17: =Input!G19 | H17: =Input!H19 | I17: =Input!I19
A18: =Input!A20 | B18: =Input!B20 | C18: =Input!C20 | D18: =Input!D20 | E18: =Input!E20 | F18: =Input!F20 | G18: =Input!G20 | H18: =Input!H20 | I18: =Input!I20
A19: =Input!A21 | B19: =Input!B21 | C19: =Input!C21 | D19: =Input!D21 | E19: =Input!E21 | F19: =Input!F21 | G19: =Input!G21 | H19: =Input!H21 | I19: =Input!I21
A20: =Input!A22 | B20: =Input!B22 | C20: =Input!C22 | D20: =Input!D22 | E20: =Input!E22 | F20: =Input!F22 | G20: =Input!G22 | H20: =Input!H22 | I20: =Input!I22

Sheet Review_Queue
A1: Review Queue (All UNKNOWN / Low-Confidence / Non-Allowlisted Evidence)
A2: Fail-closed: no claim promotion until reviewed and evidence is tier-compliant.
A4: task_id | B4: created_at | C4: task_type | D4: priority | E4: entity_id | F4: canonical_name | G4: field_key | H4: value_text | I4: value_num | J4: confidence | K4: evidence_id | L4: evidence_url | M4: reason | N4: status | O4: resolution_notes
A5: T0001 | B5: 2026-01-12 | C5: UNKNOWN_OR_LOW_CONF | D5: HIGH | E5: E002 | F5: EnrollPro | G5: pricing_acv_mid_market | H5: UNKNOWN | J5: 0.2 | K5: EV002 | L5: file://docs/demo_sources/E002_pricing.html | M5: No explicit ACV on page | N5: OPEN
A6: T0002 | B6: 2026-01-12 | C6: UNKNOWN_OR_LOW_CONF | D6: HIGH | E6: E003 | F6: ComplianceFlow | G6: funding_round | H6: UNKNOWN | J6: 0.1 | K6: EV003 | L6: file://docs/demo_sources/E003_pricing.html | M6: Signal only; needs tier-1 corroboration | N6: OPEN
A7: T0003 | B7: 2026-01-12 | C7: UNKNOWN_OR_LOW_CONF | D7: HIGH | E7: E005 | F7: PracticeOps | G7: pricing_acv_mid_market | I7: 9000 | J7: 0.8 | K7: EV005 | L7: file://docs/demo_sources/E001_pr.html | M7: Pricing from signal source; needs tier-1 | N7: OPEN
A10: task_id | B10: created_at | C10: task_type | D10: priority | E10: entity_id | F10: canonical_name | G10: field_key | H10: value_text | I10: value_num | J10: confidence | K10: evidence_id | L10: evidence_url | M10: reason | N10: status | O10: resolution_notes
A11: =LET(c,tblClaimCandidates,mask,c[status_final]<>"PROMOTED",cand,FILTER(c[candidate_id],mask),ent,FILTER(c[entity_id],mask),key,FILTER(c[field_key],mask),vtxt,FILTER(c[value_text],mask),vnum,FILTER(c[value_num],mask),conf,FILTER(c[confidence],mask),evid,FILTER(c[evidence_id],mask),reas,FILTER(c[auto_reason],mask),cname,IFERROR(XLOOKUP(ent,tblEntities[entity_id],tblEntities[canonical_name]),""),eurl,IFERROR(XLOOKUP(evid,tblEvidence[evidence_id],tblEvidence[url]),""),prio,IF(reas="LOW_CONFIDENCE","HIGH",IF(reas="MISSING_EVIDENCE","HIGH",IF(reas="TIER1_REQUIRED","HIGH","MEDIUM"))),CHOOSE({1,2,3,4,5,6,7,8,9,10,11,12,13,14,15},"TASK-"&cand,TODAY(),"CLAIM_REVIEW",prio,ent,cname,key,vtxt,vnum,conf,evid,eurl,reas,"OPEN",""))

Sheet Logs
A1: Logs
A3: Refresh Log (append-only; use for auditability)
A5: run_id | B5: started_at | C5: ended_at | D5: mode | E5: entities_imported | F5: evidence_imported | G5: claims_promoted | H5: review_tasks_opened | I5: notes
A6: RUN_DEMO | B6: 2026-01-12 00:00 | C6: 2026-01-12 00:01 | D6: DEMO | E6: 6 | F6: 5 | G6: 6 | H6: 3 | I6: Template generated

Sheet Scraper
A1: Scraper (Optional; Autonomous Competitor Discovery)
A3: This workbook is designed to run Excel-only. For true autonomous discovery/refresh, use Power Query (From Web) or VBA/Office Script.
A5: Minimum viable workflow
A6: 1) Update Sources_Allowlist (domains + paths) and Segment_Rules.
A7: 2) Populate/refresh Input tables (Entities, Evidence, Claim Candidates) via Power Query or manual import.
A8: 3) Resolve Review_Queue items; promote claims only when evidence is tier-compliant.
A9: 4) Dashboards refresh automatically via formulas/charts.
A11: Power Query M-code (template) — Web Search → Competitor Candidates
A12: // TEMPLATE ONLY — paste into Power Query (Data > Get Data > From Other Sources > Blank Query > Advanced Editor) // Replace <API_KEY> and <QUERY>. Ensure ToS compliance for all endpoints. let Query = "<QUERY>", ApiKey = Excel.CurrentWorkbook(){[Name="BingSearchKey"]}[Content]{0}[Column1], Url = "https://api.bing.microsoft.com/v7.0/search?q=" & Uri.EscapeDataString(Query) & "&count=25", Source = Json.Document(Web.Contents(Url, [Headers=[#"Ocp-Apim-Subscription-Key"=ApiKey]])), WebPages = Source[webPages][value], Table = Table.FromList(WebPages, Splitter.SplitByNothing(), null, null, ExtraValues.Error), Expand = Table.ExpandRecordColumn(Table, "Column1", {"name","url","snippet"}, {"name","url","snippet"}) in Expand
A24: Office Script (template) — Promote resolved Review Queue items
A25: /** * TEMPLATE ONLY — paste into Excel Online > Automate > New Script. * Goal: when Review_Queue.status == RESOLVED, update Input.tblClaimCandidates status to PROMOTED * and write a log row to Logs. */ function main(workbook: ExcelScript.Workbook) { // TODO: implement based on your table names (tblReviewQueue, tblClaimCandidates, tblLogs) }

Sheet Dashboard
A4: Certify Intel — Executive Dashboard
A6: Filters | AA6: Vertical_List
A7: Segment | B7: SEG_MM | AA7: =SORT(UNIQUE(VSTACK("All",Input!tblEntities[vertical])))
A8: Vertical | B8: All
A9: Region | B9: All | AA9: Region_List
AA10: =SORT(UNIQUE(VSTACK("All",Input!tblEntities[region])))
A11: Competitors | D11: Open Reviews | G11: Evidence Items | J11: Fresh Evidence %
A12: =ROWS($AA$13#) | D12: =COUNTIF(Review_Queue!tblReviewQueue[status],"OPEN") | G12: =ROWS(Input!tblEvidence[evidence_id]) | J12: =IFERROR(1-COUNTIF(Input!tblEvidence[fetched_at],"<"&TODAY()-30)/ROWS(Input!tblEvidence[fetched_at]),0) | AA12: Filtered_Names
AA13: =LET(seg,$B$7,vert,$B$8,reg,$B$9, m,(Input!tblEntities[segment_id]=seg)*IF(vert="All",1,(Input!tblEntities[vertical]=vert))*IF(reg="All",1,(Input!tblEntities[region]=reg)), FILTER(Input!tblEntities[canonical_name], m, ""))
A14: In-scope competitors | D14: Needs human review | G14: Captured evidence | J14: Fetched <30d
AA15: Filtered_Coverage
AA16: =LET(seg,$B$7,vert,$B$8,reg,$B$9, m,(Input!tblEntities[segment_id]=seg)*IF(vert="All",1,(Input!tblEntities[vertical]=vert))*IF(reg="All",1,(Input!tblEntities[region]=reg)), FILTER(Metrics!tblMetrics[coverage_pct], m, ""))
A17: Avg Coverage % | D17: Avg Threat | G17: High Threat | J17: Fail-Closed
A18: =IFERROR(AVERAGE($AA$16#),0) | D18: =IFERROR(AVERAGE($AA$19#),0) | G18: =COUNTIF($AA$19#,">=0.75") | J18: =COUNTIF($AA$25#,"FAIL_CLOSED") | AA18: Filtered_Threat
AA19: =LET(seg,$B$7,vert,$B$8,reg,$B$9, m,(Input!tblEntities[segment_id]=seg)*IF(vert="All",1,(Input!tblEntities[vertical]=vert))*IF(reg="All",1,(Input!tblEntities[region]=reg)), FILTER(Metrics!tblMetrics[threat_score], m, ""))
A20: Known / total fields | D20: Mean threat score | G20: Threat ≥ 0.75 | J20: Blocked entities
AA21: Filtered_Opp
A22: Rankings | AA22: =LET(seg,$B$7,vert,$B$8,reg,$B$9, m,(Input!tblEntities[segment_id]=seg)*IF(vert="All",1,(Input!tblEntities[vertical]=vert))*IF(reg="All",1,(Input!tblEntities[region]=reg)), FILTER(Metrics!tblMetrics[opportunity_score], m, ""))
A24: Top Threats | AA24: Filtered_Flags
A25: Competitor | B25: Threat | AA25: =LET(seg,$B$7,vert,$B$8,reg,$B$9, m,(Input!tblEntities[segment_id]=seg)*IF(vert="All",1,(Input!tblEntities[vertical]=vert))*IF(reg="All",1,(Input!tblEntities[region]=reg)), FILTER(Metrics!tblMetrics[flags], m, ""))
A26: =IFERROR(INDEX($AA$28#, 1, 1),"") | B26: =IFERROR(INDEX($AA$28#, 1, 2),"")
A27: =IFERROR(INDEX($AA$28#, 2, 1),"") | B27: =IFERROR(INDEX($AA$28#, 2, 2),"") | AA27: TopThreat_Table
A28: =IFERROR(INDEX($AA$28#, 3, 1),"") | B28: =IFERROR(INDEX($AA$28#, 3, 2),"") | AA28: =LET(n,$AA$13#, t,$AA$19#, tbl,HSTACK(n,t), TAKE(SORTBY(tbl, CHOOSECOLS(tbl,2), -1), 10))
A29: =IFERROR(INDEX($AA$28#, 4, 1),"") | B29: =IFERROR(INDEX($AA$28#, 4, 2),"")
A30: =IFERROR(INDEX($AA$28#, 5, 1),"") | B30: =IFERROR(INDEX($AA$28#, 5, 2),"")
A31: =IFERROR(INDEX($AA$28#, 6, 1),"") | B31: =IFERROR(INDEX($AA$28#, 6, 2),"")
A32: =IFERROR(INDEX($AA$28#, 7, 1),"") | B32: =IFERROR(INDEX($AA$28#, 7, 2),"")
A33: =IFERROR(INDEX($AA$28#, 8, 1),"") | B33: =IFERROR(INDEX($AA$28#, 8, 2),"")
A34: =IFERROR(INDEX($AA$28#, 9, 1),"") | B34: =IFERROR(INDEX($AA$28#, 9, 2),"")
A35: =IFERROR(INDEX($AA$28#, 10, 1),"") | B35: =IFERROR(INDEX($AA$28#, 10, 2),"")
A38: Threat vs Opportunity
A39: Competitor | B39: Threat | C39: Opportunity
A40: =IFERROR(INDEX($AA$13#, 1),"") | B40: =IFERROR(XLOOKUP(A40, Metrics!tblMetrics[canonical_name], Metrics!tblMetrics[threat_score], ""),"") | C40: =IFERROR(XLOOKUP(A40, Metrics!tblMetrics[canonical_name], Metrics!tblMetrics[opportunity_score], ""),"")
A41: =IFERROR(INDEX($AA$13#, 2),"") | B41: =IFERROR(XLOOKUP(A41, Metrics!tblMetrics[canonical_name], Metrics!tblMetrics[threat_score], ""),"") | C41: =IFERROR(XLOOKUP(A41, Metrics!tblMetrics[canonical_name], Metrics!tblMetrics[opportunity_score], ""),"")
A42: =IFERROR(INDEX($AA$13#, 3),"") | B42: =IFERROR(XLOOKUP(A42, Metrics!tblMetrics[canonical_name], Metrics!tblMetrics[threat_score], ""),"") | C42: =IFERROR(XLOOKUP(A42, Metrics!tblMetrics[canonical_name], Metrics!tblMetrics[opportunity_score], ""),"")
A43: =IFERROR(INDEX($AA$13#, 4),"") | B43: =IFERROR(XLOOKUP(A43, Metrics!tblMetrics[canonical_name], Metrics!tblMetrics[threat_score], ""),"") | C43: =IFERROR(XLOOKUP(A43, Metrics!tblMetrics[canonical_name], Metrics!tblMetrics[opportunity_score], ""),"")
A44: =IFERROR(INDEX($AA$13#, 5),"") | B44: =IFERROR(XLOOKUP(A44, Metrics!tblMetrics[canonical_name], Metrics!tblMetrics[threat_score], ""),"") | C44: =IFERROR(XLOOKUP(A44, Metrics!tblMetrics[canonical_name], Metrics!tblMetrics[opportunity_score], ""),"")
A45: =IFERROR(INDEX($AA$13#, 6),"") | B45: =IFERROR(XLOOKUP(A45, Metrics!tblMetrics[canonical_name], Metrics!tblMetrics[threat_score], ""),"") | C45: =IFERROR(XLOOKUP(A45, Metrics!tblMetrics[canonical_name], Metrics!tblMetrics[opportunity_score], ""),"")
A46: =IFERROR(INDEX($AA$13#, 7),"") | B46: =IFERROR(XLOOKUP(A46, Metrics!tblMetrics[canonical_name], Metrics!tblMetrics[threat_score], ""),"") | C46: =IFERROR(XLOOKUP(A46, Metrics!tblMetrics[canonical_name], Metrics!tblMetrics[opportunity_score], ""),"")
A47: =IFERROR(INDEX($AA$13#, 8),"") | B47: =IFERROR(XLOOKUP(A47, Metrics!tblMetrics[canonical_name], Metrics!tblMetrics[threat_score], ""),"") | C47: =IFERROR(XLOOKUP(A47, Metrics!tblMetrics[canonical_name], Metrics!tblMetrics[opportunity_score], ""),"")
A48: =IFERROR(INDEX($AA$13#, 9),"") | B48: =IFERROR(XLOOKUP(A48, Metrics!tblMetrics[canonical_name], Metrics!tblMetrics[threat_score], ""),"") | C48: =IFERROR(XLOOKUP(A48, Metrics!tblMetrics[canonical_name], Metrics!tblMetrics[opportunity_score], ""),"")
A49: =IFERROR(INDEX($AA$13#, 10),"") | B49: =IFERROR(XLOOKUP(A49, Metrics!tblMetrics[canonical_name], Metrics!tblMetrics[threat_score], ""),"") | C49: =IFERROR(XLOOKUP(A49, Metrics!tblMetrics[canonical_name], Metrics!tblMetrics[opportunity_score], ""),"")
A50: =IFERROR(INDEX($AA$13#, 11),"") | B50: =IFERROR(XLOOKUP(A50, Metrics!tblMetrics[canonical_name], Metrics!tblMetrics[threat_score], ""),"") | C50: =IFERROR(XLOOKUP(A50, Metrics!tblMetrics[canonical_name], Metrics!tblMetrics[opportunity_score], ""),"")
A51: =IFERROR(INDEX($AA$13#, 12),"") | B51: =IFERROR(XLOOKUP(A51, Metrics!tblMetrics[canonical_name], Metrics!tblMetrics[threat_score], ""),"") | C51: =IFERROR(XLOOKUP(A51, Metrics!tblMetrics[canonical_name], Metrics!tblMetrics[opportunity_score], ""),"")
A52: =IFERROR(INDEX($AA$13#, 13),"") | B52: =IFERROR(XLOOKUP(A52, Metrics!tblMetrics[canonical_name], Metrics!tblMetrics[threat_score], ""),"") | C52: =IFERROR(XLOOKUP(A52, Metrics!tblMetrics[canonical_name], Metrics!tblMetrics[opportunity_score], ""),"")
A53: =IFERROR(INDEX($AA$13#, 14),"") | B53: =IFERROR(XLOOKUP(A53, Metrics!tblMetrics[canonical_name], Metrics!tblMetrics[threat_score], ""),"") | C53: =IFERROR(XLOOKUP(A53, Metrics!tblMetrics[canonical_name], Metrics!tblMetrics[opportunity_score], ""),"")
A54: =IFERROR(INDEX($AA$13#, 15),"") | B54: =IFERROR(XLOOKUP(A54, Metrics!tblMetrics[canonical_name], Metrics!tblMetrics[threat_score], ""),"") | C54: =IFERROR(XLOOKUP(A54, Metrics!tblMetrics[canonical_name], Metrics!tblMetrics[opportunity_score], ""),"")
A55: =IFERROR(INDEX($AA$13#, 16),"") | B55: =IFERROR(XLOOKUP(A55, Metrics!tblMetrics[canonical_name], Metrics!tblMetrics[threat_score], ""),"") | C55: =IFERROR(XLOOKUP(A55, Metrics!tblMetrics[canonical_name], Metrics!tblMetrics[opportunity_score], ""),"")
A56: =IFERROR(INDEX($AA$13#, 17),"") | B56: =IFERROR(XLOOKUP(A56, Metrics!tblMetrics[canonical_name], Metrics!tblMetrics[threat_score], ""),"") | C56: =IFERROR(XLOOKUP(A56, Metrics!tblMetrics[canonical_name], Metrics!tblMetrics[opportunity_score], ""),"")
